Workbook

Sheet Read me
A1: Roth Conversion Analyzer
A2: Built from Robert Mac Arthur's (KSM) 'IRA analysis.xlsx' framing: convert and pay the tax from outside cash, versus keep the IRA and invest that same outside cash. Extended to answer three questions: Is it worth converting at all? All at once, or over time? And how sensitive is the answer to the assumptions?
A4: HOW TO USE
A5: 1. Change only the blue cells on yellow fill (tab 'Inputs'). Everything else is formulas.
A6: 2. The 'Compare' tab is the answer page: after-tax wealth at your horizon for each strategy, the advantage over not converting, total tax paid, and the year each strategy pulls ahead.
A7: 3. The 'Engine' tab holds six side-by-side strategies (no conversion, all at once, over 3 / 5 / 8 / 10 years). The number of conversion years in each block header is editable, so you can test any spread.
A8: 4. The 'Lump vs None' tab is the CPA's original two-column layout, year by year, with the after-tax value of each side every year so you can see the crossover.
A9: 5. 'Sensitivity' shows the lump-sum advantage across future tax rates and returns, and the break-even future tax rate.
A10: 6. 'RMD & heirs' shows what an unconverted IRA looks like at 75 (required withdrawals) and what the kids keep.
A12: THE FAIR COMPARISON (why this is apples to apples)
A13: Every strategy starts with the same resources: the IRA plus an outside cash pool. A conversion spends pool cash on tax. Not converting leaves that cash in the pool, invested in a taxable account. After-tax wealth each year = Roth (tax-free) + IRA x (1 - future tax rate) + pool (less the deferred tax on its gains). Comparing strategies on after-tax wealth from identical starting resources is the only way the 'all at once vs over time vs never' question is fair.
A15: WHAT THE CPA'S SHEET ASSUMED, AND WHAT THIS ONE ADDS
... A26: Illustrative only, not tax advice. Prepared October 2026 with Claude Code from the KSM worksheet dated the same month.

Sheet Compare
A1: Compare: after-tax wealth by strategy
A2: ="Horizon: "&Inputs!B10&" years (change on Inputs). Start year "&Inputs!B11&", age "&Inputs!B12&" to "&(Inputs!B12+Inputs!B10)&". IRA $"&TEXT(Inputs!B3,"#,##0")&", return "&TEXT(Inputs!B4,"0.0%")&", rate now "&TEXT(Inputs!B5,"0%")&", rate later "&TEXT(Inputs!B6,"0%")&"." -> Horizon: 10 years (change on Inputs). Start year 2026, age 57 to 67. IRA $1,150,000, return 10.0%, rate now 38%, rate later 30%.
A4: Strategy | B4: Conversion years | C4: After-tax wealth at horizon | D4: Advantage vs never ($) | E4: Advantage vs never (%) | F4: Total tax paid (from pool) | G4: Average conversion rate | H4: First year ahead of never | I4: Roth share at horizon
A5: Never convert | B5: =Engine!$F$4 -> 0 | C5: =INDEX(Engine!M7:M47,Inputs!$B$10+1) -> 3689263.9 | D5: =C5-$C$5 -> 0 | E5: =IF($C$5=0,0,D5/$C$5) -> 0 | F5: =Engine!G49 -> 0 | G5: =Engine!F50 -> 0 | H5: =Engine!F51 -> never | I5: =INDEX(Engine!N7:N47,Inputs!$B$10+1) -> 0
A6: All at once | B6: =Engine!$W$4 -> 1 | C6: =INDEX(Engine!AD7:AD47,Inputs!$B$10+1) -> 3669075.8 | D6: =C6-$C$5 -> -20188.097 | E6: =IF($C$5=0,0,D6/$C$5) -> -0.0054721206 | F6: =Engine!X49 -> 437000 | G6: =Engine!W50 -> 0.38 | H6: =Engine!W51 -> 12 | I6: =INDEX(Engine!AE7:AE47,Inputs!$B$10+1) -> 0.78597367
A7: Over 3 years | B7: =Engine!$AN$4 -> 3 | C7: =INDEX(Engine!AU7:AU47,Inputs!$B$10+1) -> 3664891.2 | D7: =C7-$C$5 -> -24372.672 | E7: =IF($C$5=0,0,D7/$C$5) -> -0.0066063782 | F7: =Engine!AO49 -> 482156.67 | G7: =Engine!AN50 -> 0.38 | H7: =Engine!AN51 -> 12 | I7: =INDEX(Engine!AV7:AV47,Inputs!$B$10+1) -> 0.78700074
A8: Over 5 years | B8: =Engine!$BE$4 -> 5 | C8: =INDEX(Engine!BL7:BL47,Inputs!$B$10+1) -> 3660681.1 | D8: =C8-$C$5 -> -28582.773 | E8: =IF($C$5=0,0,D8/$C$5) -> -0.0077475545 | F8: =Engine!BF49 -> 533585.74 | G8: =Engine!BE50 -> 0.38 | H8: =Engine!BE51 -> 13 | I8: =INDEX(Engine!BM7:BM47,Inputs!$B$10+1) -> 0.78803678
A9: Over 8 years | B9: =Engine!$BV$4 -> 8 | C9: =INDEX(Engine!CC7:CC47,Inputs!$B$10+1) -> 3654317.7 | D9: =C9-$C$5 -> -34946.167 | E9: =IF($C$5=0,0,D9/$C$5) -> -0.0094723958 | F9: =Engine!BW49 -> 624685.39 | G9: =Engine!BV50 -> 0.38 | H9: =Engine!BV51 -> 13 | I9: =INDEX(Engine!CD7:CD47,Inputs!$B$10+1) -> 0.7896079
A10: Over 10 years | B10: =Engine!$CM$4 -> 10 | C10: =INDEX(Engine!CT7:CT47,Inputs!$B$10+1) -> 3650043 | D10: =C10-$C$5 -> -39220.851 | E10: =IF($C$5=0,0,D10/$C$5) -> -0.010631078 | F10: =Engine!CN49 -> 696465.46 | G10: =Engine!CM50 -> 0.38 | H10: =Engine!CM51 -> 13 | I10: =INDEX(Engine!CU7:CU47,Inputs!$B$10+1) -> 0.79066684
A12: Best strategy at this horizon: | B12: =INDEX(A5:A10,MATCH(MAX(C5:C10),C5:C10,0)) -> Never convert
A13: Break-even future tax rate (lump sum): | B13: =(Inputs!$B$5*(1+Inputs!$B$4*(1-Inputs!$B$8))^Inputs!$B$10*(1-Inputs!$B$9)+Inputs!$B$5*Inputs!$B$9)/(1+Inputs!$B$4)^Inputs!$B$10 -> 0.30676816 | C13: If your future withdrawal rate is above this, converting all at once beats never converting at this horizon. Below it, keeping the IRA wins. It is lower than the rate you pay now because the taxable pool is taxed along the way.
A15: Fixed horizons (after-tax wealth, $)
A16: Strategy | B16: 5 yrs | C16: 10 yrs | D16: 15 yrs | E16: 20 yrs | F16: 25 yrs | G16: 30 yrs | H16: Age 75 (RMD start)
A17: Never convert | B17: =INDEX(Engine!M7:M47,5+1) -> 2386180.9 | C17: =INDEX(Engine!M7:M47,10+1) -> 3689263.9 | D17: =INDEX(Engine!M7:M47,15+1) -> 5769336.4 | E17: =INDEX(Engine!M7:M47,20+1) -> 9090102.9 | F17: =INDEX(Engine!M7:M47,25+1) -> 14392245 | G17: =INDEX(Engine!M7:M47,30+1) -> 22859007 | H17: =INDEX(Engine!M7:M47,MIN(40,75-Inputs!$B$12)+1) -> 7573282.3
A18: All at once | B18: =INDEX(Engine!AD7:AD47,5+1) -> 2319109.5 | C18: =INDEX(Engine!AD7:AD47,10+1) -> 3669075.8 | D18: =INDEX(Engine!AD7:AD47,15+1) -> 5835257.5 | E18: =INDEX(Engine!AD7:AD47,20+1) -> 9311395.8 | F18: =INDEX(Engine!AD7:AD47,25+1) -> 14890043 | G18: =INDEX(Engine!AD7:AD47,30+1) -> 23843486 | H18: =INDEX(Engine!AD7:AD47,MIN(40,75-Inputs!$B$12)+1) -> 7721425.9
A19: Over 3 years | B19: =INDEX(Engine!AU7:AU47,5+1) -> 2316261.8 | C19: =INDEX(Engine!AU7:AU47,10+1) -> 3664891.2 | D19: =INDEX(Engine!AU7:AU47,15+1) -> 5828968.4 | E19: =INDEX(Engine!AU7:AU47,20+1) -> 9301793.6 | F19: =INDEX(Engine!AU7:AU47,25+1) -> 14875226 | G19: =INDEX(Engine!AU7:AU47,30+1) -> 23820458 | H19: =INDEX(Engine!AU7:AU47,MIN(40,75-Inputs!$B$12)+1) -> 7713331.2
A20: Over 5 years | B20: =INDEX(Engine!BL7:BL47,5+1) -> 2313396.7 | C20: =INDEX(Engine!BL7:BL47,10+1) -> 3660681.1 | D20: =INDEX(Engine!BL7:BL47,15+1) -> 5822640.9 | E20: =INDEX(Engine!BL7:BL47,20+1) -> 9292132.8 | F20: =INDEX(Engine!BL7:BL47,25+1) -> 14860317 | G20: =INDEX(Engine!BL7:BL47,30+1) -> 23797289 | H20: =INDEX(Engine!BL7:BL47,MIN(40,75-Inputs!$B$12)+1) -> 7705187.2
A21: Over 8 years | B21: =INDEX(Engine!CC7:CC47,5+1) -> 2340690.8 | C21: =INDEX(Engine!CC7:CC47,10+1) -> 3654317.7 | D21: =INDEX(Engine!CC7:CC47,15+1) -> 5813077.1 | E21: =INDEX(Engine!CC7:CC47,20+1) -> 9277530.9 | F21: =INDEX(Engine!CC7:CC47,25+1) -> 14837784 | G21: =INDEX(Engine!CC7:CC47,30+1) -> 23762270 | H21: =INDEX(Engine!CC7:CC47,MIN(40,75-Inputs!$B$12)+1) -> 7692877.9
A22: Over 10 years | B22: =INDEX(Engine!CT7:CT47,5+1) -> 2349788.8 | C22: =INDEX(Engine!CT7:CT47,10+1) -> 3650043 | D22: =INDEX(Engine!CT7:CT47,15+1) -> 5806652.5 | E22: =INDEX(Engine!CT7:CT47,20+1) -> 9267721.9 | F22: =INDEX(Engine!CT7:CT47,25+1) -> 14822647 | G22: =INDEX(Engine!CT7:CT47,30+1) -> 23738746 | H22: =INDEX(Engine!CT7:CT47,MIN(40,75-Inputs!$B$12)+1) -> 7684609
A24: Advantage vs never, same horizons ($)
A25: Strategy | B25: 5 yrs | C25: 10 yrs | D25: 15 yrs | E25: 20 yrs | F25: 25 yrs | G25: 30 yrs | H25: Age 75
A26: Never convert | B26: =B17-B$17 -> 0 | C26: =C17-C$17 -> 0 | D26: =D17-D$17 -> 0 | E26: =E17-E$17 -> 0 | F26: =F17-F$17 -> 0 | G26: =G17-G$17 -> 0 | H26: =H17-H$17 -> 0
A27: All at once | B27: =B18-B$17 -> -67071.374 | C27: =C18-C$17 -> -20188.097 | D27: =D18-D$17 -> 65921.137 | E27: =E18-E$17 -> 221292.96 | F27: =F18-F$17 -> 497798.1 | G27: =G18-G$17 -> 984479.06 | H27: =H18-H$17 -> 148143.54
A28: Over 3 years | B28: =B19-B$17 -> -69919.069 | C28: =C19-C$17 -> -24372.672 | D28: =D19-D$17 -> 59631.992 | E28: =E19-E$17 -> 211690.72 | F28: =F19-F$17 -> 482980.25 | G28: =G19-G$17 -> 961450.62 | H28: =H19-H$17 -> 140048.92
A29: Over 5 years | B29: =B20-B$17 -> -72784.134 | C29: =C20-C$17 -> -28582.773 | D29: =D20-D$17 -> 53304.484 | E29: =E20-E$17 -> 202029.91 | F29: =F20-F$17 -> 468072.03 | G29: =G20-G$17 -> 938281.7 | H29: =H20-H$17 -> 131904.92
A30: Over 8 years | B30: =B21-B$17 -> -45490.084 | C30: =C21-C$17 -> -34946.167 | D30: =D21-D$17 -> 43740.716 | E30: =E21-E$17 -> 187427.99 | F30: =F21-F$17 -> 445538.85 | G30: =G21-G$17 -> 903262.84 | H30: =H21-H$17 -> 119595.6
A31: Over 10 years | B31: =B22-B$17 -> -36392.067 | C31: =C22-C$17 -> -39220.851 | D31: =D22-D$17 -> 37316.145 | E31: =E22-E$17 -> 177618.98 | F31: =F22-F$17 -> 430401.93 | G31: =G22-G$17 -> 879738.51 | H31: =H22-H$17 -> 111326.68

Sheet Lump vs None
A1: The CPA's two-column layout, with Joe's inputs and the after-tax value of each side every year
A2: Left: pay the tax from outside cash, convert everything to Roth, let it grow. Right: keep the IRA, invest the same outside cash in a taxable account. Pulled from the Engine (blocks "All at once" and "Never convert").
A4: Year | B4: Age | C4: Calendar | D4: ROTH SIDE: Roth balance | E4: Roth after-tax (no tax due) | F4: IRA SIDE: IRA balance | G4: Tax if withdrawn now | H4: IRA after tax | I4: Taxable pool | J4: Deferred tax on pool gains | K4: IRA side after-tax total | L4: Roth side advantage ($) | M4: Roth side advantage (%)
A5: 0 | B5: =Engine!S7 -> 57 | C5: =Engine!T7 -> 2025 | D5: =Engine!AA7 -> 0 | E5: =D5+Engine!AB7-(Engine!AB7-Engine!AC7)*Inputs!$B$9 -> 764750 | F5: =Engine!I7 -> 1150000 | G5: =-F5*Inputs!$B$6 -> -345000 | H5: =F5+G5 -> 805000 | I5: =Engine!K7 -> 764750 | J5: =-(I5-Engine!L7)*Inputs!$B$9 -> 0 | K5: =H5+I5+J5 -> 1569750 | L5: =E5-K5 -> -805000 | M5: =IF(K5=0,0,L5/K5) -> -0.51282051
A6: 1 | B6: =Engine!S8 -> 58 | C6: =Engine!T8 -> 2026 | D6: =Engine!AA8 -> 1265000 | E6: =D6+Engine!AB8-(Engine!AB8-Engine!AC8)*Inputs!$B$9 -> 1615790.8 | F6: =Engine!I8 -> 1265000 | G6: =-F6*Inputs!$B$6 -> -379500 | H6: =F6+G6 -> 885500 | I6: =Engine!K8 -> 837401.25 | J6: =-(I6-Engine!L8)*Inputs!$B$9 -> -18889.325 | K6: =H6+I6+J6 -> 1704011.9 | L6: =E6-K6 -> -88221.1 | M6: =IF(K6=0,0,L6/K6) -> -0.051772584
A7: 2 | B7: =Engine!S9 -> 59 | C7: =Engine!T9 -> 2027 | D7: =Engine!AA9 -> 1391500 | E7: =D7+Engine!AB9-(Engine!AB9-Engine!AC9)*Inputs!$B$9 -> 1767520.5 | F7: =Engine!I9 -> 1391500 | G7: =-F7*Inputs!$B$6 -> -417450 | H7: =F7+G7 -> 974050 | I7: =Engine!K9 -> 916954.37 | J7: =-(I7-Engine!L9)*Inputs!$B$9 -> -39573.136 | K7: =H7+I7+J7 -> 1851431.2 | L7: =E7-K7 -> -83910.705 | M7: =IF(K7=0,0,L7/K7) -> -0.045322075
A8: 3 | B8: =Engine!S10 -> 60 | C8: =Engine!T10 -> 2028 | D8: =Engine!AA10 -> 1530650 | E8: =D8+Engine!AB10-(Engine!AB10-Engine!AC10)*Inputs!$B$9 -> 1934297.1 | F8: =Engine!I10 -> 1530650 | G8: =-F8*Inputs!$B$6 -> -459195 | H8: =F8+G8 -> 1071455 | I8: =Engine!K10 -> 1004065 | J8: =-(I8-Engine!L10)*Inputs!$B$9 -> -62221.909 | K8: =H8+I8+J8 -> 2013298.1 | L8: =E8-K8 -> -79001.071 | M8: =IF(K8=0,0,L8/K8) -> -0.039239629
A9: 4 | B9: =Engine!S11 -> 61 | C9: =Engine!T11 -> 2029 | D9: =Engine!AA11 -> 1683715 | E9: =D9+Engine!AB11-(Engine!AB11-Engine!AC11)*Inputs!$B$9 -> 2117613.1 | F9: =Engine!I11 -> 1683715 | G9: =-F9*Inputs!$B$6 -> -505114.5 | H9: =F9+G9 -> 1178600.5 | I9: =Engine!K11 -> 1099451.2 | J9: =-(I9-Engine!L11)*Inputs!$B$9 -> -87022.315 | K9: =H9+I9+J9 -> 2191029.4 | L9: =E9-K9 -> -73416.298 | M9: =IF(K9=0,0,L9/K9) -> -0.033507674
A10: 5 | B10: =Engine!S12 -> 62 | C10: =Engine!T12 -> 2030 | D10: =Engine!AA12 -> 1852086.5 | E10: =D10+Engine!AB12-(Engine!AB12-Engine!AC12)*Inputs!$B$9 -> 2319109.5 | F10: =Engine!I12 -> 1852086.5 | G10: =-F10*Inputs!$B$6 -> -555625.95 | H10: =F10+G10 -> 1296460.6 | I10: =Engine!K12 -> 1203899.1 | J10: =-(I10-Engine!L12)*Inputs!$B$9 -> -114178.76 | K10: =H10+I10+J10 -> 2386180.9 | L10: =E10-K10 -> -67071.374 | M10: =IF(K10=0,0,L10/K10) -> -0.028108252
A11: 6 | B11: =Engine!S13 -> 63 | C11: =Engine!T13 -> 2031 | D11: =Engine!AA13 -> 2037295.1 | E11: =D11+Engine!AB13-(Engine!AB13-Engine!AC13)*Inputs!$B$9 -> 2540589.9 | F11: =Engine!I13 -> 2037295.1 | G11: =-F11*Inputs!$B$6 -> -611188.55 | H11: =F11+G11 -> 1426106.6 | I11: =Engine!K13 -> 1318269.5 | J11: =-(I11-Engine!L13)*Inputs!$B$9 -> -143915.07 | K11: =H11+I11+J11 -> 2600461 | L11: =E11-K11 -> -59871.125 | M11: =IF(K11=0,0,L11/K11) -> -0.023023273
A12: 7 | B12: =Engine!S14 -> 64 | C12: =Engine!T14 -> 2032 | D12: =Engine!AA14 -> 2241024.7 | E12: =D12+Engine!AB14-(Engine!AB14-Engine!AC14)*Inputs!$B$9 -> 2784037 | F12: =Engine!I14 -> 2241024.7 | G12: =-F12*Inputs!$B$6 -> -672307.4 | H12: =F12+G12 -> 1568717.3 | I12: =Engine!K14 -> 1443505.1 | J12: =-(I12-Engine!L14)*Inputs!$B$9 -> -176476.32 | K12: =H12+I12+J12 -> 2835746 | L12: =E12-K12 -> -51709.039 | M12: =IF(K12=0,0,L12/K12) -> -0.018234721
A13: 8 | B13: =Engine!S15 -> 65 | C13: =Engine!T15 -> 2033 | D13: =Engine!AA15 -> 2465127.1 | E13: =D13+Engine!AB15-(Engine!AB15-Engine!AC15)*Inputs!$B$9 -> 3051630.2 | F13: =Engine!I15 -> 2465127.1 | G13: =-F13*Inputs!$B$6 -> -739538.14 | H13: =F13+G13 -> 1725589 | I13: =Engine!K15 -> 1580638.1 | J13: =-(I13-Engine!L15)*Inputs!$B$9 -> -212130.9 | K13: =H13+I13+J13 -> 3094096.2 | L13: =E13-K13 -> -42465.961 | M13: =IF(K13=0,0,L13/K13) -> -0.013724835
A14: 9 | B14: =Engine!S16 -> 66 | C14: =Engine!T16 -> 2034 | D14: =Engine!AA16 -> 2711639.8 | E14: =D14+Engine!AB16-(Engine!AB16-Engine!AC16)*Inputs!$B$9 -> 3345765.3 | F14: =Engine!I16 -> 2711639.8 | G14: =-F14*Inputs!$B$6 -> -813491.95 | H14: =F14+G14 -> 1898147.9 | I14: =Engine!K16 -> 1730798.7 | J14: =-(I14-Engine!L16)*Inputs!$B$9 -> -251172.66 | K14: =H14+I14+J14 -> 3377773.9 | L14: =E14-K14 -> -32008.636 | M14: =IF(K14=0,0,L14/K14) -> -0.0094762518
A15: 10 | B15: =Engine!S17 -> 67 | C15: =Engine!T17 -> 2035 | D15: =Engine!AA17 -> 2982803.8 | E15: =D15+Engine!AB17-(Engine!AB17-Engine!AC17)*Inputs!$B$9 -> 3669075.8 | F15: =Engine!I17 -> 2982803.8 | G15: =-F15*Inputs!$B$6 -> -894841.15 | H15: =F15+G15 -> 2087962.7 | I15: =Engine!K17 -> 1895224.6 | J15: =-(I15-Engine!L17)*Inputs!$B$9 -> -293923.39 | K15: =H15+I15+J15 -> 3689263.9 | L15: =E15-K15 -> -20188.097 | M15: =IF(K15=0,0,L15/K15) -> -0.0054721206
A16: 11 | B16: =Engine!S18 -> 68 | C16: =Engine!T18 -> 2036 | D16: =Engine!AA18 -> 3281084.2 | E16: =D16+Engine!AB18-(Engine!AB18-Engine!AC18)*Inputs!$B$9 -> 4024456.6 | F16: =Engine!I18 -> 3281084.2 | G16: =-F16*Inputs!$B$6 -> -984325.26 | H16: =F16+G16 -> 2296758.9 | I16: =Engine!K18 -> 2075270.9 | J16: =-(I16-Engine!L18)*Inputs!$B$9 -> -340735.43 | K16: =H16+I16+J16 -> 4031294.4 | L16: =E16-K16 -> -6837.8604 | M16: =IF(K16=0,0,L16/K16) -> -0.0016961947
... A45: 40 | B45: =Engine!S47 -> 97 | C45: =Engine!T47 -> 2065 | D45: =Engine!AA47 -> 52048144 | E45: =D45+Engine!AB47-(Engine!AB47-Engine!AC47)*Inputs!$B$9 -> 61281633 | F45: =Engine!I47 -> 52048144 | G45: =-F45*Inputs!$B$6 -> -15614443 | H45: =F45+G45 -> 36433701 | I45: =Engine!K47 -> 28845911 | J45: =-(I45-Engine!L47)*Inputs!$B$9 -> -7301101.7 | K45: =H45+I45+J45 -> 57978510 | L45: =E45-K45 -> 3303123.8 | M45: =IF(K45=0,0,L45/K45) -> 0.056971521

Sheet Inputs
A1: Inputs (blue on yellow = change me)
A3: Pre-tax IRA balance today | B3: 1150000 | C3: Joe: own IRA ~$948k + Keli inherited ~$202k (IBKR, Sept 2026). CPA example used $100,000.
A4: Annual return, all accounts | B4: 0.1 | C4: Same investments in IRA, Roth and taxable, as the CPA assumed. 10% = long-run S&P; CPA used 7%.
A5: Default tax rate on conversions (combined federal + NJ) | B5: 0.38 | C5: Used for every year of the schedule below unless you overwrite a year. CPA used 25%.
A6: Tax rate on IRA withdrawals later (combined) | B6: 0.3 | C6: Rate you expect on IRA money when it eventually comes out (RMDs at 75, or earlier draws). Joe retired, single, NJ: ~24% fed + 6.4% NJ. CPA used 25%.
A7: Outside cash pool available for tax | B7: =B3*B5*1.75 -> 764750 | C7: Defaults to 1.75 x the tax on an all-at-once conversion (IRA x default rate x 1.75), enough to cover the slower schedules, which pay more total tax because the IRA keeps growing. Set it to the tax on a lump conversion (IRA x rate) to match the CPA exactly; the comparison between strategies does not change with the pool size as long as no strategy runs short (the Engine flags SHORT). Overwrite with the cash you actually have outside the IRA.
A8: Taxable-account drag (share of return lost to annual tax) | B8: 0.05 | C8: An S&P index fund pays ~1.3% dividends taxed ~30%, so about 4-5% of a 10% return is lost each year. CPA used 25% (return x 0.75). Enter 0.25 to match him.
A9: Capital-gains tax on pool gains at liquidation (combined) | B9: 0.26 | C9: Deferred tax on the taxable pool's unrealized gains when it is finally sold: 20% federal + 3.8% NIIT + NJ ~6.4% at Joe's level. CPA assumed 0. Enter 0 to match him.
A10: Horizon (years) for the Compare tab | B10: 10 | C10: Any whole number 1 to 40. "Update years" here and every tab follows.
A11: Start year | B11: 2026 | C11: Calendar year of the first conversion.
A12: Age at start | B12: 57 | C12: Used for the age column and the RMD tab (RMDs begin at 75).
A13: Heirs' tax rate on an inherited IRA (combined) | B13: 0.35 | C13: Kids must empty an inherited traditional IRA within 10 years and pay ordinary tax; an inherited Roth is tax-free. Rough guess for a working adult child in a high-tax state.
A14: RMD divisor at age 75 (IRS Uniform Lifetime Table) | B14: 24.6 | C14: IRS Publication 590-B, Table III, age 75 = 24.6. Source: irs.gov.
A15: Which conversion-rate schedule to use (A or B) | B15: A | C15: Type A or B. Schedule B is pre-filled with Joe's bracket-managed rates; schedule A is flat at B5. The Engine, Compare and every other tab follow whichever is selected.
A17: Conversion tax rate by year (overwrite any year)
A18: Year # | B18: Calendar | C18: Schedule A: flat (default = B5) | D18: Schedule B: bracket-managed (Joe)
A19: 1 | B19: =Inputs!$B$11+1-1 -> 2026 | C19: =Inputs!$B$5 -> 0.38 | D19: 0.38
A20: 2 | B20: =Inputs!$B$11+2-1 -> 2027 | C20: =Inputs!$B$5 -> 0.38 | D20: 0.38
A21: 3 | B21: =Inputs!$B$11+3-1 -> 2028 | C21: =Inputs!$B$5 -> 0.38 | D21: 0.38
A22: 4 | B22: =Inputs!$B$11+4-1 -> 2029 | C22: =Inputs!$B$5 -> 0.38 | D22: 0.42
A23: 5 | B23: =Inputs!$B$11+5-1 -> 2030 | C23: =Inputs!$B$5 -> 0.38 | D23: 0.42
A24: 6 | B24: =Inputs!$B$11+6-1 -> 2031 | C24: =Inputs!$B$5 -> 0.38 | D24: 0.3
A25: 7 | B25: =Inputs!$B$11+7-1 -> 2032 | C25: =Inputs!$B$5 -> 0.38 | D25: 0.3
A26: 8 | B26: =Inputs!$B$11+8-1 -> 2033 | C26: =Inputs!$B$5 -> 0.38 | D26: 0.3
A27: 9 | B27: =Inputs!$B$11+9-1 -> 2034 | C27: =Inputs!$B$5 -> 0.38 | D27: 0.3
A28: 10 | B28: =Inputs!$B$11+10-1 -> 2035 | C28: =Inputs!$B$5 -> 0.38 | D28: 0.3
A29: 11 | B29: =Inputs!$B$11+11-1 -> 2036 | C29: =Inputs!$B$5 -> 0.38 | D29: 0.3
A30: 12 | B30: =Inputs!$B$11+12-1 -> 2037 | C30: =Inputs!$B$5 -> 0.38 | D30: 0.3
A31: 13 | B31: =Inputs!$B$11+13-1 -> 2038 | C31: =Inputs!$B$5 -> 0.38 | D31: 0.3
A32: 14 | B32: =Inputs!$B$11+14-1 -> 2039 | C32: =Inputs!$B$5 -> 0.38 | D32: 0.3
A33: 15 | B33: =Inputs!$B$11+15-1 -> 2040 | C33: =Inputs!$B$5 -> 0.38 | D33: 0.3
A34: 16 | B34: =Inputs!$B$11+16-1 -> 2041 | C34: =Inputs!$B$5 -> 0.38 | D34: 0.3
A35: 17 | B35: =Inputs!$B$11+17-1 -> 2042 | C35: =Inputs!$B$5 -> 0.38 | D35: 0.3
A36: 18 | B36: =Inputs!$B$11+18-1 -> 2043 | C36: =Inputs!$B$5 -> 0.38 | D36: 0.3
A37: 19 | B37: =Inputs!$B$11+19-1 -> 2044 | C37: =Inputs!$B$5 -> 0.38 | D37: 0.3
A38: 20 | B38: =Inputs!$B$11+20-1 -> 2045 | C38: =Inputs!$B$5 -> 0.38 | D38: 0.3
A39: 21 | B39: =Inputs!$B$11+21-1 -> 2046 | C39: =Inputs!$B$5 -> 0.38 | D39: 0.3
A40: 22 | B40: =Inputs!$B$11+22-1 -> 2047 | C40: =Inputs!$B$5 -> 0.38 | D40: 0.3
A41: 23 | B41: =Inputs!$B$11+23-1 -> 2048 | C41: =Inputs!$B$5 -> 0.38 | D41: 0.3
A42: 24 | B42: =Inputs!$B$11+24-1 -> 2049 | C42: =Inputs!$B$5 -> 0.38 | D42: 0.3
A43: 25 | B43: =Inputs!$B$11+25-1 -> 2050 | C43: =Inputs!$B$5 -> 0.38 | D43: 0.3
A44: 26 | B44: =Inputs!$B$11+26-1 -> 2051 | C44: =Inputs!$B$5 -> 0.38 | D44: 0.3
A45: 27 | B45: =Inputs!$B$11+27-1 -> 2052 | C45: =Inputs!$B$5 -> 0.38 | D45: 0.3
A46: 28 | B46: =Inputs!$B$11+28-1 -> 2053 | C46: =Inputs!$B$5 -> 0.38 | D46: 0.3
A47: 29 | B47: =Inputs!$B$11+29-1 -> 2054 | C47: =Inputs!$B$5 -> 0.38 | D47: 0.3
A48: 30 | B48: =Inputs!$B$11+30-1 -> 2055 | C48: =Inputs!$B$5 -> 0.38 | D48: 0.3
A49: 31 | B49: =Inputs!$B$11+31-1 -> 2056 | C49: =Inputs!$B$5 -> 0.38 | D49: 0.3
A50: 32 | B50: =Inputs!$B$11+32-1 -> 2057 | C50: =Inputs!$B$5 -> 0.38 | D50: 0.3
A51: 33 | B51: =Inputs!$B$11+33-1 -> 2058 | C51: =Inputs!$B$5 -> 0.38 | D51: 0.3
A52: 34 | B52: =Inputs!$B$11+34-1 -> 2059 | C52: =Inputs!$B$5 -> 0.38 | D52: 0.3
A53: 35 | B53: =Inputs!$B$11+35-1 -> 2060 | C53: =Inputs!$B$5 -> 0.38 | D53: 0.3
A54: 36 | B54: =Inputs!$B$11+36-1 -> 2061 | C54: =Inputs!$B$5 -> 0.38 | D54: 0.3
A55: 37 | B55: =Inputs!$B$11+37-1 -> 2062 | C55: =Inputs!$B$5 -> 0.38 | D55: 0.3
A56: 38 | B56: =Inputs!$B$11+38-1 -> 2063 | C56: =Inputs!$B$5 -> 0.38 | D56: 0.3
A57: 39 | B57: =Inputs!$B$11+39-1 -> 2064 | C57: =Inputs!$B$5 -> 0.38 | D57: 0.3
A58: 40 | B58: =Inputs!$B$11+40-1 -> 2065 | C58: =Inputs!$B$5 -> 0.38 | D58: 0.3
A60: Legend: blue text on yellow = input you can change. Green = pulled from another tab. Black = formula. Illustrative, not tax advice.

Sheet Engine
A1: Engine: six strategies side by side. Each block: conversion years N in the yellow cell (0 = never convert, 1 = all at once). Rows = years 0 to 40.
A2: After-tax wealth = Roth + IRA x (1 - later rate) + Pool - (Pool - Pool basis) x liquidation rate. Pool pays every conversion tax; a red "SHORT" means the pool could not cover it.
A4: Never convert | E4: Conversion years N: | F4: 0 | R4: All at once | V4: Conversion years N: | W4: 1 | AI4: Over 3 years | AM4: Conversion years N: | AN4: 3 | AZ4: Over 5 years | BD4: Conversion years N: | BE4: 5 | BQ4: Over 8 years | BU4: Conversion years N: | BV4: 8 | CH4: Over 10 years | CL4: Conversion years N: | CM4: 10
A6: Yr | B6: Age | C6: Calendar | D6: Rate | E6: IRA begin | F6: Converted | G6: Tax paid | H6: Pool after tax | I6: IRA end | J6: Roth end | K6: Pool end | L6: Pool basis | M6: After-tax wealth | N6: Roth share | O6: Beats never? | P6: Check | R6: Yr | S6: Age | T6: Calendar | U6: Rate | V6: IRA begin | W6: Converted | X6: Tax paid | Y6: Pool after tax | Z6: IRA end | AA6: Roth end | AB6: Pool end | AC6: Pool basis | AD6: After-tax wealth | AE6: Roth share | AF6: Beats never? | AG6: Check | AI6: Yr | AJ6: Age | AK6: Calendar | AL6: Rate | AM6: IRA begin | AN6: Converted | AO6: Tax paid | AP6: Pool after tax | AQ6: IRA end | AR6: Roth end | AS6: Pool end | AT6: Pool basis | AU6: After-tax wealth | AV6: Roth share | AW6: Beats never? | AX6: Check | AZ6: Yr | BA6: Age | BB6: Calendar | BC6: Rate | BD6: IRA begin | BE6: Converted | BF6: Tax paid | BG6: Pool after tax | BH6: IRA end | BI6: Roth end | BJ6: Pool end | BK6: Pool basis | BL6: After-tax wealth | BM6: Roth share | BN6: Beats never? | BO6: Check | BQ6: Yr | BR6: Age | BS6: Calendar | BT6: Rate | BU6: IRA begin | BV6: Converted | BW6: Tax paid | BX6: Pool after tax | BY6: IRA end | BZ6: Roth end | CA6: Pool end | CB6: Pool basis | CC6: After-tax wealth | CD6: Roth share | CE6: Beats never? | CF6: Check | CH6: Yr | CI6: Age | CJ6: Calendar | CK6: Rate | CL6: IRA begin | CM6: Converted | CN6: Tax paid | CO6: Pool after tax | CP6: IRA end | CQ6: Roth end | CR6: Pool end | CS6: Pool basis | CT6: After-tax wealth | CU6: Roth share | CV6: Beats never? | CW6: Check
A7: 0 | B7: =Inputs!$B$12 -> 57 | C7: =Inputs!$B$11-1 -> 2025 | I7: =Inputs!$B$3 -> 1150000 | J7: 0 | K7: =Inputs!$B$7 -> 764750 | L7: =Inputs!$B$7 -> 764750 | M7: =J7+I7*(1-Inputs!$B$6)+K7-(K7-L7)*Inputs!$B$9 -> 1569750 | N7: =IF(M7=0,0,J7/(J7+I7+K7)) -> 0 | R7: 0 | S7: =Inputs!$B$12 -> 57 | T7: =Inputs!$B$11-1 -> 2025 | Z7: =Inputs!$B$3 -> 1150000 | AA7: 0 | AB7: =Inputs!$B$7 -> 764750 | AC7: =Inputs!$B$7 -> 764750 | AD7: =AA7+Z7*(1-Inputs!$B$6)+AB7-(AB7-AC7)*Inputs!$B$9 -> 1569750 | AE7: =IF(AD7=0,0,AA7/(AA7+Z7+AB7)) -> 0 | AI7: 0 | AJ7: =Inputs!$B$12 -> 57 | AK7: =Inputs!$B$11-1 -> 2025 | AQ7: =Inputs!$B$3 -> 1150000 | AR7: 0 | AS7: =Inputs!$B$7 -> 764750 | AT7: =Inputs!$B$7 -> 764750 | AU7: =AR7+AQ7*(1-Inputs!$B$6)+AS7-(AS7-AT7)*Inputs!$B$9 -> 1569750 | AV7: =IF(AU7=0,0,AR7/(AR7+AQ7+AS7)) -> 0 | AZ7: 0 | BA7: =Inputs!$B$12 -> 57 | BB7: =Inputs!$B$11-1 -> 2025 | BH7: =Inputs!$B$3 -> 1150000 | BI7: 0 | BJ7: =Inputs!$B$7 -> 764750 | BK7: =Inputs!$B$7 -> 764750 | BL7: =BI7+BH7*(1-Inputs!$B$6)+BJ7-(BJ7-BK7)*Inputs!$B$9 -> 1569750 | BM7: =IF(BL7=0,0,BI7/(BI7+BH7+BJ7)) -> 0 | BQ7: 0 | BR7: =Inputs!$B$12 -> 57 | BS7: =Inputs!$B$11-1 -> 2025 | BY7: =Inputs!$B$3 -> 1150000 | BZ7: 0 | CA7: =Inputs!$B$7 -> 764750 | CB7: =Inputs!$B$7 -> 764750 | CC7: =BZ7+BY7*(1-Inputs!$B$6)+CA7-(CA7-CB7)*Inputs!$B$9 -> 1569750 | CD7: =IF(CC7=0,0,BZ7/(BZ7+BY7+CA7)) -> 0 | CH7: 0 | CI7: =Inputs!$B$12 -> 57 | CJ7: =Inputs!$B$11-1 -> 2025 | CP7: =Inputs!$B$3 -> 1150000 | CQ7: 0 | CR7: =Inputs!$B$7 -> 764750 | CS7: =Inputs!$B$7 -> 764750 | CT7: =CQ7+CP7*(1-Inputs!$B$6)+CR7-(CR7-CS7)*Inputs!$B$9 -> 1569750 | CU7: =IF(CT7=0,0,CQ7/(CQ7+CP7+CR7)) -> 0
A8: 1 | B8: =B7+1 -> 58 | C8: =C7+1 -> 2026 | D8: =IF(Inputs!$B$15="B",Inputs!$D$19,Inputs!$C$19) -> 0.38 | E8: =I7 -> 1150000 | F8: =IF(A8<=$F$4,E8/($F$4-A8+1),0) -> 0 | G8: =F8*D8 -> 0 | H8: =K7-G8 -> 764750 | I8: =(E8-F8)*(1+Inputs!$B$4) -> 1265000 | J8: =(J7+F8)*(1+Inputs!$B$4) -> 0 | K8: =H8*(1+Inputs!$B$4*(1-Inputs!$B$8)) -> 837401.25 | L8: =IF(K7<=0,0,L7*H8/K7) -> 764750 | M8: =J8+I8*(1-Inputs!$B$6)+K8-(K8-L8)*Inputs!$B$9 -> 1704011.9 | N8: =J8/(J8+I8+K8) -> 0 | O8: =IF(M8>M8,1,0) -> 0 | P8: =IF(H8<0,"SHORT","ok") -> ok | R8: 1 | S8: =S7+1 -> 58 | T8: =T7+1 -> 2026 | U8: =IF(Inputs!$B$15="B",Inputs!$D$19,Inputs!$C$19) -> 0.38 | V8: =Z7 -> 1150000 | W8: =IF(R8<=$W$4,V8/($W$4-R8+1),0) -> 1150000 | X8: =W8*U8 -> 437000 | Y8: =AB7-X8 -> 327750 | Z8: =(V8-W8)*(1+Inputs!$B$4) -> 0 | AA8: =(AA7+W8)*(1+Inputs!$B$4) -> 1265000 | AB8: =Y8*(1+Inputs!$B$4*(1-Inputs!$B$8)) -> 358886.25 | AC8: =IF(AB7<=0,0,AC7*Y8/AB7) -> 327750 | AD8: =AA8+Z8*(1-Inputs!$B$6)+AB8-(AB8-AC8)*Inputs!$B$9 -> 1615790.8 | AE8: =AA8/(AA8+Z8+AB8) -> 0.77899545 | AF8: =IF(AD8>M8,1,0) -> 0 | AG8: =IF(Y8<0,"SHORT","ok") -> ok | AI8: 1 | AJ8: =AJ7+1 -> 58 | AK8: =AK7+1 -> 2026 | AL8: =IF(Inputs!$B$15="B",Inputs!$D$19,Inputs!$C$19) -> 0.38 | AM8: =AQ7 -> 1150000 | AN8: =IF(AI8<=$AN$4,AM8/($AN$4-AI8+1),0) -> 383333.33 | AO8: =AN8*AL8 -> 145666.67 | AP8: =AS7-AO8 -> 619083.33 | AQ8: =(AM8-AN8)*(1+Inputs!$B$4) -> 843333.33 | AR8: =(AR7+AN8)*(1+Inputs!$B$4) -> 421666.67 | AS8: =AP8*(1+Inputs!$B$4*(1-Inputs!$B$8)) -> 677896.25 | AT8: =IF(AS7<=0,0,AT7*AP8/AS7) -> 619083.33 | AU8: =AR8+AQ8*(1-Inputs!$B$6)+AS8-(AS8-AT8)*Inputs!$B$9 -> 1674604.9 | AV8: =AR8/(AR8+AQ8+AS8) -> 0.21702995 | AW8: =IF(AU8>M8,1,0) -> 0 | AX8: =IF(AP8<0,"SHORT","ok") -> ok | AZ8: 1 | BA8: =BA7+1 -> 58 | BB8: =BB7+1 -> 2026 | BC8: =IF(Inputs!$B$15="B",Inputs!$D$19,Inputs!$C$19) -> 0.38 | BD8: =BH7 -> 1150000 | BE8: =IF(AZ8<=$BE$4,BD8/($BE$4-AZ8+1),0) -> 230000 | BF8: =BE8*BC8 -> 87400 | BG8: =BJ7-BF8 -> 677350 | BH8: =(BD8-BE8)*(1+Inputs!$B$4) -> 1012000 | BI8: =(BI7+BE8)*(1+Inputs!$B$4) -> 253000 | BJ8: =BG8*(1+Inputs!$B$4*(1-Inputs!$B$8)) -> 741698.25 | BK8: =IF(BJ7<=0,0,BK7*BG8/BJ7) -> 677350 | BL8: =BI8+BH8*(1-Inputs!$B$6)+BJ8-(BJ8-BK8)*Inputs!$B$9 -> 1686367.7 | BM8: =BI8/(BI8+BH8+BJ8) -> 0.12607775 | BN8: =IF(BL8>M8,1,0) -> 0 | BO8: =IF(BG8<0,"SHORT","ok") -> ok | BQ8: 1 | BR8: =BR7+1 -> 58 | BS8: =BS7+1 -> 2026 | BT8: =IF(Inputs!$B$15="B",Inputs!$D$19,Inputs!$C$19) -> 0.38 | BU8: =BY7 -> 1150000 | BV8: =IF(BQ8<=$BV$4,BU8/($BV$4-BQ8+1),0) -> 143750 | BW8: =BV8*BT8 -> 54625 | BX8: =CA7-BW8 -> 710125 | BY8: =(BU8-BV8)*(1+Inputs!$B$4) -> 1106875 | BZ8: =(BZ7+BV8)*(1+Inputs!$B$4) -> 158125 | CA8: =BX8*(1+Inputs!$B$4*(1-Inputs!$B$8)) -> 777586.88 | CB8: =IF(CA7<=0,0,CB7*BX8/CA7) -> 710125 | CC8: =BZ8+BY8*(1-Inputs!$B$6)+CA8-(CA8-CB8)*Inputs!$B$9 -> 1692984.3 | CD8: =BZ8/(BZ8+BY8+CA8) -> 0.077414088 | CE8: =IF(CC8>M8,1,0) -> 0 | CF8: =IF(BX8<0,"SHORT","ok") -> ok | CH8: 1 | CI8: =CI7+1 -> 58 | CJ8: =CJ7+1 -> 2026 | CK8: =IF(Inputs!$B$15="B",Inputs!$D$19,Inputs!$C$19) -> 0.38 | CL8: =CP7 -> 1150000 | CM8: =IF(CH8<=$CM$4,CL8/($CM$4-CH8+1),0) -> 115000 | CN8: =CM8*CK8 -> 43700 | CO8: =CR7-CN8 -> 721050 | CP8: =(CL8-CM8)*(1+Inputs!$B$4) -> 1138500 | CQ8: =(CQ7+CM8)*(1+Inputs!$B$4) -> 126500 | CR8: =CO8*(1+Inputs!$B$4*(1-Inputs!$B$8)) -> 789549.75 | CS8: =IF(CR7<=0,0,CS7*CO8/CR7) -> 721050 | CT8: =CQ8+CP8*(1-Inputs!$B$6)+CR8-(CR8-CS8)*Inputs!$B$9 -> 1695189.8 | CU8: =CQ8/(CQ8+CP8+CR8) -> 0.061570668 | CV8: =IF(CT8>M8,1,0) -> 0 | CW8: =IF(CO8<0,"SHORT","ok") -> ok
A9: 2 | B9: =B8+1 -> 59 | C9: =C8+1 -> 2027 | D9: =IF(Inputs!$B$15="B",Inputs!$D$20,Inputs!$C$20) -> 0.38 | E9: =I8 -> 1265000 | F9: =IF(A9<=$F$4,E9/($F$4-A9+1),0) -> 0 | G9: =F9*D9 -> 0 | H9: =K8-G9 -> 837401.25 | I9: =(E9-F9)*(1+Inputs!$B$4) -> 1391500 | J9: =(J8+F9)*(1+Inputs!$B$4) -> 0 | K9: =H9*(1+Inputs!$B$4*(1-Inputs!$B$8)) -> 916954.37 | L9: =IF(K8<=0,0,L8*H9/K8) -> 764750 | M9: =J9+I9*(1-Inputs!$B$6)+K9-(K9-L9)*Inputs!$B$9 -> 1851431.2 | N9: =J9/(J9+I9+K9) -> 0 | O9: =IF(M9>M9,1,0) -> 0 | P9: =IF(H9<0,"SHORT","ok") -> ok | R9: 2 | S9: =S8+1 -> 59 | T9: =T8+1 -> 2027 | U9: =IF(Inputs!$B$15="B",Inputs!$D$20,Inputs!$C$20) -> 0.38 | V9: =Z8 -> 0 | W9: =IF(R9<=$W$4,V9/($W$4-R9+1),0) -> 0 | X9: =W9*U9 -> 0 | Y9: =AB8-X9 -> 358886.25 | Z9: =(V9-W9)*(1+Inputs!$B$4) -> 0 | AA9: =(AA8+W9)*(1+Inputs!$B$4) -> 1391500 | AB9: =Y9*(1+Inputs!$B$4*(1-Inputs!$B$8)) -> 392980.44 | AC9: =IF(AB8<=0,0,AC8*Y9/AB8) -> 327750 | AD9: =AA9+Z9*(1-Inputs!$B$6)+AB9-(AB9-AC9)*Inputs!$B$9 -> 1767520.5 | AE9: =AA9/(AA9+Z9+AB9) -> 0.77977879 | AF9: =IF(AD9>M9,1,0) -> 0 | AG9: =IF(Y9<0,"SHORT","ok") -> ok | AI9: 2 | AJ9: =AJ8+1 -> 59 | AK9: =AK8+1 -> 2027 | AL9: =IF(Inputs!$B$15="B",Inputs!$D$20,Inputs!$C$20) -> 0.38 | AM9: =AQ8 -> 843333.33 | AN9: =IF(AI9<=$AN$4,AM9/($AN$4-AI9+1),0) -> 421666.67 | AO9: =AN9*AL9 -> 160233.33 | AP9: =AS8-AO9 -> 517662.92 | AQ9: =(AM9-AN9)*(1+Inputs!$B$4) -> 463833.33 | AR9: =(AR8+AN9)*(1+Inputs!$B$4) -> 927666.67 | AS9: =AP9*(1+Inputs!$B$4*(1-Inputs!$B$8)) -> 566840.89 | AT9: =IF(AS8<=0,0,AT8*AP9/AS8) -> 472751.52 | AU9: =AR9+AQ9*(1-Inputs!$B$6)+AS9-(AS9-AT9)*Inputs!$B$9 -> 1794727.7 | AV9: =AR9/(AR9+AQ9+AS9) -> 0.4737003 | AW9: =IF(AU9>M9,1,0) -> 0 | AX9: =IF(AP9<0,"SHORT","ok") -> ok | AZ9: 2 | BA9: =BA8+1 -> 59 | BB9: =BB8+1 -> 2027 | BC9: =IF(Inputs!$B$15="B",Inputs!$D$20,Inputs!$C$20) -> 0.38 | BD9: =BH8 -> 1012000 | BE9: =IF(AZ9<=$BE$4,BD9/($BE$4-AZ9+1),0) -> 253000 | BF9: =BE9*BC9 -> 96140 | BG9: =BJ8-BF9 -> 645558.25 | BH9: =(BD9-BE9)*(1+Inputs!$B$4) -> 834900 | BI9: =(BI8+BE9)*(1+Inputs!$B$4) -> 556600 | BJ9: =BG9*(1+Inputs!$B$4*(1-Inputs!$B$8)) -> 706886.28 | BK9: =IF(BJ8<=0,0,BK8*BG9/BJ8) -> 589550.91 | BL9: =BI9+BH9*(1-Inputs!$B$6)+BJ9-(BJ9-BK9)*Inputs!$B$9 -> 1817409.1 | BM9: =BI9/(BI9+BH9+BJ9) -> 0.26525145 | BN9: =IF(BL9>M9,1,0) -> 0 | BO9: =IF(BG9<0,"SHORT","ok") -> ok | BQ9: 2 | BR9: =BR8+1 -> 59 | BS9: =BS8+1 -> 2027 | BT9: =IF(Inputs!$B$15="B",Inputs!$D$20,Inputs!$C$20) -> 0.38 | BU9: =BY8 -> 1106875 | BV9: =IF(BQ9<=$BV$4,BU9/($BV$4-BQ9+1),0) -> 158125 | BW9: =BV9*BT9 -> 60087.5 | BX9: =CA8-BW9 -> 717499.38 | BY9: =(BU9-BV9)*(1+Inputs!$B$4) -> 1043625 | BZ9: =(BZ8+BV9)*(1+Inputs!$B$4) -> 347875 | CA9: =BX9*(1+Inputs!$B$4*(1-Inputs!$B$8)) -> 785661.82 | CB9: =IF(CA8<=0,0,CB8*BX9/CA8) -> 655250.57 | CC9: =BZ9+BY9*(1-Inputs!$B$6)+CA9-(CA9-CB9)*Inputs!$B$9 -> 1830167.4 | CD9: =BZ9/(BZ9+BY9+CA9) -> 0.15978371 | CE9: =IF(CC9>M9,1,0) -> 0 | CF9: =IF(BX9<0,"SHORT","ok") -> ok | CH9: 2 | CI9: =CI8+1 -> 59 | CJ9: =CJ8+1 -> 2027 | CK9: =IF(Inputs!$B$15="B",Inputs!$D$20,Inputs!$C$20) -> 0.38 | CL9: =CP8 -> 1138500 | CM9: =IF(CH9<=$CM$4,CL9/($CM$4-CH9+1),0) -> 126500 | CN9: =CM9*CK9 -> 48070 | CO9: =CR8-CN9 -> 741479.75 | CP9: =(CL9-CM9)*(1+Inputs!$B$4) -> 1113200 | CQ9: =(CQ8+CM9)*(1+Inputs!$B$4) -> 278300 | CR9: =CO9*(1+Inputs!$B$4*(1-Inputs!$B$8)) -> 811920.33 | CS9: =IF(CR8<=0,0,CS8*CO9/CR8) -> 677150.46 | CT9: =CQ9+CP9*(1-Inputs!$B$6)+CR9-(CR9-CS9)*Inputs!$B$9 -> 1834420.2 | CU9: =CQ9/(CQ9+CP9+CR9) -> 0.12630364 | CV9: =IF(CT9>M9,1,0) -> 0 | CW9: =IF(CO9<0,"SHORT","ok") -> ok
A10: 3 | B10: =B9+1 -> 60 | C10: =C9+1 -> 2028 | D10: =IF(Inputs!$B$15="B",Inputs!$D$21,Inputs!$C$21) -> 0.38 | E10: =I9 -> 1391500 | F10: =IF(A10<=$F$4,E10/($F$4-A10+1),0) -> 0 | G10: =F10*D10 -> 0 | H10: =K9-G10 -> 916954.37 | I10: =(E10-F10)*(1+Inputs!$B$4) -> 1530650 | J10: =(J9+F10)*(1+Inputs!$B$4) -> 0 | K10: =H10*(1+Inputs!$B$4*(1-Inputs!$B$8)) -> 1004065 | L10: =IF(K9<=0,0,L9*H10/K9) -> 764750 | M10: =J10+I10*(1-Inputs!$B$6)+K10-(K10-L10)*Inputs!$B$9 -> 2013298.1 | N10: =J10/(J10+I10+K10) -> 0 | O10: =IF(M10>M10,1,0) -> 0 | P10: =IF(H10<0,"SHORT","ok") -> ok | R10: 3 | S10: =S9+1 -> 60 | T10: =T9+1 -> 2028 | U10: =IF(Inputs!$B$15="B",Inputs!$D$21,Inputs!$C$21) -> 0.38 | V10: =Z9 -> 0 | W10: =IF(R10<=$W$4,V10/($W$4-R10+1),0) -> 0 | X10: =W10*U10 -> 0 | Y10: =AB9-X10 -> 392980.44 | Z10: =(V10-W10)*(1+Inputs!$B$4) -> 0 | AA10: =(AA9+W10)*(1+Inputs!$B$4) -> 1530650 | AB10: =Y10*(1+Inputs!$B$4*(1-Inputs!$B$8)) -> 430313.59 | AC10: =IF(AB9<=0,0,AC9*Y10/AB9) -> 327750 | AD10: =AA10+Z10*(1-Inputs!$B$6)+AB10-(AB10-AC10)*Inputs!$B$9 -> 1934297.1 | AE10: =AA10/(AA10+Z10+AB10) -> 0.78056013 | AF10: =IF(AD10>M10,1,0) -> 0 | AG10: =IF(Y10<0,"SHORT","ok") -> ok | AI10: 3 | AJ10: =AJ9+1 -> 60 | AK10: =AK9+1 -> 2028 | AL10: =IF(Inputs!$B$15="B",Inputs!$D$21,Inputs!$C$21) -> 0.38 | AM10: =AQ9 -> 463833.33 | AN10: =IF(AI10<=$AN$4,AM10/($AN$4-AI10+1),0) -> 463833.33 | AO10: =AN10*AL10 -> 176256.67 | AP10: =AS9-AO10 -> 390584.23 | AQ10: =(AM10-AN10)*(1+Inputs!$B$4) -> 0 | AR10: =(AR9+AN10)*(1+Inputs!$B$4) -> 1530650 | AS10: =AP10*(1+Inputs!$B$4*(1-Inputs!$B$8)) -> 427689.73 | AT10: =IF(AS9<=0,0,AT9*AP10/AS9) -> 325751.53 | AU10: =AR10+AQ10*(1-Inputs!$B$6)+AS10-(AS10-AT10)*Inputs!$B$9 -> 1931835.8 | AV10: =AR10/(AR10+AQ10+AS10) -> 0.78160596 | AW10: =IF(AU10>M10,1,0) -> 0 | AX10: =IF(AP10<0,"SHORT","ok") -> ok | AZ10: 3 | BA10: =BA9+1 -> 60 | BB10: =BB9+1 -> 2028 | BC10: =IF(Inputs!$B$15="B",Inputs!$D$21,Inputs!$C$21) -> 0.38 | BD10: =BH9 -> 834900 | BE10: =IF(AZ10<=$BE$4,BD10/($BE$4-AZ10+1),0) -> 278300 | BF10: =BE10*BC10 -> 105754 | BG10: =BJ9-BF10 -> 601132.28 | BH10: =(BD10-BE10)*(1+Inputs!$B$4) -> 612260 | BI10: =(BI9+BE10)*(1+Inputs!$B$4) -> 918390 | BJ10: =BG10*(1+Inputs!$B$4*(1-Inputs!$B$8)) -> 658239.85 | BK10: =IF(BJ9<=0,0,BK9*BG10/BJ9) -> 501350.92 | BL10: =BI10+BH10*(1-Inputs!$B$6)+BJ10-(BJ10-BK10)*Inputs!$B$9 -> 1964420.7 | BM10: =BI10/(BI10+BH10+BJ10) -> 0.41956885 | BN10: =IF(BL10>M10,1,0) -> 0 | BO10: =IF(BG10<0,"SHORT","ok") -> ok | BQ10: 3 | BR10: =BR9+1 -> 60 | BS10: =BS9+1 -> 2028 | BT10: =IF(Inputs!$B$15="B",Inputs!$D$21,Inputs!$C$21) -> 0.38 | BU10: =BY9 -> 1043625 | BV10: =IF(BQ10<=$BV$4,BU10/($BV$4-BQ10+1),0) -> 173937.5 | BW10: =BV10*BT10 -> 66096.25 | BX10: =CA9-BW10 -> 719565.57 | BY10: =(BU10-BV10)*(1+Inputs!$B$4) -> 956656.25 | BZ10: =(BZ9+BV10)*(1+Inputs!$B$4) -> 573993.75 | CA10: =BX10*(1+Inputs!$B$4*(1-Inputs!$B$8)) -> 787924.29 | CB10: =IF(CA9<=0,0,CB9*BX10/CA9) -> 600125.57 | CC10: =BZ10+BY10*(1-Inputs!$B$6)+CA10-(CA10-CB10)*Inputs!$B$9 -> 1982749.8 | CD10: =BZ10/(BZ10+BY10+CA10) -> 0.24756323 | CE10: =IF(CC10>M10,1,0) -> 0 | CF10: =IF(BX10<0,"SHORT","ok") -> ok | CH10: 3 | CI10: =CI9+1 -> 60 | CJ10: =CJ9+1 -> 2028 | CK10: =IF(Inputs!$B$15="B",Inputs!$D$21,Inputs!$C$21) -> 0.38 | CL10: =CP9 -> 1113200 | CM10: =IF(CH10<=$CM$4,CL10/($CM$4-CH10+1),0) -> 139150 | CN10: =CM10*CK10 -> 52877 | CO10: =CR9-CN10 -> 759043.33 | CP10: =(CL10-CM10)*(1+Inputs!$B$4) -> 1071455 | CQ10: =(CQ9+CM10)*(1+Inputs!$B$4) -> 459195 | CR10: =CO10*(1+Inputs!$B$4*(1-Inputs!$B$8)) -> 831152.44 | CS10: =IF(CR9<=0,0,CS9*CO10/CR9) -> 633050.46 | CT10: =CQ10+CP10*(1-Inputs!$B$6)+CR10-(CR10-CS10)*Inputs!$B$9 -> 1988859.4 | CU10: =CQ10/(CQ10+CP10+CR10) -> 0.19442566 | CV10: =IF(CT10>M10,1,0) -> 0 | CW10: =IF(CO10<0,"SHORT","ok") -> ok
A11: 4 | B11: =B10+1 -> 61 | C11: =C10+1 -> 2029 | D11: =IF(Inputs!$B$15="B",Inputs!$D$22,Inputs!$C$22) -> 0.38 | E11: =I10 -> 1530650 | F11: =IF(A11<=$F$4,E11/($F$4-A11+1),0) -> 0 | G11: =F11*D11 -> 0 | H11: =K10-G11 -> 1004065 | I11: =(E11-F11)*(1+Inputs!$B$4) -> 1683715 | J11: =(J10+F11)*(1+Inputs!$B$4) -> 0 | K11: =H11*(1+Inputs!$B$4*(1-Inputs!$B$8)) -> 1099451.2 | L11: =IF(K10<=0,0,L10*H11/K10) -> 764750 | M11: =J11+I11*(1-Inputs!$B$6)+K11-(K11-L11)*Inputs!$B$9 -> 2191029.4 | N11: =J11/(J11+I11+K11) -> 0 | O11: =IF(M11>M11,1,0) -> 0 | P11: =IF(H11<0,"SHORT","ok") -> ok | R11: 4 | S11: =S10+1 -> 61 | T11: =T10+1 -> 2029 | U11: =IF(Inputs!$B$15="B",Inputs!$D$22,Inputs!$C$22) -> 0.38 | V11: =Z10 -> 0 | W11: =IF(R11<=$W$4,V11/($W$4-R11+1),0) -> 0 | X11: =W11*U11 -> 0 | Y11: =AB10-X11 -> 430313.59 | Z11: =(V11-W11)*(1+Inputs!$B$4) -> 0 | AA11: =(AA10+W11)*(1+Inputs!$B$4) -> 1683715 | AB11: =Y11*(1+Inputs!$B$4*(1-Inputs!$B$8)) -> 471193.38 | AC11: =IF(AB10<=0,0,AC10*Y11/AB10) -> 327750 | AD11: =AA11+Z11*(1-Inputs!$B$6)+AB11-(AB11-AC11)*Inputs!$B$9 -> 2117613.1 | AE11: =AA11/(AA11+Z11+AB11) -> 0.78133948 | AF11: =IF(AD11>M11,1,0) -> 0 | AG11: =IF(Y11<0,"SHORT","ok") -> ok | AI11: 4 | AJ11: =AJ10+1 -> 61 | AK11: =AK10+1 -> 2029 | AL11: =IF(Inputs!$B$15="B",Inputs!$D$22,Inputs!$C$22) -> 0.38 | AM11: =AQ10 -> 0 | AN11: =IF(AI11<=$AN$4,AM11/($AN$4-AI11+1),0) -> 0 | AO11: =AN11*AL11 -> 0 | AP11: =AS10-AO11 -> 427689.73 | AQ11: =(AM11-AN11)*(1+Inputs!$B$4) -> 0 | AR11: =(AR10+AN11)*(1+Inputs!$B$4) -> 1683715 | AS11: =AP11*(1+Inputs!$B$4*(1-Inputs!$B$8)) -> 468320.25 | AT11: =IF(AS10<=0,0,AT10*AP11/AS10) -> 325751.53 | AU11: =AR11+AQ11*(1-Inputs!$B$6)+AS11-(AS11-AT11)*Inputs!$B$9 -> 2114967.4 | AV11: =AR11/(AR11+AQ11+AS11) -> 0.78238263 | AW11: =IF(AU11>M11,1,0) -> 0 | AX11: =IF(AP11<0,"SHORT","ok") -> ok | AZ11: 4 | BA11: =BA10+1 -> 61 | BB11: =BB10+1 -> 2029 | BC11: =IF(Inputs!$B$15="B",Inputs!$D$22,Inputs!$C$22) -> 0.38 | BD11: =BH10 -> 612260 | BE11: =IF(AZ11<=$BE$4,BD11/($BE$4-AZ11+1),0) -> 306130 | BF11: =BE11*BC11 -> 116329.4 | BG11: =BJ10-BF11 -> 541910.45 | BH11: =(BD11-BE11)*(1+Inputs!$B$4) -> 336743 | BI11: =(BI10+BE11)*(1+Inputs!$B$4) -> 1346972 | BJ11: =BG11*(1+Inputs!$B$4*(1-Inputs!$B$8)) -> 593391.94 | BK11: =IF(BJ10<=0,0,BK10*BG11/BJ10) -> 412748.18 | BL11: =BI11+BH11*(1-Inputs!$B$6)+BJ11-(BJ11-BK11)*Inputs!$B$9 -> 2129116.7 | BM11: =BI11/(BI11+BH11+BJ11) -> 0.59152777 | BN11: =IF(BL11>M11,1,0) -> 0 | BO11: =IF(BG11<0,"SHORT","ok") -> ok | BQ11: 4 | BR11: =BR10+1 -> 61 | BS11: =BS10+1 -> 2029 | BT11: =IF(Inputs!$B$15="B",Inputs!$D$22,Inputs!$C$22) -> 0.38 | BU11: =BY10 -> 956656.25 | BV11: =IF(BQ11<=$BV$4,BU11/($BV$4-BQ11+1),0) -> 191331.25 | BW11: =BV11*BT11 -> 72705.875 | BX11: =CA10-BW11 -> 715218.42 | BY11: =(BU11-BV11)*(1+Inputs!$B$4) -> 841857.5 | BZ11: =(BZ10+BV11)*(1+Inputs!$B$4) -> 841857.5 | CA11: =BX11*(1+Inputs!$B$4*(1-Inputs!$B$8)) -> 783164.17 | CB11: =IF(CA10<=0,0,CB10*BX11/CA10) -> 544748.86 | CC11: =BZ11+BY11*(1-Inputs!$B$6)+CA11-(CA11-CB11)*Inputs!$B$9 -> 2152333.9 | CD11: =BZ11/(BZ11+BY11+CA11) -> 0.34126418 | CE11: =IF(CC11>M11,1,0) -> 0 | CF11: =IF(BX11<0,"SHORT","ok") -> ok | CH11: 4 | CI11: =CI10+1 -> 61 | CJ11: =CJ10+1 -> 2029 | CK11: =IF(Inputs!$B$15="B",Inputs!$D$22,Inputs!$C$22) -> 0.38 | CL11: =CP10 -> 1071455 | CM11: =IF(CH11<=$CM$4,CL11/($CM$4-CH11+1),0) -> 153065 | CN11: =CM11*CK11 -> 58164.7 | CO11: =CR10-CN11 -> 772987.74 | CP11: =(CL11-CM11)*(1+Inputs!$B$4) -> 1010229 | CQ11: =(CQ10+CM11)*(1+Inputs!$B$4) -> 673486 | CR11: =CO11*(1+Inputs!$B$4*(1-Inputs!$B$8)) -> 846421.58 | CS11: =IF(CR10<=0,0,CS10*CO11/CR10) -> 588749.09 | CT11: =CQ11+CP11*(1-Inputs!$B$6)+CR11-(CR11-CS11)*Inputs!$B$9 -> 2160073 | CU11: =CQ11/(CQ11+CP11+CR11) -> 0.26618563 | CV11: =IF(CT11>M11,1,0) -> 0 | CW11: =IF(CO11<0,"SHORT","ok") -> ok
A12: 5 | B12: =B11+1 -> 62 | C12: =C11+1 -> 2030 | D12: =IF(Inputs!$B$15="B",Inputs!$D$23,Inputs!$C$23) -> 0.38 | E12: =I11 -> 1683715 | F12: =IF(A12<=$F$4,E12/($F$4-A12+1),0) -> 0 | G12: =F12*D12 -> 0 | H12: =K11-G12 -> 1099451.2 | I12: =(E12-F12)*(1+Inputs!$B$4) -> 1852086.5 | J12: =(J11+F12)*(1+Inputs!$B$4) -> 0 | K12: =H12*(1+Inputs!$B$4*(1-Inputs!$B$8)) -> 1203899.1 | L12: =IF(K11<=0,0,L11*H12/K11) -> 764750 | M12: =J12+I12*(1-Inputs!$B$6)+K12-(K12-L12)*Inputs!$B$9 -> 2386180.9 | N12: =J12/(J12+I12+K12) -> 0 | O12: =IF(M12>M12,1,0) -> 0 | P12: =IF(H12<0,"SHORT","ok") -> ok | R12: 5 | S12: =S11+1 -> 62 | T12: =T11+1 -> 2030 | U12: =IF(Inputs!$B$15="B",Inputs!$D$23,Inputs!$C$23) -> 0.38 | V12: =Z11 -> 0 | W12: =IF(R12<=$W$4,V12/($W$4-R12+1),0) -> 0 | X12: =W12*U12 -> 0 | Y12: =AB11-X12 -> 471193.38 | Z12: =(V12-W12)*(1+Inputs!$B$4) -> 0 | AA12: =(AA11+W12)*(1+Inputs!$B$4) -> 1852086.5 | AB12: =Y12*(1+Inputs!$B$4*(1-Inputs!$B$8)) -> 515956.75 | AC12: =IF(AB11<=0,0,AC11*Y12/AB11) -> 327750 | AD12: =AA12+Z12*(1-Inputs!$B$6)+AB12-(AB12-AC12)*Inputs!$B$9 -> 2319109.5 | AE12: =AA12/(AA12+Z12+AB12) -> 0.78211684 | AF12: =IF(AD12>M12,1,0) -> 0 | AG12: =IF(Y12<0,"SHORT","ok") -> ok | AI12: 5 | AJ12: =AJ11+1 -> 62 | AK12: =AK11+1 -> 2030 | AL12: =IF(Inputs!$B$15="B",Inputs!$D$23,Inputs!$C$23) -> 0.38 | AM12: =AQ11 -> 0 | AN12: =IF(AI12<=$AN$4,AM12/($AN$4-AI12+1),0) -> 0 | AO12: =AN12*AL12 -> 0 | AP12: =AS11-AO12 -> 468320.25 | AQ12: =(AM12-AN12)*(1+Inputs!$B$4) -> 0 | AR12: =(AR11+AN12)*(1+Inputs!$B$4) -> 1852086.5 | AS12: =AP12*(1+Inputs!$B$4*(1-Inputs!$B$8)) -> 512810.68 | AT12: =IF(AS11<=0,0,AT11*AP12/AS11) -> 325751.53 | AU12: =AR12+AQ12*(1-Inputs!$B$6)+AS12-(AS12-AT12)*Inputs!$B$9 -> 2316261.8 | AV12: =AR12/(AR12+AQ12+AS12) -> 0.78315731 | AW12: =IF(AU12>M12,1,0) -> 0 | AX12: =IF(AP12<0,"SHORT","ok") -> ok | AZ12: 5 | BA12: =BA11+1 -> 62 | BB12: =BB11+1 -> 2030 | BC12: =IF(Inputs!$B$15="B",Inputs!$D$23,Inputs!$C$23) -> 0.38 | BD12: =BH11 -> 336743 | BE12: =IF(AZ12<=$BE$4,BD12/($BE$4-AZ12+1),0) -> 336743 | BF12: =BE12*BC12 -> 127962.34 | BG12: =BJ11-BF12 -> 465429.6 | BH12: =(BD12-BE12)*(1+Inputs!$B$4) -> 0 | BI12: =(BI11+BE12)*(1+Inputs!$B$4) -> 1852086.5 | BJ12: =BG12*(1+Inputs!$B$4*(1-Inputs!$B$8)) -> 509645.42 | BK12: =IF(BJ11<=0,0,BK11*BG12/BJ11) -> 323740.87 | BL12: =BI12+BH12*(1-Inputs!$B$6)+BJ12-(BJ12-BK12)*Inputs!$B$9 -> 2313396.7 | BM12: =BI12/(BI12+BH12+BJ12) -> 0.78420692 | BN12: =IF(BL12>M12,1,0) -> 0 | BO12: =IF(BG12<0,"SHORT","ok") -> ok | BQ12: 5 | BR12: =BR11+1 -> 62 | BS12: =BS11+1 -> 2030 | BT12: =IF(Inputs!$B$15="B",Inputs!$D$23,Inputs!$C$23) -> 0.38 | BU12: =BY11 -> 841857.5 | BV12: =IF(BQ12<=$BV$4,BU12/($BV$4-BQ12+1),0) -> 210464.38 | BW12: =BV12*BT12 -> 79976.462 | BX12: =CA11-BW12 -> 703187.71 | BY12: =(BU12-BV12)*(1+Inputs!$B$4) -> 694532.44 | BZ12: =(BZ11+BV12)*(1+Inputs!$B$4) -> 1157554.1 | CA12: =BX12*(1+Inputs!$B$4*(1-Inputs!$B$8)) -> 769990.54 | CB12: =IF(CA11<=0,0,CB11*BX12/CA11) -> 489119.29 | CC12: =BZ12+BY12*(1-Inputs!$B$6)+CA12-(CA12-CB12)*Inputs!$B$9 -> 2340690.8 | CD12: =BZ12/(BZ12+BY12+CA12) -> 0.44146455 | CE12: =IF(CC12>M12,1,0) -> 0 | CF12: =IF(BX12<0,"SHORT","ok") -> ok | CH12: 5 | CI12: =CI11+1 -> 62 | CJ12: =CJ11+1 -> 2030 | CK12: =IF(Inputs!$B$15="B",Inputs!$D$23,Inputs!$C$23) -> 0.38 | CL12: =CP11 -> 1010229 | CM12: =IF(CH12<=$CM$4,CL12/($CM$4-CH12+1),0) -> 168371.5 | CN12: =CM12*CK12 -> 63981.17 | CO12: =CR11-CN12 -> 782440.41 | CP12: =(CL12-CM12)*(1+Inputs!$B$4) -> 926043.25 | CQ12: =(CQ11+CM12)*(1+Inputs!$B$4) -> 926043.25 | CR12: =CO12*(1+Inputs!$B$4*(1-Inputs!$B$8)) -> 856772.25 | CS12: =IF(CR11<=0,0,CS11*CO12/CR11) -> 544245.43 | CT12: =CQ12+CP12*(1-Inputs!$B$6)+CR12-(CR12-CS12)*Inputs!$B$9 -> 2349788.8 | CU12: =CQ12/(CQ12+CP12+CR12) -> 0.34185734 | CV12: =IF(CT12>M12,1,0) -> 0 | CW12: =IF(CO12<0,"SHORT","ok") -> ok
A13: 6 | B13: =B12+1 -> 63 | C13: =C12+1 -> 2031 | D13: =IF(Inputs!$B$15="B",Inputs!$D$24,Inputs!$C$24) -> 0.38 | E13: =I12 -> 1852086.5 | F13: =IF(A13<=$F$4,E13/($F$4-A13+1),0) -> 0 | G13: =F13*D13 -> 0 | H13: =K12-G13 -> 1203899.1 | I13: =(E13-F13)*(1+Inputs!$B$4) -> 2037295.1 | J13: =(J12+F13)*(1+Inputs!$B$4) -> 0 | K13: =H13*(1+Inputs!$B$4*(1-Inputs!$B$8)) -> 1318269.5 | L13: =IF(K12<=0,0,L12*H13/K12) -> 764750 | M13: =J13+I13*(1-Inputs!$B$6)+K13-(K13-L13)*Inputs!$B$9 -> 2600461 | N13: =J13/(J13+I13+K13) -> 0 | O13: =IF(M13>M13,1,0) -> 0 | P13: =IF(H13<0,"SHORT","ok") -> ok | R13: 6 | S13: =S12+1 -> 63 | T13: =T12+1 -> 2031 | U13: =IF(Inputs!$B$15="B",Inputs!$D$24,Inputs!$C$24) -> 0.38 | V13: =Z12 -> 0 | W13: =IF(R13<=$W$4,V13/($W$4-R13+1),0) -> 0 | X13: =W13*U13 -> 0 | Y13: =AB12-X13 -> 515956.75 | Z13: =(V13-W13)*(1+Inputs!$B$4) -> 0 | AA13: =(AA12+W13)*(1+Inputs!$B$4) -> 2037295.1 | AB13: =Y13*(1+Inputs!$B$4*(1-Inputs!$B$8)) -> 564972.64 | AC13: =IF(AB12<=0,0,AC12*Y13/AB12) -> 327750 | AD13: =AA13+Z13*(1-Inputs!$B$6)+AB13-(AB13-AC13)*Inputs!$B$9 -> 2540589.9 | AE13: =AA13/(AA13+Z13+AB13) -> 0.7828922 | AF13: =IF(AD13>M13,1,0) -> 0 | AG13: =IF(Y13<0,"SHORT","ok") -> ok | AI13: 6 | AJ13: =AJ12+1 -> 63 | AK13: =AK12+1 -> 2031 | AL13: =IF(Inputs!$B$15="B",Inputs!$D$24,Inputs!$C$24) -> 0.38 | AM13: =AQ12 -> 0 | AN13: =IF(AI13<=$AN$4,AM13/($AN$4-AI13+1),0) -> 0 | AO13: =AN13*AL13 -> 0 | AP13: =AS12-AO13 -> 512810.68 | AQ13: =(AM13-AN13)*(1+Inputs!$B$4) -> 0 | AR13: =(AR12+AN13)*(1+Inputs!$B$4) -> 2037295.1 | AS13: =AP13*(1+Inputs!$B$4*(1-Inputs!$B$8)) -> 561527.69 | AT13: =IF(AS12<=0,0,AT12*AP13/AS12) -> 325751.53 | AU13: =AR13+AQ13*(1-Inputs!$B$6)+AS13-(AS13-AT13)*Inputs!$B$9 -> 2537521 | AV13: =AR13/(AR13+AQ13+AS13) -> 0.78392998 | AW13: =IF(AU13>M13,1,0) -> 0 | AX13: =IF(AP13<0,"SHORT","ok") -> ok | AZ13: 6 | BA13: =BA12+1 -> 63 | BB13: =BB12+1 -> 2031 | BC13: =IF(Inputs!$B$15="B",Inputs!$D$24,Inputs!$C$24) -> 0.38 | BD13: =BH12 -> 0 | BE13: =IF(AZ13<=$BE$4,BD13/($BE$4-AZ13+1),0) -> 0 | BF13: =BE13*BC13 -> 0 | BG13: =BJ12-BF13 -> 509645.42 | BH13: =(BD13-BE13)*(1+Inputs!$B$4) -> 0 | BI13: =(BI12+BE13)*(1+Inputs!$B$4) -> 2037295.1 | BJ13: =BG13*(1+Inputs!$B$4*(1-Inputs!$B$8)) -> 558061.73 | BK13: =IF(BJ12<=0,0,BK12*BG13/BJ12) -> 323740.87 | BL13: =BI13+BH13*(1-Inputs!$B$6)+BJ13-(BJ13-BK13)*Inputs!$B$9 -> 2534433.5 | BM13: =BI13/(BI13+BH13+BJ13) -> 0.78497688 | BN13: =IF(BL13>M13,1,0) -> 0 | BO13: =IF(BG13<0,"SHORT","ok") -> ok | BQ13: 6 | BR13: =BR12+1 -> 63 | BS13: =BS12+1 -> 2031 | BT13: =IF(Inputs!$B$15="B",Inputs!$D$24,Inputs!$C$24) -> 0.38 | BU13: =BY12 -> 694532.44 | BV13: =IF(BQ13<=$BV$4,BU13/($BV$4-BQ13+1),0) -> 231510.81 | BW13: =BV13*BT13 -> 87974.109 | BX13: =CA12-BW13 -> 682016.43 | BY13: =(BU13-BV13)*(1+Inputs!$B$4) -> 509323.79 | BZ13: =(BZ12+BV13)*(1+Inputs!$B$4) -> 1527971.4 | CA13: =BX13*(1+Inputs!$B$4*(1-Inputs!$B$8)) -> 746807.99 | CB13: =IF(CA12<=0,0,CB12*BX13/CA12) -> 433235.7 | CC13: =BZ13+BY13*(1-Inputs!$B$6)+CA13-(CA13-CB13)*Inputs!$B$9 -> 2549777.2 | CD13: =BZ13/(BZ13+BY13+CA13) -> 0.54881996 | CE13: =IF(CC13>M13,1,0) -> 0 | CF13: =IF(BX13<0,"SHORT","ok") -> ok | CH13: 6 | CI13: =CI12+1 -> 63 | CJ13: =CJ12+1 -> 2031 | CK13: =IF(Inputs!$B$15="B",Inputs!$D$24,Inputs!$C$24) -> 0.38 | CL13: =CP12 -> 926043.25 | CM13: =IF(CH13<=$CM$4,CL13/($CM$4-CH13+1),0) -> 185208.65 | CN13: =CM13*CK13 -> 70379.287 | CO13: =CR12-CN13 -> 786392.96 | CP13: =(CL13-CM13)*(1+Inputs!$B$4) -> 814918.06 | CQ13: =(CQ12+CM13)*(1+Inputs!$B$4) -> 1222377.1 | CR13: =CO13*(1+Inputs!$B$4*(1-Inputs!$B$8)) -> 861100.29 | CS13: =IF(CR12<=0,0,CS12*CO13/CR12) -> 499538.56 | CT13: =CQ13+CP13*(1-Inputs!$B$6)+CR13-(CR13-CS13)*Inputs!$B$9 -> 2559914 | CU13: =CQ13/(CQ13+CP13+CR13) -> 0.42174269 | CV13: =IF(CT13>M13,1,0) -> 0 | CW13: =IF(CO13<0,"SHORT","ok") -> ok
A14: 7 | B14: =B13+1 -> 64 | C14: =C13+1 -> 2032 | D14: =IF(Inputs!$B$15="B",Inputs!$D$25,Inputs!$C$25) -> 0.38 | E14: =I13 -> 2037295.1 | F14: =IF(A14<=$F$4,E14/($F$4-A14+1),0) -> 0 | G14: =F14*D14 -> 0 | H14: =K13-G14 -> 1318269.5 | I14: =(E14-F14)*(1+Inputs!$B$4) -> 2241024.7 | J14: =(J13+F14)*(1+Inputs!$B$4) -> 0 | K14: =H14*(1+Inputs!$B$4*(1-Inputs!$B$8)) -> 1443505.1 | L14: =IF(K13<=0,0,L13*H14/K13) -> 764750 | M14: =J14+I14*(1-Inputs!$B$6)+K14-(K14-L14)*Inputs!$B$9 -> 2835746 | N14: =J14/(J14+I14+K14) -> 0 | O14: =IF(M14>M14,1,0) -> 0 | P14: =IF(H14<0,"SHORT","ok") -> ok | R14: 7 | S14: =S13+1 -> 64 | T14: =T13+1 -> 2032 | U14: =IF(Inputs!$B$15="B",Inputs!$D$25,Inputs!$C$25) -> 0.38 | V14: =Z13 -> 0 | W14: =IF(R14<=$W$4,V14/($W$4-R14+1),0) -> 0 | X14: =W14*U14 -> 0 | Y14: =AB13-X14 -> 564972.64 | Z14: =(V14-W14)*(1+Inputs!$B$4) -> 0 | AA14: =(AA13+W14)*(1+Inputs!$B$4) -> 2241024.7 | AB14: =Y14*(1+Inputs!$B$4*(1-Inputs!$B$8)) -> 618645.04 | AC14: =IF(AB13<=0,0,AC13*Y14/AB13) -> 327750 | AD14: =AA14+Z14*(1-Inputs!$B$6)+AB14-(AB14-AC14)*Inputs!$B$9 -> 2784037 | AE14: =AA14/(AA14+Z14+AB14) -> 0.78366556 | AF14: =IF(AD14>M14,1,0) -> 0 | AG14: =IF(Y14<0,"SHORT","ok") -> ok | AI14: 7 | AJ14: =AJ13+1 -> 64 | AK14: =AK13+1 -> 2032 | AL14: =IF(Inputs!$B$15="B",Inputs!$D$25,Inputs!$C$25) -> 0.38 | AM14: =AQ13 -> 0 | AN14: =IF(AI14<=$AN$4,AM14/($AN$4-AI14+1),0) -> 0 | AO14: =AN14*AL14 -> 0 | AP14: =AS13-AO14 -> 561527.69 | AQ14: =(AM14-AN14)*(1+Inputs!$B$4) -> 0 | AR14: =(AR13+AN14)*(1+Inputs!$B$4) -> 2241024.7 | AS14: =AP14*(1+Inputs!$B$4*(1-Inputs!$B$8)) -> 614872.82 | AT14: =IF(AS13<=0,0,AT13*AP14/AS13) -> 325751.53 | AU14: =AR14+AQ14*(1-Inputs!$B$6)+AS14-(AS14-AT14)*Inputs!$B$9 -> 2780726 | AV14: =AR14/(AR14+AQ14+AS14) -> 0.78470067 | AW14: =IF(AU14>M14,1,0) -> 0 | AX14: =IF(AP14<0,"SHORT","ok") -> ok | AZ14: 7 | BA14: =BA13+1 -> 64 | BB14: =BB13+1 -> 2032 | BC14: =IF(Inputs!$B$15="B",Inputs!$D$25,Inputs!$C$25) -> 0.38 | BD14: =BH13 -> 0 | BE14: =IF(AZ14<=$BE$4,BD14/($BE$4-AZ14+1),0) -> 0 | BF14: =BE14*BC14 -> 0 | BG14: =BJ13-BF14 -> 558061.73 | BH14: =(BD14-BE14)*(1+Inputs!$B$4) -> 0 | BI14: =(BI13+BE14)*(1+Inputs!$B$4) -> 2241024.7 | BJ14: =BG14*(1+Inputs!$B$4*(1-Inputs!$B$8)) -> 611077.59 | BK14: =IF(BJ13<=0,0,BK13*BG14/BJ13) -> 323740.87 | BL14: =BI14+BH14*(1-Inputs!$B$6)+BJ14-(BJ14-BK14)*Inputs!$B$9 -> 2777394.7 | BM14: =BI14/(BI14+BH14+BJ14) -> 0.78574485 | BN14: =IF(BL14>M14,1,0) -> 0 | BO14: =IF(BG14<0,"SHORT","ok") -> ok | BQ14: 7 | BR14: =BR13+1 -> 64 | BS14: =BS13+1 -> 2032 | BT14: =IF(Inputs!$B$15="B",Inputs!$D$25,Inputs!$C$25) -> 0.38 | BU14: =BY13 -> 509323.79 | BV14: =IF(BQ14<=$BV$4,BU14/($BV$4-BQ14+1),0) -> 254661.89 | BW14: =BV14*BT14 -> 96771.52 | BX14: =CA13-BW14 -> 650036.47 | BY14: =(BU14-BV14)*(1+Inputs!$B$4) -> 280128.08 | BZ14: =(BZ13+BV14)*(1+Inputs!$B$4) -> 1960896.6 | CA14: =BX14*(1+Inputs!$B$4*(1-Inputs!$B$8)) -> 711789.94 | CB14: =IF(CA13<=0,0,CB13*BX14/CA13) -> 377096.94 | CC14: =BZ14+BY14*(1-Inputs!$B$6)+CA14-(CA14-CB14)*Inputs!$B$9 -> 2781756 | CD14: =BZ14/(BZ14+BY14+CA14) -> 0.66407711 | CE14: =IF(CC14>M14,1,0) -> 0 | CF14: =IF(BX14<0,"SHORT","ok") -> ok | CH14: 7 | CI14: =CI13+1 -> 64 | CJ14: =CJ13+1 -> 2032 | CK14: =IF(Inputs!$B$15="B",Inputs!$D$25,Inputs!$C$25) -> 0.38 | CL14: =CP13 -> 814918.06 | CM14: =IF(CH14<=$CM$4,CL14/($CM$4-CH14+1),0) -> 203729.52 | CN14: =CM14*CK14 -> 77417.216 | CO14: =CR13-CN14 -> 783683.07 | CP14: =(CL14-CM14)*(1+Inputs!$B$4) -> 672307.4 | CQ14: =(CQ13+CM14)*(1+Inputs!$B$4) -> 1568717.3 | CR14: =CO14*(1+Inputs!$B$4*(1-Inputs!$B$8)) -> 858132.97 | CS14: =IF(CR13<=0,0,CS13*CO14/CR13) -> 454627.55 | CT14: =CQ14+CP14*(1-Inputs!$B$6)+CR14-(CR14-CS14)*Inputs!$B$9 -> 2792554 | CU14: =CQ14/(CQ14+CP14+CR14) -> 0.50617537 | CV14: =IF(CT14>M14,1,0) -> 0 | CW14: =IF(CO14<0,"SHORT","ok") -> ok
A15: 8 | B15: =B14+1 -> 65 | C15: =C14+1 -> 2033 | D15: =IF(Inputs!$B$15="B",Inputs!$D$26,Inputs!$C$26) -> 0.38 | E15: =I14 -> 2241024.7 | F15: =IF(A15<=$F$4,E15/($F$4-A15+1),0) -> 0 | G15: =F15*D15 -> 0 | H15: =K14-G15 -> 1443505.1 | I15: =(E15-F15)*(1+Inputs!$B$4) -> 2465127.1 | J15: =(J14+F15)*(1+Inputs!$B$4) -> 0 | K15: =H15*(1+Inputs!$B$4*(1-Inputs!$B$8)) -> 1580638.1 | L15: =IF(K14<=0,0,L14*H15/K14) -> 764750 | M15: =J15+I15*(1-Inputs!$B$6)+K15-(K15-L15)*Inputs!$B$9 -> 3094096.2 | N15: =J15/(J15+I15+K15) -> 0 | O15: =IF(M15>M15,1,0) -> 0 | P15: =IF(H15<0,"SHORT","ok") -> ok | R15: 8 | S15: =S14+1 -> 65 | T15: =T14+1 -> 2033 | U15: =IF(Inputs!$B$15="B",Inputs!$D$26,Inputs!$C$26) -> 0.38 | V15: =Z14 -> 0 | W15: =IF(R15<=$W$4,V15/($W$4-R15+1),0) -> 0 | X15: =W15*U15 -> 0 | Y15: =AB14-X15 -> 618645.04 | Z15: =(V15-W15)*(1+Inputs!$B$4) -> 0 | AA15: =(AA14+W15)*(1+Inputs!$B$4) -> 2465127.1 | AB15: =Y15*(1+Inputs!$B$4*(1-Inputs!$B$8)) -> 677416.32 | AC15: =IF(AB14<=0,0,AC14*Y15/AB14) -> 327750 | AD15: =AA15+Z15*(1-Inputs!$B$6)+AB15-(AB15-AC15)*Inputs!$B$9 -> 3051630.2 | AE15: =AA15/(AA15+Z15+AB15) -> 0.78443693 | AF15: =IF(AD15>M15,1,0) -> 0 | AG15: =IF(Y15<0,"SHORT","ok") -> ok | AI15: 8 | AJ15: =AJ14+1 -> 65 | AK15: =AK14+1 -> 2033 | AL15: =IF(Inputs!$B$15="B",Inputs!$D$26,Inputs!$C$26) -> 0.38 | AM15: =AQ14 -> 0 | AN15: =IF(AI15<=$AN$4,AM15/($AN$4-AI15+1),0) -> 0 | AO15: =AN15*AL15 -> 0 | AP15: =AS14-AO15 -> 614872.82 | AQ15: =(AM15-AN15)*(1+Inputs!$B$4) -> 0 | AR15: =(AR14+AN15)*(1+Inputs!$B$4) -> 2465127.1 | AS15: =AP15*(1+Inputs!$B$4*(1-Inputs!$B$8)) -> 673285.74 | AT15: =IF(AS14<=0,0,AT14*AP15/AS14) -> 325751.53 | AU15: =AR15+AQ15*(1-Inputs!$B$6)+AS15-(AS15-AT15)*Inputs!$B$9 -> 3048054 | AV15: =AR15/(AR15+AQ15+AS15) -> 0.78546935 | AW15: =IF(AU15>M15,1,0) -> 0 | AX15: =IF(AP15<0,"SHORT","ok") -> ok | AZ15: 8 | BA15: =BA14+1 -> 65 | BB15: =BB14+1 -> 2033 | BC15: =IF(Inputs!$B$15="B",Inputs!$D$26,Inputs!$C$26) -> 0.38 | BD15: =BH14 -> 0 | BE15: =IF(AZ15<=$BE$4,BD15/($BE$4-AZ15+1),0) -> 0 | BF15: =BE15*BC15 -> 0 | BG15: =BJ14-BF15 -> 611077.59 | BH15: =(BD15-BE15)*(1+Inputs!$B$4) -> 0 | BI15: =(BI14+BE15)*(1+Inputs!$B$4) -> 2465127.1 | BJ15: =BG15*(1+Inputs!$B$4*(1-Inputs!$B$8)) -> 669129.97 | BK15: =IF(BJ14<=0,0,BK14*BG15/BJ14) -> 323740.87 | BL15: =BI15+BH15*(1-Inputs!$B$6)+BJ15-(BJ15-BK15)*Inputs!$B$9 -> 3044455.9 | BM15: =BI15/(BI15+BH15+BJ15) -> 0.78651082 | BN15: =IF(BL15>M15,1,0) -> 0 | BO15: =IF(BG15<0,"SHORT","ok") -> ok | BQ15: 8 | BR15: =BR14+1 -> 65 | BS15: =BS14+1 -> 2033 | BT15: =IF(Inputs!$B$15="B",Inputs!$D$26,Inputs!$C$26) -> 0.38 | BU15: =BY14 -> 280128.08 | BV15: =IF(BQ15<=$BV$4,BU15/($BV$4-BQ15+1),0) -> 280128.08 | BW15: =BV15*BT15 -> 106448.67 | BX15: =CA14-BW15 -> 605341.26 | BY15: =(BU15-BV15)*(1+Inputs!$B$4) -> 0 | BZ15: =(BZ14+BV15)*(1+Inputs!$B$4) -> 2465127.1 | CA15: =BX15*(1+Inputs!$B$4*(1-Inputs!$B$8)) -> 662848.68 | CB15: =IF(CA14<=0,0,CB14*BX15/CA14) -> 320701.84 | CC15: =BZ15+BY15*(1-Inputs!$B$6)+CA15-(CA15-CB15)*Inputs!$B$9 -> 3039017.6 | CD15: =BZ15/(BZ15+BY15+CA15) -> 0.78809021 | CE15: =IF(CC15>M15,1,0) -> 0 | CF15: =IF(BX15<0,"SHORT","ok") -> ok | CH15: 8 | CI15: =CI14+1 -> 65 | CJ15: =CJ14+1 -> 2033 | CK15: =IF(Inputs!$B$15="B",Inputs!$D$26,Inputs!$C$26) -> 0.38 | CL15: =CP14 -> 672307.4 | CM15: =IF(CH15<=$CM$4,CL15/($CM$4-CH15+1),0) -> 224102.47 | CN15: =CM15*CK15 -> 85158.937 | CO15: =CR14-CN15 -> 772974.03 | CP15: =(CL15-CM15)*(1+Inputs!$B$4) -> 493025.43 | CQ15: =(CQ14+CM15)*(1+Inputs!$B$4) -> 1972101.7 | CR15: =CO15*(1+Inputs!$B$4*(1-Inputs!$B$8)) -> 846406.56 | CS15: =IF(CR14<=0,0,CS14*CO15/CR14) -> 409511.47 | CT15: =CQ15+CP15*(1-Inputs!$B$6)+CR15-(CR15-CS15)*Inputs!$B$9 -> 3050033.3 | CU15: =CQ15/(CQ15+CP15+CR15) -> 0.59552518 | CV15: =IF(CT15>M15,1,0) -> 0 | CW15: =IF(CO15<0,"SHORT","ok") -> ok
A16: 9 | B16: =B15+1 -> 66 | C16: =C15+1 -> 2034 | D16: =IF(Inputs!$B$15="B",Inputs!$D$27,Inputs!$C$27) -> 0.38 | E16: =I15 -> 2465127.1 | F16: =IF(A16<=$F$4,E16/($F$4-A16+1),0) -> 0 | G16: =F16*D16 -> 0 | H16: =K15-G16 -> 1580638.1 | I16: =(E16-F16)*(1+Inputs!$B$4) -> 2711639.8 | J16: =(J15+F16)*(1+Inputs!$B$4) -> 0 | K16: =H16*(1+Inputs!$B$4*(1-Inputs!$B$8)) -> 1730798.7 | L16: =IF(K15<=0,0,L15*H16/K15) -> 764750 | M16: =J16+I16*(1-Inputs!$B$6)+K16-(K16-L16)*Inputs!$B$9 -> 3377773.9 | N16: =J16/(J16+I16+K16) -> 0 | O16: =IF(M16>M16,1,0) -> 0 | P16: =IF(H16<0,"SHORT","ok") -> ok | R16: 9 | S16: =S15+1 -> 66 | T16: =T15+1 -> 2034 | U16: =IF(Inputs!$B$15="B",Inputs!$D$27,Inputs!$C$27) -> 0.38 | V16: =Z15 -> 0 | W16: =IF(R16<=$W$4,V16/($W$4-R16+1),0) -> 0 | X16: =W16*U16 -> 0 | Y16: =AB15-X16 -> 677416.32 | Z16: =(V16-W16)*(1+Inputs!$B$4) -> 0 | AA16: =(AA15+W16)*(1+Inputs!$B$4) -> 2711639.8 | AB16: =Y16*(1+Inputs!$B$4*(1-Inputs!$B$8)) -> 741770.87 | AC16: =IF(AB15<=0,0,AC15*Y16/AB15) -> 327750 | AD16: =AA16+Z16*(1-Inputs!$B$6)+AB16-(AB16-AC16)*Inputs!$B$9 -> 3345765.3 | AE16: =AA16/(AA16+Z16+AB16) -> 0.7852063 | AF16: =IF(AD16>M16,1,0) -> 0 | AG16: =IF(Y16<0,"SHORT","ok") -> ok | AI16: 9 | AJ16: =AJ15+1 -> 66 | AK16: =AK15+1 -> 2034 | AL16: =IF(Inputs!$B$15="B",Inputs!$D$27,Inputs!$C$27) -> 0.38 | AM16: =AQ15 -> 0 | AN16: =IF(AI16<=$AN$4,AM16/($AN$4-AI16+1),0) -> 0 | AO16: =AN16*AL16 -> 0 | AP16: =AS15-AO16 -> 673285.74 | AQ16: =(AM16-AN16)*(1+Inputs!$B$4) -> 0 | AR16: =(AR15+AN16)*(1+Inputs!$B$4) -> 2711639.8 | AS16: =AP16*(1+Inputs!$B$4*(1-Inputs!$B$8)) -> 737247.89 | AT16: =IF(AS15<=0,0,AT15*AP16/AS15) -> 325751.53 | AU16: =AR16+AQ16*(1-Inputs!$B$6)+AS16-(AS16-AT16)*Inputs!$B$9 -> 3341898.7 | AV16: =AR16/(AR16+AQ16+AS16) -> 0.78623604 | AW16: =IF(AU16>M16,1,0) -> 0 | AX16: =IF(AP16<0,"SHORT","ok") -> ok | AZ16: 9 | BA16: =BA15+1 -> 66 | BB16: =BB15+1 -> 2034 | BC16: =IF(Inputs!$B$15="B",Inputs!$D$27,Inputs!$C$27) -> 0.38 | BD16: =BH15 -> 0 | BE16: =IF(AZ16<=$BE$4,BD16/($BE$4-AZ16+1),0) -> 0 | BF16: =BE16*BC16 -> 0 | BG16: =BJ15-BF16 -> 669129.97 | BH16: =(BD16-BE16)*(1+Inputs!$B$4) -> 0 | BI16: =(BI15+BE16)*(1+Inputs!$B$4) -> 2711639.8 | BJ16: =BG16*(1+Inputs!$B$4*(1-Inputs!$B$8)) -> 732697.31 | BK16: =IF(BJ15<=0,0,BK15*BG16/BJ15) -> 323740.87 | BL16: =BI16+BH16*(1-Inputs!$B$6)+BJ16-(BJ16-BK16)*Inputs!$B$9 -> 3338008.5 | BM16: =BI16/(BI16+BH16+BJ16) -> 0.7872748 | BN16: =IF(BL16>M16,1,0) -> 0 | BO16: =IF(BG16<0,"SHORT","ok") -> ok | BQ16: 9 | BR16: =BR15+1 -> 66 | BS16: =BS15+1 -> 2034 | BT16: =IF(Inputs!$B$15="B",Inputs!$D$27,Inputs!$C$27) -> 0.38 | BU16: =BY15 -> 0 | BV16: =IF(BQ16<=$BV$4,BU16/($BV$4-BQ16+1),0) -> 0 | BW16: =BV16*BT16 -> 0 | BX16: =CA15-BW16 -> 662848.68 | BY16: =(BU16-BV16)*(1+Inputs!$B$4) -> 0 | BZ16: =(BZ15+BV16)*(1+Inputs!$B$4) -> 2711639.8 | CA16: =BX16*(1+Inputs!$B$4*(1-Inputs!$B$8)) -> 725819.31 | CB16: =IF(CA15<=0,0,CB15*BX16/CA15) -> 320701.84 | CC16: =BZ16+BY16*(1-Inputs!$B$6)+CA16-(CA16-CB16)*Inputs!$B$9 -> 3332128.6 | CD16: =BZ16/(BZ16+BY16+CA16) -> 0.78885006 | CE16: =IF(CC16>M16,1,0) -> 0 | CF16: =IF(BX16<0,"SHORT","ok") -> ok | CH16: 9 | CI16: =CI15+1 -> 66 | CJ16: =CJ15+1 -> 2034 | CK16: =IF(Inputs!$B$15="B",Inputs!$D$27,Inputs!$C$27) -> 0.38 | CL16: =CP15 -> 493025.43 | CM16: =IF(CH16<=$CM$4,CL16/($CM$4-CH16+1),0) -> 246512.71 | CN16: =CM16*CK16 -> 93674.831 | CO16: =CR15-CN16 -> 752731.73 | CP16: =(CL16-CM16)*(1+Inputs!$B$4) -> 271163.98 | CQ16: =(CQ15+CM16)*(1+Inputs!$B$4) -> 2440475.9 | CR16: =CO16*(1+Inputs!$B$4*(1-Inputs!$B$8)) -> 824241.25 | CS16: =IF(CR15<=0,0,CS15*CO16/CR15) -> 364189.37 | CT16: =CQ16+CP16*(1-Inputs!$B$6)+CR16-(CR16-CS16)*Inputs!$B$9 -> 3334918.4 | CU16: =CQ16/(CQ16+CP16+CR16) -> 0.69020303 | CV16: =IF(CT16>M16,1,0) -> 0 | CW16: =IF(CO16<0,"SHORT","ok") -> ok
A17: 10 | B17: =B16+1 -> 67 | C17: =C16+1 -> 2035 | D17: =IF(Inputs!$B$15="B",Inputs!$D$28,Inputs!$C$28) -> 0.38 | E17: =I16 -> 2711639.8 | F17: =IF(A17<=$F$4,E17/($F$4-A17+1),0) -> 0 | G17: =F17*D17 -> 0 | H17: =K16-G17 -> 1730798.7 | I17: =(E17-F17)*(1+Inputs!$B$4) -> 2982803.8 | J17: =(J16+F17)*(1+Inputs!$B$4) -> 0 | K17: =H17*(1+Inputs!$B$4*(1-Inputs!$B$8)) -> 1895224.6 | L17: =IF(K16<=0,0,L16*H17/K16) -> 764750 | M17: =J17+I17*(1-Inputs!$B$6)+K17-(K17-L17)*Inputs!$B$9 -> 3689263.9 | N17: =J17/(J17+I17+K17) -> 0 | O17: =IF(M17>M17,1,0) -> 0 | P17: =IF(H17<0,"SHORT","ok") -> ok | R17: 10 | S17: =S16+1 -> 67 | T17: =T16+1 -> 2035 | U17: =IF(Inputs!$B$15="B",Inputs!$D$28,Inputs!$C$28) -> 0.38 | V17: =Z16 -> 0 | W17: =IF(R17<=$W$4,V17/($W$4-R17+1),0) -> 0 | X17: =W17*U17 -> 0 | Y17: =AB16-X17 -> 741770.87 | Z17: =(V17-W17)*(1+Inputs!$B$4) -> 0 | AA17: =(AA16+W17)*(1+Inputs!$B$4) -> 2982803.8 | AB17: =Y17*(1+Inputs!$B$4*(1-Inputs!$B$8)) -> 812239.1 | AC17: =IF(AB16<=0,0,AC16*Y17/AB16) -> 327750 | AD17: =AA17+Z17*(1-Inputs!$B$6)+AB17-(AB17-AC17)*Inputs!$B$9 -> 3669075.8 | AE17: =AA17/(AA17+Z17+AB17) -> 0.78597367 | AF17: =IF(AD17>M17,1,0) -> 0 | AG17: =IF(Y17<0,"SHORT","ok") -> ok | AI17: 10 | AJ17: =AJ16+1 -> 67 | AK17: =AK16+1 -> 2035 | AL17: =IF(Inputs!$B$15="B",Inputs!$D$28,Inputs!$C$28) -> 0.38 | AM17: =AQ16 -> 0 | AN17: =IF(AI17<=$AN$4,AM17/($AN$4-AI17+1),0) -> 0 | AO17: =AN17*AL17 -> 0 | AP17: =AS16-AO17 -> 737247.89 | AQ17: =(AM17-AN17)*(1+Inputs!$B$4) -> 0 | AR17: =(AR16+AN17)*(1+Inputs!$B$4) -> 2982803.8 | AS17: =AP17*(1+Inputs!$B$4*(1-Inputs!$B$8)) -> 807286.43 | AT17: =IF(AS16<=0,0,AT16*AP17/AS16) -> 325751.53 | AU17: =AR17+AQ17*(1-Inputs!$B$6)+AS17-(AS17-AT17)*Inputs!$B$9 -> 3664891.2 | AV17: =AR17/(AR17+AQ17+AS17) -> 0.78700074 | AW17: =IF(AU17>M17,1,0) -> 0 | AX17: =IF(AP17<0,"SHORT","ok") -> ok | AZ17: 10 | BA17: =BA16+1 -> 67 | BB17: =BB16+1 -> 2035 | BC17: =IF(Inputs!$B$15="B",Inputs!$D$28,Inputs!$C$28) -> 0.38 | BD17: =BH16 -> 0 | BE17: =IF(AZ17<=$BE$4,BD17/($BE$4-AZ17+1),0) -> 0 | BF17: =BE17*BC17 -> 0 | BG17: =BJ16-BF17 -> 732697.31 | BH17: =(BD17-BE17)*(1+Inputs!$B$4) -> 0 | BI17: =(BI16+BE17)*(1+Inputs!$B$4) -> 2982803.8 | BJ17: =BG17*(1+Inputs!$B$4*(1-Inputs!$B$8)) -> 802303.56 | BK17: =IF(BJ16<=0,0,BK16*BG17/BJ16) -> 323740.87 | BL17: =BI17+BH17*(1-Inputs!$B$6)+BJ17-(BJ17-BK17)*Inputs!$B$9 -> 3660681.1 | BM17: =BI17/(BI17+BH17+BJ17) -> 0.78803678 | BN17: =IF(BL17>M17,1,0) -> 0 | BO17: =IF(BG17<0,"SHORT","ok") -> ok | BQ17: 10 | BR17: =BR16+1 -> 67 | BS17: =BS16+1 -> 2035 | BT17: =IF(Inputs!$B$15="B",Inputs!$D$28,Inputs!$C$28) -> 0.38 | BU17: =BY16 -> 0 | BV17: =IF(BQ17<=$BV$4,BU17/($BV$4-BQ17+1),0) -> 0 | BW17: =BV17*BT17 -> 0 | BX17: =CA16-BW17 -> 725819.31 | BY17: =(BU17-BV17)*(1+Inputs!$B$4) -> 0 | BZ17: =(BZ16+BV17)*(1+Inputs!$B$4) -> 2982803.8 | CA17: =BX17*(1+Inputs!$B$4*(1-Inputs!$B$8)) -> 794772.14 | CB17: =IF(CA16<=0,0,CB16*BX17/CA16) -> 320701.84 | CC17: =BZ17+BY17*(1-Inputs!$B$6)+CA17-(CA17-CB17)*Inputs!$B$9 -> 3654317.7 | CD17: =BZ17/(BZ17+BY17+CA17) -> 0.7896079 | CE17: =IF(CC17>M17,1,0) -> 0 | CF17: =IF(BX17<0,"SHORT","ok") -> ok | CH17: 10 | CI17: =CI16+1 -> 67 | CJ17: =CJ16+1 -> 2035 | CK17: =IF(Inputs!$B$15="B",Inputs!$D$28,Inputs!$C$28) -> 0.38 | CL17: =CP16 -> 271163.98 | CM17: =IF(CH17<=$CM$4,CL17/($CM$4-CH17+1),0) -> 271163.98 | CN17: =CM17*CK17 -> 103042.31 | CO17: =CR16-CN17 -> 721198.93 | CP17: =(CL17-CM17)*(1+Inputs!$B$4) -> 0 | CQ17: =(CQ16+CM17)*(1+Inputs!$B$4) -> 2982803.8 | CR17: =CO17*(1+Inputs!$B$4*(1-Inputs!$B$8)) -> 789712.83 | CS17: =IF(CR16<=0,0,CS16*CO17/CR16) -> 318660.33 | CT17: =CQ17+CP17*(1-Inputs!$B$6)+CR17-(CR17-CS17)*Inputs!$B$9 -> 3650043 | CU17: =CQ17/(CQ17+CP17+CR17) -> 0.79066684 | CV17: =IF(CT17>M17,1,0) -> 0 | CW17: =IF(CO17<0,"SHORT","ok") -> ok
A18: 11 | B18: =B17+1 -> 68 | C18: =C17+1 -> 2036 | D18: =IF(Inputs!$B$15="B",Inputs!$D$29,Inputs!$C$29) -> 0.38 | E18: =I17 -> 2982803.8 | F18: =IF(A18<=$F$4,E18/($F$4-A18+1),0) -> 0 | G18: =F18*D18 -> 0 | H18: =K17-G18 -> 1895224.6 | I18: =(E18-F18)*(1+Inputs!$B$4) -> 3281084.2 | J18: =(J17+F18)*(1+Inputs!$B$4) -> 0 | K18: =H18*(1+Inputs!$B$4*(1-Inputs!$B$8)) -> 2075270.9 | L18: =IF(K17<=0,0,L17*H18/K17) -> 764750 | M18: =J18+I18*(1-Inputs!$B$6)+K18-(K18-L18)*Inputs!$B$9 -> 4031294.4 | N18: =J18/(J18+I18+K18) -> 0 | O18: =IF(M18>M18,1,0) -> 0 | P18: =IF(H18<0,"SHORT","ok") -> ok | R18: 11 | S18: =S17+1 -> 68 | T18: =T17+1 -> 2036 | U18: =IF(Inputs!$B$15="B",Inputs!$D$29,Inputs!$C$29) -> 0.38 | V18: =Z17 -> 0 | W18: =IF(R18<=$W$4,V18/($W$4-R18+1),0) -> 0 | X18: =W18*U18 -> 0 | Y18: =AB17-X18 -> 812239.1 | Z18: =(V18-W18)*(1+Inputs!$B$4) -> 0 | AA18: =(AA17+W18)*(1+Inputs!$B$4) -> 3281084.2 | AB18: =Y18*(1+Inputs!$B$4*(1-Inputs!$B$8)) -> 889401.81 | AC18: =IF(AB17<=0,0,AC17*Y18/AB17) -> 327750 | AD18: =AA18+Z18*(1-Inputs!$B$6)+AB18-(AB18-AC18)*Inputs!$B$9 -> 4024456.6 | AE18: =AA18/(AA18+Z18+AB18) -> 0.78673905 | AF18: =IF(AD18>M18,1,0) -> 0 | AG18: =IF(Y18<0,"SHORT","ok") -> ok | AI18: 11 | AJ18: =AJ17+1 -> 68 | AK18: =AK17+1 -> 2036 | AL18: =IF(Inputs!$B$15="B",Inputs!$D$29,Inputs!$C$29) -> 0.38 | AM18: =AQ17 -> 0 | AN18: =IF(AI18<=$AN$4,AM18/($AN$4-AI18+1),0) -> 0 | AO18: =AN18*AL18 -> 0 | AP18: =AS17-AO18 -> 807286.43 | AQ18: =(AM18-AN18)*(1+Inputs!$B$4) -> 0 | AR18: =(AR17+AN18)*(1+Inputs!$B$4) -> 3281084.2 | AS18: =AP18*(1+Inputs!$B$4*(1-Inputs!$B$8)) -> 883978.65 | AT18: =IF(AS17<=0,0,AT17*AP18/AS17) -> 325751.53 | AU18: =AR18+AQ18*(1-Inputs!$B$6)+AS18-(AS18-AT18)*Inputs!$B$9 -> 4019923.8 | AV18: =AR18/(AR18+AQ18+AS18) -> 0.78776343 | AW18: =IF(AU18>M18,1,0) -> 0 | AX18: =IF(AP18<0,"SHORT","ok") -> ok | AZ18: 11 | BA18: =BA17+1 -> 68 | BB18: =BB17+1 -> 2036 | BC18: =IF(Inputs!$B$15="B",Inputs!$D$29,Inputs!$C$29) -> 0.38 | BD18: =BH17 -> 0 | BE18: =IF(AZ18<=$BE$4,BD18/($BE$4-AZ18+1),0) -> 0 | BF18: =BE18*BC18 -> 0 | BG18: =BJ17-BF18 -> 802303.56 | BH18: =(BD18-BE18)*(1+Inputs!$B$4) -> 0 | BI18: =(BI17+BE18)*(1+Inputs!$B$4) -> 3281084.2 | BJ18: =BG18*(1+Inputs!$B$4*(1-Inputs!$B$8)) -> 878522.4 | BK18: =IF(BJ17<=0,0,BK17*BG18/BJ17) -> 323740.87 | BL18: =BI18+BH18*(1-Inputs!$B$6)+BJ18-(BJ18-BK18)*Inputs!$B$9 -> 4015363.4 | BM18: =BI18/(BI18+BH18+BJ18) -> 0.78879676 | BN18: =IF(BL18>M18,1,0) -> 0 | BO18: =IF(BG18<0,"SHORT","ok") -> ok | BQ18: 11 | BR18: =BR17+1 -> 68 | BS18: =BS17+1 -> 2036 | BT18: =IF(Inputs!$B$15="B",Inputs!$D$29,Inputs!$C$29) -> 0.38 | BU18: =BY17 -> 0 | BV18: =IF(BQ18<=$BV$4,BU18/($BV$4-BQ18+1),0) -> 0 | BW18: =BV18*BT18 -> 0 | BX18: =CA17-BW18 -> 794772.14 | BY18: =(BU18-BV18)*(1+Inputs!$B$4) -> 0 | BZ18: =(BZ17+BV18)*(1+Inputs!$B$4) -> 3281084.2 | CA18: =BX18*(1+Inputs!$B$4*(1-Inputs!$B$8)) -> 870275.5 | CB18: =IF(CA17<=0,0,CB17*BX18/CA17) -> 320701.84 | CC18: =BZ18+BY18*(1-Inputs!$B$6)+CA18-(CA18-CB18)*Inputs!$B$9 -> 4008470.6 | CD18: =BZ18/(BZ18+BY18+CA18) -> 0.79036375 | CE18: =IF(CC18>M18,1,0) -> 0 | CF18: =IF(BX18<0,"SHORT","ok") -> ok | CH18: 11 | CI18: =CI17+1 -> 68 | CJ18: =CJ17+1 -> 2036 | CK18: =IF(Inputs!$B$15="B",Inputs!$D$29,Inputs!$C$29) -> 0.38 | CL18: =CP17 -> 0 | CM18: =IF(CH18<=$CM$4,CL18/($CM$4-CH18+1),0) -> 0 | CN18: =CM18*CK18 -> 0 | CO18: =CR17-CN18 -> 789712.83 | CP18: =(CL18-CM18)*(1+Inputs!$B$4) -> 0 | CQ18: =(CQ17+CM18)*(1+Inputs!$B$4) -> 3281084.2 | CR18: =CO18*(1+Inputs!$B$4*(1-Inputs!$B$8)) -> 864735.55 | CS18: =IF(CR17<=0,0,CS17*CO18/CR17) -> 318660.33 | CT18: =CQ18+CP18*(1-Inputs!$B$6)+CR18-(CR18-CS18)*Inputs!$B$9 -> 4003840.2 | CU18: =CQ18/(CQ18+CP18+CR18) -> 0.79141989 | CV18: =IF(CT18>M18,1,0) -> 0 | CW18: =IF(CO18<0,"SHORT","ok") -> ok
A19: 12 | B19: =B18+1 -> 69 | C19: =C18+1 -> 2037 | D19: =IF(Inputs!$B$15="B",Inputs!$D$30,Inputs!$C$30) -> 0.38 | E19: =I18 -> 3281084.2 | F19: =IF(A19<=$F$4,E19/($F$4-A19+1),0) -> 0 | G19: =F19*D19 -> 0 | H19: =K18-G19 -> 2075270.9 | I19: =(E19-F19)*(1+Inputs!$B$4) -> 3609192.6 | J19: =(J18+F19)*(1+Inputs!$B$4) -> 0 | K19: =H19*(1+Inputs!$B$4*(1-Inputs!$B$8)) -> 2272421.6 | L19: =IF(K18<=0,0,L18*H19/K18) -> 764750 | M19: =J19+I19*(1-Inputs!$B$6)+K19-(K19-L19)*Inputs!$B$9 -> 4406861.9 | N19: =J19/(J19+I19+K19) -> 0 | O19: =IF(M19>M19,1,0) -> 0 | P19: =IF(H19<0,"SHORT","ok") -> ok | R19: 12 | S19: =S18+1 -> 69 | T19: =T18+1 -> 2037 | U19: =IF(Inputs!$B$15="B",Inputs!$D$30,Inputs!$C$30) -> 0.38 | V19: =Z18 -> 0 | W19: =IF(R19<=$W$4,V19/($W$4-R19+1),0) -> 0 | X19: =W19*U19 -> 0 | Y19: =AB18-X19 -> 889401.81 | Z19: =(V19-W19)*(1+Inputs!$B$4) -> 0 | AA19: =(AA18+W19)*(1+Inputs!$B$4) -> 3609192.6 | AB19: =Y19*(1+Inputs!$B$4*(1-Inputs!$B$8)) -> 973894.99 | AC19: =IF(AB18<=0,0,AC18*Y19/AB18) -> 327750 | AD19: =AA19+Z19*(1-Inputs!$B$6)+AB19-(AB19-AC19)*Inputs!$B$9 -> 4415089.9 | AE19: =AA19/(AA19+Z19+AB19) -> 0.78750243 | AF19: =IF(AD19>M19,1,0) -> 1 | AG19: =IF(Y19<0,"SHORT","ok") -> ok | AI19: 12 | AJ19: =AJ18+1 -> 69 | AK19: =AK18+1 -> 2037 | AL19: =IF(Inputs!$B$15="B",Inputs!$D$30,Inputs!$C$30) -> 0.38 | AM19: =AQ18 -> 0 | AN19: =IF(AI19<=$AN$4,AM19/($AN$4-AI19+1),0) -> 0 | AO19: =AN19*AL19 -> 0 | AP19: =AS18-AO19 -> 883978.65 | AQ19: =(AM19-AN19)*(1+Inputs!$B$4) -> 0 | AR19: =(AR18+AN19)*(1+Inputs!$B$4) -> 3609192.6 | AS19: =AP19*(1+Inputs!$B$4*(1-Inputs!$B$8)) -> 967956.62 | AT19: =IF(AS18<=0,0,AT18*AP19/AS18) -> 325751.53 | AU19: =AR19+AQ19*(1-Inputs!$B$6)+AS19-(AS19-AT19)*Inputs!$B$9 -> 4410175.9 | AV19: =AR19/(AR19+AQ19+AS19) -> 0.78852413 | AW19: =IF(AU19>M19,1,0) -> 1 | AX19: =IF(AP19<0,"SHORT","ok") -> ok | AZ19: 12 | BA19: =BA18+1 -> 69 | BB19: =BB18+1 -> 2037 | BC19: =IF(Inputs!$B$15="B",Inputs!$D$30,Inputs!$C$30) -> 0.38 | BD19: =BH18 -> 0 | BE19: =IF(AZ19<=$BE$4,BD19/($BE$4-AZ19+1),0) -> 0 | BF19: =BE19*BC19 -> 0 | BG19: =BJ18-BF19 -> 878522.4 | BH19: =(BD19-BE19)*(1+Inputs!$B$4) -> 0 | BI19: =(BI18+BE19)*(1+Inputs!$B$4) -> 3609192.6 | BJ19: =BG19*(1+Inputs!$B$4*(1-Inputs!$B$8)) -> 961982.02 | BK19: =IF(BJ18<=0,0,BK18*BG19/BJ18) -> 323740.87 | BL19: =BI19+BH19*(1-Inputs!$B$6)+BJ19-(BJ19-BK19)*Inputs!$B$9 -> 4405232 | BM19: =BI19/(BI19+BH19+BJ19) -> 0.78955474 | BN19: =IF(BL19>M19,1,0) -> 0 | BO19: =IF(BG19<0,"SHORT","ok") -> ok | BQ19: 12 | BR19: =BR18+1 -> 69 | BS19: =BS18+1 -> 2037 | BT19: =IF(Inputs!$B$15="B",Inputs!$D$30,Inputs!$C$30) -> 0.38 | BU19: =BY18 -> 0 | BV19: =IF(BQ19<=$BV$4,BU19/($BV$4-BQ19+1),0) -> 0 | BW19: =BV19*BT19 -> 0 | BX19: =CA18-BW19 -> 870275.5 | BY19: =(BU19-BV19)*(1+Inputs!$B$4) -> 0 | BZ19: =(BZ18+BV19)*(1+Inputs!$B$4) -> 3609192.6 | CA19: =BX19*(1+Inputs!$B$4*(1-Inputs!$B$8)) -> 952951.67 | CB19: =IF(CA18<=0,0,CB18*BX19/CA18) -> 320701.84 | CC19: =BZ19+BY19*(1-Inputs!$B$6)+CA19-(CA19-CB19)*Inputs!$B$9 -> 4397759.3 | CD19: =BZ19/(BZ19+BY19+CA19) -> 0.7911176 | CE19: =IF(CC19>M19,1,0) -> 0 | CF19: =IF(BX19<0,"SHORT","ok") -> ok | CH19: 12 | CI19: =CI18+1 -> 69 | CJ19: =CJ18+1 -> 2037 | CK19: =IF(Inputs!$B$15="B",Inputs!$D$30,Inputs!$C$30) -> 0.38 | CL19: =CP18 -> 0 | CM19: =IF(CH19<=$CM$4,CL19/($CM$4-CH19+1),0) -> 0 | CN19: =CM19*CK19 -> 0 | CO19: =CR18-CN19 -> 864735.55 | CP19: =(CL19-CM19)*(1+Inputs!$B$4) -> 0 | CQ19: =(CQ18+CM19)*(1+Inputs!$B$4) -> 3609192.6 | CR19: =CO19*(1+Inputs!$B$4*(1-Inputs!$B$8)) -> 946885.43 | CS19: =IF(CR18<=0,0,CS18*CO19/CR18) -> 318660.33 | CT19: =CQ19+CP19*(1-Inputs!$B$6)+CR19-(CR19-CS19)*Inputs!$B$9 -> 4392739.5 | CU19: =CQ19/(CQ19+CP19+CR19) -> 0.79217094 | CV19: =IF(CT19>M19,1,0) -> 0 | CW19: =IF(CO19<0,"SHORT","ok") -> ok
A20: 13 | B20: =B19+1 -> 70 | C20: =C19+1 -> 2038 | D20: =IF(Inputs!$B$15="B",Inputs!$D$31,Inputs!$C$31) -> 0.38 | E20: =I19 -> 3609192.6 | F20: =IF(A20<=$F$4,E20/($F$4-A20+1),0) -> 0 | G20: =F20*D20 -> 0 | H20: =K19-G20 -> 2272421.6 | I20: =(E20-F20)*(1+Inputs!$B$4) -> 3970111.9 | J20: =(J19+F20)*(1+Inputs!$B$4) -> 0 | K20: =H20*(1+Inputs!$B$4*(1-Inputs!$B$8)) -> 2488301.7 | L20: =IF(K19<=0,0,L19*H20/K19) -> 764750 | M20: =J20+I20*(1-Inputs!$B$6)+K20-(K20-L20)*Inputs!$B$9 -> 4819256.6 | N20: =J20/(J20+I20+K20) -> 0 | O20: =IF(M20>M20,1,0) -> 0 | P20: =IF(H20<0,"SHORT","ok") -> ok | R20: 13 | S20: =S19+1 -> 70 | T20: =T19+1 -> 2038 | U20: =IF(Inputs!$B$15="B",Inputs!$D$31,Inputs!$C$31) -> 0.38 | V20: =Z19 -> 0 | W20: =IF(R20<=$W$4,V20/($W$4-R20+1),0) -> 0 | X20: =W20*U20 -> 0 | Y20: =AB19-X20 -> 973894.99 | Z20: =(V20-W20)*(1+Inputs!$B$4) -> 0 | AA20: =(AA19+W20)*(1+Inputs!$B$4) -> 3970111.9 | AB20: =Y20*(1+Inputs!$B$4*(1-Inputs!$B$8)) -> 1066415 | AC20: =IF(AB19<=0,0,AC19*Y20/AB19) -> 327750 | AD20: =AA20+Z20*(1-Inputs!$B$6)+AB20-(AB20-AC20)*Inputs!$B$9 -> 4844474 | AE20: =AA20/(AA20+Z20+AB20) -> 0.78826381 | AF20: =IF(AD20>M20,1,0) -> 1 | AG20: =IF(Y20<0,"SHORT","ok") -> ok | AI20: 13 | AJ20: =AJ19+1 -> 70 | AK20: =AK19+1 -> 2038 | AL20: =IF(Inputs!$B$15="B",Inputs!$D$31,Inputs!$C$31) -> 0.38 | AM20: =AQ19 -> 0 | AN20: =IF(AI20<=$AN$4,AM20/($AN$4-AI20+1),0) -> 0 | AO20: =AN20*AL20 -> 0 | AP20: =AS19-AO20 -> 967956.62 | AQ20: =(AM20-AN20)*(1+Inputs!$B$4) -> 0 | AR20: =(AR19+AN20)*(1+Inputs!$B$4) -> 3970111.9 | AS20: =AP20*(1+Inputs!$B$4*(1-Inputs!$B$8)) -> 1059912.5 | AT20: =IF(AS19<=0,0,AT19*AP20/AS19) -> 325751.53 | AU20: =AR20+AQ20*(1-Inputs!$B$6)+AS20-(AS20-AT20)*Inputs!$B$9 -> 4839142.5 | AV20: =AR20/(AR20+AQ20+AS20) -> 0.78928283 | AW20: =IF(AU20>M20,1,0) -> 1 | AX20: =IF(AP20<0,"SHORT","ok") -> ok | AZ20: 13 | BA20: =BA19+1 -> 70 | BB20: =BB19+1 -> 2038 | BC20: =IF(Inputs!$B$15="B",Inputs!$D$31,Inputs!$C$31) -> 0.38 | BD20: =BH19 -> 0 | BE20: =IF(AZ20<=$BE$4,BD20/($BE$4-AZ20+1),0) -> 0 | BF20: =BE20*BC20 -> 0 | BG20: =BJ19-BF20 -> 961982.02 | BH20: =(BD20-BE20)*(1+Inputs!$B$4) -> 0 | BI20: =(BI19+BE20)*(1+Inputs!$B$4) -> 3970111.9 | BJ20: =BG20*(1+Inputs!$B$4*(1-Inputs!$B$8)) -> 1053370.3 | BK20: =IF(BJ19<=0,0,BK19*BG20/BJ19) -> 323740.87 | BL20: =BI20+BH20*(1-Inputs!$B$6)+BJ20-(BJ20-BK20)*Inputs!$B$9 -> 4833778.6 | BM20: =BI20/(BI20+BH20+BJ20) -> 0.79031073 | BN20: =IF(BL20>M20,1,0) -> 1 | BO20: =IF(BG20<0,"SHORT","ok") -> ok | BQ20: 13 | BR20: =BR19+1 -> 70 | BS20: =BS19+1 -> 2038 | BT20: =IF(Inputs!$B$15="B",Inputs!$D$31,Inputs!$C$31) -> 0.38 | BU20: =BY19 -> 0 | BV20: =IF(BQ20<=$BV$4,BU20/($BV$4-BQ20+1),0) -> 0 | BW20: =BV20*BT20 -> 0 | BX20: =CA19-BW20 -> 952951.67 | BY20: =(BU20-BV20)*(1+Inputs!$B$4) -> 0 | BZ20: =(BZ19+BV20)*(1+Inputs!$B$4) -> 3970111.9 | CA20: =BX20*(1+Inputs!$B$4*(1-Inputs!$B$8)) -> 1043482.1 | CB20: =IF(CA19<=0,0,CB19*BX20/CA19) -> 320701.84 | CC20: =BZ20+BY20*(1-Inputs!$B$6)+CA20-(CA20-CB20)*Inputs!$B$9 -> 4825671.1 | CD20: =BZ20/(BZ20+BY20+CA20) -> 0.79186945 | CE20: =IF(CC20>M20,1,0) -> 1 | CF20: =IF(BX20<0,"SHORT","ok") -> ok | CH20: 13 | CI20: =CI19+1 -> 70 | CJ20: =CJ19+1 -> 2038 | CK20: =IF(Inputs!$B$15="B",Inputs!$D$31,Inputs!$C$31) -> 0.38 | CL20: =CP19 -> 0 | CM20: =IF(CH20<=$CM$4,CL20/($CM$4-CH20+1),0) -> 0 | CN20: =CM20*CK20 -> 0 | CO20: =CR19-CN20 -> 946885.43 | CP20: =(CL20-CM20)*(1+Inputs!$B$4) -> 0 | CQ20: =(CQ19+CM20)*(1+Inputs!$B$4) -> 3970111.9 | CR20: =CO20*(1+Inputs!$B$4*(1-Inputs!$B$8)) -> 1036839.5 | CS20: =IF(CR19<=0,0,CS19*CO20/CR19) -> 318660.33 | CT20: =CQ20+CP20*(1-Inputs!$B$6)+CR20-(CR20-CS20)*Inputs!$B$9 -> 4820224.8 | CU20: =CQ20/(CQ20+CP20+CR20) -> 0.79291999 | CV20: =IF(CT20>M20,1,0) -> 1 | CW20: =IF(CO20<0,"SHORT","ok") -> ok
A21: 14 | B21: =B20+1 -> 71 | C21: =C20+1 -> 2039 | D21: =IF(Inputs!$B$15="B",Inputs!$D$32,Inputs!$C$32) -> 0.38 | E21: =I20 -> 3970111.9 | F21: =IF(A21<=$F$4,E21/($F$4-A21+1),0) -> 0 | G21: =F21*D21 -> 0 | H21: =K20-G21 -> 2488301.7 | I21: =(E21-F21)*(1+Inputs!$B$4) -> 4367123.1 | J21: =(J20+F21)*(1+Inputs!$B$4) -> 0 | K21: =H21*(1+Inputs!$B$4*(1-Inputs!$B$8)) -> 2724690.4 | L21: =IF(K20<=0,0,L20*H21/K20) -> 764750 | M21: =J21+I21*(1-Inputs!$B$6)+K21-(K21-L21)*Inputs!$B$9 -> 5272092 | N21: =J21/(J21+I21+K21) -> 0 | O21: =IF(M21>M21,1,0) -> 0 | P21: =IF(H21<0,"SHORT","ok") -> ok | R21: 14 | S21: =S20+1 -> 71 | T21: =T20+1 -> 2039 | U21: =IF(Inputs!$B$15="B",Inputs!$D$32,Inputs!$C$32) -> 0.38 | V21: =Z20 -> 0 | W21: =IF(R21<=$W$4,V21/($W$4-R21+1),0) -> 0 | X21: =W21*U21 -> 0 | Y21: =AB20-X21 -> 1066415 | Z21: =(V21-W21)*(1+Inputs!$B$4) -> 0 | AA21: =(AA20+W21)*(1+Inputs!$B$4) -> 4367123.1 | AB21: =Y21*(1+Inputs!$B$4*(1-Inputs!$B$8)) -> 1167724.4 | AC21: =IF(AB20<=0,0,AC20*Y21/AB20) -> 327750 | AD21: =AA21+Z21*(1-Inputs!$B$6)+AB21-(AB21-AC21)*Inputs!$B$9 -> 5316454.2 | AE21: =AA21/(AA21+Z21+AB21) -> 0.7890232 | AF21: =IF(AD21>M21,1,0) -> 1 | AG21: =IF(Y21<0,"SHORT","ok") -> ok | AI21: 14 | AJ21: =AJ20+1 -> 71 | AK21: =AK20+1 -> 2039 | AL21: =IF(Inputs!$B$15="B",Inputs!$D$32,Inputs!$C$32) -> 0.38 | AM21: =AQ20 -> 0 | AN21: =IF(AI21<=$AN$4,AM21/($AN$4-AI21+1),0) -> 0 | AO21: =AN21*AL21 -> 0 | AP21: =AS20-AO21 -> 1059912.5 | AQ21: =(AM21-AN21)*(1+Inputs!$B$4) -> 0 | AR21: =(AR20+AN21)*(1+Inputs!$B$4) -> 4367123.1 | AS21: =AP21*(1+Inputs!$B$4*(1-Inputs!$B$8)) -> 1160604.2 | AT21: =IF(AS20<=0,0,AT20*AP21/AS20) -> 325751.53 | AU21: =AR21+AQ21*(1-Inputs!$B$6)+AS21-(AS21-AT21)*Inputs!$B$9 -> 5310665.6 | AV21: =AR21/(AR21+AQ21+AS21) -> 0.79003954 | AW21: =IF(AU21>M21,1,0) -> 1 | AX21: =IF(AP21<0,"SHORT","ok") -> ok | AZ21: 14 | BA21: =BA20+1 -> 71 | BB21: =BB20+1 -> 2039 | BC21: =IF(Inputs!$B$15="B",Inputs!$D$32,Inputs!$C$32) -> 0.38 | BD21: =BH20 -> 0 | BE21: =IF(AZ21<=$BE$4,BD21/($BE$4-AZ21+1),0) -> 0 | BF21: =BE21*BC21 -> 0 | BG21: =BJ20-BF21 -> 1053370.3 | BH21: =(BD21-BE21)*(1+Inputs!$B$4) -> 0 | BI21: =(BI20+BE21)*(1+Inputs!$B$4) -> 4367123.1 | BJ21: =BG21*(1+Inputs!$B$4*(1-Inputs!$B$8)) -> 1153440.5 | BK21: =IF(BJ20<=0,0,BK20*BG21/BJ20) -> 323740.87 | BL21: =BI21+BH21*(1-Inputs!$B$6)+BJ21-(BJ21-BK21)*Inputs!$B$9 -> 5304841.7 | BM21: =BI21/(BI21+BH21+BJ21) -> 0.79106472 | BN21: =IF(BL21>M21,1,0) -> 1 | BO21: =IF(BG21<0,"SHORT","ok") -> ok | BQ21: 14 | BR21: =BR20+1 -> 71 | BS21: =BS20+1 -> 2039 | BT21: =IF(Inputs!$B$15="B",Inputs!$D$32,Inputs!$C$32) -> 0.38 | BU21: =BY20 -> 0 | BV21: =IF(BQ21<=$BV$4,BU21/($BV$4-BQ21+1),0) -> 0 | BW21: =BV21*BT21 -> 0 | BX21: =CA20-BW21 -> 1043482.1 | BY21: =(BU21-BV21)*(1+Inputs!$B$4) -> 0 | BZ21: =(BZ20+BV21)*(1+Inputs!$B$4) -> 4367123.1 | CA21: =BX21*(1+Inputs!$B$4*(1-Inputs!$B$8)) -> 1142612.9 | CB21: =IF(CA20<=0,0,CB20*BX21/CA20) -> 320701.84 | CC21: =BZ21+BY21*(1-Inputs!$B$6)+CA21-(CA21-CB21)*Inputs!$B$9 -> 5296039.1 | CD21: =BZ21/(BZ21+BY21+CA21) -> 0.7926193 | CE21: =IF(CC21>M21,1,0) -> 1 | CF21: =IF(BX21<0,"SHORT","ok") -> ok | CH21: 14 | CI21: =CI20+1 -> 71 | CJ21: =CJ20+1 -> 2039 | CK21: =IF(Inputs!$B$15="B",Inputs!$D$32,Inputs!$C$32) -> 0.38 | CL21: =CP20 -> 0 | CM21: =IF(CH21<=$CM$4,CL21/($CM$4-CH21+1),0) -> 0 | CN21: =CM21*CK21 -> 0 | CO21: =CR20-CN21 -> 1036839.5 | CP21: =(CL21-CM21)*(1+Inputs!$B$4) -> 0 | CQ21: =(CQ20+CM21)*(1+Inputs!$B$4) -> 4367123.1 | CR21: =CO21*(1+Inputs!$B$4*(1-Inputs!$B$8)) -> 1135339.3 | CS21: =IF(CR20<=0,0,CS20*CO21/CR20) -> 318660.33 | CT21: =CQ21+CP21*(1-Inputs!$B$6)+CR21-(CR21-CS21)*Inputs!$B$9 -> 5290125.9 | CU21: =CQ21/(CQ21+CP21+CR21) -> 0.79366705 | CV21: =IF(CT21>M21,1,0) -> 1 | CW21: =IF(CO21<0,"SHORT","ok") -> ok
A22: 15 | B22: =B21+1 -> 72 | C22: =C21+1 -> 2040 | D22: =IF(Inputs!$B$15="B",Inputs!$D$33,Inputs!$C$33) -> 0.38 | E22: =I21 -> 4367123.1 | F22: =IF(A22<=$F$4,E22/($F$4-A22+1),0) -> 0 | G22: =F22*D22 -> 0 | H22: =K21-G22 -> 2724690.4 | I22: =(E22-F22)*(1+Inputs!$B$4) -> 4803835.4 | J22: =(J21+F22)*(1+Inputs!$B$4) -> 0 | K22: =H22*(1+Inputs!$B$4*(1-Inputs!$B$8)) -> 2983535.9 | L22: =IF(K21<=0,0,L21*H22/K21) -> 764750 | M22: =J22+I22*(1-Inputs!$B$6)+K22-(K22-L22)*Inputs!$B$9 -> 5769336.4 | N22: =J22/(J22+I22+K22) -> 0 | O22: =IF(M22>M22,1,0) -> 0 | P22: =IF(H22<0,"SHORT","ok") -> ok | R22: 15 | S22: =S21+1 -> 72 | T22: =T21+1 -> 2040 | U22: =IF(Inputs!$B$15="B",Inputs!$D$33,Inputs!$C$33) -> 0.38 | V22: =Z21 -> 0 | W22: =IF(R22<=$W$4,V22/($W$4-R22+1),0) -> 0 | X22: =W22*U22 -> 0 | Y22: =AB21-X22 -> 1167724.4 | Z22: =(V22-W22)*(1+Inputs!$B$4) -> 0 | AA22: =(AA21+W22)*(1+Inputs!$B$4) -> 4803835.4 | AB22: =Y22*(1+Inputs!$B$4*(1-Inputs!$B$8)) -> 1278658.3 | AC22: =IF(AB21<=0,0,AC21*Y22/AB21) -> 327750 | AD22: =AA22+Z22*(1-Inputs!$B$6)+AB22-(AB22-AC22)*Inputs!$B$9 -> 5835257.5 | AE22: =AA22/(AA22+Z22+AB22) -> 0.78978058 | AF22: =IF(AD22>M22,1,0) -> 1 | AG22: =IF(Y22<0,"SHORT","ok") -> ok | AI22: 15 | AJ22: =AJ21+1 -> 72 | AK22: =AK21+1 -> 2040 | AL22: =IF(Inputs!$B$15="B",Inputs!$D$33,Inputs!$C$33) -> 0.38 | AM22: =AQ21 -> 0 | AN22: =IF(AI22<=$AN$4,AM22/($AN$4-AI22+1),0) -> 0 | AO22: =AN22*AL22 -> 0 | AP22: =AS21-AO22 -> 1160604.2 | AQ22: =(AM22-AN22)*(1+Inputs!$B$4) -> 0 | AR22: =(AR21+AN22)*(1+Inputs!$B$4) -> 4803835.4 | AS22: =AP22*(1+Inputs!$B$4*(1-Inputs!$B$8)) -> 1270861.6 | AT22: =IF(AS21<=0,0,AT21*AP22/AS21) -> 325751.53 | AU22: =AR22+AQ22*(1-Inputs!$B$6)+AS22-(AS22-AT22)*Inputs!$B$9 -> 5828968.4 | AV22: =AR22/(AR22+AQ22+AS22) -> 0.79079424 | AW22: =IF(AU22>M22,1,0) -> 1 | AX22: =IF(AP22<0,"SHORT","ok") -> ok | AZ22: 15 | BA22: =BA21+1 -> 72 | BB22: =BB21+1 -> 2040 | BC22: =IF(Inputs!$B$15="B",Inputs!$D$33,Inputs!$C$33) -> 0.38 | BD22: =BH21 -> 0 | BE22: =IF(AZ22<=$BE$4,BD22/($BE$4-AZ22+1),0) -> 0 | BF22: =BE22*BC22 -> 0 | BG22: =BJ21-BF22 -> 1153440.5 | BH22: =(BD22-BE22)*(1+Inputs!$B$4) -> 0 | BI22: =(BI21+BE22)*(1+Inputs!$B$4) -> 4803835.4 | BJ22: =BG22*(1+Inputs!$B$4*(1-Inputs!$B$8)) -> 1263017.3 | BK22: =IF(BJ21<=0,0,BK21*BG22/BJ21) -> 323740.87 | BL22: =BI22+BH22*(1-Inputs!$B$6)+BJ22-(BJ22-BK22)*Inputs!$B$9 -> 5822640.9 | BM22: =BI22/(BI22+BH22+BJ22) -> 0.79181671 | BN22: =IF(BL22>M22,1,0) -> 1 | BO22: =IF(BG22<0,"SHORT","ok") -> ok | BQ22: 15 | BR22: =BR21+1 -> 72 | BS22: =BS21+1 -> 2040 | BT22: =IF(Inputs!$B$15="B",Inputs!$D$33,Inputs!$C$33) -> 0.38 | BU22: =BY21 -> 0 | BV22: =IF(BQ22<=$BV$4,BU22/($BV$4-BQ22+1),0) -> 0 | BW22: =BV22*BT22 -> 0 | BX22: =CA21-BW22 -> 1142612.9 | BY22: =(BU22-BV22)*(1+Inputs!$B$4) -> 0 | BZ22: =(BZ21+BV22)*(1+Inputs!$B$4) -> 4803835.4 | CA22: =BX22*(1+Inputs!$B$4*(1-Inputs!$B$8)) -> 1251161.1 | CB22: =IF(CA21<=0,0,CB21*BX22/CA21) -> 320701.84 | CC22: =BZ22+BY22*(1-Inputs!$B$6)+CA22-(CA22-CB22)*Inputs!$B$9 -> 5813077.1 | CD22: =BZ22/(BZ22+BY22+CA22) -> 0.79336716 | CE22: =IF(CC22>M22,1,0) -> 1 | CF22: =IF(BX22<0,"SHORT","ok") -> ok | CH22: 15 | CI22: =CI21+1 -> 72 | CJ22: =CJ21+1 -> 2040 | CK22: =IF(Inputs!$B$15="B",Inputs!$D$33,Inputs!$C$33) -> 0.38 | CL22: =CP21 -> 0 | CM22: =IF(CH22<=$CM$4,CL22/($CM$4-CH22+1),0) -> 0 | CN22: =CM22*CK22 -> 0 | CO22: =CR21-CN22 -> 1135339.3 | CP22: =(CL22-CM22)*(1+Inputs!$B$4) -> 0 | CQ22: =(CQ21+CM22)*(1+Inputs!$B$4) -> 4803835.4 | CR22: =CO22*(1+Inputs!$B$4*(1-Inputs!$B$8)) -> 1243196.5 | CS22: =IF(CR21<=0,0,CS21*CO22/CR21) -> 318660.33 | CT22: =CQ22+CP22*(1-Inputs!$B$6)+CR22-(CR22-CS22)*Inputs!$B$9 -> 5806652.5 | CU22: =CQ22/(CQ22+CP22+CR22) -> 0.79441211 | CV22: =IF(CT22>M22,1,0) -> 1 | CW22: =IF(CO22<0,"SHORT","ok") -> ok
A23: 16 | B23: =B22+1 -> 73 | C23: =C22+1 -> 2041 | D23: =IF(Inputs!$B$15="B",Inputs!$D$34,Inputs!$C$34) -> 0.38 | E23: =I22 -> 4803835.4 | F23: =IF(A23<=$F$4,E23/($F$4-A23+1),0) -> 0 | G23: =F23*D23 -> 0 | H23: =K22-G23 -> 2983535.9 | I23: =(E23-F23)*(1+Inputs!$B$4) -> 5284218.9 | J23: =(J22+F23)*(1+Inputs!$B$4) -> 0 | K23: =H23*(1+Inputs!$B$4*(1-Inputs!$B$8)) -> 3266971.9 | L23: =IF(K22<=0,0,L22*H23/K22) -> 764750 | M23: =J23+I23*(1-Inputs!$B$6)+K23-(K23-L23)*Inputs!$B$9 -> 6315347.4 | N23: =J23/(J23+I23+K23) -> 0 | O23: =IF(M23>M23,1,0) -> 0 | P23: =IF(H23<0,"SHORT","ok") -> ok | R23: 16 | S23: =S22+1 -> 73 | T23: =T22+1 -> 2041 | U23: =IF(Inputs!$B$15="B",Inputs!$D$34,Inputs!$C$34) -> 0.38 | V23: =Z22 -> 0 | W23: =IF(R23<=$W$4,V23/($W$4-R23+1),0) -> 0 | X23: =W23*U23 -> 0 | Y23: =AB22-X23 -> 1278658.3 | Z23: =(V23-W23)*(1+Inputs!$B$4) -> 0 | AA23: =(AA22+W23)*(1+Inputs!$B$4) -> 5284218.9 | AB23: =Y23*(1+Inputs!$B$4*(1-Inputs!$B$8)) -> 1400130.8 | AC23: =IF(AB22<=0,0,AC22*Y23/AB22) -> 327750 | AD23: =AA23+Z23*(1-Inputs!$B$6)+AB23-(AB23-AC23)*Inputs!$B$9 -> 6405530.7 | AE23: =AA23/(AA23+Z23+AB23) -> 0.79053598 | AF23: =IF(AD23>M23,1,0) -> 1 | AG23: =IF(Y23<0,"SHORT","ok") -> ok | AI23: 16 | AJ23: =AJ22+1 -> 73 | AK23: =AK22+1 -> 2041 | AL23: =IF(Inputs!$B$15="B",Inputs!$D$34,Inputs!$C$34) -> 0.38 | AM23: =AQ22 -> 0 | AN23: =IF(AI23<=$AN$4,AM23/($AN$4-AI23+1),0) -> 0 | AO23: =AN23*AL23 -> 0 | AP23: =AS22-AO23 -> 1270861.6 | AQ23: =(AM23-AN23)*(1+Inputs!$B$4) -> 0 | AR23: =(AR22+AN23)*(1+Inputs!$B$4) -> 5284218.9 | AS23: =AP23*(1+Inputs!$B$4*(1-Inputs!$B$8)) -> 1391593.4 | AT23: =IF(AS22<=0,0,AT22*AP23/AS22) -> 325751.53 | AU23: =AR23+AQ23*(1-Inputs!$B$6)+AS23-(AS23-AT23)*Inputs!$B$9 -> 6398693.5 | AV23: =AR23/(AR23+AQ23+AS23) -> 0.79154695 | AW23: =IF(AU23>M23,1,0) -> 1 | AX23: =IF(AP23<0,"SHORT","ok") -> ok | AZ23: 16 | BA23: =BA22+1 -> 73 | BB23: =BB22+1 -> 2041 | BC23: =IF(Inputs!$B$15="B",Inputs!$D$34,Inputs!$C$34) -> 0.38 | BD23: =BH22 -> 0 | BE23: =IF(AZ23<=$BE$4,BD23/($BE$4-AZ23+1),0) -> 0 | BF23: =BE23*BC23 -> 0 | BG23: =BJ22-BF23 -> 1263017.3 | BH23: =(BD23-BE23)*(1+Inputs!$B$4) -> 0 | BI23: =(BI22+BE23)*(1+Inputs!$B$4) -> 5284218.9 | BJ23: =BG23*(1+Inputs!$B$4*(1-Inputs!$B$8)) -> 1383004 | BK23: =IF(BJ22<=0,0,BK22*BG23/BJ22) -> 323740.87 | BL23: =BI23+BH23*(1-Inputs!$B$6)+BJ23-(BJ23-BK23)*Inputs!$B$9 -> 6391814.5 | BM23: =BI23/(BI23+BH23+BJ23) -> 0.79256671 | BN23: =IF(BL23>M23,1,0) -> 1 | BO23: =IF(BG23<0,"SHORT","ok") -> ok | BQ23: 16 | BR23: =BR22+1 -> 73 | BS23: =BS22+1 -> 2041 | BT23: =IF(Inputs!$B$15="B",Inputs!$D$34,Inputs!$C$34) -> 0.38 | BU23: =BY22 -> 0 | BV23: =IF(BQ23<=$BV$4,BU23/($BV$4-BQ23+1),0) -> 0 | BW23: =BV23*BT23 -> 0 | BX23: =CA22-BW23 -> 1251161.1 | BY23: =(BU23-BV23)*(1+Inputs!$B$4) -> 0 | BZ23: =(BZ22+BV23)*(1+Inputs!$B$4) -> 5284218.9 | CA23: =BX23*(1+Inputs!$B$4*(1-Inputs!$B$8)) -> 1370021.4 | CB23: =IF(CA22<=0,0,CB22*BX23/CA22) -> 320701.84 | CC23: =BZ23+BY23*(1-Inputs!$B$6)+CA23-(CA23-CB23)*Inputs!$B$9 -> 6381417.3 | CD23: =BZ23/(BZ23+BY23+CA23) -> 0.79411303 | CE23: =IF(CC23>M23,1,0) -> 1 | CF23: =IF(BX23<0,"SHORT","ok") -> ok | CH23: 16 | CI23: =CI22+1 -> 73 | CJ23: =CJ22+1 -> 2041 | CK23: =IF(Inputs!$B$15="B",Inputs!$D$34,Inputs!$C$34) -> 0.38 | CL23: =CP22 -> 0 | CM23: =IF(CH23<=$CM$4,CL23/($CM$4-CH23+1),0) -> 0 | CN23: =CM23*CK23 -> 0 | CO23: =CR22-CN23 -> 1243196.5 | CP23: =(CL23-CM23)*(1+Inputs!$B$4) -> 0 | CQ23: =(CQ22+CM23)*(1+Inputs!$B$4) -> 5284218.9 | CR23: =CO23*(1+Inputs!$B$4*(1-Inputs!$B$8)) -> 1361300.2 | CS23: =IF(CR22<=0,0,CS22*CO23/CR22) -> 318660.33 | CT23: =CQ23+CP23*(1-Inputs!$B$6)+CR23-(CR23-CS23)*Inputs!$B$9 -> 6374432.8 | CU23: =CQ23/(CQ23+CP23+CR23) -> 0.79515518 | CV23: =IF(CT23>M23,1,0) -> 1 | CW23: =IF(CO23<0,"SHORT","ok") -> ok
A24: 17 | B24: =B23+1 -> 74 | C24: =C23+1 -> 2042 | D24: =IF(Inputs!$B$15="B",Inputs!$D$35,Inputs!$C$35) -> 0.38 | E24: =I23 -> 5284218.9 | F24: =IF(A24<=$F$4,E24/($F$4-A24+1),0) -> 0 | G24: =F24*D24 -> 0 | H24: =K23-G24 -> 3266971.9 | I24: =(E24-F24)*(1+Inputs!$B$4) -> 5812640.8 | J24: =(J23+F24)*(1+Inputs!$B$4) -> 0 | K24: =H24*(1+Inputs!$B$4*(1-Inputs!$B$8)) -> 3577334.2 | L24: =IF(K23<=0,0,L23*H24/K23) -> 764750 | M24: =J24+I24*(1-Inputs!$B$6)+K24-(K24-L24)*Inputs!$B$9 -> 6914910.9 | N24: =J24/(J24+I24+K24) -> 0 | O24: =IF(M24>M24,1,0) -> 0 | P24: =IF(H24<0,"SHORT","ok") -> ok | R24: 17 | S24: =S23+1 -> 74 | T24: =T23+1 -> 2042 | U24: =IF(Inputs!$B$15="B",Inputs!$D$35,Inputs!$C$35) -> 0.38 | V24: =Z23 -> 0 | W24: =IF(R24<=$W$4,V24/($W$4-R24+1),0) -> 0 | X24: =W24*U24 -> 0 | Y24: =AB23-X24 -> 1400130.8 | Z24: =(V24-W24)*(1+Inputs!$B$4) -> 0 | AA24: =(AA23+W24)*(1+Inputs!$B$4) -> 5812640.8 | AB24: =Y24*(1+Inputs!$B$4*(1-Inputs!$B$8)) -> 1533143.2 | AC24: =IF(AB23<=0,0,AC23*Y24/AB23) -> 327750 | AD24: =AA24+Z24*(1-Inputs!$B$6)+AB24-(AB24-AC24)*Inputs!$B$9 -> 7032381.8 | AE24: =AA24/(AA24+Z24+AB24) -> 0.79128937 | AF24: =IF(AD24>M24,1,0) -> 1 | AG24: =IF(Y24<0,"SHORT","ok") -> ok | AI24: 17 | AJ24: =AJ23+1 -> 74 | AK24: =AK23+1 -> 2042 | AL24: =IF(Inputs!$B$15="B",Inputs!$D$35,Inputs!$C$35) -> 0.38 | AM24: =AQ23 -> 0 | AN24: =IF(AI24<=$AN$4,AM24/($AN$4-AI24+1),0) -> 0 | AO24: =AN24*AL24 -> 0 | AP24: =AS23-AO24 -> 1391593.4 | AQ24: =(AM24-AN24)*(1+Inputs!$B$4) -> 0 | AR24: =(AR23+AN24)*(1+Inputs!$B$4) -> 5812640.8 | AS24: =AP24*(1+Inputs!$B$4*(1-Inputs!$B$8)) -> 1523794.8 | AT24: =IF(AS23<=0,0,AT23*AP24/AS23) -> 325751.53 | AU24: =AR24+AQ24*(1-Inputs!$B$6)+AS24-(AS24-AT24)*Inputs!$B$9 -> 7024944.4 | AV24: =AR24/(AR24+AQ24+AS24) -> 0.79229767 | AW24: =IF(AU24>M24,1,0) -> 1 | AX24: =IF(AP24<0,"SHORT","ok") -> ok | AZ24: 17 | BA24: =BA23+1 -> 74 | BB24: =BB23+1 -> 2042 | BC24: =IF(Inputs!$B$15="B",Inputs!$D$35,Inputs!$C$35) -> 0.38 | BD24: =BH23 -> 0 | BE24: =IF(AZ24<=$BE$4,BD24/($BE$4-AZ24+1),0) -> 0 | BF24: =BE24*BC24 -> 0 | BG24: =BJ23-BF24 -> 1383004 | BH24: =(BD24-BE24)*(1+Inputs!$B$4) -> 0 | BI24: =(BI23+BE24)*(1+Inputs!$B$4) -> 5812640.8 | BJ24: =BG24*(1+Inputs!$B$4*(1-Inputs!$B$8)) -> 1514389.4 | BK24: =IF(BJ23<=0,0,BK23*BG24/BJ23) -> 323740.87 | BL24: =BI24+BH24*(1-Inputs!$B$6)+BJ24-(BJ24-BK24)*Inputs!$B$9 -> 7017461.6 | BM24: =BI24/(BI24+BH24+BJ24) -> 0.79331471 | BN24: =IF(BL24>M24,1,0) -> 1 | BO24: =IF(BG24<0,"SHORT","ok") -> ok | BQ24: 17 | BR24: =BR23+1 -> 74 | BS24: =BS23+1 -> 2042 | BT24: =IF(Inputs!$B$15="B",Inputs!$D$35,Inputs!$C$35) -> 0.38 | BU24: =BY23 -> 0 | BV24: =IF(BQ24<=$BV$4,BU24/($BV$4-BQ24+1),0) -> 0 | BW24: =BV24*BT24 -> 0 | BX24: =CA23-BW24 -> 1370021.4 | BY24: =(BU24-BV24)*(1+Inputs!$B$4) -> 0 | BZ24: =(BZ23+BV24)*(1+Inputs!$B$4) -> 5812640.8 | CA24: =BX24*(1+Inputs!$B$4*(1-Inputs!$B$8)) -> 1500173.4 | CB24: =IF(CA23<=0,0,CB23*BX24/CA23) -> 320701.84 | CC24: =BZ24+BY24*(1-Inputs!$B$6)+CA24-(CA24-CB24)*Inputs!$B$9 -> 7006151.6 | CD24: =BZ24/(BZ24+BY24+CA24) -> 0.79485689 | CE24: =IF(CC24>M24,1,0) -> 1 | CF24: =IF(BX24<0,"SHORT","ok") -> ok | CH24: 17 | CI24: =CI23+1 -> 74 | CJ24: =CJ23+1 -> 2042 | CK24: =IF(Inputs!$B$15="B",Inputs!$D$35,Inputs!$C$35) -> 0.38 | CL24: =CP23 -> 0 | CM24: =IF(CH24<=$CM$4,CL24/($CM$4-CH24+1),0) -> 0 | CN24: =CM24*CK24 -> 0 | CO24: =CR23-CN24 -> 1361300.2 | CP24: =(CL24-CM24)*(1+Inputs!$B$4) -> 0 | CQ24: =(CQ23+CM24)*(1+Inputs!$B$4) -> 5812640.8 | CR24: =CO24*(1+Inputs!$B$4*(1-Inputs!$B$8)) -> 1490623.7 | CS24: =IF(CR23<=0,0,CS23*CO24/CR23) -> 318660.33 | CT24: =CQ24+CP24*(1-Inputs!$B$6)+CR24-(CR24-CS24)*Inputs!$B$9 -> 6998554.1 | CU24: =CQ24/(CQ24+CP24+CR24) -> 0.79589624 | CV24: =IF(CT24>M24,1,0) -> 1 | CW24: =IF(CO24<0,"SHORT","ok") -> ok
A25: 18 | B25: =B24+1 -> 75 | C25: =C24+1 -> 2043 | D25: =IF(Inputs!$B$15="B",Inputs!$D$36,Inputs!$C$36) -> 0.38 | E25: =I24 -> 5812640.8 | F25: =IF(A25<=$F$4,E25/($F$4-A25+1),0) -> 0 | G25: =F25*D25 -> 0 | H25: =K24-G25 -> 3577334.2 | I25: =(E25-F25)*(1+Inputs!$B$4) -> 6393904.9 | J25: =(J24+F25)*(1+Inputs!$B$4) -> 0 | K25: =H25*(1+Inputs!$B$4*(1-Inputs!$B$8)) -> 3917180.9 | L25: =IF(K24<=0,0,L24*H25/K24) -> 764750 | M25: =J25+I25*(1-Inputs!$B$6)+K25-(K25-L25)*Inputs!$B$9 -> 7573282.3 | N25: =J25/(J25+I25+K25) -> 0 | O25: =IF(M25>M25,1,0) -> 0 | P25: =IF(H25<0,"SHORT","ok") -> ok | R25: 18 | S25: =S24+1 -> 75 | T25: =T24+1 -> 2043 | U25: =IF(Inputs!$B$15="B",Inputs!$D$36,Inputs!$C$36) -> 0.38 | V25: =Z24 -> 0 | W25: =IF(R25<=$W$4,V25/($W$4-R25+1),0) -> 0 | X25: =W25*U25 -> 0 | Y25: =AB24-X25 -> 1533143.2 | Z25: =(V25-W25)*(1+Inputs!$B$4) -> 0 | AA25: =(AA24+W25)*(1+Inputs!$B$4) -> 6393904.9 | AB25: =Y25*(1+Inputs!$B$4*(1-Inputs!$B$8)) -> 1678791.8 | AC25: =IF(AB24<=0,0,AC24*Y25/AB24) -> 327750 | AD25: =AA25+Z25*(1-Inputs!$B$6)+AB25-(AB25-AC25)*Inputs!$B$9 -> 7721425.9 | AE25: =AA25/(AA25+Z25+AB25) -> 0.79204077 | AF25: =IF(AD25>M25,1,0) -> 1 | AG25: =IF(Y25<0,"SHORT","ok") -> ok | AI25: 18 | AJ25: =AJ24+1 -> 75 | AK25: =AK24+1 -> 2043 | AL25: =IF(Inputs!$B$15="B",Inputs!$D$36,Inputs!$C$36) -> 0.38 | AM25: =AQ24 -> 0 | AN25: =IF(AI25<=$AN$4,AM25/($AN$4-AI25+1),0) -> 0 | AO25: =AN25*AL25 -> 0 | AP25: =AS24-AO25 -> 1523794.8 | AQ25: =(AM25-AN25)*(1+Inputs!$B$4) -> 0 | AR25: =(AR24+AN25)*(1+Inputs!$B$4) -> 6393904.9 | AS25: =AP25*(1+Inputs!$B$4*(1-Inputs!$B$8)) -> 1668555.3 | AT25: =IF(AS24<=0,0,AT24*AP25/AS24) -> 325751.53 | AU25: =AR25+AQ25*(1-Inputs!$B$6)+AS25-(AS25-AT25)*Inputs!$B$9 -> 7713331.2 | AV25: =AR25/(AR25+AQ25+AS25) -> 0.79304638 | AW25: =IF(AU25>M25,1,0) -> 1 | AX25: =IF(AP25<0,"SHORT","ok") -> ok | AZ25: 18 | BA25: =BA24+1 -> 75 | BB25: =BB24+1 -> 2043 | BC25: =IF(Inputs!$B$15="B",Inputs!$D$36,Inputs!$C$36) -> 0.38 | BD25: =BH24 -> 0 | BE25: =IF(AZ25<=$BE$4,BD25/($BE$4-AZ25+1),0) -> 0 | BF25: =BE25*BC25 -> 0 | BG25: =BJ24-BF25 -> 1514389.4 | BH25: =(BD25-BE25)*(1+Inputs!$B$4) -> 0 | BI25: =(BI24+BE25)*(1+Inputs!$B$4) -> 6393904.9 | BJ25: =BG25*(1+Inputs!$B$4*(1-Inputs!$B$8)) -> 1658256.4 | BK25: =IF(BJ24<=0,0,BK24*BG25/BJ24) -> 323740.87 | BL25: =BI25+BH25*(1-Inputs!$B$6)+BJ25-(BJ25-BK25)*Inputs!$B$9 -> 7705187.2 | BM25: =BI25/(BI25+BH25+BJ25) -> 0.79406071 | BN25: =IF(BL25>M25,1,0) -> 1 | BO25: =IF(BG25<0,"SHORT","ok") -> ok | BQ25: 18 | BR25: =BR24+1 -> 75 | BS25: =BS24+1 -> 2043 | BT25: =IF(Inputs!$B$15="B",Inputs!$D$36,Inputs!$C$36) -> 0.38 | BU25: =BY24 -> 0 | BV25: =IF(BQ25<=$BV$4,BU25/($BV$4-BQ25+1),0) -> 0 | BW25: =BV25*BT25 -> 0 | BX25: =CA24-BW25 -> 1500173.4 | BY25: =(BU25-BV25)*(1+Inputs!$B$4) -> 0 | BZ25: =(BZ24+BV25)*(1+Inputs!$B$4) -> 6393904.9 | CA25: =BX25*(1+Inputs!$B$4*(1-Inputs!$B$8)) -> 1642689.9 | CB25: =IF(CA24<=0,0,CB24*BX25/CA24) -> 320701.84 | CC25: =BZ25+BY25*(1-Inputs!$B$6)+CA25-(CA25-CB25)*Inputs!$B$9 -> 7692877.9 | CD25: =BZ25/(BZ25+BY25+CA25) -> 0.79559876 | CE25: =IF(CC25>M25,1,0) -> 1 | CF25: =IF(BX25<0,"SHORT","ok") -> ok | CH25: 18 | CI25: =CI24+1 -> 75 | CJ25: =CJ24+1 -> 2043 | CK25: =IF(Inputs!$B$15="B",Inputs!$D$36,Inputs!$C$36) -> 0.38 | CL25: =CP24 -> 0 | CM25: =IF(CH25<=$CM$4,CL25/($CM$4-CH25+1),0) -> 0 | CN25: =CM25*CK25 -> 0 | CO25: =CR24-CN25 -> 1490623.7 | CP25: =(CL25-CM25)*(1+Inputs!$B$4) -> 0 | CQ25: =(CQ24+CM25)*(1+Inputs!$B$4) -> 6393904.9 | CR25: =CO25*(1+Inputs!$B$4*(1-Inputs!$B$8)) -> 1632233 | CS25: =IF(CR24<=0,0,CS24*CO25/CR24) -> 318660.33 | CT25: =CQ25+CP25*(1-Inputs!$B$6)+CR25-(CR25-CS25)*Inputs!$B$9 -> 7684609 | CU25: =CQ25/(CQ25+CP25+CR25) -> 0.79663532 | CV25: =IF(CT25>M25,1,0) -> 1 | CW25: =IF(CO25<0,"SHORT","ok") -> ok
A26: 19 | B26: =B25+1 -> 76 | C26: =C25+1 -> 2044 | D26: =IF(Inputs!$B$15="B",Inputs!$D$37,Inputs!$C$37) -> 0.38 | E26: =I25 -> 6393904.9 | F26: =IF(A26<=$F$4,E26/($F$4-A26+1),0) -> 0 | G26: =F26*D26 -> 0 | H26: =K25-G26 -> 3917180.9 | I26: =(E26-F26)*(1+Inputs!$B$4) -> 7033295.4 | J26: =(J25+F26)*(1+Inputs!$B$4) -> 0 | K26: =H26*(1+Inputs!$B$4*(1-Inputs!$B$8)) -> 4289313.1 | L26: =IF(K25<=0,0,L25*H26/K25) -> 764750 | M26: =J26+I26*(1-Inputs!$B$6)+K26-(K26-L26)*Inputs!$B$9 -> 8296233.5 | N26: =J26/(J26+I26+K26) -> 0 | O26: =IF(M26>M26,1,0) -> 0 | P26: =IF(H26<0,"SHORT","ok") -> ok | R26: 19 | S26: =S25+1 -> 76 | T26: =T25+1 -> 2044 | U26: =IF(Inputs!$B$15="B",Inputs!$D$37,Inputs!$C$37) -> 0.38 | V26: =Z25 -> 0 | W26: =IF(R26<=$W$4,V26/($W$4-R26+1),0) -> 0 | X26: =W26*U26 -> 0 | Y26: =AB25-X26 -> 1678791.8 | Z26: =(V26-W26)*(1+Inputs!$B$4) -> 0 | AA26: =(AA25+W26)*(1+Inputs!$B$4) -> 7033295.4 | AB26: =Y26*(1+Inputs!$B$4*(1-Inputs!$B$8)) -> 1838277 | AC26: =IF(AB25<=0,0,AC25*Y26/AB25) -> 327750 | AD26: =AA26+Z26*(1-Inputs!$B$6)+AB26-(AB26-AC26)*Inputs!$B$9 -> 8478835.4 | AE26: =AA26/(AA26+Z26+AB26) -> 0.79279017 | AF26: =IF(AD26>M26,1,0) -> 1 | AG26: =IF(Y26<0,"SHORT","ok") -> ok | AI26: 19 | AJ26: =AJ25+1 -> 76 | AK26: =AK25+1 -> 2044 | AL26: =IF(Inputs!$B$15="B",Inputs!$D$37,Inputs!$C$37) -> 0.38 | AM26: =AQ25 -> 0 | AN26: =IF(AI26<=$AN$4,AM26/($AN$4-AI26+1),0) -> 0 | AO26: =AN26*AL26 -> 0 | AP26: =AS25-AO26 -> 1668555.3 | AQ26: =(AM26-AN26)*(1+Inputs!$B$4) -> 0 | AR26: =(AR25+AN26)*(1+Inputs!$B$4) -> 7033295.4 | AS26: =AP26*(1+Inputs!$B$4*(1-Inputs!$B$8)) -> 1827068.1 | AT26: =IF(AS25<=0,0,AT25*AP26/AS25) -> 325751.53 | AU26: =AR26+AQ26*(1-Inputs!$B$6)+AS26-(AS26-AT26)*Inputs!$B$9 -> 8470021.2 | AV26: =AR26/(AR26+AQ26+AS26) -> 0.7937931 | AW26: =IF(AU26>M26,1,0) -> 1 | AX26: =IF(AP26<0,"SHORT","ok") -> ok | AZ26: 19 | BA26: =BA25+1 -> 76 | BB26: =BB25+1 -> 2044 | BC26: =IF(Inputs!$B$15="B",Inputs!$D$37,Inputs!$C$37) -> 0.38 | BD26: =BH25 -> 0 | BE26: =IF(AZ26<=$BE$4,BD26/($BE$4-AZ26+1),0) -> 0 | BF26: =BE26*BC26 -> 0 | BG26: =BJ25-BF26 -> 1658256.4 | BH26: =(BD26-BE26)*(1+Inputs!$B$4) -> 0 | BI26: =(BI25+BE26)*(1+Inputs!$B$4) -> 7033295.4 | BJ26: =BG26*(1+Inputs!$B$4*(1-Inputs!$B$8)) -> 1815790.7 | BK26: =IF(BJ25<=0,0,BK25*BG26/BJ25) -> 323740.87 | BL26: =BI26+BH26*(1-Inputs!$B$6)+BJ26-(BJ26-BK26)*Inputs!$B$9 -> 8461153.2 | BM26: =BI26/(BI26+BH26+BJ26) -> 0.79480472 | BN26: =IF(BL26>M26,1,0) -> 1 | BO26: =IF(BG26<0,"SHORT","ok") -> ok | BQ26: 19 | BR26: =BR25+1 -> 76 | BS26: =BS25+1 -> 2044 | BT26: =IF(Inputs!$B$15="B",Inputs!$D$37,Inputs!$C$37) -> 0.38 | BU26: =BY25 -> 0 | BV26: =IF(BQ26<=$BV$4,BU26/($BV$4-BQ26+1),0) -> 0 | BW26: =BV26*BT26 -> 0 | BX26: =CA25-BW26 -> 1642689.9 | BY26: =(BU26-BV26)*(1+Inputs!$B$4) -> 0 | BZ26: =(BZ25+BV26)*(1+Inputs!$B$4) -> 7033295.4 | CA26: =BX26*(1+Inputs!$B$4*(1-Inputs!$B$8)) -> 1798745.5 | CB26: =IF(CA25<=0,0,CB25*BX26/CA25) -> 320701.84 | CC26: =BZ26+BY26*(1-Inputs!$B$6)+CA26-(CA26-CB26)*Inputs!$B$9 -> 8447749.5 | CD26: =BZ26/(BZ26+BY26+CA26) -> 0.79633864 | CE26: =IF(CC26>M26,1,0) -> 1 | CF26: =IF(BX26<0,"SHORT","ok") -> ok | CH26: 19 | CI26: =CI25+1 -> 76 | CJ26: =CJ25+1 -> 2044 | CK26: =IF(Inputs!$B$15="B",Inputs!$D$37,Inputs!$C$37) -> 0.38 | CL26: =CP25 -> 0 | CM26: =IF(CH26<=$CM$4,CL26/($CM$4-CH26+1),0) -> 0 | CN26: =CM26*CK26 -> 0 | CO26: =CR25-CN26 -> 1632233 | CP26: =(CL26-CM26)*(1+Inputs!$B$4) -> 0 | CQ26: =(CQ25+CM26)*(1+Inputs!$B$4) -> 7033295.4 | CR26: =CO26*(1+Inputs!$B$4*(1-Inputs!$B$8)) -> 1787295.1 | CS26: =IF(CR25<=0,0,CS25*CO26/CR25) -> 318660.33 | CT26: =CQ26+CP26*(1-Inputs!$B$6)+CR26-(CR26-CS26)*Inputs!$B$9 -> 8438745.5 | CU26: =CQ26/(CQ26+CP26+CR26) -> 0.7973724 | CV26: =IF(CT26>M26,1,0) -> 1 | CW26: =IF(CO26<0,"SHORT","ok") -> ok
A27: 20 | B27: =B26+1 -> 77 | C27: =C26+1 -> 2045 | D27: =IF(Inputs!$B$15="B",Inputs!$D$38,Inputs!$C$38) -> 0.38 | E27: =I26 -> 7033295.4 | F27: =IF(A27<=$F$4,E27/($F$4-A27+1),0) -> 0 | G27: =F27*D27 -> 0 | H27: =K26-G27 -> 4289313.1 | I27: =(E27-F27)*(1+Inputs!$B$4) -> 7736624.9 | J27: =(J26+F27)*(1+Inputs!$B$4) -> 0 | K27: =H27*(1+Inputs!$B$4*(1-Inputs!$B$8)) -> 4696797.9 | L27: =IF(K26<=0,0,L26*H27/K26) -> 764750 | M27: =J27+I27*(1-Inputs!$B$6)+K27-(K27-L27)*Inputs!$B$9 -> 9090102.9 | N27: =J27/(J27+I27+K27) -> 0 | O27: =IF(M27>M27,1,0) -> 0 | P27: =IF(H27<0,"SHORT","ok") -> ok | R27: 20 | S27: =S26+1 -> 77 | T27: =T26+1 -> 2045 | U27: =IF(Inputs!$B$15="B",Inputs!$D$38,Inputs!$C$38) -> 0.38 | V27: =Z26 -> 0 | W27: =IF(R27<=$W$4,V27/($W$4-R27+1),0) -> 0 | X27: =W27*U27 -> 0 | Y27: =AB26-X27 -> 1838277 | Z27: =(V27-W27)*(1+Inputs!$B$4) -> 0 | AA27: =(AA26+W27)*(1+Inputs!$B$4) -> 7736624.9 | AB27: =Y27*(1+Inputs!$B$4*(1-Inputs!$B$8)) -> 2012913.4 | AC27: =IF(AB26<=0,0,AC26*Y27/AB26) -> 327750 | AD27: =AA27+Z27*(1-Inputs!$B$6)+AB27-(AB27-AC27)*Inputs!$B$9 -> 9311395.8 | AE27: =AA27/(AA27+Z27+AB27) -> 0.79353757 | AF27: =IF(AD27>M27,1,0) -> 1 | AG27: =IF(Y27<0,"SHORT","ok") -> ok | AI27: 20 | AJ27: =AJ26+1 -> 77 | AK27: =AK26+1 -> 2045 | AL27: =IF(Inputs!$B$15="B",Inputs!$D$38,Inputs!$C$38) -> 0.38 | AM27: =AQ26 -> 0 | AN27: =IF(AI27<=$AN$4,AM27/($AN$4-AI27+1),0) -> 0 | AO27: =AN27*AL27 -> 0 | AP27: =AS26-AO27 -> 1827068.1 | AQ27: =(AM27-AN27)*(1+Inputs!$B$4) -> 0 | AR27: =(AR26+AN27)*(1+Inputs!$B$4) -> 7736624.9 | AS27: =AP27*(1+Inputs!$B$4*(1-Inputs!$B$8)) -> 2000639.5 | AT27: =IF(AS26<=0,0,AT26*AP27/AS26) -> 325751.53 | AU27: =AR27+AQ27*(1-Inputs!$B$6)+AS27-(AS27-AT27)*Inputs!$B$9 -> 9301793.6 | AV27: =AR27/(AR27+AQ27+AS27) -> 0.79453783 | AW27: =IF(AU27>M27,1,0) -> 1 | AX27: =IF(AP27<0,"SHORT","ok") -> ok | AZ27: 20 | BA27: =BA26+1 -> 77 | BB27: =BB26+1 -> 2045 | BC27: =IF(Inputs!$B$15="B",Inputs!$D$38,Inputs!$C$38) -> 0.38 | BD27: =BH26 -> 0 | BE27: =IF(AZ27<=$BE$4,BD27/($BE$4-AZ27+1),0) -> 0 | BF27: =BE27*BC27 -> 0 | BG27: =BJ26-BF27 -> 1815790.7 | BH27: =(BD27-BE27)*(1+Inputs!$B$4) -> 0 | BI27: =(BI26+BE27)*(1+Inputs!$B$4) -> 7736624.9 | BJ27: =BG27*(1+Inputs!$B$4*(1-Inputs!$B$8)) -> 1988290.8 | BK27: =IF(BJ26<=0,0,BK26*BG27/BJ26) -> 323740.87 | BL27: =BI27+BH27*(1-Inputs!$B$6)+BJ27-(BJ27-BK27)*Inputs!$B$9 -> 9292132.8 | BM27: =BI27/(BI27+BH27+BJ27) -> 0.79554673 | BN27: =IF(BL27>M27,1,0) -> 1 | BO27: =IF(BG27<0,"SHORT","ok") -> ok | BQ27: 20 | BR27: =BR26+1 -> 77 | BS27: =BS26+1 -> 2045 | BT27: =IF(Inputs!$B$15="B",Inputs!$D$38,Inputs!$C$38) -> 0.38 | BU27: =BY26 -> 0 | BV27: =IF(BQ27<=$BV$4,BU27/($BV$4-BQ27+1),0) -> 0 | BW27: =BV27*BT27 -> 0 | BX27: =CA26-BW27 -> 1798745.5 | BY27: =(BU27-BV27)*(1+Inputs!$B$4) -> 0 | BZ27: =(BZ26+BV27)*(1+Inputs!$B$4) -> 7736624.9 | CA27: =BX27*(1+Inputs!$B$4*(1-Inputs!$B$8)) -> 1969626.3 | CB27: =IF(CA26<=0,0,CB26*BX27/CA26) -> 320701.84 | CC27: =BZ27+BY27*(1-Inputs!$B$6)+CA27-(CA27-CB27)*Inputs!$B$9 -> 9277530.9 | CD27: =BZ27/(BZ27+BY27+CA27) -> 0.79707652 | CE27: =IF(CC27>M27,1,0) -> 1 | CF27: =IF(BX27<0,"SHORT","ok") -> ok | CH27: 20 | CI27: =CI26+1 -> 77 | CJ27: =CJ26+1 -> 2045 | CK27: =IF(Inputs!$B$15="B",Inputs!$D$38,Inputs!$C$38) -> 0.38 | CL27: =CP26 -> 0 | CM27: =IF(CH27<=$CM$4,CL27/($CM$4-CH27+1),0) -> 0 | CN27: =CM27*CK27 -> 0 | CO27: =CR26-CN27 -> 1787295.1 | CP27: =(CL27-CM27)*(1+Inputs!$B$4) -> 0 | CQ27: =(CQ26+CM27)*(1+Inputs!$B$4) -> 7736624.9 | CR27: =CO27*(1+Inputs!$B$4*(1-Inputs!$B$8)) -> 1957088.1 | CS27: =IF(CR26<=0,0,CS26*CO27/CR26) -> 318660.33 | CT27: =CQ27+CP27*(1-Inputs!$B$6)+CR27-(CR27-CS27)*Inputs!$B$9 -> 9267721.9 | CU27: =CQ27/(CQ27+CP27+CR27) -> 0.79810748 | CV27: =IF(CT27>M27,1,0) -> 1 | CW27: =IF(CO27<0,"SHORT","ok") -> ok
A28: 21 | B28: =B27+1 -> 78 | C28: =C27+1 -> 2046 | D28: =IF(Inputs!$B$15="B",Inputs!$D$39,Inputs!$C$39) -> 0.38 | E28: =I27 -> 7736624.9 | F28: =IF(A28<=$F$4,E28/($F$4-A28+1),0) -> 0 | G28: =F28*D28 -> 0 | H28: =K27-G28 -> 4696797.9 | I28: =(E28-F28)*(1+Inputs!$B$4) -> 8510287.4 | J28: =(J27+F28)*(1+Inputs!$B$4) -> 0 | K28: =H28*(1+Inputs!$B$4*(1-Inputs!$B$8)) -> 5142993.7 | L28: =IF(K27<=0,0,L27*H28/K27) -> 764750 | M28: =J28+I28*(1-Inputs!$B$6)+K28-(K28-L28)*Inputs!$B$9 -> 9961851.5 | N28: =J28/(J28+I28+K28) -> 0 | O28: =IF(M28>M28,1,0) -> 0 | P28: =IF(H28<0,"SHORT","ok") -> ok | R28: 21 | S28: =S27+1 -> 78 | T28: =T27+1 -> 2046 | U28: =IF(Inputs!$B$15="B",Inputs!$D$39,Inputs!$C$39) -> 0.38 | V28: =Z27 -> 0 | W28: =IF(R28<=$W$4,V28/($W$4-R28+1),0) -> 0 | X28: =W28*U28 -> 0 | Y28: =AB27-X28 -> 2012913.4 | Z28: =(V28-W28)*(1+Inputs!$B$4) -> 0 | AA28: =(AA27+W28)*(1+Inputs!$B$4) -> 8510287.4 | AB28: =Y28*(1+Inputs!$B$4*(1-Inputs!$B$8)) -> 2204140.1 | AC28: =IF(AB27<=0,0,AC27*Y28/AB27) -> 327750 | AD28: =AA28+Z28*(1-Inputs!$B$6)+AB28-(AB28-AC28)*Inputs!$B$9 -> 10226566 | AE28: =AA28/(AA28+Z28+AB28) -> 0.79428298 | AF28: =IF(AD28>M28,1,0) -> 1 | AG28: =IF(Y28<0,"SHORT","ok") -> ok | AI28: 21 | AJ28: =AJ27+1 -> 78 | AK28: =AK27+1 -> 2046 | AL28: =IF(Inputs!$B$15="B",Inputs!$D$39,Inputs!$C$39) -> 0.38 | AM28: =AQ27 -> 0 | AN28: =IF(AI28<=$AN$4,AM28/($AN$4-AI28+1),0) -> 0 | AO28: =AN28*AL28 -> 0 | AP28: =AS27-AO28 -> 2000639.5 | AQ28: =(AM28-AN28)*(1+Inputs!$B$4) -> 0 | AR28: =(AR27+AN28)*(1+Inputs!$B$4) -> 8510287.4 | AS28: =AP28*(1+Inputs!$B$4*(1-Inputs!$B$8)) -> 2190700.3 | AT28: =IF(AS27<=0,0,AT27*AP28/AS27) -> 325751.53 | AU28: =AR28+AQ28*(1-Inputs!$B$6)+AS28-(AS28-AT28)*Inputs!$B$9 -> 10216101 | AV28: =AR28/(AR28+AQ28+AS28) -> 0.79528055 | AW28: =IF(AU28>M28,1,0) -> 1 | AX28: =IF(AP28<0,"SHORT","ok") -> ok | AZ28: 21 | BA28: =BA27+1 -> 78 | BB28: =BB27+1 -> 2046 | BC28: =IF(Inputs!$B$15="B",Inputs!$D$39,Inputs!$C$39) -> 0.38 | BD28: =BH27 -> 0 | BE28: =IF(AZ28<=$BE$4,BD28/($BE$4-AZ28+1),0) -> 0 | BF28: =BE28*BC28 -> 0 | BG28: =BJ27-BF28 -> 1988290.8 | BH28: =(BD28-BE28)*(1+Inputs!$B$4) -> 0 | BI28: =(BI27+BE28)*(1+Inputs!$B$4) -> 8510287.4 | BJ28: =BG28*(1+Inputs!$B$4*(1-Inputs!$B$8)) -> 2177178.5 | BK28: =IF(BJ27<=0,0,BK27*BG28/BJ27) -> 323740.87 | BL28: =BI28+BH28*(1-Inputs!$B$6)+BJ28-(BJ28-BK28)*Inputs!$B$9 -> 10205572 | BM28: =BI28/(BI28+BH28+BJ28) -> 0.79628675 | BN28: =IF(BL28>M28,1,0) -> 1 | BO28: =IF(BG28<0,"SHORT","ok") -> ok | BQ28: 21 | BR28: =BR27+1 -> 78 | BS28: =BS27+1 -> 2046 | BT28: =IF(Inputs!$B$15="B",Inputs!$D$39,Inputs!$C$39) -> 0.38 | BU28: =BY27 -> 0 | BV28: =IF(BQ28<=$BV$4,BU28/($BV$4-BQ28+1),0) -> 0 | BW28: =BV28*BT28 -> 0 | BX28: =CA27-BW28 -> 1969626.3 | BY28: =(BU28-BV28)*(1+Inputs!$B$4) -> 0 | BZ28: =(BZ27+BV28)*(1+Inputs!$B$4) -> 8510287.4 | CA28: =BX28*(1+Inputs!$B$4*(1-Inputs!$B$8)) -> 2156740.8 | CB28: =IF(CA27<=0,0,CB27*BX28/CA27) -> 320701.84 | CC28: =BZ28+BY28*(1-Inputs!$B$6)+CA28-(CA28-CB28)*Inputs!$B$9 -> 10189658 | CD28: =BZ28/(BZ28+BY28+CA28) -> 0.79781241 | CE28: =IF(CC28>M28,1,0) -> 1 | CF28: =IF(BX28<0,"SHORT","ok") -> ok | CH28: 21 | CI28: =CI27+1 -> 78 | CJ28: =CJ27+1 -> 2046 | CK28: =IF(Inputs!$B$15="B",Inputs!$D$39,Inputs!$C$39) -> 0.38 | CL28: =CP27 -> 0 | CM28: =IF(CH28<=$CM$4,CL28/($CM$4-CH28+1),0) -> 0 | CN28: =CM28*CK28 -> 0 | CO28: =CR27-CN28 -> 1957088.1 | CP28: =(CL28-CM28)*(1+Inputs!$B$4) -> 0 | CQ28: =(CQ27+CM28)*(1+Inputs!$B$4) -> 8510287.4 | CR28: =CO28*(1+Inputs!$B$4*(1-Inputs!$B$8)) -> 2143011.5 | CS28: =IF(CR27<=0,0,CS27*CO28/CR27) -> 318660.33 | CT28: =CQ28+CP28*(1-Inputs!$B$6)+CR28-(CR28-CS28)*Inputs!$B$9 -> 10178968 | CU28: =CQ28/(CQ28+CP28+CR28) -> 0.79884057 | CV28: =IF(CT28>M28,1,0) -> 1 | CW28: =IF(CO28<0,"SHORT","ok") -> ok
A29: 22 | B29: =B28+1 -> 79 | C29: =C28+1 -> 2047 | D29: =IF(Inputs!$B$15="B",Inputs!$D$40,Inputs!$C$40) -> 0.38 | E29: =I28 -> 8510287.4 | F29: =IF(A29<=$F$4,E29/($F$4-A29+1),0) -> 0 | G29: =F29*D29 -> 0 | H29: =K28-G29 -> 5142993.7 | I29: =(E29-F29)*(1+Inputs!$B$4) -> 9361316.2 | J29: =(J28+F29)*(1+Inputs!$B$4) -> 0 | K29: =H29*(1+Inputs!$B$4*(1-Inputs!$B$8)) -> 5631578.1 | L29: =IF(K28<=0,0,L28*H29/K28) -> 764750 | M29: =J29+I29*(1-Inputs!$B$6)+K29-(K29-L29)*Inputs!$B$9 -> 10919124 | N29: =J29/(J29+I29+K29) -> 0 | O29: =IF(M29>M29,1,0) -> 0 | P29: =IF(H29<0,"SHORT","ok") -> ok | R29: 22 | S29: =S28+1 -> 79 | T29: =T28+1 -> 2047 | U29: =IF(Inputs!$B$15="B",Inputs!$D$40,Inputs!$C$40) -> 0.38 | V29: =Z28 -> 0 | W29: =IF(R29<=$W$4,V29/($W$4-R29+1),0) -> 0 | X29: =W29*U29 -> 0 | Y29: =AB28-X29 -> 2204140.1 | Z29: =(V29-W29)*(1+Inputs!$B$4) -> 0 | AA29: =(AA28+W29)*(1+Inputs!$B$4) -> 9361316.2 | AB29: =Y29*(1+Inputs!$B$4*(1-Inputs!$B$8)) -> 2413533.5 | AC29: =IF(AB28<=0,0,AC28*Y29/AB28) -> 327750 | AD29: =AA29+Z29*(1-Inputs!$B$6)+AB29-(AB29-AC29)*Inputs!$B$9 -> 11232546 | AE29: =AA29/(AA29+Z29+AB29) -> 0.79502639 | AF29: =IF(AD29>M29,1,0) -> 1 | AG29: =IF(Y29<0,"SHORT","ok") -> ok | AI29: 22 | AJ29: =AJ28+1 -> 79 | AK29: =AK28+1 -> 2047 | AL29: =IF(Inputs!$B$15="B",Inputs!$D$40,Inputs!$C$40) -> 0.38 | AM29: =AQ28 -> 0 | AN29: =IF(AI29<=$AN$4,AM29/($AN$4-AI29+1),0) -> 0 | AO29: =AN29*AL29 -> 0 | AP29: =AS28-AO29 -> 2190700.3 | AQ29: =(AM29-AN29)*(1+Inputs!$B$4) -> 0 | AR29: =(AR28+AN29)*(1+Inputs!$B$4) -> 9361316.2 | AS29: =AP29*(1+Inputs!$B$4*(1-Inputs!$B$8)) -> 2398816.8 | AT29: =IF(AS28<=0,0,AT28*AP29/AS28) -> 325751.53 | AU29: =AR29+AQ29*(1-Inputs!$B$6)+AS29-(AS29-AT29)*Inputs!$B$9 -> 11221136 | AV29: =AR29/(AR29+AQ29+AS29) -> 0.79602129 | AW29: =IF(AU29>M29,1,0) -> 1 | AX29: =IF(AP29<0,"SHORT","ok") -> ok | AZ29: 22 | BA29: =BA28+1 -> 79 | BB29: =BB28+1 -> 2047 | BC29: =IF(Inputs!$B$15="B",Inputs!$D$40,Inputs!$C$40) -> 0.38 | BD29: =BH28 -> 0 | BE29: =IF(AZ29<=$BE$4,BD29/($BE$4-AZ29+1),0) -> 0 | BF29: =BE29*BC29 -> 0 | BG29: =BJ28-BF29 -> 2177178.5 | BH29: =(BD29-BE29)*(1+Inputs!$B$4) -> 0 | BI29: =(BI28+BE29)*(1+Inputs!$B$4) -> 9361316.2 | BJ29: =BG29*(1+Inputs!$B$4*(1-Inputs!$B$8)) -> 2384010.4 | BK29: =IF(BJ28<=0,0,BK28*BG29/BJ28) -> 323740.87 | BL29: =BI29+BH29*(1-Inputs!$B$6)+BJ29-(BJ29-BK29)*Inputs!$B$9 -> 11209657 | BM29: =BI29/(BI29+BH29+BJ29) -> 0.79702477 | BN29: =IF(BL29>M29,1,0) -> 1 | BO29: =IF(BG29<0,"SHORT","ok") -> ok | BQ29: 22 | BR29: =BR28+1 -> 79 | BS29: =BS28+1 -> 2047 | BT29: =IF(Inputs!$B$15="B",Inputs!$D$40,Inputs!$C$40) -> 0.38 | BU29: =BY28 -> 0 | BV29: =IF(BQ29<=$BV$4,BU29/($BV$4-BQ29+1),0) -> 0 | BW29: =BV29*BT29 -> 0 | BX29: =CA28-BW29 -> 2156740.8 | BY29: =(BU29-BV29)*(1+Inputs!$B$4) -> 0 | BZ29: =(BZ28+BV29)*(1+Inputs!$B$4) -> 9361316.2 | CA29: =BX29*(1+Inputs!$B$4*(1-Inputs!$B$8)) -> 2361631.1 | CB29: =IF(CA28<=0,0,CB28*BX29/CA28) -> 320701.84 | CC29: =BZ29+BY29*(1-Inputs!$B$6)+CA29-(CA29-CB29)*Inputs!$B$9 -> 11192306 | CD29: =BZ29/(BZ29+BY29+CA29) -> 0.7985463 | CE29: =IF(CC29>M29,1,0) -> 1 | CF29: =IF(BX29<0,"SHORT","ok") -> ok | CH29: 22 | CI29: =CI28+1 -> 79 | CJ29: =CJ28+1 -> 2047 | CK29: =IF(Inputs!$B$15="B",Inputs!$D$40,Inputs!$C$40) -> 0.38 | CL29: =CP28 -> 0 | CM29: =IF(CH29<=$CM$4,CL29/($CM$4-CH29+1),0) -> 0 | CN29: =CM29*CK29 -> 0 | CO29: =CR28-CN29 -> 2143011.5 | CP29: =(CL29-CM29)*(1+Inputs!$B$4) -> 0 | CQ29: =(CQ28+CM29)*(1+Inputs!$B$4) -> 9361316.2 | CR29: =CO29*(1+Inputs!$B$4*(1-Inputs!$B$8)) -> 2346597.6 | CS29: =IF(CR28<=0,0,CS28*CO29/CR28) -> 318660.33 | CT29: =CQ29+CP29*(1-Inputs!$B$6)+CR29-(CR29-CS29)*Inputs!$B$9 -> 11180650 | CU29: =CQ29/(CQ29+CP29+CR29) -> 0.79957167 | CV29: =IF(CT29>M29,1,0) -> 1 | CW29: =IF(CO29<0,"SHORT","ok") -> ok
A30: 23 | B30: =B29+1 -> 80 | C30: =C29+1 -> 2048 | D30: =IF(Inputs!$B$15="B",Inputs!$D$41,Inputs!$C$41) -> 0.38 | E30: =I29 -> 9361316.2 | F30: =IF(A30<=$F$4,E30/($F$4-A30+1),0) -> 0 | G30: =F30*D30 -> 0 | H30: =K29-G30 -> 5631578.1 | I30: =(E30-F30)*(1+Inputs!$B$4) -> 10297448 | J30: =(J29+F30)*(1+Inputs!$B$4) -> 0 | K30: =H30*(1+Inputs!$B$4*(1-Inputs!$B$8)) -> 6166578 | L30: =IF(K29<=0,0,L29*H30/K29) -> 764750 | M30: =J30+I30*(1-Inputs!$B$6)+K30-(K30-L30)*Inputs!$B$9 -> 11970316 | N30: =J30/(J30+I30+K30) -> 0 | O30: =IF(M30>M30,1,0) -> 0 | P30: =IF(H30<0,"SHORT","ok") -> ok | R30: 23 | S30: =S29+1 -> 80 | T30: =T29+1 -> 2048 | U30: =IF(Inputs!$B$15="B",Inputs!$D$41,Inputs!$C$41) -> 0.38 | V30: =Z29 -> 0 | W30: =IF(R30<=$W$4,V30/($W$4-R30+1),0) -> 0 | X30: =W30*U30 -> 0 | Y30: =AB29-X30 -> 2413533.5 | Z30: =(V30-W30)*(1+Inputs!$B$4) -> 0 | AA30: =(AA29+W30)*(1+Inputs!$B$4) -> 10297448 | AB30: =Y30*(1+Inputs!$B$4*(1-Inputs!$B$8)) -> 2642819.1 | AC30: =IF(AB29<=0,0,AC29*Y30/AB29) -> 327750 | AD30: =AA30+Z30*(1-Inputs!$B$6)+AB30-(AB30-AC30)*Inputs!$B$9 -> 12338349 | AE30: =AA30/(AA30+Z30+AB30) -> 0.7957678 | AF30: =IF(AD30>M30,1,0) -> 1 | AG30: =IF(Y30<0,"SHORT","ok") -> ok | AI30: 23 | AJ30: =AJ29+1 -> 80 | AK30: =AK29+1 -> 2048 | AL30: =IF(Inputs!$B$15="B",Inputs!$D$41,Inputs!$C$41) -> 0.38 | AM30: =AQ29 -> 0 | AN30: =IF(AI30<=$AN$4,AM30/($AN$4-AI30+1),0) -> 0 | AO30: =AN30*AL30 -> 0 | AP30: =AS29-AO30 -> 2398816.8 | AQ30: =(AM30-AN30)*(1+Inputs!$B$4) -> 0 | AR30: =(AR29+AN30)*(1+Inputs!$B$4) -> 10297448 | AS30: =AP30*(1+Inputs!$B$4*(1-Inputs!$B$8)) -> 2626704.4 | AT30: =IF(AS29<=0,0,AT29*AP30/AS29) -> 325751.53 | AU30: =AR30+AQ30*(1-Inputs!$B$6)+AS30-(AS30-AT30)*Inputs!$B$9 -> 12325904 | AV30: =AR30/(AR30+AQ30+AS30) -> 0.79676002 | AW30: =IF(AU30>M30,1,0) -> 1 | AX30: =IF(AP30<0,"SHORT","ok") -> ok | AZ30: 23 | BA30: =BA29+1 -> 80 | BB30: =BB29+1 -> 2048 | BC30: =IF(Inputs!$B$15="B",Inputs!$D$41,Inputs!$C$41) -> 0.38 | BD30: =BH29 -> 0 | BE30: =IF(AZ30<=$BE$4,BD30/($BE$4-AZ30+1),0) -> 0 | BF30: =BE30*BC30 -> 0 | BG30: =BJ29-BF30 -> 2384010.4 | BH30: =(BD30-BE30)*(1+Inputs!$B$4) -> 0 | BI30: =(BI29+BE30)*(1+Inputs!$B$4) -> 10297448 | BJ30: =BG30*(1+Inputs!$B$4*(1-Inputs!$B$8)) -> 2610491.4 | BK30: =IF(BJ29<=0,0,BK29*BG30/BJ29) -> 323740.87 | BL30: =BI30+BH30*(1-Inputs!$B$6)+BJ30-(BJ30-BK30)*Inputs!$B$9 -> 12313384 | BM30: =BI30/(BI30+BH30+BJ30) -> 0.79776079 | BN30: =IF(BL30>M30,1,0) -> 1 | BO30: =IF(BG30<0,"SHORT","ok") -> ok | BQ30: 23 | BR30: =BR29+1 -> 80 | BS30: =BS29+1 -> 2048 | BT30: =IF(Inputs!$B$15="B",Inputs!$D$41,Inputs!$C$41) -> 0.38 | BU30: =BY29 -> 0 | BV30: =IF(BQ30<=$BV$4,BU30/($BV$4-BQ30+1),0) -> 0 | BW30: =BV30*BT30 -> 0 | BX30: =CA29-BW30 -> 2361631.1 | BY30: =(BU30-BV30)*(1+Inputs!$B$4) -> 0 | BZ30: =(BZ29+BV30)*(1+Inputs!$B$4) -> 10297448 | CA30: =BX30*(1+Inputs!$B$4*(1-Inputs!$B$8)) -> 2585986.1 | CB30: =IF(CA29<=0,0,CB29*BX30/CA29) -> 320701.84 | CC30: =BZ30+BY30*(1-Inputs!$B$6)+CA30-(CA30-CB30)*Inputs!$B$9 -> 12294460 | CD30: =BZ30/(BZ30+BY30+CA30) -> 0.7992782 | CE30: =IF(CC30>M30,1,0) -> 1 | CF30: =IF(BX30<0,"SHORT","ok") -> ok | CH30: 23 | CI30: =CI29+1 -> 80 | CJ30: =CJ29+1 -> 2048 | CK30: =IF(Inputs!$B$15="B",Inputs!$D$41,Inputs!$C$41) -> 0.38 | CL30: =CP29 -> 0 | CM30: =IF(CH30<=$CM$4,CL30/($CM$4-CH30+1),0) -> 0 | CN30: =CM30*CK30 -> 0 | CO30: =CR29-CN30 -> 2346597.6 | CP30: =(CL30-CM30)*(1+Inputs!$B$4) -> 0 | CQ30: =(CQ29+CM30)*(1+Inputs!$B$4) -> 10297448 | CR30: =CO30*(1+Inputs!$B$4*(1-Inputs!$B$8)) -> 2569524.4 | CS30: =IF(CR29<=0,0,CS29*CO30/CR29) -> 318660.33 | CT30: =CQ30+CP30*(1-Inputs!$B$6)+CR30-(CR30-CS30)*Inputs!$B$9 -> 12281748 | CU30: =CQ30/(CQ30+CP30+CR30) -> 0.80030077 | CV30: =IF(CT30>M30,1,0) -> 1 | CW30: =IF(CO30<0,"SHORT","ok") -> ok
A31: 24 | B31: =B30+1 -> 81 | C31: =C30+1 -> 2049 | D31: =IF(Inputs!$B$15="B",Inputs!$D$42,Inputs!$C$42) -> 0.38 | E31: =I30 -> 10297448 | F31: =IF(A31<=$F$4,E31/($F$4-A31+1),0) -> 0 | G31: =F31*D31 -> 0 | H31: =K30-G31 -> 6166578 | I31: =(E31-F31)*(1+Inputs!$B$4) -> 11327193 | J31: =(J30+F31)*(1+Inputs!$B$4) -> 0 | K31: =H31*(1+Inputs!$B$4*(1-Inputs!$B$8)) -> 6752402.9 | L31: =IF(K30<=0,0,L30*H31/K30) -> 764750 | M31: =J31+I31*(1-Inputs!$B$6)+K31-(K31-L31)*Inputs!$B$9 -> 13124648 | N31: =J31/(J31+I31+K31) -> 0 | O31: =IF(M31>M31,1,0) -> 0 | P31: =IF(H31<0,"SHORT","ok") -> ok | R31: 24 | S31: =S30+1 -> 81 | T31: =T30+1 -> 2049 | U31: =IF(Inputs!$B$15="B",Inputs!$D$42,Inputs!$C$42) -> 0.38 | V31: =Z30 -> 0 | W31: =IF(R31<=$W$4,V31/($W$4-R31+1),0) -> 0 | X31: =W31*U31 -> 0 | Y31: =AB30-X31 -> 2642819.1 | Z31: =(V31-W31)*(1+Inputs!$B$4) -> 0 | AA31: =(AA30+W31)*(1+Inputs!$B$4) -> 11327193 | AB31: =Y31*(1+Inputs!$B$4*(1-Inputs!$B$8)) -> 2893886.9 | AC31: =IF(AB30<=0,0,AC30*Y31/AB30) -> 327750 | AD31: =AA31+Z31*(1-Inputs!$B$6)+AB31-(AB31-AC31)*Inputs!$B$9 -> 13553884 | AE31: =AA31/(AA31+Z31+AB31) -> 0.79650722 | AF31: =IF(AD31>M31,1,0) -> 1 | AG31: =IF(Y31<0,"SHORT","ok") -> ok | AI31: 24 | AJ31: =AJ30+1 -> 81 | AK31: =AK30+1 -> 2049 | AL31: =IF(Inputs!$B$15="B",Inputs!$D$42,Inputs!$C$42) -> 0.38 | AM31: =AQ30 -> 0 | AN31: =IF(AI31<=$AN$4,AM31/($AN$4-AI31+1),0) -> 0 | AO31: =AN31*AL31 -> 0 | AP31: =AS30-AO31 -> 2626704.4 | AQ31: =(AM31-AN31)*(1+Inputs!$B$4) -> 0 | AR31: =(AR30+AN31)*(1+Inputs!$B$4) -> 11327193 | AS31: =AP31*(1+Inputs!$B$4*(1-Inputs!$B$8)) -> 2876241.3 | AT31: =IF(AS30<=0,0,AT30*AP31/AS30) -> 325751.53 | AU31: =AR31+AQ31*(1-Inputs!$B$6)+AS31-(AS31-AT31)*Inputs!$B$9 -> 13540307 | AV31: =AR31/(AR31+AQ31+AS31) -> 0.79749676 | AW31: =IF(AU31>M31,1,0) -> 1 | AX31: =IF(AP31<0,"SHORT","ok") -> ok | AZ31: 24 | BA31: =BA30+1 -> 81 | BB31: =BB30+1 -> 2049 | BC31: =IF(Inputs!$B$15="B",Inputs!$D$42,Inputs!$C$42) -> 0.38 | BD31: =BH30 -> 0 | BE31: =IF(AZ31<=$BE$4,BD31/($BE$4-AZ31+1),0) -> 0 | BF31: =BE31*BC31 -> 0 | BG31: =BJ30-BF31 -> 2610491.4 | BH31: =(BD31-BE31)*(1+Inputs!$B$4) -> 0 | BI31: =(BI30+BE31)*(1+Inputs!$B$4) -> 11327193 | BJ31: =BG31*(1+Inputs!$B$4*(1-Inputs!$B$8)) -> 2858488.1 | BK31: =IF(BJ30<=0,0,BK30*BG31/BJ30) -> 323740.87 | BL31: =BI31+BH31*(1-Inputs!$B$6)+BJ31-(BJ31-BK31)*Inputs!$B$9 -> 13526646 | BM31: =BI31/(BI31+BH31+BJ31) -> 0.79849482 | BN31: =IF(BL31>M31,1,0) -> 1 | BO31: =IF(BG31<0,"SHORT","ok") -> ok | BQ31: 24 | BR31: =BR30+1 -> 81 | BS31: =BS30+1 -> 2049 | BT31: =IF(Inputs!$B$15="B",Inputs!$D$42,Inputs!$C$42) -> 0.38 | BU31: =BY30 -> 0 | BV31: =IF(BQ31<=$BV$4,BU31/($BV$4-BQ31+1),0) -> 0 | BW31: =BV31*BT31 -> 0 | BX31: =CA30-BW31 -> 2585986.1 | BY31: =(BU31-BV31)*(1+Inputs!$B$4) -> 0 | BZ31: =(BZ30+BV31)*(1+Inputs!$B$4) -> 11327193 | CA31: =BX31*(1+Inputs!$B$4*(1-Inputs!$B$8)) -> 2831654.8 | CB31: =IF(CA30<=0,0,CB30*BX31/CA30) -> 320701.84 | CC31: =BZ31+BY31*(1-Inputs!$B$6)+CA31-(CA31-CB31)*Inputs!$B$9 -> 13506000 | CD31: =BZ31/(BZ31+BY31+CA31) -> 0.8000081 | CE31: =IF(CC31>M31,1,0) -> 1 | CF31: =IF(BX31<0,"SHORT","ok") -> ok | CH31: 24 | CI31: =CI30+1 -> 81 | CJ31: =CJ30+1 -> 2049 | CK31: =IF(Inputs!$B$15="B",Inputs!$D$42,Inputs!$C$42) -> 0.38 | CL31: =CP30 -> 0 | CM31: =IF(CH31<=$CM$4,CL31/($CM$4-CH31+1),0) -> 0 | CN31: =CM31*CK31 -> 0 | CO31: =CR30-CN31 -> 2569524.4 | CP31: =(CL31-CM31)*(1+Inputs!$B$4) -> 0 | CQ31: =(CQ30+CM31)*(1+Inputs!$B$4) -> 11327193 | CR31: =CO31*(1+Inputs!$B$4*(1-Inputs!$B$8)) -> 2813629.2 | CS31: =IF(CR30<=0,0,CS30*CO31/CR30) -> 318660.33 | CT31: =CQ31+CP31*(1-Inputs!$B$6)+CR31-(CR31-CS31)*Inputs!$B$9 -> 13492130 | CU31: =CQ31/(CQ31+CP31+CR31) -> 0.80102789 | CV31: =IF(CT31>M31,1,0) -> 1 | CW31: =IF(CO31<0,"SHORT","ok") -> ok
A32: 25 | B32: =B31+1 -> 82 | C32: =C31+1 -> 2050 | D32: =IF(Inputs!$B$15="B",Inputs!$D$43,Inputs!$C$43) -> 0.38 | E32: =I31 -> 11327193 | F32: =IF(A32<=$F$4,E32/($F$4-A32+1),0) -> 0 | G32: =F32*D32 -> 0 | H32: =K31-G32 -> 6752402.9 | I32: =(E32-F32)*(1+Inputs!$B$4) -> 12459912 | J32: =(J31+F32)*(1+Inputs!$B$4) -> 0 | K32: =H32*(1+Inputs!$B$4*(1-Inputs!$B$8)) -> 7393881.1 | L32: =IF(K31<=0,0,L31*H32/K31) -> 764750 | M32: =J32+I32*(1-Inputs!$B$6)+K32-(K32-L32)*Inputs!$B$9 -> 14392245 | N32: =J32/(J32+I32+K32) -> 0 | O32: =IF(M32>M32,1,0) -> 0 | P32: =IF(H32<0,"SHORT","ok") -> ok | R32: 25 | S32: =S31+1 -> 82 | T32: =T31+1 -> 2050 | U32: =IF(Inputs!$B$15="B",Inputs!$D$43,Inputs!$C$43) -> 0.38 | V32: =Z31 -> 0 | W32: =IF(R32<=$W$4,V32/($W$4-R32+1),0) -> 0 | X32: =W32*U32 -> 0 | Y32: =AB31-X32 -> 2893886.9 | Z32: =(V32-W32)*(1+Inputs!$B$4) -> 0 | AA32: =(AA31+W32)*(1+Inputs!$B$4) -> 12459912 | AB32: =Y32*(1+Inputs!$B$4*(1-Inputs!$B$8)) -> 3168806.2 | AC32: =IF(AB31<=0,0,AC31*Y32/AB31) -> 327750 | AD32: =AA32+Z32*(1-Inputs!$B$6)+AB32-(AB32-AC32)*Inputs!$B$9 -> 14890043 | AE32: =AA32/(AA32+Z32+AB32) -> 0.79724465 | AF32: =IF(AD32>M32,1,0) -> 1 | AG32: =IF(Y32<0,"SHORT","ok") -> ok | AI32: 25 | AJ32: =AJ31+1 -> 82 | AK32: =AK31+1 -> 2050 | AL32: =IF(Inputs!$B$15="B",Inputs!$D$43,Inputs!$C$43) -> 0.38 | AM32: =AQ31 -> 0 | AN32: =IF(AI32<=$AN$4,AM32/($AN$4-AI32+1),0) -> 0 | AO32: =AN32*AL32 -> 0 | AP32: =AS31-AO32 -> 2876241.3 | AQ32: =(AM32-AN32)*(1+Inputs!$B$4) -> 0 | AR32: =(AR31+AN32)*(1+Inputs!$B$4) -> 12459912 | AS32: =AP32*(1+Inputs!$B$4*(1-Inputs!$B$8)) -> 3149484.3 | AT32: =IF(AS31<=0,0,AT31*AP32/AS31) -> 325751.53 | AU32: =AR32+AQ32*(1-Inputs!$B$6)+AS32-(AS32-AT32)*Inputs!$B$9 -> 14875226 | AV32: =AR32/(AR32+AQ32+AS32) -> 0.79823151 | AW32: =IF(AU32>M32,1,0) -> 1 | AX32: =IF(AP32<0,"SHORT","ok") -> ok | AZ32: 25 | BA32: =BA31+1 -> 82 | BB32: =BB31+1 -> 2050 | BC32: =IF(Inputs!$B$15="B",Inputs!$D$43,Inputs!$C$43) -> 0.38 | BD32: =BH31 -> 0 | BE32: =IF(AZ32<=$BE$4,BD32/($BE$4-AZ32+1),0) -> 0 | BF32: =BE32*BC32 -> 0 | BG32: =BJ31-BF32 -> 2858488.1 | BH32: =(BD32-BE32)*(1+Inputs!$B$4) -> 0 | BI32: =(BI31+BE32)*(1+Inputs!$B$4) -> 12459912 | BJ32: =BG32*(1+Inputs!$B$4*(1-Inputs!$B$8)) -> 3130044.5 | BK32: =IF(BJ31<=0,0,BK31*BG32/BJ31) -> 323740.87 | BL32: =BI32+BH32*(1-Inputs!$B$6)+BJ32-(BJ32-BK32)*Inputs!$B$9 -> 14860317 | BM32: =BI32/(BI32+BH32+BJ32) -> 0.79922686 | BN32: =IF(BL32>M32,1,0) -> 1 | BO32: =IF(BG32<0,"SHORT","ok") -> ok | BQ32: 25 | BR32: =BR31+1 -> 82 | BS32: =BS31+1 -> 2050 | BT32: =IF(Inputs!$B$15="B",Inputs!$D$43,Inputs!$C$43) -> 0.38 | BU32: =BY31 -> 0 | BV32: =IF(BQ32<=$BV$4,BU32/($BV$4-BQ32+1),0) -> 0 | BW32: =BV32*BT32 -> 0 | BX32: =CA31-BW32 -> 2831654.8 | BY32: =(BU32-BV32)*(1+Inputs!$B$4) -> 0 | BZ32: =(BZ31+BV32)*(1+Inputs!$B$4) -> 12459912 | CA32: =BX32*(1+Inputs!$B$4*(1-Inputs!$B$8)) -> 3100662 | CB32: =IF(CA31<=0,0,CB31*BX32/CA31) -> 320701.84 | CC32: =BZ32+BY32*(1-Inputs!$B$6)+CA32-(CA32-CB32)*Inputs!$B$9 -> 14837784 | CD32: =BZ32/(BZ32+BY32+CA32) -> 0.80073601 | CE32: =IF(CC32>M32,1,0) -> 1 | CF32: =IF(BX32<0,"SHORT","ok") -> ok | CH32: 25 | CI32: =CI31+1 -> 82 | CJ32: =CJ31+1 -> 2050 | CK32: =IF(Inputs!$B$15="B",Inputs!$D$43,Inputs!$C$43) -> 0.38 | CL32: =CP31 -> 0 | CM32: =IF(CH32<=$CM$4,CL32/($CM$4-CH32+1),0) -> 0 | CN32: =CM32*CK32 -> 0 | CO32: =CR31-CN32 -> 2813629.2 | CP32: =(CL32-CM32)*(1+Inputs!$B$4) -> 0 | CQ32: =(CQ31+CM32)*(1+Inputs!$B$4) -> 12459912 | CR32: =CO32*(1+Inputs!$B$4*(1-Inputs!$B$8)) -> 3080924 | CS32: =IF(CR31<=0,0,CS31*CO32/CR31) -> 318660.33 | CT32: =CQ32+CP32*(1-Inputs!$B$6)+CR32-(CR32-CS32)*Inputs!$B$9 -> 14822647 | CU32: =CQ32/(CQ32+CP32+CR32) -> 0.80175301 | CV32: =IF(CT32>M32,1,0) -> 1 | CW32: =IF(CO32<0,"SHORT","ok") -> ok
A33: 26 | B33: =B32+1 -> 83 | C33: =C32+1 -> 2051 | D33: =IF(Inputs!$B$15="B",Inputs!$D$44,Inputs!$C$44) -> 0.38 | E33: =I32 -> 12459912 | F33: =IF(A33<=$F$4,E33/($F$4-A33+1),0) -> 0 | G33: =F33*D33 -> 0 | H33: =K32-G33 -> 7393881.1 | I33: =(E33-F33)*(1+Inputs!$B$4) -> 13705903 | J33: =(J32+F33)*(1+Inputs!$B$4) -> 0 | K33: =H33*(1+Inputs!$B$4*(1-Inputs!$B$8)) -> 8096299.9 | L33: =IF(K32<=0,0,L32*H33/K32) -> 764750 | M33: =J33+I33*(1-Inputs!$B$6)+K33-(K33-L33)*Inputs!$B$9 -> 15784229 | N33: =J33/(J33+I33+K33) -> 0 | O33: =IF(M33>M33,1,0) -> 0 | P33: =IF(H33<0,"SHORT","ok") -> ok | R33: 26 | S33: =S32+1 -> 83 | T33: =T32+1 -> 2051 | U33: =IF(Inputs!$B$15="B",Inputs!$D$44,Inputs!$C$44) -> 0.38 | V33: =Z32 -> 0 | W33: =IF(R33<=$W$4,V33/($W$4-R33+1),0) -> 0 | X33: =W33*U33 -> 0 | Y33: =AB32-X33 -> 3168806.2 | Z33: =(V33-W33)*(1+Inputs!$B$4) -> 0 | AA33: =(AA32+W33)*(1+Inputs!$B$4) -> 13705903 | AB33: =Y33*(1+Inputs!$B$4*(1-Inputs!$B$8)) -> 3469842.8 | AC33: =IF(AB32<=0,0,AC32*Y33/AB32) -> 327750 | AD33: =AA33+Z33*(1-Inputs!$B$6)+AB33-(AB33-AC33)*Inputs!$B$9 -> 16358802 | AE33: =AA33/(AA33+Z33+AB33) -> 0.79798008 | AF33: =IF(AD33>M33,1,0) -> 1 | AG33: =IF(Y33<0,"SHORT","ok") -> ok | AI33: 26 | AJ33: =AJ32+1 -> 83 | AK33: =AK32+1 -> 2051 | AL33: =IF(Inputs!$B$15="B",Inputs!$D$44,Inputs!$C$44) -> 0.38 | AM33: =AQ32 -> 0 | AN33: =IF(AI33<=$AN$4,AM33/($AN$4-AI33+1),0) -> 0 | AO33: =AN33*AL33 -> 0 | AP33: =AS32-AO33 -> 3149484.3 | AQ33: =(AM33-AN33)*(1+Inputs!$B$4) -> 0 | AR33: =(AR32+AN33)*(1+Inputs!$B$4) -> 13705903 | AS33: =AP33*(1+Inputs!$B$4*(1-Inputs!$B$8)) -> 3448685.3 | AT33: =IF(AS32<=0,0,AT32*AP33/AS32) -> 325751.53 | AU33: =AR33+AQ33*(1-Inputs!$B$6)+AS33-(AS33-AT33)*Inputs!$B$9 -> 16342626 | AV33: =AR33/(AR33+AQ33+AS33) -> 0.79896426 | AW33: =IF(AU33>M33,1,0) -> 1 | AX33: =IF(AP33<0,"SHORT","ok") -> ok | AZ33: 26 | BA33: =BA32+1 -> 83 | BB33: =BB32+1 -> 2051 | BC33: =IF(Inputs!$B$15="B",Inputs!$D$44,Inputs!$C$44) -> 0.38 | BD33: =BH32 -> 0 | BE33: =IF(AZ33<=$BE$4,BD33/($BE$4-AZ33+1),0) -> 0 | BF33: =BE33*BC33 -> 0 | BG33: =BJ32-BF33 -> 3130044.5 | BH33: =(BD33-BE33)*(1+Inputs!$B$4) -> 0 | BI33: =(BI32+BE33)*(1+Inputs!$B$4) -> 13705903 | BJ33: =BG33*(1+Inputs!$B$4*(1-Inputs!$B$8)) -> 3427398.7 | BK33: =IF(BJ32<=0,0,BK32*BG33/BJ32) -> 323740.87 | BL33: =BI33+BH33*(1-Inputs!$B$6)+BJ33-(BJ33-BK33)*Inputs!$B$9 -> 16326351 | BM33: =BI33/(BI33+BH33+BJ33) -> 0.79995691 | BN33: =IF(BL33>M33,1,0) -> 1 | BO33: =IF(BG33<0,"SHORT","ok") -> ok | BQ33: 26 | BR33: =BR32+1 -> 83 | BS33: =BS32+1 -> 2051 | BT33: =IF(Inputs!$B$15="B",Inputs!$D$44,Inputs!$C$44) -> 0.38 | BU33: =BY32 -> 0 | BV33: =IF(BQ33<=$BV$4,BU33/($BV$4-BQ33+1),0) -> 0 | BW33: =BV33*BT33 -> 0 | BX33: =CA32-BW33 -> 3100662 | BY33: =(BU33-BV33)*(1+Inputs!$B$4) -> 0 | BZ33: =(BZ32+BV33)*(1+Inputs!$B$4) -> 13705903 | CA33: =BX33*(1+Inputs!$B$4*(1-Inputs!$B$8)) -> 3395224.9 | CB33: =IF(CA32<=0,0,CB32*BX33/CA32) -> 320701.84 | CC33: =BZ33+BY33*(1-Inputs!$B$6)+CA33-(CA33-CB33)*Inputs!$B$9 -> 16301752 | CD33: =BZ33/(BZ33+BY33+CA33) -> 0.80146193 | CE33: =IF(CC33>M33,1,0) -> 1 | CF33: =IF(BX33<0,"SHORT","ok") -> ok | CH33: 26 | CI33: =CI32+1 -> 83 | CJ33: =CJ32+1 -> 2051 | CK33: =IF(Inputs!$B$15="B",Inputs!$D$44,Inputs!$C$44) -> 0.38 | CL33: =CP32 -> 0 | CM33: =IF(CH33<=$CM$4,CL33/($CM$4-CH33+1),0) -> 0 | CN33: =CM33*CK33 -> 0 | CO33: =CR32-CN33 -> 3080924 | CP33: =(CL33-CM33)*(1+Inputs!$B$4) -> 0 | CQ33: =(CQ32+CM33)*(1+Inputs!$B$4) -> 13705903 | CR33: =CO33*(1+Inputs!$B$4*(1-Inputs!$B$8)) -> 3373611.8 | CS33: =IF(CR32<=0,0,CS32*CO33/CR32) -> 318660.33 | CT33: =CQ33+CP33*(1-Inputs!$B$6)+CR33-(CR33-CS33)*Inputs!$B$9 -> 16285227 | CU33: =CQ33/(CQ33+CP33+CR33) -> 0.80247614 | CV33: =IF(CT33>M33,1,0) -> 1 | CW33: =IF(CO33<0,"SHORT","ok") -> ok
A34: 27 | B34: =B33+1 -> 84 | C34: =C33+1 -> 2052 | D34: =IF(Inputs!$B$15="B",Inputs!$D$45,Inputs!$C$45) -> 0.38 | E34: =I33 -> 13705903 | F34: =IF(A34<=$F$4,E34/($F$4-A34+1),0) -> 0 | G34: =F34*D34 -> 0 | H34: =K33-G34 -> 8096299.9 | I34: =(E34-F34)*(1+Inputs!$B$4) -> 15076493 | J34: =(J33+F34)*(1+Inputs!$B$4) -> 0 | K34: =H34*(1+Inputs!$B$4*(1-Inputs!$B$8)) -> 8865448.3 | L34: =IF(K33<=0,0,L33*H34/K33) -> 764750 | M34: =J34+I34*(1-Inputs!$B$6)+K34-(K34-L34)*Inputs!$B$9 -> 17312812 | N34: =J34/(J34+I34+K34) -> 0 | O34: =IF(M34>M34,1,0) -> 0 | P34: =IF(H34<0,"SHORT","ok") -> ok | R34: 27 | S34: =S33+1 -> 84 | T34: =T33+1 -> 2052 | U34: =IF(Inputs!$B$15="B",Inputs!$D$45,Inputs!$C$45) -> 0.38 | V34: =Z33 -> 0 | W34: =IF(R34<=$W$4,V34/($W$4-R34+1),0) -> 0 | X34: =W34*U34 -> 0 | Y34: =AB33-X34 -> 3469842.8 | Z34: =(V34-W34)*(1+Inputs!$B$4) -> 0 | AA34: =(AA33+W34)*(1+Inputs!$B$4) -> 15076493 | AB34: =Y34*(1+Inputs!$B$4*(1-Inputs!$B$8)) -> 3799477.9 | AC34: =IF(AB33<=0,0,AC33*Y34/AB33) -> 327750 | AD34: =AA34+Z34*(1-Inputs!$B$6)+AB34-(AB34-AC34)*Inputs!$B$9 -> 17973322 | AE34: =AA34/(AA34+Z34+AB34) -> 0.79871352 | AF34: =IF(AD34>M34,1,0) -> 1 | AG34: =IF(Y34<0,"SHORT","ok") -> ok | AI34: 27 | AJ34: =AJ33+1 -> 84 | AK34: =AK33+1 -> 2052 | AL34: =IF(Inputs!$B$15="B",Inputs!$D$45,Inputs!$C$45) -> 0.38 | AM34: =AQ33 -> 0 | AN34: =IF(AI34<=$AN$4,AM34/($AN$4-AI34+1),0) -> 0 | AO34: =AN34*AL34 -> 0 | AP34: =AS33-AO34 -> 3448685.3 | AQ34: =(AM34-AN34)*(1+Inputs!$B$4) -> 0 | AR34: =(AR33+AN34)*(1+Inputs!$B$4) -> 15076493 | AS34: =AP34*(1+Inputs!$B$4*(1-Inputs!$B$8)) -> 3776310.4 | AT34: =IF(AS33<=0,0,AT33*AP34/AS33) -> 325751.53 | AU34: =AR34+AQ34*(1-Inputs!$B$6)+AS34-(AS34-AT34)*Inputs!$B$9 -> 17955658 | AV34: =AR34/(AR34+AQ34+AS34) -> 0.79969503 | AW34: =IF(AU34>M34,1,0) -> 1 | AX34: =IF(AP34<0,"SHORT","ok") -> ok | AZ34: 27 | BA34: =BA33+1 -> 84 | BB34: =BB33+1 -> 2052 | BC34: =IF(Inputs!$B$15="B",Inputs!$D$45,Inputs!$C$45) -> 0.38 | BD34: =BH33 -> 0 | BE34: =IF(AZ34<=$BE$4,BD34/($BE$4-AZ34+1),0) -> 0 | BF34: =BE34*BC34 -> 0 | BG34: =BJ33-BF34 -> 3427398.7 | BH34: =(BD34-BE34)*(1+Inputs!$B$4) -> 0 | BI34: =(BI33+BE34)*(1+Inputs!$B$4) -> 15076493 | BJ34: =BG34*(1+Inputs!$B$4*(1-Inputs!$B$8)) -> 3753001.6 | BK34: =IF(BJ33<=0,0,BK33*BG34/BJ33) -> 323740.87 | BL34: =BI34+BH34*(1-Inputs!$B$6)+BJ34-(BJ34-BK34)*Inputs!$B$9 -> 17937887 | BM34: =BI34/(BI34+BH34+BJ34) -> 0.80068496 | BN34: =IF(BL34>M34,1,0) -> 1 | BO34: =IF(BG34<0,"SHORT","ok") -> ok | BQ34: 27 | BR34: =BR33+1 -> 84 | BS34: =BS33+1 -> 2052 | BT34: =IF(Inputs!$B$15="B",Inputs!$D$45,Inputs!$C$45) -> 0.38 | BU34: =BY33 -> 0 | BV34: =IF(BQ34<=$BV$4,BU34/($BV$4-BQ34+1),0) -> 0 | BW34: =BV34*BT34 -> 0 | BX34: =CA33-BW34 -> 3395224.9 | BY34: =(BU34-BV34)*(1+Inputs!$B$4) -> 0 | BZ34: =(BZ33+BV34)*(1+Inputs!$B$4) -> 15076493 | CA34: =BX34*(1+Inputs!$B$4*(1-Inputs!$B$8)) -> 3717771.2 | CB34: =IF(CA33<=0,0,CB33*BX34/CA33) -> 320701.84 | CC34: =BZ34+BY34*(1-Inputs!$B$6)+CA34-(CA34-CB34)*Inputs!$B$9 -> 17911027 | CD34: =BZ34/(BZ34+BY34+CA34) -> 0.80218586 | CE34: =IF(CC34>M34,1,0) -> 1 | CF34: =IF(BX34<0,"SHORT","ok") -> ok | CH34: 27 | CI34: =CI33+1 -> 84 | CJ34: =CJ33+1 -> 2052 | CK34: =IF(Inputs!$B$15="B",Inputs!$D$45,Inputs!$C$45) -> 0.38 | CL34: =CP33 -> 0 | CM34: =IF(CH34<=$CM$4,CL34/($CM$4-CH34+1),0) -> 0 | CN34: =CM34*CK34 -> 0 | CO34: =CR33-CN34 -> 3373611.8 | CP34: =(CL34-CM34)*(1+Inputs!$B$4) -> 0 | CQ34: =(CQ33+CM34)*(1+Inputs!$B$4) -> 15076493 | CR34: =CO34*(1+Inputs!$B$4*(1-Inputs!$B$8)) -> 3694104.9 | CS34: =IF(CR33<=0,0,CS33*CO34/CR33) -> 318660.33 | CT34: =CQ34+CP34*(1-Inputs!$B$6)+CR34-(CR34-CS34)*Inputs!$B$9 -> 17892983 | CU34: =CQ34/(CQ34+CP34+CR34) -> 0.80319728 | CV34: =IF(CT34>M34,1,0) -> 1 | CW34: =IF(CO34<0,"SHORT","ok") -> ok
A35: 28 | B35: =B34+1 -> 85 | C35: =C34+1 -> 2053 | D35: =IF(Inputs!$B$15="B",Inputs!$D$46,Inputs!$C$46) -> 0.38 | E35: =I34 -> 15076493 | F35: =IF(A35<=$F$4,E35/($F$4-A35+1),0) -> 0 | G35: =F35*D35 -> 0 | H35: =K34-G35 -> 8865448.3 | I35: =(E35-F35)*(1+Inputs!$B$4) -> 16584143 | J35: =(J34+F35)*(1+Inputs!$B$4) -> 0 | K35: =H35*(1+Inputs!$B$4*(1-Inputs!$B$8)) -> 9707665.9 | L35: =IF(K34<=0,0,L34*H35/K34) -> 764750 | M35: =J35+I35*(1-Inputs!$B$6)+K35-(K35-L35)*Inputs!$B$9 -> 18991408 | N35: =J35/(J35+I35+K35) -> 0 | O35: =IF(M35>M35,1,0) -> 0 | P35: =IF(H35<0,"SHORT","ok") -> ok | R35: 28 | S35: =S34+1 -> 85 | T35: =T34+1 -> 2053 | U35: =IF(Inputs!$B$15="B",Inputs!$D$46,Inputs!$C$46) -> 0.38 | V35: =Z34 -> 0 | W35: =IF(R35<=$W$4,V35/($W$4-R35+1),0) -> 0 | X35: =W35*U35 -> 0 | Y35: =AB34-X35 -> 3799477.9 | Z35: =(V35-W35)*(1+Inputs!$B$4) -> 0 | AA35: =(AA34+W35)*(1+Inputs!$B$4) -> 16584143 | AB35: =Y35*(1+Inputs!$B$4*(1-Inputs!$B$8)) -> 4160428.3 | AC35: =IF(AB34<=0,0,AC34*Y35/AB34) -> 327750 | AD35: =AA35+Z35*(1-Inputs!$B$6)+AB35-(AB35-AC35)*Inputs!$B$9 -> 19748075 | AE35: =AA35/(AA35+Z35+AB35) -> 0.79944496 | AF35: =IF(AD35>M35,1,0) -> 1 | AG35: =IF(Y35<0,"SHORT","ok") -> ok | AI35: 28 | AJ35: =AJ34+1 -> 85 | AK35: =AK34+1 -> 2053 | AL35: =IF(Inputs!$B$15="B",Inputs!$D$46,Inputs!$C$46) -> 0.38 | AM35: =AQ34 -> 0 | AN35: =IF(AI35<=$AN$4,AM35/($AN$4-AI35+1),0) -> 0 | AO35: =AN35*AL35 -> 0 | AP35: =AS34-AO35 -> 3776310.4 | AQ35: =(AM35-AN35)*(1+Inputs!$B$4) -> 0 | AR35: =(AR34+AN35)*(1+Inputs!$B$4) -> 16584143 | AS35: =AP35*(1+Inputs!$B$4*(1-Inputs!$B$8)) -> 4135059.9 | AT35: =IF(AS34<=0,0,AT34*AP35/AS34) -> 325751.53 | AU35: =AR35+AQ35*(1-Inputs!$B$6)+AS35-(AS35-AT35)*Inputs!$B$9 -> 19728782 | AV35: =AR35/(AR35+AQ35+AS35) -> 0.80042379 | AW35: =IF(AU35>M35,1,0) -> 1 | AX35: =IF(AP35<0,"SHORT","ok") -> ok | AZ35: 28 | BA35: =BA34+1 -> 85 | BB35: =BB34+1 -> 2053 | BC35: =IF(Inputs!$B$15="B",Inputs!$D$46,Inputs!$C$46) -> 0.38 | BD35: =BH34 -> 0 | BE35: =IF(AZ35<=$BE$4,BD35/($BE$4-AZ35+1),0) -> 0 | BF35: =BE35*BC35 -> 0 | BG35: =BJ34-BF35 -> 3753001.6 | BH35: =(BD35-BE35)*(1+Inputs!$B$4) -> 0 | BI35: =(BI34+BE35)*(1+Inputs!$B$4) -> 16584143 | BJ35: =BG35*(1+Inputs!$B$4*(1-Inputs!$B$8)) -> 4109536.7 | BK35: =IF(BJ34<=0,0,BK34*BG35/BJ34) -> 323740.87 | BL35: =BI35+BH35*(1-Inputs!$B$6)+BJ35-(BJ35-BK35)*Inputs!$B$9 -> 19709372 | BM35: =BI35/(BI35+BH35+BJ35) -> 0.80141102 | BN35: =IF(BL35>M35,1,0) -> 1 | BO35: =IF(BG35<0,"SHORT","ok") -> ok | BQ35: 28 | BR35: =BR34+1 -> 85 | BS35: =BS34+1 -> 2053 | BT35: =IF(Inputs!$B$15="B",Inputs!$D$46,Inputs!$C$46) -> 0.38 | BU35: =BY34 -> 0 | BV35: =IF(BQ35<=$BV$4,BU35/($BV$4-BQ35+1),0) -> 0 | BW35: =BV35*BT35 -> 0 | BX35: =CA34-BW35 -> 3717771.2 | BY35: =(BU35-BV35)*(1+Inputs!$B$4) -> 0 | BZ35: =(BZ34+BV35)*(1+Inputs!$B$4) -> 16584143 | CA35: =BX35*(1+Inputs!$B$4*(1-Inputs!$B$8)) -> 4070959.5 | CB35: =IF(CA34<=0,0,CB34*BX35/CA34) -> 320701.84 | CC35: =BZ35+BY35*(1-Inputs!$B$6)+CA35-(CA35-CB35)*Inputs!$B$9 -> 19680035 | CD35: =BZ35/(BZ35+BY35+CA35) -> 0.8029078 | CE35: =IF(CC35>M35,1,0) -> 1 | CF35: =IF(BX35<0,"SHORT","ok") -> ok | CH35: 28 | CI35: =CI34+1 -> 85 | CJ35: =CJ34+1 -> 2053 | CK35: =IF(Inputs!$B$15="B",Inputs!$D$46,Inputs!$C$46) -> 0.38 | CL35: =CP34 -> 0 | CM35: =IF(CH35<=$CM$4,CL35/($CM$4-CH35+1),0) -> 0 | CN35: =CM35*CK35 -> 0 | CO35: =CR34-CN35 -> 3694104.9 | CP35: =(CL35-CM35)*(1+Inputs!$B$4) -> 0 | CQ35: =(CQ34+CM35)*(1+Inputs!$B$4) -> 16584143 | CR35: =CO35*(1+Inputs!$B$4*(1-Inputs!$B$8)) -> 4045044.8 | CS35: =IF(CR34<=0,0,CS34*CO35/CR34) -> 318660.33 | CT35: =CQ35+CP35*(1-Inputs!$B$6)+CR35-(CR35-CS35)*Inputs!$B$9 -> 19660328 | CU35: =CQ35/(CQ35+CP35+CR35) -> 0.80391642 | CV35: =IF(CT35>M35,1,0) -> 1 | CW35: =IF(CO35<0,"SHORT","ok") -> ok
A36: 29 | B36: =B35+1 -> 86 | C36: =C35+1 -> 2054 | D36: =IF(Inputs!$B$15="B",Inputs!$D$47,Inputs!$C$47) -> 0.38 | E36: =I35 -> 16584143 | F36: =IF(A36<=$F$4,E36/($F$4-A36+1),0) -> 0 | G36: =F36*D36 -> 0 | H36: =K35-G36 -> 9707665.9 | I36: =(E36-F36)*(1+Inputs!$B$4) -> 18242557 | J36: =(J35+F36)*(1+Inputs!$B$4) -> 0 | K36: =H36*(1+Inputs!$B$4*(1-Inputs!$B$8)) -> 10629894 | L36: =IF(K35<=0,0,L35*H36/K35) -> 764750 | M36: =J36+I36*(1-Inputs!$B$6)+K36-(K36-L36)*Inputs!$B$9 -> 20834747 | N36: =J36/(J36+I36+K36) -> 0 | O36: =IF(M36>M36,1,0) -> 0 | P36: =IF(H36<0,"SHORT","ok") -> ok | R36: 29 | S36: =S35+1 -> 86 | T36: =T35+1 -> 2054 | U36: =IF(Inputs!$B$15="B",Inputs!$D$47,Inputs!$C$47) -> 0.38 | V36: =Z35 -> 0 | W36: =IF(R36<=$W$4,V36/($W$4-R36+1),0) -> 0 | X36: =W36*U36 -> 0 | Y36: =AB35-X36 -> 4160428.3 | Z36: =(V36-W36)*(1+Inputs!$B$4) -> 0 | AA36: =(AA35+W36)*(1+Inputs!$B$4) -> 18242557 | AB36: =Y36*(1+Inputs!$B$4*(1-Inputs!$B$8)) -> 4555668.9 | AC36: =IF(AB35<=0,0,AC35*Y36/AB35) -> 327750 | AD36: =AA36+Z36*(1-Inputs!$B$6)+AB36-(AB36-AC36)*Inputs!$B$9 -> 21698967 | AE36: =AA36/(AA36+Z36+AB36) -> 0.80017441 | AF36: =IF(AD36>M36,1,0) -> 1 | AG36: =IF(Y36<0,"SHORT","ok") -> ok | AI36: 29 | AJ36: =AJ35+1 -> 86 | AK36: =AK35+1 -> 2054 | AL36: =IF(Inputs!$B$15="B",Inputs!$D$47,Inputs!$C$47) -> 0.38 | AM36: =AQ35 -> 0 | AN36: =IF(AI36<=$AN$4,AM36/($AN$4-AI36+1),0) -> 0 | AO36: =AN36*AL36 -> 0 | AP36: =AS35-AO36 -> 4135059.9 | AQ36: =(AM36-AN36)*(1+Inputs!$B$4) -> 0 | AR36: =(AR35+AN36)*(1+Inputs!$B$4) -> 18242557 | AS36: =AP36*(1+Inputs!$B$4*(1-Inputs!$B$8)) -> 4527890.5 | AT36: =IF(AS35<=0,0,AT35*AP36/AS35) -> 325751.53 | AU36: =AR36+AQ36*(1-Inputs!$B$6)+AS36-(AS36-AT36)*Inputs!$B$9 -> 21677891 | AV36: =AR36/(AR36+AQ36+AS36) -> 0.80115057 | AW36: =IF(AU36>M36,1,0) -> 1 | AX36: =IF(AP36<0,"SHORT","ok") -> ok | AZ36: 29 | BA36: =BA35+1 -> 86 | BB36: =BB35+1 -> 2054 | BC36: =IF(Inputs!$B$15="B",Inputs!$D$47,Inputs!$C$47) -> 0.38 | BD36: =BH35 -> 0 | BE36: =IF(AZ36<=$BE$4,BD36/($BE$4-AZ36+1),0) -> 0 | BF36: =BE36*BC36 -> 0 | BG36: =BJ35-BF36 -> 4109536.7 | BH36: =(BD36-BE36)*(1+Inputs!$B$4) -> 0 | BI36: =(BI35+BE36)*(1+Inputs!$B$4) -> 18242557 | BJ36: =BG36*(1+Inputs!$B$4*(1-Inputs!$B$8)) -> 4499942.7 | BK36: =IF(BJ35<=0,0,BK35*BG36/BJ35) -> 323740.87 | BL36: =BI36+BH36*(1-Inputs!$B$6)+BJ36-(BJ36-BK36)*Inputs!$B$9 -> 21656687 | BM36: =BI36/(BI36+BH36+BJ36) -> 0.80213509 | BN36: =IF(BL36>M36,1,0) -> 1 | BO36: =IF(BG36<0,"SHORT","ok") -> ok | BQ36: 29 | BR36: =BR35+1 -> 86 | BS36: =BS35+1 -> 2054 | BT36: =IF(Inputs!$B$15="B",Inputs!$D$47,Inputs!$C$47) -> 0.38 | BU36: =BY35 -> 0 | BV36: =IF(BQ36<=$BV$4,BU36/($BV$4-BQ36+1),0) -> 0 | BW36: =BV36*BT36 -> 0 | BX36: =CA35-BW36 -> 4070959.5 | BY36: =(BU36-BV36)*(1+Inputs!$B$4) -> 0 | BZ36: =(BZ35+BV36)*(1+Inputs!$B$4) -> 18242557 | CA36: =BX36*(1+Inputs!$B$4*(1-Inputs!$B$8)) -> 4457700.7 | CB36: =IF(CA35<=0,0,CB35*BX36/CA35) -> 320701.84 | CC36: =BZ36+BY36*(1-Inputs!$B$6)+CA36-(CA36-CB36)*Inputs!$B$9 -> 21624638 | CD36: =BZ36/(BZ36+BY36+CA36) -> 0.80362775 | CE36: =IF(CC36>M36,1,0) -> 1 | CF36: =IF(BX36<0,"SHORT","ok") -> ok | CH36: 29 | CI36: =CI35+1 -> 86 | CJ36: =CJ35+1 -> 2054 | CK36: =IF(Inputs!$B$15="B",Inputs!$D$47,Inputs!$C$47) -> 0.38 | CL36: =CP35 -> 0 | CM36: =IF(CH36<=$CM$4,CL36/($CM$4-CH36+1),0) -> 0 | CN36: =CM36*CK36 -> 0 | CO36: =CR35-CN36 -> 4045044.8 | CP36: =(CL36-CM36)*(1+Inputs!$B$4) -> 0 | CQ36: =(CQ35+CM36)*(1+Inputs!$B$4) -> 18242557 | CR36: =CO36*(1+Inputs!$B$4*(1-Inputs!$B$8)) -> 4429324.1 | CS36: =IF(CR35<=0,0,CS35*CO36/CR35) -> 318660.33 | CT36: =CQ36+CP36*(1-Inputs!$B$6)+CR36-(CR36-CS36)*Inputs!$B$9 -> 21603108 | CU36: =CQ36/(CQ36+CP36+CR36) -> 0.80463359 | CV36: =IF(CT36>M36,1,0) -> 1 | CW36: =IF(CO36<0,"SHORT","ok") -> ok
A37: 30 | B37: =B36+1 -> 87 | C37: =C36+1 -> 2055 | D37: =IF(Inputs!$B$15="B",Inputs!$D$48,Inputs!$C$48) -> 0.38 | E37: =I36 -> 18242557 | F37: =IF(A37<=$F$4,E37/($F$4-A37+1),0) -> 0 | G37: =F37*D37 -> 0 | H37: =K36-G37 -> 10629894 | I37: =(E37-F37)*(1+Inputs!$B$4) -> 20066813 | J37: =(J36+F37)*(1+Inputs!$B$4) -> 0 | K37: =H37*(1+Inputs!$B$4*(1-Inputs!$B$8)) -> 11639734 | L37: =IF(K36<=0,0,L36*H37/K36) -> 764750 | M37: =J37+I37*(1-Inputs!$B$6)+K37-(K37-L37)*Inputs!$B$9 -> 22859007 | N37: =J37/(J37+I37+K37) -> 0 | O37: =IF(M37>M37,1,0) -> 0 | P37: =IF(H37<0,"SHORT","ok") -> ok | R37: 30 | S37: =S36+1 -> 87 | T37: =T36+1 -> 2055 | U37: =IF(Inputs!$B$15="B",Inputs!$D$48,Inputs!$C$48) -> 0.38 | V37: =Z36 -> 0 | W37: =IF(R37<=$W$4,V37/($W$4-R37+1),0) -> 0 | X37: =W37*U37 -> 0 | Y37: =AB36-X37 -> 4555668.9 | Z37: =(V37-W37)*(1+Inputs!$B$4) -> 0 | AA37: =(AA36+W37)*(1+Inputs!$B$4) -> 20066813 | AB37: =Y37*(1+Inputs!$B$4*(1-Inputs!$B$8)) -> 4988457.5 | AC37: =IF(AB36<=0,0,AC36*Y37/AB36) -> 327750 | AD37: =AA37+Z37*(1-Inputs!$B$6)+AB37-(AB37-AC37)*Inputs!$B$9 -> 23843486 | AE37: =AA37/(AA37+Z37+AB37) -> 0.80090187 | AF37: =IF(AD37>M37,1,0) -> 1 | AG37: =IF(Y37<0,"SHORT","ok") -> ok | AI37: 30 | AJ37: =AJ36+1 -> 87 | AK37: =AK36+1 -> 2055 | AL37: =IF(Inputs!$B$15="B",Inputs!$D$48,Inputs!$C$48) -> 0.38 | AM37: =AQ36 -> 0 | AN37: =IF(AI37<=$AN$4,AM37/($AN$4-AI37+1),0) -> 0 | AO37: =AN37*AL37 -> 0 | AP37: =AS36-AO37 -> 4527890.5 | AQ37: =(AM37-AN37)*(1+Inputs!$B$4) -> 0 | AR37: =(AR36+AN37)*(1+Inputs!$B$4) -> 20066813 | AS37: =AP37*(1+Inputs!$B$4*(1-Inputs!$B$8)) -> 4958040.1 | AT37: =IF(AS36<=0,0,AT36*AP37/AS36) -> 325751.53 | AU37: =AR37+AQ37*(1-Inputs!$B$6)+AS37-(AS37-AT37)*Inputs!$B$9 -> 23820458 | AV37: =AR37/(AR37+AQ37+AS37) -> 0.80187535 | AW37: =IF(AU37>M37,1,0) -> 1 | AX37: =IF(AP37<0,"SHORT","ok") -> ok | AZ37: 30 | BA37: =BA36+1 -> 87 | BB37: =BB36+1 -> 2055 | BC37: =IF(Inputs!$B$15="B",Inputs!$D$48,Inputs!$C$48) -> 0.38 | BD37: =BH36 -> 0 | BE37: =IF(AZ37<=$BE$4,BD37/($BE$4-AZ37+1),0) -> 0 | BF37: =BE37*BC37 -> 0 | BG37: =BJ36-BF37 -> 4499942.7 | BH37: =(BD37-BE37)*(1+Inputs!$B$4) -> 0 | BI37: =(BI36+BE37)*(1+Inputs!$B$4) -> 20066813 | BJ37: =BG37*(1+Inputs!$B$4*(1-Inputs!$B$8)) -> 4927437.2 | BK37: =IF(BJ36<=0,0,BK36*BG37/BJ36) -> 323740.87 | BL37: =BI37+BH37*(1-Inputs!$B$6)+BJ37-(BJ37-BK37)*Inputs!$B$9 -> 23797289 | BM37: =BI37/(BI37+BH37+BJ37) -> 0.80285717 | BN37: =IF(BL37>M37,1,0) -> 1 | BO37: =IF(BG37<0,"SHORT","ok") -> ok | BQ37: 30 | BR37: =BR36+1 -> 87 | BS37: =BS36+1 -> 2055 | BT37: =IF(Inputs!$B$15="B",Inputs!$D$48,Inputs!$C$48) -> 0.38 | BU37: =BY36 -> 0 | BV37: =IF(BQ37<=$BV$4,BU37/($BV$4-BQ37+1),0) -> 0 | BW37: =BV37*BT37 -> 0 | BX37: =CA36-BW37 -> 4457700.7 | BY37: =(BU37-BV37)*(1+Inputs!$B$4) -> 0 | BZ37: =(BZ36+BV37)*(1+Inputs!$B$4) -> 20066813 | CA37: =BX37*(1+Inputs!$B$4*(1-Inputs!$B$8)) -> 4881182.2 | CB37: =IF(CA36<=0,0,CB36*BX37/CA36) -> 320701.84 | CC37: =BZ37+BY37*(1-Inputs!$B$6)+CA37-(CA37-CB37)*Inputs!$B$9 -> 23762270 | CD37: =BZ37/(BZ37+BY37+CA37) -> 0.80434571 | CE37: =IF(CC37>M37,1,0) -> 1 | CF37: =IF(BX37<0,"SHORT","ok") -> ok | CH37: 30 | CI37: =CI36+1 -> 87 | CJ37: =CJ36+1 -> 2055 | CK37: =IF(Inputs!$B$15="B",Inputs!$D$48,Inputs!$C$48) -> 0.38 | CL37: =CP36 -> 0 | CM37: =IF(CH37<=$CM$4,CL37/($CM$4-CH37+1),0) -> 0 | CN37: =CM37*CK37 -> 0 | CO37: =CR36-CN37 -> 4429324.1 | CP37: =(CL37-CM37)*(1+Inputs!$B$4) -> 0 | CQ37: =(CQ36+CM37)*(1+Inputs!$B$4) -> 20066813 | CR37: =CO37*(1+Inputs!$B$4*(1-Inputs!$B$8)) -> 4850109.9 | CS37: =IF(CR36<=0,0,CS36*CO37/CR36) -> 318660.33 | CT37: =CQ37+CP37*(1-Inputs!$B$6)+CR37-(CR37-CS37)*Inputs!$B$9 -> 23738746 | CU37: =CQ37/(CQ37+CP37+CR37) -> 0.80534876 | CV37: =IF(CT37>M37,1,0) -> 1 | CW37: =IF(CO37<0,"SHORT","ok") -> ok
A38: 31 | B38: =B37+1 -> 88 | C38: =C37+1 -> 2056 | D38: =IF(Inputs!$B$15="B",Inputs!$D$49,Inputs!$C$49) -> 0.38 | E38: =I37 -> 20066813 | F38: =IF(A38<=$F$4,E38/($F$4-A38+1),0) -> 0 | G38: =F38*D38 -> 0 | H38: =K37-G38 -> 11639734 | I38: =(E38-F38)*(1+Inputs!$B$4) -> 22073494 | J38: =(J37+F38)*(1+Inputs!$B$4) -> 0 | K38: =H38*(1+Inputs!$B$4*(1-Inputs!$B$8)) -> 12745509 | L38: =IF(K37<=0,0,L37*H38/K37) -> 764750 | M38: =J38+I38*(1-Inputs!$B$6)+K38-(K38-L38)*Inputs!$B$9 -> 25081957 | N38: =J38/(J38+I38+K38) -> 0 | O38: =IF(M38>M38,1,0) -> 0 | P38: =IF(H38<0,"SHORT","ok") -> ok | R38: 31 | S38: =S37+1 -> 88 | T38: =T37+1 -> 2056 | U38: =IF(Inputs!$B$15="B",Inputs!$D$49,Inputs!$C$49) -> 0.38 | V38: =Z37 -> 0 | W38: =IF(R38<=$W$4,V38/($W$4-R38+1),0) -> 0 | X38: =W38*U38 -> 0 | Y38: =AB37-X38 -> 4988457.5 | Z38: =(V38-W38)*(1+Inputs!$B$4) -> 0 | AA38: =(AA37+W38)*(1+Inputs!$B$4) -> 22073494 | AB38: =Y38*(1+Inputs!$B$4*(1-Inputs!$B$8)) -> 5462361 | AC38: =IF(AB37<=0,0,AC37*Y38/AB37) -> 327750 | AD38: =AA38+Z38*(1-Inputs!$B$6)+AB38-(AB38-AC38)*Inputs!$B$9 -> 26200856 | AE38: =AA38/(AA38+Z38+AB38) -> 0.80162733 | AF38: =IF(AD38>M38,1,0) -> 1 | AG38: =IF(Y38<0,"SHORT","ok") -> ok | AI38: 31 | AJ38: =AJ37+1 -> 88 | AK38: =AK37+1 -> 2056 | AL38: =IF(Inputs!$B$15="B",Inputs!$D$49,Inputs!$C$49) -> 0.38 | AM38: =AQ37 -> 0 | AN38: =IF(AI38<=$AN$4,AM38/($AN$4-AI38+1),0) -> 0 | AO38: =AN38*AL38 -> 0 | AP38: =AS37-AO38 -> 4958040.1 | AQ38: =(AM38-AN38)*(1+Inputs!$B$4) -> 0 | AR38: =(AR37+AN38)*(1+Inputs!$B$4) -> 22073494 | AS38: =AP38*(1+Inputs!$B$4*(1-Inputs!$B$8)) -> 5429053.9 | AT38: =IF(AS37<=0,0,AT37*AP38/AS37) -> 325751.53 | AU38: =AR38+AQ38*(1-Inputs!$B$6)+AS38-(AS38-AT38)*Inputs!$B$9 -> 26175689 | AV38: =AR38/(AR38+AQ38+AS38) -> 0.80259815 | AW38: =IF(AU38>M38,1,0) -> 1 | AX38: =IF(AP38<0,"SHORT","ok") -> ok | AZ38: 31 | BA38: =BA37+1 -> 88 | BB38: =BB37+1 -> 2056 | BC38: =IF(Inputs!$B$15="B",Inputs!$D$49,Inputs!$C$49) -> 0.38 | BD38: =BH37 -> 0 | BE38: =IF(AZ38<=$BE$4,BD38/($BE$4-AZ38+1),0) -> 0 | BF38: =BE38*BC38 -> 0 | BG38: =BJ37-BF38 -> 4927437.2 | BH38: =(BD38-BE38)*(1+Inputs!$B$4) -> 0 | BI38: =(BI37+BE38)*(1+Inputs!$B$4) -> 22073494 | BJ38: =BG38*(1+Inputs!$B$4*(1-Inputs!$B$8)) -> 5395543.8 | BK38: =IF(BJ37<=0,0,BK37*BG38/BJ37) -> 323740.87 | BL38: =BI38+BH38*(1-Inputs!$B$6)+BJ38-(BJ38-BK38)*Inputs!$B$9 -> 26150369 | BM38: =BI38/(BI38+BH38+BJ38) -> 0.80357725 | BN38: =IF(BL38>M38,1,0) -> 1 | BO38: =IF(BG38<0,"SHORT","ok") -> ok | BQ38: 31 | BR38: =BR37+1 -> 88 | BS38: =BS37+1 -> 2056 | BT38: =IF(Inputs!$B$15="B",Inputs!$D$49,Inputs!$C$49) -> 0.38 | BU38: =BY37 -> 0 | BV38: =IF(BQ38<=$BV$4,BU38/($BV$4-BQ38+1),0) -> 0 | BW38: =BV38*BT38 -> 0 | BX38: =CA37-BW38 -> 4881182.2 | BY38: =(BU38-BV38)*(1+Inputs!$B$4) -> 0 | BZ38: =(BZ37+BV38)*(1+Inputs!$B$4) -> 22073494 | CA38: =BX38*(1+Inputs!$B$4*(1-Inputs!$B$8)) -> 5344894.5 | CB38: =IF(CA37<=0,0,CB37*BX38/CA37) -> 320701.84 | CC38: =BZ38+BY38*(1-Inputs!$B$6)+CA38-(CA38-CB38)*Inputs!$B$9 -> 26112098 | CD38: =BZ38/(BZ38+BY38+CA38) -> 0.80506168 | CE38: =IF(CC38>M38,1,0) -> 1 | CF38: =IF(BX38<0,"SHORT","ok") -> ok | CH38: 31 | CI38: =CI37+1 -> 88 | CJ38: =CJ37+1 -> 2056 | CK38: =IF(Inputs!$B$15="B",Inputs!$D$49,Inputs!$C$49) -> 0.38 | CL38: =CP37 -> 0 | CM38: =IF(CH38<=$CM$4,CL38/($CM$4-CH38+1),0) -> 0 | CN38: =CM38*CK38 -> 0 | CO38: =CR37-CN38 -> 4850109.9 | CP38: =(CL38-CM38)*(1+Inputs!$B$4) -> 0 | CQ38: =(CQ37+CM38)*(1+Inputs!$B$4) -> 22073494 | CR38: =CO38*(1+Inputs!$B$4*(1-Inputs!$B$8)) -> 5310870.3 | CS38: =IF(CR37<=0,0,CS37*CO38/CR37) -> 318660.33 | CT38: =CQ38+CP38*(1-Inputs!$B$6)+CR38-(CR38-CS38)*Inputs!$B$9 -> 26086390 | CU38: =CQ38/(CQ38+CP38+CR38) -> 0.80606195 | CV38: =IF(CT38>M38,1,0) -> 1 | CW38: =IF(CO38<0,"SHORT","ok") -> ok
A39: 32 | B39: =B38+1 -> 89 | C39: =C38+1 -> 2057 | D39: =IF(Inputs!$B$15="B",Inputs!$D$50,Inputs!$C$50) -> 0.38 | E39: =I38 -> 22073494 | F39: =IF(A39<=$F$4,E39/($F$4-A39+1),0) -> 0 | G39: =F39*D39 -> 0 | H39: =K38-G39 -> 12745509 | I39: =(E39-F39)*(1+Inputs!$B$4) -> 24280843 | J39: =(J38+F39)*(1+Inputs!$B$4) -> 0 | K39: =H39*(1+Inputs!$B$4*(1-Inputs!$B$8)) -> 13956332 | L39: =IF(K38<=0,0,L38*H39/K38) -> 764750 | M39: =J39+I39*(1-Inputs!$B$6)+K39-(K39-L39)*Inputs!$B$9 -> 27523111 | N39: =J39/(J39+I39+K39) -> 0 | O39: =IF(M39>M39,1,0) -> 0 | P39: =IF(H39<0,"SHORT","ok") -> ok | R39: 32 | S39: =S38+1 -> 89 | T39: =T38+1 -> 2057 | U39: =IF(Inputs!$B$15="B",Inputs!$D$50,Inputs!$C$50) -> 0.38 | V39: =Z38 -> 0 | W39: =IF(R39<=$W$4,V39/($W$4-R39+1),0) -> 0 | X39: =W39*U39 -> 0 | Y39: =AB38-X39 -> 5462361 | Z39: =(V39-W39)*(1+Inputs!$B$4) -> 0 | AA39: =(AA38+W39)*(1+Inputs!$B$4) -> 24280843 | AB39: =Y39*(1+Inputs!$B$4*(1-Inputs!$B$8)) -> 5981285.2 | AC39: =IF(AB38<=0,0,AC38*Y39/AB38) -> 327750 | AD39: =AA39+Z39*(1-Inputs!$B$6)+AB39-(AB39-AC39)*Inputs!$B$9 -> 28792209 | AE39: =AA39/(AA39+Z39+AB39) -> 0.80235081 | AF39: =IF(AD39>M39,1,0) -> 1 | AG39: =IF(Y39<0,"SHORT","ok") -> ok | AI39: 32 | AJ39: =AJ38+1 -> 89 | AK39: =AK38+1 -> 2057 | AL39: =IF(Inputs!$B$15="B",Inputs!$D$50,Inputs!$C$50) -> 0.38 | AM39: =AQ38 -> 0 | AN39: =IF(AI39<=$AN$4,AM39/($AN$4-AI39+1),0) -> 0 | AO39: =AN39*AL39 -> 0 | AP39: =AS38-AO39 -> 5429053.9 | AQ39: =(AM39-AN39)*(1+Inputs!$B$4) -> 0 | AR39: =(AR38+AN39)*(1+Inputs!$B$4) -> 24280843 | AS39: =AP39*(1+Inputs!$B$4*(1-Inputs!$B$8)) -> 5944814.1 | AT39: =IF(AS38<=0,0,AT38*AP39/AS38) -> 325751.53 | AU39: =AR39+AQ39*(1-Inputs!$B$6)+AS39-(AS39-AT39)*Inputs!$B$9 -> 28764701 | AV39: =AR39/(AR39+AQ39+AS39) -> 0.80331895 | AW39: =IF(AU39>M39,1,0) -> 1 | AX39: =IF(AP39<0,"SHORT","ok") -> ok | AZ39: 32 | BA39: =BA38+1 -> 89 | BB39: =BB38+1 -> 2057 | BC39: =IF(Inputs!$B$15="B",Inputs!$D$50,Inputs!$C$50) -> 0.38 | BD39: =BH38 -> 0 | BE39: =IF(AZ39<=$BE$4,BD39/($BE$4-AZ39+1),0) -> 0 | BF39: =BE39*BC39 -> 0 | BG39: =BJ38-BF39 -> 5395543.8 | BH39: =(BD39-BE39)*(1+Inputs!$B$4) -> 0 | BI39: =(BI38+BE39)*(1+Inputs!$B$4) -> 24280843 | BJ39: =BG39*(1+Inputs!$B$4*(1-Inputs!$B$8)) -> 5908120.4 | BK39: =IF(BJ38<=0,0,BK38*BG39/BJ38) -> 323740.87 | BL39: =BI39+BH39*(1-Inputs!$B$6)+BJ39-(BJ39-BK39)*Inputs!$B$9 -> 28737025 | BM39: =BI39/(BI39+BH39+BJ39) -> 0.80429535 | BN39: =IF(BL39>M39,1,0) -> 1 | BO39: =IF(BG39<0,"SHORT","ok") -> ok | BQ39: 32 | BR39: =BR38+1 -> 89 | BS39: =BS38+1 -> 2057 | BT39: =IF(Inputs!$B$15="B",Inputs!$D$50,Inputs!$C$50) -> 0.38 | BU39: =BY38 -> 0 | BV39: =IF(BQ39<=$BV$4,BU39/($BV$4-BQ39+1),0) -> 0 | BW39: =BV39*BT39 -> 0 | BX39: =CA38-BW39 -> 5344894.5 | BY39: =(BU39-BV39)*(1+Inputs!$B$4) -> 0 | BZ39: =(BZ38+BV39)*(1+Inputs!$B$4) -> 24280843 | CA39: =BX39*(1+Inputs!$B$4*(1-Inputs!$B$8)) -> 5852659.5 | CB39: =IF(CA38<=0,0,CB38*BX39/CA38) -> 320701.84 | CC39: =BZ39+BY39*(1-Inputs!$B$6)+CA39-(CA39-CB39)*Inputs!$B$9 -> 28695194 | CD39: =BZ39/(BZ39+BY39+CA39) -> 0.80577567 | CE39: =IF(CC39>M39,1,0) -> 1 | CF39: =IF(BX39<0,"SHORT","ok") -> ok | CH39: 32 | CI39: =CI38+1 -> 89 | CJ39: =CJ38+1 -> 2057 | CK39: =IF(Inputs!$B$15="B",Inputs!$D$50,Inputs!$C$50) -> 0.38 | CL39: =CP38 -> 0 | CM39: =IF(CH39<=$CM$4,CL39/($CM$4-CH39+1),0) -> 0 | CN39: =CM39*CK39 -> 0 | CO39: =CR38-CN39 -> 5310870.3 | CP39: =(CL39-CM39)*(1+Inputs!$B$4) -> 0 | CQ39: =(CQ38+CM39)*(1+Inputs!$B$4) -> 24280843 | CR39: =CO39*(1+Inputs!$B$4*(1-Inputs!$B$8)) -> 5815403 | CS39: =IF(CR38<=0,0,CS38*CO39/CR38) -> 318660.33 | CT39: =CQ39+CP39*(1-Inputs!$B$6)+CR39-(CR39-CS39)*Inputs!$B$9 -> 28667093 | CU39: =CQ39/(CQ39+CP39+CR39) -> 0.80677315 | CV39: =IF(CT39>M39,1,0) -> 1 | CW39: =IF(CO39<0,"SHORT","ok") -> ok
A40: 33 | B40: =B39+1 -> 90 | C40: =C39+1 -> 2058 | D40: =IF(Inputs!$B$15="B",Inputs!$D$51,Inputs!$C$51) -> 0.38 | E40: =I39 -> 24280843 | F40: =IF(A40<=$F$4,E40/($F$4-A40+1),0) -> 0 | G40: =F40*D40 -> 0 | H40: =K39-G40 -> 13956332 | I40: =(E40-F40)*(1+Inputs!$B$4) -> 26708928 | J40: =(J39+F40)*(1+Inputs!$B$4) -> 0 | K40: =H40*(1+Inputs!$B$4*(1-Inputs!$B$8)) -> 15282184 | L40: =IF(K39<=0,0,L39*H40/K39) -> 764750 | M40: =J40+I40*(1-Inputs!$B$6)+K40-(K40-L40)*Inputs!$B$9 -> 30203900 | N40: =J40/(J40+I40+K40) -> 0 | O40: =IF(M40>M40,1,0) -> 0 | P40: =IF(H40<0,"SHORT","ok") -> ok | R40: 33 | S40: =S39+1 -> 90 | T40: =T39+1 -> 2058 | U40: =IF(Inputs!$B$15="B",Inputs!$D$51,Inputs!$C$51) -> 0.38 | V40: =Z39 -> 0 | W40: =IF(R40<=$W$4,V40/($W$4-R40+1),0) -> 0 | X40: =W40*U40 -> 0 | Y40: =AB39-X40 -> 5981285.2 | Z40: =(V40-W40)*(1+Inputs!$B$4) -> 0 | AA40: =(AA39+W40)*(1+Inputs!$B$4) -> 26708928 | AB40: =Y40*(1+Inputs!$B$4*(1-Inputs!$B$8)) -> 6549507.3 | AC40: =IF(AB39<=0,0,AC39*Y40/AB39) -> 327750 | AD40: =AA40+Z40*(1-Inputs!$B$6)+AB40-(AB40-AC40)*Inputs!$B$9 -> 31640778 | AE40: =AA40/(AA40+Z40+AB40) -> 0.80307229 | AF40: =IF(AD40>M40,1,0) -> 1 | AG40: =IF(Y40<0,"SHORT","ok") -> ok | AI40: 33 | AJ40: =AJ39+1 -> 90 | AK40: =AK39+1 -> 2058 | AL40: =IF(Inputs!$B$15="B",Inputs!$D$51,Inputs!$C$51) -> 0.38 | AM40: =AQ39 -> 0 | AN40: =IF(AI40<=$AN$4,AM40/($AN$4-AI40+1),0) -> 0 | AO40: =AN40*AL40 -> 0 | AP40: =AS39-AO40 -> 5944814.1 | AQ40: =(AM40-AN40)*(1+Inputs!$B$4) -> 0 | AR40: =(AR39+AN40)*(1+Inputs!$B$4) -> 26708928 | AS40: =AP40*(1+Inputs!$B$4*(1-Inputs!$B$8)) -> 6509571.4 | AT40: =IF(AS39<=0,0,AT39*AP40/AS39) -> 325751.53 | AU40: =AR40+AQ40*(1-Inputs!$B$6)+AS40-(AS40-AT40)*Inputs!$B$9 -> 31610706 | AV40: =AR40/(AR40+AQ40+AS40) -> 0.80403776 | AW40: =IF(AU40>M40,1,0) -> 1 | AX40: =IF(AP40<0,"SHORT","ok") -> ok | AZ40: 33 | BA40: =BA39+1 -> 90 | BB40: =BB39+1 -> 2058 | BC40: =IF(Inputs!$B$15="B",Inputs!$D$51,Inputs!$C$51) -> 0.38 | BD40: =BH39 -> 0 | BE40: =IF(AZ40<=$BE$4,BD40/($BE$4-AZ40+1),0) -> 0 | BF40: =BE40*BC40 -> 0 | BG40: =BJ39-BF40 -> 5908120.4 | BH40: =(BD40-BE40)*(1+Inputs!$B$4) -> 0 | BI40: =(BI39+BE40)*(1+Inputs!$B$4) -> 26708928 | BJ40: =BG40*(1+Inputs!$B$4*(1-Inputs!$B$8)) -> 6469391.9 | BK40: =IF(BJ39<=0,0,BK39*BG40/BJ39) -> 323740.87 | BL40: =BI40+BH40*(1-Inputs!$B$6)+BJ40-(BJ40-BK40)*Inputs!$B$9 -> 31580450 | BM40: =BI40/(BI40+BH40+BJ40) -> 0.80501147 | BN40: =IF(BL40>M40,1,0) -> 1 | BO40: =IF(BG40<0,"SHORT","ok") -> ok | BQ40: 33 | BR40: =BR39+1 -> 90 | BS40: =BS39+1 -> 2058 | BT40: =IF(Inputs!$B$15="B",Inputs!$D$51,Inputs!$C$51) -> 0.38 | BU40: =BY39 -> 0 | BV40: =IF(BQ40<=$BV$4,BU40/($BV$4-BQ40+1),0) -> 0 | BW40: =BV40*BT40 -> 0 | BX40: =CA39-BW40 -> 5852659.5 | BY40: =(BU40-BV40)*(1+Inputs!$B$4) -> 0 | BZ40: =(BZ39+BV40)*(1+Inputs!$B$4) -> 26708928 | CA40: =BX40*(1+Inputs!$B$4*(1-Inputs!$B$8)) -> 6408662.2 | CB40: =IF(CA39<=0,0,CB39*BX40/CA39) -> 320701.84 | CC40: =BZ40+BY40*(1-Inputs!$B$6)+CA40-(CA40-CB40)*Inputs!$B$9 -> 31534720 | CD40: =BZ40/(BZ40+BY40+CA40) -> 0.80648766 | CE40: =IF(CC40>M40,1,0) -> 1 | CF40: =IF(BX40<0,"SHORT","ok") -> ok | CH40: 33 | CI40: =CI39+1 -> 90 | CJ40: =CJ39+1 -> 2058 | CK40: =IF(Inputs!$B$15="B",Inputs!$D$51,Inputs!$C$51) -> 0.38 | CL40: =CP39 -> 0 | CM40: =IF(CH40<=$CM$4,CL40/($CM$4-CH40+1),0) -> 0 | CN40: =CM40*CK40 -> 0 | CO40: =CR39-CN40 -> 5815403 | CP40: =(CL40-CM40)*(1+Inputs!$B$4) -> 0 | CQ40: =(CQ39+CM40)*(1+Inputs!$B$4) -> 26708928 | CR40: =CO40*(1+Inputs!$B$4*(1-Inputs!$B$8)) -> 6367866.3 | CS40: =IF(CR39<=0,0,CS39*CO40/CR39) -> 318660.33 | CT40: =CQ40+CP40*(1-Inputs!$B$6)+CR40-(CR40-CS40)*Inputs!$B$9 -> 31504000 | CU40: =CQ40/(CQ40+CP40+CR40) -> 0.80748236 | CV40: =IF(CT40>M40,1,0) -> 1 | CW40: =IF(CO40<0,"SHORT","ok") -> ok
A41: 34 | B41: =B40+1 -> 91 | C41: =C40+1 -> 2059 | D41: =IF(Inputs!$B$15="B",Inputs!$D$52,Inputs!$C$52) -> 0.38 | E41: =I40 -> 26708928 | F41: =IF(A41<=$F$4,E41/($F$4-A41+1),0) -> 0 | G41: =F41*D41 -> 0 | H41: =K40-G41 -> 15282184 | I41: =(E41-F41)*(1+Inputs!$B$4) -> 29379820 | J41: =(J40+F41)*(1+Inputs!$B$4) -> 0 | K41: =H41*(1+Inputs!$B$4*(1-Inputs!$B$8)) -> 16733991 | L41: =IF(K40<=0,0,L40*H41/K40) -> 764750 | M41: =J41+I41*(1-Inputs!$B$6)+K41-(K41-L41)*Inputs!$B$9 -> 33147863 | N41: =J41/(J41+I41+K41) -> 0 | O41: =IF(M41>M41,1,0) -> 0 | P41: =IF(H41<0,"SHORT","ok") -> ok | R41: 34 | S41: =S40+1 -> 91 | T41: =T40+1 -> 2059 | U41: =IF(Inputs!$B$15="B",Inputs!$D$52,Inputs!$C$52) -> 0.38 | V41: =Z40 -> 0 | W41: =IF(R41<=$W$4,V41/($W$4-R41+1),0) -> 0 | X41: =W41*U41 -> 0 | Y41: =AB40-X41 -> 6549507.3 | Z41: =(V41-W41)*(1+Inputs!$B$4) -> 0 | AA41: =(AA40+W41)*(1+Inputs!$B$4) -> 29379820 | AB41: =Y41*(1+Inputs!$B$4*(1-Inputs!$B$8)) -> 7171710.5 | AC41: =IF(AB40<=0,0,AC40*Y41/AB40) -> 327750 | AD41: =AA41+Z41*(1-Inputs!$B$6)+AB41-(AB41-AC41)*Inputs!$B$9 -> 34772101 | AE41: =AA41/(AA41+Z41+AB41) -> 0.80379179 | AF41: =IF(AD41>M41,1,0) -> 1 | AG41: =IF(Y41<0,"SHORT","ok") -> ok | AI41: 34 | AJ41: =AJ40+1 -> 91 | AK41: =AK40+1 -> 2059 | AL41: =IF(Inputs!$B$15="B",Inputs!$D$52,Inputs!$C$52) -> 0.38 | AM41: =AQ40 -> 0 | AN41: =IF(AI41<=$AN$4,AM41/($AN$4-AI41+1),0) -> 0 | AO41: =AN41*AL41 -> 0 | AP41: =AS40-AO41 -> 6509571.4 | AQ41: =(AM41-AN41)*(1+Inputs!$B$4) -> 0 | AR41: =(AR40+AN41)*(1+Inputs!$B$4) -> 29379820 | AS41: =AP41*(1+Inputs!$B$4*(1-Inputs!$B$8)) -> 7127980.7 | AT41: =IF(AS40<=0,0,AT40*AP41/AS40) -> 325751.53 | AU41: =AR41+AQ41*(1-Inputs!$B$6)+AS41-(AS41-AT41)*Inputs!$B$9 -> 34739221 | AV41: =AR41/(AR41+AQ41+AS41) -> 0.80475459 | AW41: =IF(AU41>M41,1,0) -> 1 | AX41: =IF(AP41<0,"SHORT","ok") -> ok | AZ41: 34 | BA41: =BA40+1 -> 91 | BB41: =BB40+1 -> 2059 | BC41: =IF(Inputs!$B$15="B",Inputs!$D$52,Inputs!$C$52) -> 0.38 | BD41: =BH40 -> 0 | BE41: =IF(AZ41<=$BE$4,BD41/($BE$4-AZ41+1),0) -> 0 | BF41: =BE41*BC41 -> 0 | BG41: =BJ40-BF41 -> 6469391.9 | BH41: =(BD41-BE41)*(1+Inputs!$B$4) -> 0 | BI41: =(BI40+BE41)*(1+Inputs!$B$4) -> 29379820 | BJ41: =BG41*(1+Inputs!$B$4*(1-Inputs!$B$8)) -> 7083984.1 | BK41: =IF(BJ40<=0,0,BK40*BG41/BJ40) -> 323740.87 | BL41: =BI41+BH41*(1-Inputs!$B$6)+BJ41-(BJ41-BK41)*Inputs!$B$9 -> 34706141 | BM41: =BI41/(BI41+BH41+BJ41) -> 0.80572559 | BN41: =IF(BL41>M41,1,0) -> 1 | BO41: =IF(BG41<0,"SHORT","ok") -> ok | BQ41: 34 | BR41: =BR40+1 -> 91 | BS41: =BS40+1 -> 2059 | BT41: =IF(Inputs!$B$15="B",Inputs!$D$52,Inputs!$C$52) -> 0.38 | BU41: =BY40 -> 0 | BV41: =IF(BQ41<=$BV$4,BU41/($BV$4-BQ41+1),0) -> 0 | BW41: =BV41*BT41 -> 0 | BX41: =CA40-BW41 -> 6408662.2 | BY41: =(BU41-BV41)*(1+Inputs!$B$4) -> 0 | BZ41: =(BZ40+BV41)*(1+Inputs!$B$4) -> 29379820 | CA41: =BX41*(1+Inputs!$B$4*(1-Inputs!$B$8)) -> 7017485.1 | CB41: =IF(CA40<=0,0,CB40*BX41/CA40) -> 320701.84 | CC41: =BZ41+BY41*(1-Inputs!$B$6)+CA41-(CA41-CB41)*Inputs!$B$9 -> 34656142 | CD41: =BZ41/(BZ41+BY41+CA41) -> 0.80719768 | CE41: =IF(CC41>M41,1,0) -> 1 | CF41: =IF(BX41<0,"SHORT","ok") -> ok | CH41: 34 | CI41: =CI40+1 -> 91 | CJ41: =CJ40+1 -> 2059 | CK41: =IF(Inputs!$B$15="B",Inputs!$D$52,Inputs!$C$52) -> 0.38 | CL41: =CP40 -> 0 | CM41: =IF(CH41<=$CM$4,CL41/($CM$4-CH41+1),0) -> 0 | CN41: =CM41*CK41 -> 0 | CO41: =CR40-CN41 -> 6367866.3 | CP41: =(CL41-CM41)*(1+Inputs!$B$4) -> 0 | CQ41: =(CQ40+CM41)*(1+Inputs!$B$4) -> 29379820 | CR41: =CO41*(1+Inputs!$B$4*(1-Inputs!$B$8)) -> 6972813.6 | CS41: =IF(CR40<=0,0,CS40*CO41/CR40) -> 318660.33 | CT41: =CQ41+CP41*(1-Inputs!$B$6)+CR41-(CR41-CS41)*Inputs!$B$9 -> 34622554 | CU41: =CQ41/(CQ41+CP41+CR41) -> 0.80818959 | CV41: =IF(CT41>M41,1,0) -> 1 | CW41: =IF(CO41<0,"SHORT","ok") -> ok
A42: 35 | B42: =B41+1 -> 92 | C42: =C41+1 -> 2060 | D42: =IF(Inputs!$B$15="B",Inputs!$D$53,Inputs!$C$53) -> 0.38 | E42: =I41 -> 29379820 | F42: =IF(A42<=$F$4,E42/($F$4-A42+1),0) -> 0 | G42: =F42*D42 -> 0 | H42: =K41-G42 -> 16733991 | I42: =(E42-F42)*(1+Inputs!$B$4) -> 32317802 | J42: =(J41+F42)*(1+Inputs!$B$4) -> 0 | K42: =H42*(1+Inputs!$B$4*(1-Inputs!$B$8)) -> 18323720 | L42: =IF(K41<=0,0,L41*H42/K41) -> 764750 | M42: =J42+I42*(1-Inputs!$B$6)+K42-(K42-L42)*Inputs!$B$9 -> 36380850 | N42: =J42/(J42+I42+K42) -> 0 | O42: =IF(M42>M42,1,0) -> 0 | P42: =IF(H42<0,"SHORT","ok") -> ok | R42: 35 | S42: =S41+1 -> 92 | T42: =T41+1 -> 2060 | U42: =IF(Inputs!$B$15="B",Inputs!$D$53,Inputs!$C$53) -> 0.38 | V42: =Z41 -> 0 | W42: =IF(R42<=$W$4,V42/($W$4-R42+1),0) -> 0 | X42: =W42*U42 -> 0 | Y42: =AB41-X42 -> 7171710.5 | Z42: =(V42-W42)*(1+Inputs!$B$4) -> 0 | AA42: =(AA41+W42)*(1+Inputs!$B$4) -> 32317802 | AB42: =Y42*(1+Inputs!$B$4*(1-Inputs!$B$8)) -> 7853023 | AC42: =IF(AB41<=0,0,AC41*Y42/AB41) -> 327750 | AD42: =AA42+Z42*(1-Inputs!$B$6)+AB42-(AB42-AC42)*Inputs!$B$9 -> 38214254 | AE42: =AA42/(AA42+Z42+AB42) -> 0.80450929 | AF42: =IF(AD42>M42,1,0) -> 1 | AG42: =IF(Y42<0,"SHORT","ok") -> ok | AI42: 35 | AJ42: =AJ41+1 -> 92 | AK42: =AK41+1 -> 2060 | AL42: =IF(Inputs!$B$15="B",Inputs!$D$53,Inputs!$C$53) -> 0.38 | AM42: =AQ41 -> 0 | AN42: =IF(AI42<=$AN$4,AM42/($AN$4-AI42+1),0) -> 0 | AO42: =AN42*AL42 -> 0 | AP42: =AS41-AO42 -> 7127980.7 | AQ42: =(AM42-AN42)*(1+Inputs!$B$4) -> 0 | AR42: =(AR41+AN42)*(1+Inputs!$B$4) -> 32317802 | AS42: =AP42*(1+Inputs!$B$4*(1-Inputs!$B$8)) -> 7805138.9 | AT42: =IF(AS41<=0,0,AT41*AP42/AS41) -> 325751.53 | AU42: =AR42+AQ42*(1-Inputs!$B$6)+AS42-(AS42-AT42)*Inputs!$B$9 -> 38178301 | AV42: =AR42/(AR42+AQ42+AS42) -> 0.80546942 | AW42: =IF(AU42>M42,1,0) -> 1 | AX42: =IF(AP42<0,"SHORT","ok") -> ok | AZ42: 35 | BA42: =BA41+1 -> 92 | BB42: =BB41+1 -> 2060 | BC42: =IF(Inputs!$B$15="B",Inputs!$D$53,Inputs!$C$53) -> 0.38 | BD42: =BH41 -> 0 | BE42: =IF(AZ42<=$BE$4,BD42/($BE$4-AZ42+1),0) -> 0 | BF42: =BE42*BC42 -> 0 | BG42: =BJ41-BF42 -> 7083984.1 | BH42: =(BD42-BE42)*(1+Inputs!$B$4) -> 0 | BI42: =(BI41+BE42)*(1+Inputs!$B$4) -> 32317802 | BJ42: =BG42*(1+Inputs!$B$4*(1-Inputs!$B$8)) -> 7756962.6 | BK42: =IF(BJ41<=0,0,BK41*BG42/BJ41) -> 323740.87 | BL42: =BI42+BH42*(1-Inputs!$B$6)+BJ42-(BJ42-BK42)*Inputs!$B$9 -> 38142127 | BM42: =BI42/(BI42+BH42+BJ42) -> 0.80643773 | BN42: =IF(BL42>M42,1,0) -> 1 | BO42: =IF(BG42<0,"SHORT","ok") -> ok | BQ42: 35 | BR42: =BR41+1 -> 92 | BS42: =BS41+1 -> 2060 | BT42: =IF(Inputs!$B$15="B",Inputs!$D$53,Inputs!$C$53) -> 0.38 | BU42: =BY41 -> 0 | BV42: =IF(BQ42<=$BV$4,BU42/($BV$4-BQ42+1),0) -> 0 | BW42: =BV42*BT42 -> 0 | BX42: =CA41-BW42 -> 7017485.1 | BY42: =(BU42-BV42)*(1+Inputs!$B$4) -> 0 | BZ42: =(BZ41+BV42)*(1+Inputs!$B$4) -> 32317802 | CA42: =BX42*(1+Inputs!$B$4*(1-Inputs!$B$8)) -> 7684146.2 | CB42: =IF(CA41<=0,0,CB41*BX42/CA41) -> 320701.84 | CC42: =BZ42+BY42*(1-Inputs!$B$6)+CA42-(CA42-CB42)*Inputs!$B$9 -> 38087453 | CD42: =BZ42/(BZ42+BY42+CA42) -> 0.8079057 | CE42: =IF(CC42>M42,1,0) -> 1 | CF42: =IF(BX42<0,"SHORT","ok") -> ok | CH42: 35 | CI42: =CI41+1 -> 92 | CJ42: =CJ41+1 -> 2060 | CK42: =IF(Inputs!$B$15="B",Inputs!$D$53,Inputs!$C$53) -> 0.38 | CL42: =CP41 -> 0 | CM42: =IF(CH42<=$CM$4,CL42/($CM$4-CH42+1),0) -> 0 | CN42: =CM42*CK42 -> 0 | CO42: =CR41-CN42 -> 6972813.6 | CP42: =(CL42-CM42)*(1+Inputs!$B$4) -> 0 | CQ42: =(CQ41+CM42)*(1+Inputs!$B$4) -> 32317802 | CR42: =CO42*(1+Inputs!$B$4*(1-Inputs!$B$8)) -> 7635230.9 | CS42: =IF(CR41<=0,0,CS41*CO42/CR41) -> 318660.33 | CT42: =CQ42+CP42*(1-Inputs!$B$6)+CR42-(CR42-CS42)*Inputs!$B$9 -> 38050725 | CU42: =CQ42/(CQ42+CP42+CR42) -> 0.80889484 | CV42: =IF(CT42>M42,1,0) -> 1 | CW42: =IF(CO42<0,"SHORT","ok") -> ok
A43: 36 | B43: =B42+1 -> 93 | C43: =C42+1 -> 2061 | D43: =IF(Inputs!$B$15="B",Inputs!$D$54,Inputs!$C$54) -> 0.38 | E43: =I42 -> 32317802 | F43: =IF(A43<=$F$4,E43/($F$4-A43+1),0) -> 0 | G43: =F43*D43 -> 0 | H43: =K42-G43 -> 18323720 | I43: =(E43-F43)*(1+Inputs!$B$4) -> 35549583 | J43: =(J42+F43)*(1+Inputs!$B$4) -> 0 | K43: =H43*(1+Inputs!$B$4*(1-Inputs!$B$8)) -> 20064474 | L43: =IF(K42<=0,0,L42*H43/K42) -> 764750 | M43: =J43+I43*(1-Inputs!$B$6)+K43-(K43-L43)*Inputs!$B$9 -> 39931253 | N43: =J43/(J43+I43+K43) -> 0 | O43: =IF(M43>M43,1,0) -> 0 | P43: =IF(H43<0,"SHORT","ok") -> ok | R43: 36 | S43: =S42+1 -> 93 | T43: =T42+1 -> 2061 | U43: =IF(Inputs!$B$15="B",Inputs!$D$54,Inputs!$C$54) -> 0.38 | V43: =Z42 -> 0 | W43: =IF(R43<=$W$4,V43/($W$4-R43+1),0) -> 0 | X43: =W43*U43 -> 0 | Y43: =AB42-X43 -> 7853023 | Z43: =(V43-W43)*(1+Inputs!$B$4) -> 0 | AA43: =(AA42+W43)*(1+Inputs!$B$4) -> 35549583 | AB43: =Y43*(1+Inputs!$B$4*(1-Inputs!$B$8)) -> 8599060.2 | AC43: =IF(AB42<=0,0,AC42*Y43/AB42) -> 327750 | AD43: =AA43+Z43*(1-Inputs!$B$6)+AB43-(AB43-AC43)*Inputs!$B$9 -> 41998102 | AE43: =AA43/(AA43+Z43+AB43) -> 0.80522481 | AF43: =IF(AD43>M43,1,0) -> 1 | AG43: =IF(Y43<0,"SHORT","ok") -> ok | AI43: 36 | AJ43: =AJ42+1 -> 93 | AK43: =AK42+1 -> 2061 | AL43: =IF(Inputs!$B$15="B",Inputs!$D$54,Inputs!$C$54) -> 0.38 | AM43: =AQ42 -> 0 | AN43: =IF(AI43<=$AN$4,AM43/($AN$4-AI43+1),0) -> 0 | AO43: =AN43*AL43 -> 0 | AP43: =AS42-AO43 -> 7805138.9 | AQ43: =(AM43-AN43)*(1+Inputs!$B$4) -> 0 | AR43: =(AR42+AN43)*(1+Inputs!$B$4) -> 35549583 | AS43: =AP43*(1+Inputs!$B$4*(1-Inputs!$B$8)) -> 8546627.1 | AT43: =IF(AS42<=0,0,AT42*AP43/AS42) -> 325751.53 | AU43: =AR43+AQ43*(1-Inputs!$B$6)+AS43-(AS43-AT43)*Inputs!$B$9 -> 41958782 | AV43: =AR43/(AR43+AQ43+AS43) -> 0.80618227 | AW43: =IF(AU43>M43,1,0) -> 1 | AX43: =IF(AP43<0,"SHORT","ok") -> ok | AZ43: 36 | BA43: =BA42+1 -> 93 | BB43: =BB42+1 -> 2061 | BC43: =IF(Inputs!$B$15="B",Inputs!$D$54,Inputs!$C$54) -> 0.38 | BD43: =BH42 -> 0 | BE43: =IF(AZ43<=$BE$4,BD43/($BE$4-AZ43+1),0) -> 0 | BF43: =BE43*BC43 -> 0 | BG43: =BJ42-BF43 -> 7756962.6 | BH43: =(BD43-BE43)*(1+Inputs!$B$4) -> 0 | BI43: =(BI42+BE43)*(1+Inputs!$B$4) -> 35549583 | BJ43: =BG43*(1+Inputs!$B$4*(1-Inputs!$B$8)) -> 8493874 | BK43: =IF(BJ42<=0,0,BK42*BG43/BJ42) -> 323740.87 | BL43: =BI43+BH43*(1-Inputs!$B$6)+BJ43-(BJ43-BK43)*Inputs!$B$9 -> 41919222 | BM43: =BI43/(BI43+BH43+BJ43) -> 0.80714788 | BN43: =IF(BL43>M43,1,0) -> 1 | BO43: =IF(BG43<0,"SHORT","ok") -> ok | BQ43: 36 | BR43: =BR42+1 -> 93 | BS43: =BS42+1 -> 2061 | BT43: =IF(Inputs!$B$15="B",Inputs!$D$54,Inputs!$C$54) -> 0.38 | BU43: =BY42 -> 0 | BV43: =IF(BQ43<=$BV$4,BU43/($BV$4-BQ43+1),0) -> 0 | BW43: =BV43*BT43 -> 0 | BX43: =CA42-BW43 -> 7684146.2 | BY43: =(BU43-BV43)*(1+Inputs!$B$4) -> 0 | BZ43: =(BZ42+BV43)*(1+Inputs!$B$4) -> 35549583 | CA43: =BX43*(1+Inputs!$B$4*(1-Inputs!$B$8)) -> 8414140 | CB43: =IF(CA42<=0,0,CB42*BX43/CA42) -> 320701.84 | CC43: =BZ43+BY43*(1-Inputs!$B$6)+CA43-(CA43-CB43)*Inputs!$B$9 -> 41859429 | CD43: =BZ43/(BZ43+BY43+CA43) -> 0.80861175 | CE43: =IF(CC43>M43,1,0) -> 1 | CF43: =IF(BX43<0,"SHORT","ok") -> ok | CH43: 36 | CI43: =CI42+1 -> 93 | CJ43: =CJ42+1 -> 2061 | CK43: =IF(Inputs!$B$15="B",Inputs!$D$54,Inputs!$C$54) -> 0.38 | CL43: =CP42 -> 0 | CM43: =IF(CH43<=$CM$4,CL43/($CM$4-CH43+1),0) -> 0 | CN43: =CM43*CK43 -> 0 | CO43: =CR42-CN43 -> 7635230.9 | CP43: =(CL43-CM43)*(1+Inputs!$B$4) -> 0 | CQ43: =(CQ42+CM43)*(1+Inputs!$B$4) -> 35549583 | CR43: =CO43*(1+Inputs!$B$4*(1-Inputs!$B$8)) -> 8360577.8 | CS43: =IF(CR42<=0,0,CS42*CO43/CR42) -> 318660.33 | CT43: =CQ43+CP43*(1-Inputs!$B$6)+CR43-(CR43-CS43)*Inputs!$B$9 -> 41819262 | CU43: =CQ43/(CQ43+CP43+CR43) -> 0.8095981 | CV43: =IF(CT43>M43,1,0) -> 1 | CW43: =IF(CO43<0,"SHORT","ok") -> ok
A44: 37 | B44: =B43+1 -> 94 | C44: =C43+1 -> 2062 | D44: =IF(Inputs!$B$15="B",Inputs!$D$55,Inputs!$C$55) -> 0.38 | E44: =I43 -> 35549583 | F44: =IF(A44<=$F$4,E44/($F$4-A44+1),0) -> 0 | G44: =F44*D44 -> 0 | H44: =K43-G44 -> 20064474 | I44: =(E44-F44)*(1+Inputs!$B$4) -> 39104541 | J44: =(J43+F44)*(1+Inputs!$B$4) -> 0 | K44: =H44*(1+Inputs!$B$4*(1-Inputs!$B$8)) -> 21970599 | L44: =IF(K43<=0,0,L43*H44/K43) -> 764750 | M44: =J44+I44*(1-Inputs!$B$6)+K44-(K44-L44)*Inputs!$B$9 -> 43830257 | N44: =J44/(J44+I44+K44) -> 0 | O44: =IF(M44>M44,1,0) -> 0 | P44: =IF(H44<0,"SHORT","ok") -> ok | R44: 37 | S44: =S43+1 -> 94 | T44: =T43+1 -> 2062 | U44: =IF(Inputs!$B$15="B",Inputs!$D$55,Inputs!$C$55) -> 0.38 | V44: =Z43 -> 0 | W44: =IF(R44<=$W$4,V44/($W$4-R44+1),0) -> 0 | X44: =W44*U44 -> 0 | Y44: =AB43-X44 -> 8599060.2 | Z44: =(V44-W44)*(1+Inputs!$B$4) -> 0 | AA44: =(AA43+W44)*(1+Inputs!$B$4) -> 39104541 | AB44: =Y44*(1+Inputs!$B$4*(1-Inputs!$B$8)) -> 9415970.9 | AC44: =IF(AB43<=0,0,AC43*Y44/AB43) -> 327750 | AD44: =AA44+Z44*(1-Inputs!$B$6)+AB44-(AB44-AC44)*Inputs!$B$9 -> 46157574 | AE44: =AA44/(AA44+Z44+AB44) -> 0.80593834 | AF44: =IF(AD44>M44,1,0) -> 1 | AG44: =IF(Y44<0,"SHORT","ok") -> ok | AI44: 37 | AJ44: =AJ43+1 -> 94 | AK44: =AK43+1 -> 2062 | AL44: =IF(Inputs!$B$15="B",Inputs!$D$55,Inputs!$C$55) -> 0.38 | AM44: =AQ43 -> 0 | AN44: =IF(AI44<=$AN$4,AM44/($AN$4-AI44+1),0) -> 0 | AO44: =AN44*AL44 -> 0 | AP44: =AS43-AO44 -> 8546627.1 | AQ44: =(AM44-AN44)*(1+Inputs!$B$4) -> 0 | AR44: =(AR43+AN44)*(1+Inputs!$B$4) -> 39104541 | AS44: =AP44*(1+Inputs!$B$4*(1-Inputs!$B$8)) -> 9358556.6 | AT44: =IF(AS43<=0,0,AT43*AP44/AS43) -> 325751.53 | AU44: =AR44+AQ44*(1-Inputs!$B$6)+AS44-(AS44-AT44)*Inputs!$B$9 -> 46114568 | AV44: =AR44/(AR44+AQ44+AS44) -> 0.80689314 | AW44: =IF(AU44>M44,1,0) -> 1 | AX44: =IF(AP44<0,"SHORT","ok") -> ok | AZ44: 37 | BA44: =BA43+1 -> 94 | BB44: =BB43+1 -> 2062 | BC44: =IF(Inputs!$B$15="B",Inputs!$D$55,Inputs!$C$55) -> 0.38 | BD44: =BH43 -> 0 | BE44: =IF(AZ44<=$BE$4,BD44/($BE$4-AZ44+1),0) -> 0 | BF44: =BE44*BC44 -> 0 | BG44: =BJ43-BF44 -> 8493874 | BH44: =(BD44-BE44)*(1+Inputs!$B$4) -> 0 | BI44: =(BI43+BE44)*(1+Inputs!$B$4) -> 39104541 | BJ44: =BG44*(1+Inputs!$B$4*(1-Inputs!$B$8)) -> 9300792.1 | BK44: =IF(BJ43<=0,0,BK43*BG44/BJ43) -> 323740.87 | BL44: =BI44+BH44*(1-Inputs!$B$6)+BJ44-(BJ44-BK44)*Inputs!$B$9 -> 46071300 | BM44: =BI44/(BI44+BH44+BJ44) -> 0.80785605 | BN44: =IF(BL44>M44,1,0) -> 1 | BO44: =IF(BG44<0,"SHORT","ok") -> ok | BQ44: 37 | BR44: =BR43+1 -> 94 | BS44: =BS43+1 -> 2062 | BT44: =IF(Inputs!$B$15="B",Inputs!$D$55,Inputs!$C$55) -> 0.38 | BU44: =BY43 -> 0 | BV44: =IF(BQ44<=$BV$4,BU44/($BV$4-BQ44+1),0) -> 0 | BW44: =BV44*BT44 -> 0 | BX44: =CA43-BW44 -> 8414140 | BY44: =(BU44-BV44)*(1+Inputs!$B$4) -> 0 | BZ44: =(BZ43+BV44)*(1+Inputs!$B$4) -> 39104541 | CA44: =BX44*(1+Inputs!$B$4*(1-Inputs!$B$8)) -> 9213483.3 | CB44: =IF(CA43<=0,0,CB43*BX44/CA43) -> 320701.84 | CC44: =BZ44+BY44*(1-Inputs!$B$6)+CA44-(CA44-CB44)*Inputs!$B$9 -> 46005901 | CD44: =BZ44/(BZ44+BY44+CA44) -> 0.80931581 | CE44: =IF(CC44>M44,1,0) -> 1 | CF44: =IF(BX44<0,"SHORT","ok") -> ok | CH44: 37 | CI44: =CI43+1 -> 94 | CJ44: =CJ43+1 -> 2062 | CK44: =IF(Inputs!$B$15="B",Inputs!$D$55,Inputs!$C$55) -> 0.38 | CL44: =CP43 -> 0 | CM44: =IF(CH44<=$CM$4,CL44/($CM$4-CH44+1),0) -> 0 | CN44: =CM44*CK44 -> 0 | CO44: =CR43-CN44 -> 8360577.8 | CP44: =(CL44-CM44)*(1+Inputs!$B$4) -> 0 | CQ44: =(CQ43+CM44)*(1+Inputs!$B$4) -> 39104541 | CR44: =CO44*(1+Inputs!$B$4*(1-Inputs!$B$8)) -> 9154832.7 | CS44: =IF(CR43<=0,0,CS43*CO44/CR43) -> 318660.33 | CT44: =CQ44+CP44*(1-Inputs!$B$6)+CR44-(CR44-CS44)*Inputs!$B$9 -> 45961969 | CU44: =CQ44/(CQ44+CP44+CR44) -> 0.81029939 | CV44: =IF(CT44>M44,1,0) -> 1 | CW44: =IF(CO44<0,"SHORT","ok") -> ok
A45: 38 | B45: =B44+1 -> 95 | C45: =C44+1 -> 2063 | D45: =IF(Inputs!$B$15="B",Inputs!$D$56,Inputs!$C$56) -> 0.38 | E45: =I44 -> 39104541 | F45: =IF(A45<=$F$4,E45/($F$4-A45+1),0) -> 0 | G45: =F45*D45 -> 0 | H45: =K44-G45 -> 21970599 | I45: =(E45-F45)*(1+Inputs!$B$4) -> 43014995 | J45: =(J44+F45)*(1+Inputs!$B$4) -> 0 | K45: =H45*(1+Inputs!$B$4*(1-Inputs!$B$8)) -> 24057806 | L45: =IF(K44<=0,0,L44*H45/K44) -> 764750 | M45: =J45+I45*(1-Inputs!$B$6)+K45-(K45-L45)*Inputs!$B$9 -> 48112108 | N45: =J45/(J45+I45+K45) -> 0 | O45: =IF(M45>M45,1,0) -> 0 | P45: =IF(H45<0,"SHORT","ok") -> ok | R45: 38 | S45: =S44+1 -> 95 | T45: =T44+1 -> 2063 | U45: =IF(Inputs!$B$15="B",Inputs!$D$56,Inputs!$C$56) -> 0.38 | V45: =Z44 -> 0 | W45: =IF(R45<=$W$4,V45/($W$4-R45+1),0) -> 0 | X45: =W45*U45 -> 0 | Y45: =AB44-X45 -> 9415970.9 | Z45: =(V45-W45)*(1+Inputs!$B$4) -> 0 | AA45: =(AA44+W45)*(1+Inputs!$B$4) -> 43014995 | AB45: =Y45*(1+Inputs!$B$4*(1-Inputs!$B$8)) -> 10310488 | AC45: =IF(AB44<=0,0,AC44*Y45/AB44) -> 327750 | AD45: =AA45+Z45*(1-Inputs!$B$6)+AB45-(AB45-AC45)*Inputs!$B$9 -> 50729971 | AE45: =AA45/(AA45+Z45+AB45) -> 0.80664989 | AF45: =IF(AD45>M45,1,0) -> 1 | AG45: =IF(Y45<0,"SHORT","ok") -> ok | AI45: 38 | AJ45: =AJ44+1 -> 95 | AK45: =AK44+1 -> 2063 | AL45: =IF(Inputs!$B$15="B",Inputs!$D$56,Inputs!$C$56) -> 0.38 | AM45: =AQ44 -> 0 | AN45: =IF(AI45<=$AN$4,AM45/($AN$4-AI45+1),0) -> 0 | AO45: =AN45*AL45 -> 0 | AP45: =AS44-AO45 -> 9358556.6 | AQ45: =(AM45-AN45)*(1+Inputs!$B$4) -> 0 | AR45: =(AR44+AN45)*(1+Inputs!$B$4) -> 43014995 | AS45: =AP45*(1+Inputs!$B$4*(1-Inputs!$B$8)) -> 10247620 | AT45: =IF(AS44<=0,0,AT44*AP45/AS44) -> 325751.53 | AU45: =AR45+AQ45*(1-Inputs!$B$6)+AS45-(AS45-AT45)*Inputs!$B$9 -> 50682929 | AV45: =AR45/(AR45+AQ45+AS45) -> 0.80760202 | AW45: =IF(AU45>M45,1,0) -> 1 | AX45: =IF(AP45<0,"SHORT","ok") -> ok | AZ45: 38 | BA45: =BA44+1 -> 95 | BB45: =BB44+1 -> 2063 | BC45: =IF(Inputs!$B$15="B",Inputs!$D$56,Inputs!$C$56) -> 0.38 | BD45: =BH44 -> 0 | BE45: =IF(AZ45<=$BE$4,BD45/($BE$4-AZ45+1),0) -> 0 | BF45: =BE45*BC45 -> 0 | BG45: =BJ44-BF45 -> 9300792.1 | BH45: =(BD45-BE45)*(1+Inputs!$B$4) -> 0 | BI45: =(BI44+BE45)*(1+Inputs!$B$4) -> 43014995 | BJ45: =BG45*(1+Inputs!$B$4*(1-Inputs!$B$8)) -> 10184367 | BK45: =IF(BJ44<=0,0,BK44*BG45/BJ44) -> 323740.87 | BL45: =BI45+BH45*(1-Inputs!$B$6)+BJ45-(BJ45-BK45)*Inputs!$B$9 -> 50635599 | BM45: =BI45/(BI45+BH45+BJ45) -> 0.80856223 | BN45: =IF(BL45>M45,1,0) -> 1 | BO45: =IF(BG45<0,"SHORT","ok") -> ok | BQ45: 38 | BR45: =BR44+1 -> 95 | BS45: =BS44+1 -> 2063 | BT45: =IF(Inputs!$B$15="B",Inputs!$D$56,Inputs!$C$56) -> 0.38 | BU45: =BY44 -> 0 | BV45: =IF(BQ45<=$BV$4,BU45/($BV$4-BQ45+1),0) -> 0 | BW45: =BV45*BT45 -> 0 | BX45: =CA44-BW45 -> 9213483.3 | BY45: =(BU45-BV45)*(1+Inputs!$B$4) -> 0 | BZ45: =(BZ44+BV45)*(1+Inputs!$B$4) -> 43014995 | CA45: =BX45*(1+Inputs!$B$4*(1-Inputs!$B$8)) -> 10088764 | CB45: =IF(CA44<=0,0,CB44*BX45/CA44) -> 320701.84 | CC45: =BZ45+BY45*(1-Inputs!$B$6)+CA45-(CA45-CB45)*Inputs!$B$9 -> 50564063 | CD45: =BZ45/(BZ45+BY45+CA45) -> 0.81001789 | CE45: =IF(CC45>M45,1,0) -> 1 | CF45: =IF(BX45<0,"SHORT","ok") -> ok | CH45: 38 | CI45: =CI44+1 -> 95 | CJ45: =CJ44+1 -> 2063 | CK45: =IF(Inputs!$B$15="B",Inputs!$D$56,Inputs!$C$56) -> 0.38 | CL45: =CP44 -> 0 | CM45: =IF(CH45<=$CM$4,CL45/($CM$4-CH45+1),0) -> 0 | CN45: =CM45*CK45 -> 0 | CO45: =CR44-CN45 -> 9154832.7 | CP45: =(CL45-CM45)*(1+Inputs!$B$4) -> 0 | CQ45: =(CQ44+CM45)*(1+Inputs!$B$4) -> 43014995 | CR45: =CO45*(1+Inputs!$B$4*(1-Inputs!$B$8)) -> 10024542 | CS45: =IF(CR44<=0,0,CS44*CO45/CR44) -> 318660.33 | CT45: =CQ45+CP45*(1-Inputs!$B$6)+CR45-(CR45-CS45)*Inputs!$B$9 -> 50516008 | CU45: =CQ45/(CQ45+CP45+CR45) -> 0.81099869 | CV45: =IF(CT45>M45,1,0) -> 1 | CW45: =IF(CO45<0,"SHORT","ok") -> ok
A46: 39 | B46: =B45+1 -> 96 | C46: =C45+1 -> 2064 | D46: =IF(Inputs!$B$15="B",Inputs!$D$57,Inputs!$C$57) -> 0.38 | E46: =I45 -> 43014995 | F46: =IF(A46<=$F$4,E46/($F$4-A46+1),0) -> 0 | G46: =F46*D46 -> 0 | H46: =K45-G46 -> 24057806 | I46: =(E46-F46)*(1+Inputs!$B$4) -> 47316494 | J46: =(J45+F46)*(1+Inputs!$B$4) -> 0 | K46: =H46*(1+Inputs!$B$4*(1-Inputs!$B$8)) -> 26343297 | L46: =IF(K45<=0,0,L45*H46/K45) -> 764750 | M46: =J46+I46*(1-Inputs!$B$6)+K46-(K46-L46)*Inputs!$B$9 -> 52814421 | N46: =J46/(J46+I46+K46) -> 0 | O46: =IF(M46>M46,1,0) -> 0 | P46: =IF(H46<0,"SHORT","ok") -> ok | R46: 39 | S46: =S45+1 -> 96 | T46: =T45+1 -> 2064 | U46: =IF(Inputs!$B$15="B",Inputs!$D$57,Inputs!$C$57) -> 0.38 | V46: =Z45 -> 0 | W46: =IF(R46<=$W$4,V46/($W$4-R46+1),0) -> 0 | X46: =W46*U46 -> 0 | Y46: =AB45-X46 -> 10310488 | Z46: =(V46-W46)*(1+Inputs!$B$4) -> 0 | AA46: =(AA45+W46)*(1+Inputs!$B$4) -> 47316494 | AB46: =Y46*(1+Inputs!$B$4*(1-Inputs!$B$8)) -> 11289985 | AC46: =IF(AB45<=0,0,AC45*Y46/AB45) -> 327750 | AD46: =AA46+Z46*(1-Inputs!$B$6)+AB46-(AB46-AC46)*Inputs!$B$9 -> 55756298 | AE46: =AA46/(AA46+Z46+AB46) -> 0.80735945 | AF46: =IF(AD46>M46,1,0) -> 1 | AG46: =IF(Y46<0,"SHORT","ok") -> ok | AI46: 39 | AJ46: =AJ45+1 -> 96 | AK46: =AK45+1 -> 2064 | AL46: =IF(Inputs!$B$15="B",Inputs!$D$57,Inputs!$C$57) -> 0.38 | AM46: =AQ45 -> 0 | AN46: =IF(AI46<=$AN$4,AM46/($AN$4-AI46+1),0) -> 0 | AO46: =AN46*AL46 -> 0 | AP46: =AS45-AO46 -> 10247620 | AQ46: =(AM46-AN46)*(1+Inputs!$B$4) -> 0 | AR46: =(AR45+AN46)*(1+Inputs!$B$4) -> 47316494 | AS46: =AP46*(1+Inputs!$B$4*(1-Inputs!$B$8)) -> 11221143 | AT46: =IF(AS45<=0,0,AT45*AP46/AS45) -> 325751.53 | AU46: =AR46+AQ46*(1-Inputs!$B$6)+AS46-(AS46-AT46)*Inputs!$B$9 -> 55704836 | AV46: =AR46/(AR46+AQ46+AS46) -> 0.80830891 | AW46: =IF(AU46>M46,1,0) -> 1 | AX46: =IF(AP46<0,"SHORT","ok") -> ok | AZ46: 39 | BA46: =BA45+1 -> 96 | BB46: =BB45+1 -> 2064 | BC46: =IF(Inputs!$B$15="B",Inputs!$D$57,Inputs!$C$57) -> 0.38 | BD46: =BH45 -> 0 | BE46: =IF(AZ46<=$BE$4,BD46/($BE$4-AZ46+1),0) -> 0 | BF46: =BE46*BC46 -> 0 | BG46: =BJ45-BF46 -> 10184367 | BH46: =(BD46-BE46)*(1+Inputs!$B$4) -> 0 | BI46: =(BI45+BE46)*(1+Inputs!$B$4) -> 47316494 | BJ46: =BG46*(1+Inputs!$B$4*(1-Inputs!$B$8)) -> 11151882 | BK46: =IF(BJ45<=0,0,BK45*BG46/BJ45) -> 323740.87 | BL46: =BI46+BH46*(1-Inputs!$B$6)+BJ46-(BJ46-BK46)*Inputs!$B$9 -> 55653060 | BM46: =BI46/(BI46+BH46+BJ46) -> 0.80926643 | BN46: =IF(BL46>M46,1,0) -> 1 | BO46: =IF(BG46<0,"SHORT","ok") -> ok | BQ46: 39 | BR46: =BR45+1 -> 96 | BS46: =BS45+1 -> 2064 | BT46: =IF(Inputs!$B$15="B",Inputs!$D$57,Inputs!$C$57) -> 0.38 | BU46: =BY45 -> 0 | BV46: =IF(BQ46<=$BV$4,BU46/($BV$4-BQ46+1),0) -> 0 | BW46: =BV46*BT46 -> 0 | BX46: =CA45-BW46 -> 10088764 | BY46: =(BU46-BV46)*(1+Inputs!$B$4) -> 0 | BZ46: =(BZ45+BV46)*(1+Inputs!$B$4) -> 47316494 | CA46: =BX46*(1+Inputs!$B$4*(1-Inputs!$B$8)) -> 11047197 | CB46: =IF(CA45<=0,0,CB45*BX46/CA45) -> 320701.84 | CC46: =BZ46+BY46*(1-Inputs!$B$6)+CA46-(CA46-CB46)*Inputs!$B$9 -> 55574803 | CD46: =BZ46/(BZ46+BY46+CA46) -> 0.81071799 | CE46: =IF(CC46>M46,1,0) -> 1 | CF46: =IF(BX46<0,"SHORT","ok") -> ok | CH46: 39 | CI46: =CI45+1 -> 96 | CJ46: =CJ45+1 -> 2064 | CK46: =IF(Inputs!$B$15="B",Inputs!$D$57,Inputs!$C$57) -> 0.38 | CL46: =CP45 -> 0 | CM46: =IF(CH46<=$CM$4,CL46/($CM$4-CH46+1),0) -> 0 | CN46: =CM46*CK46 -> 0 | CO46: =CR45-CN46 -> 10024542 | CP46: =(CL46-CM46)*(1+Inputs!$B$4) -> 0 | CQ46: =(CQ45+CM46)*(1+Inputs!$B$4) -> 47316494 | CR46: =CO46*(1+Inputs!$B$4*(1-Inputs!$B$8)) -> 10976873 | CS46: =IF(CR45<=0,0,CS45*CO46/CR45) -> 318660.33 | CT46: =CQ46+CP46*(1-Inputs!$B$6)+CR46-(CR46-CS46)*Inputs!$B$9 -> 55522232 | CU46: =CQ46/(CQ46+CP46+CR46) -> 0.81169602 | CV46: =IF(CT46>M46,1,0) -> 1 | CW46: =IF(CO46<0,"SHORT","ok") -> ok
A47: 40 | B47: =B46+1 -> 97 | C47: =C46+1 -> 2065 | D47: =IF(Inputs!$B$15="B",Inputs!$D$58,Inputs!$C$58) -> 0.38 | E47: =I46 -> 47316494 | F47: =IF(A47<=$F$4,E47/($F$4-A47+1),0) -> 0 | G47: =F47*D47 -> 0 | H47: =K46-G47 -> 26343297 | I47: =(E47-F47)*(1+Inputs!$B$4) -> 52048144 | J47: =(J46+F47)*(1+Inputs!$B$4) -> 0 | K47: =H47*(1+Inputs!$B$4*(1-Inputs!$B$8)) -> 28845911 | L47: =IF(K46<=0,0,L46*H47/K46) -> 764750 | M47: =J47+I47*(1-Inputs!$B$6)+K47-(K47-L47)*Inputs!$B$9 -> 57978510 | N47: =J47/(J47+I47+K47) -> 0 | O47: =IF(M47>M47,1,0) -> 0 | P47: =IF(H47<0,"SHORT","ok") -> ok | R47: 40 | S47: =S46+1 -> 97 | T47: =T46+1 -> 2065 | U47: =IF(Inputs!$B$15="B",Inputs!$D$58,Inputs!$C$58) -> 0.38 | V47: =Z46 -> 0 | W47: =IF(R47<=$W$4,V47/($W$4-R47+1),0) -> 0 | X47: =W47*U47 -> 0 | Y47: =AB46-X47 -> 11289985 | Z47: =(V47-W47)*(1+Inputs!$B$4) -> 0 | AA47: =(AA46+W47)*(1+Inputs!$B$4) -> 52048144 | AB47: =Y47*(1+Inputs!$B$4*(1-Inputs!$B$8)) -> 12362533 | AC47: =IF(AB46<=0,0,AC46*Y47/AB46) -> 327750 | AD47: =AA47+Z47*(1-Inputs!$B$6)+AB47-(AB47-AC47)*Inputs!$B$9 -> 61281633 | AE47: =AA47/(AA47+Z47+AB47) -> 0.80806702 | AF47: =IF(AD47>M47,1,0) -> 1 | AG47: =IF(Y47<0,"SHORT","ok") -> ok | AI47: 40 | AJ47: =AJ46+1 -> 97 | AK47: =AK46+1 -> 2065 | AL47: =IF(Inputs!$B$15="B",Inputs!$D$58,Inputs!$C$58) -> 0.38 | AM47: =AQ46 -> 0 | AN47: =IF(AI47<=$AN$4,AM47/($AN$4-AI47+1),0) -> 0 | AO47: =AN47*AL47 -> 0 | AP47: =AS46-AO47 -> 11221143 | AQ47: =(AM47-AN47)*(1+Inputs!$B$4) -> 0 | AR47: =(AR46+AN47)*(1+Inputs!$B$4) -> 52048144 | AS47: =AP47*(1+Inputs!$B$4*(1-Inputs!$B$8)) -> 12287152 | AT47: =IF(AS46<=0,0,AT46*AP47/AS46) -> 325751.53 | AU47: =AR47+AQ47*(1-Inputs!$B$6)+AS47-(AS47-AT47)*Inputs!$B$9 -> 61225332 | AV47: =AR47/(AR47+AQ47+AS47) -> 0.80901383 | AW47: =IF(AU47>M47,1,0) -> 1 | AX47: =IF(AP47<0,"SHORT","ok") -> ok | AZ47: 40 | BA47: =BA46+1 -> 97 | BB47: =BB46+1 -> 2065 | BC47: =IF(Inputs!$B$15="B",Inputs!$D$58,Inputs!$C$58) -> 0.38 | BD47: =BH46 -> 0 | BE47: =IF(AZ47<=$BE$4,BD47/($BE$4-AZ47+1),0) -> 0 | BF47: =BE47*BC47 -> 0 | BG47: =BJ46-BF47 -> 11151882 | BH47: =(BD47-BE47)*(1+Inputs!$B$4) -> 0 | BI47: =(BI46+BE47)*(1+Inputs!$B$4) -> 52048144 | BJ47: =BG47*(1+Inputs!$B$4*(1-Inputs!$B$8)) -> 12211311 | BK47: =IF(BJ46<=0,0,BK46*BG47/BJ46) -> 323740.87 | BL47: =BI47+BH47*(1-Inputs!$B$6)+BJ47-(BJ47-BK47)*Inputs!$B$9 -> 61168687 | BM47: =BI47/(BI47+BH47+BJ47) -> 0.80996865 | BN47: =IF(BL47>M47,1,0) -> 1 | BO47: =IF(BG47<0,"SHORT","ok") -> ok | BQ47: 40 | BR47: =BR46+1 -> 97 | BS47: =BS46+1 -> 2065 | BT47: =IF(Inputs!$B$15="B",Inputs!$D$58,Inputs!$C$58) -> 0.38 | BU47: =BY46 -> 0 | BV47: =IF(BQ47<=$BV$4,BU47/($BV$4-BQ47+1),0) -> 0 | BW47: =BV47*BT47 -> 0 | BX47: =CA46-BW47 -> 11047197 | BY47: =(BU47-BV47)*(1+Inputs!$B$4) -> 0 | BZ47: =(BZ46+BV47)*(1+Inputs!$B$4) -> 52048144 | CA47: =BX47*(1+Inputs!$B$4*(1-Inputs!$B$8)) -> 12096681 | CB47: =IF(CA46<=0,0,CB46*BX47/CA46) -> 320701.84 | CC47: =BZ47+BY47*(1-Inputs!$B$6)+CA47-(CA47-CB47)*Inputs!$B$9 -> 61083070 | CD47: =BZ47/(BZ47+BY47+CA47) -> 0.81141611 | CE47: =IF(CC47>M47,1,0) -> 1 | CF47: =IF(BX47<0,"SHORT","ok") -> ok | CH47: 40 | CI47: =CI46+1 -> 97 | CJ47: =CJ46+1 -> 2065 | CK47: =IF(Inputs!$B$15="B",Inputs!$D$58,Inputs!$C$58) -> 0.38 | CL47: =CP46 -> 0 | CM47: =IF(CH47<=$CM$4,CL47/($CM$4-CH47+1),0) -> 0 | CN47: =CM47*CK47 -> 0 | CO47: =CR46-CN47 -> 10976873 | CP47: =(CL47-CM47)*(1+Inputs!$B$4) -> 0 | CQ47: =(CQ46+CM47)*(1+Inputs!$B$4) -> 52048144 | CR47: =CO47*(1+Inputs!$B$4*(1-Inputs!$B$8)) -> 12019676 | CS47: =IF(CR46<=0,0,CS46*CO47/CR46) -> 318660.33 | CT47: =CQ47+CP47*(1-Inputs!$B$6)+CR47-(CR47-CS47)*Inputs!$B$9 -> 61025556 | CU47: =CQ47/(CQ47+CP47+CR47) -> 0.81239137 | CV47: =IF(CT47>M47,1,0) -> 1 | CW47: =IF(CO47<0,"SHORT","ok") -> ok
E49: Total converted | F49: =SUM(F8:F47) -> 0 | G49: =SUM(G8:G47) -> 0 | H49: <- total tax | V49: Total converted | W49: =SUM(W8:W47) -> 1150000 | X49: =SUM(X8:X47) -> 437000 | Y49: <- total tax | AM49: Total converted | AN49: =SUM(AN8:AN47) -> 1268833.3 | AO49: =SUM(AO8:AO47) -> 482156.67 | AP49: <- total tax | BD49: Total converted | BE49: =SUM(BE8:BE47) -> 1404173 | BF49: =SUM(BF8:BF47) -> 533585.74 | BG49: <- total tax | BU49: Total converted | BV49: =SUM(BV8:BV47) -> 1643908.9 | BW49: =SUM(BW8:BW47) -> 624685.39 | BX49: <- total tax | CL49: Total converted | CM49: =SUM(CM8:CM47) -> 1832803.8 | CN49: =SUM(CN8:CN47) -> 696465.46 | CO49: <- total tax
E50: Average rate | F50: =IF(F49=0,0,G49/F49) -> 0 | V50: Average rate | W50: =IF(W49=0,0,X49/W49) -> 0.38 | AM50: Average rate | AN50: =IF(AN49=0,0,AO49/AN49) -> 0.38 | BD50: Average rate | BE50: =IF(BE49=0,0,BF49/BE49) -> 0.38 | BU50: Average rate | BV50: =IF(BV49=0,0,BW49/BV49) -> 0.38 | CL50: Average rate | CM50: =IF(CM49=0,0,CN49/CM49) -> 0.38
E51: First year ahead | F51: =IFERROR(INDEX(A8:A47,MATCH(1,O8:O47,0)),"never") -> never | V51: First year ahead | W51: =IFERROR(INDEX(R8:R47,MATCH(1,AF8:AF47,0)),"never") -> 12 | AM51: First year ahead | AN51: =IFERROR(INDEX(AI8:AI47,MATCH(1,AW8:AW47,0)),"never") -> 12 | BD51: First year ahead | BE51: =IFERROR(INDEX(AZ8:AZ47,MATCH(1,BN8:BN47,0)),"never") -> 13 | BU51: First year ahead | BV51: =IFERROR(INDEX(BQ8:BQ47,MATCH(1,CE8:CE47,0)),"never") -> 13 | CL51: First year ahead | CM51: =IFERROR(INDEX(CH8:CH47,MATCH(1,CV8:CV47,0)),"never") -> 13
E52: Pool short years | F52: =COUNTIF(P8:P47,"SHORT") -> 0 | V52: Pool short years | W52: =COUNTIF(AG8:AG47,"SHORT") -> 0 | AM52: Pool short years | AN52: =COUNTIF(AX8:AX47,"SHORT") -> 0 | BD52: Pool short years | BE52: =COUNTIF(BO8:BO47,"SHORT") -> 0 | BU52: Pool short years | BV52: =COUNTIF(CF8:CF47,"SHORT") -> 0 | CL52: Pool short years | CM52: =COUNTIF(CW8:CW47,"SHORT") -> 0

Sheet Sensitivity
A1: Sensitivity: lump-sum conversion advantage over never converting, at the Compare horizon
A2: Closed form, so it responds instantly. Rows: tax rate on future withdrawals. Columns: annual return. Everything else from Inputs (rate now, drag, liquidation tax, horizon, IRA). Positive = converting wins.
A4: Later rate \ Return | B4: 0.05 | C4: 0.06 | D4: 0.07 | E4: 0.08 | F4: 0.1 | G4: 0.12
A5: 0.2 | B5: =Inputs!$B$3*(1+B$4)^Inputs!$B$10-(Inputs!$B$3*(1+B$4)^Inputs!$B$10*(1-$A5)+Inputs!$B$3*Inputs!$B$5*(1+B$4*(1-Inputs!$B$8))^Inputs!$B$10-(Inputs!$B$3*Inputs!$B$5*(1+B$4*(1-Inputs!$B$8))^Inputs!$B$10-Inputs!$B$3*Inputs!$B$5)*Inputs!$B$9) -> -253317.99 | C5: =Inputs!$B$3*(1+C$4)^Inputs!$B$10-(Inputs!$B$3*(1+C$4)^Inputs!$B$10*(1-$A5)+Inputs!$B$3*Inputs!$B$5*(1+C$4*(1-Inputs!$B$8))^Inputs!$B$10-(Inputs!$B$3*Inputs!$B$5*(1+C$4*(1-Inputs!$B$8))^Inputs!$B$10-Inputs!$B$3*Inputs!$B$5)*Inputs!$B$9) -> -264666.22 | D5: =Inputs!$B$3*(1+D$4)^Inputs!$B$10-(Inputs!$B$3*(1+D$4)^Inputs!$B$10*(1-$A5)+Inputs!$B$3*Inputs!$B$5*(1+D$4*(1-Inputs!$B$8))^Inputs!$B$10-(Inputs!$B$3*Inputs!$B$5*(1+D$4*(1-Inputs!$B$8))^Inputs!$B$10-Inputs!$B$3*Inputs!$B$5)*Inputs!$B$9) -> -276807.99 | E5: =Inputs!$B$3*(1+E$4)^Inputs!$B$10-(Inputs!$B$3*(1+E$4)^Inputs!$B$10*(1-$A5)+Inputs!$B$3*Inputs!$B$5*(1+E$4*(1-Inputs!$B$8))^Inputs!$B$10-(Inputs!$B$3*Inputs!$B$5*(1+E$4*(1-Inputs!$B$8))^Inputs!$B$10-Inputs!$B$3*Inputs!$B$5)*Inputs!$B$9) -> -289789.62 | F5: =Inputs!$B$3*(1+F$4)^Inputs!$B$10-(Inputs!$B$3*(1+F$4)^Inputs!$B$10*(1-$A5)+Inputs!$B$3*Inputs!$B$5*(1+F$4*(1-Inputs!$B$8))^Inputs!$B$10-(Inputs!$B$3*Inputs!$B$5*(1+F$4*(1-Inputs!$B$8))^Inputs!$B$10-Inputs!$B$3*Inputs!$B$5)*Inputs!$B$9) -> -318468.48 | G5: =Inputs!$B$3*(1+G$4)^Inputs!$B$10-(Inputs!$B$3*(1+G$4)^Inputs!$B$10*(1-$A5)+Inputs!$B$3*Inputs!$B$5*(1+G$4*(1-Inputs!$B$8))^Inputs!$B$10-(Inputs!$B$3*Inputs!$B$5*(1+G$4*(1-Inputs!$B$8))^Inputs!$B$10-Inputs!$B$3*Inputs!$B$5)*Inputs!$B$9) -> -351117.35
A6: 0.25 | B6: =Inputs!$B$3*(1+B$4)^Inputs!$B$10-(Inputs!$B$3*(1+B$4)^Inputs!$B$10*(1-$A6)+Inputs!$B$3*Inputs!$B$5*(1+B$4*(1-Inputs!$B$8))^Inputs!$B$10-(Inputs!$B$3*Inputs!$B$5*(1+B$4*(1-Inputs!$B$8))^Inputs!$B$10-Inputs!$B$3*Inputs!$B$5)*Inputs!$B$9) -> -159656.55 | C6: =Inputs!$B$3*(1+C$4)^Inputs!$B$10-(Inputs!$B$3*(1+C$4)^Inputs!$B$10*(1-$A6)+Inputs!$B$3*Inputs!$B$5*(1+C$4*(1-Inputs!$B$8))^Inputs!$B$10-(Inputs!$B$3*Inputs!$B$5*(1+C$4*(1-Inputs!$B$8))^Inputs!$B$10-Inputs!$B$3*Inputs!$B$5)*Inputs!$B$9) -> -161692.48 | D6: =Inputs!$B$3*(1+D$4)^Inputs!$B$10-(Inputs!$B$3*(1+D$4)^Inputs!$B$10*(1-$A6)+Inputs!$B$3*Inputs!$B$5*(1+D$4*(1-Inputs!$B$8))^Inputs!$B$10-(Inputs!$B$3*Inputs!$B$5*(1+D$4*(1-Inputs!$B$8))^Inputs!$B$10-Inputs!$B$3*Inputs!$B$5)*Inputs!$B$9) -> -163696.79 | E6: =Inputs!$B$3*(1+E$4)^Inputs!$B$10-(Inputs!$B$3*(1+E$4)^Inputs!$B$10*(1-$A6)+Inputs!$B$3*Inputs!$B$5*(1+E$4*(1-Inputs!$B$8))^Inputs!$B$10-(Inputs!$B$3*Inputs!$B$5*(1+E$4*(1-Inputs!$B$8))^Inputs!$B$10-Inputs!$B$3*Inputs!$B$5)*Inputs!$B$9) -> -165651.43 | F6: =Inputs!$B$3*(1+F$4)^Inputs!$B$10-(Inputs!$B$3*(1+F$4)^Inputs!$B$10*(1-$A6)+Inputs!$B$3*Inputs!$B$5*(1+F$4*(1-Inputs!$B$8))^Inputs!$B$10-(Inputs!$B$3*Inputs!$B$5*(1+F$4*(1-Inputs!$B$8))^Inputs!$B$10-Inputs!$B$3*Inputs!$B$5)*Inputs!$B$9) -> -169328.29 | G6: =Inputs!$B$3*(1+G$4)^Inputs!$B$10-(Inputs!$B$3*(1+G$4)^Inputs!$B$10*(1-$A6)+Inputs!$B$3*Inputs!$B$5*(1+G$4*(1-Inputs!$B$8))^Inputs!$B$10-(Inputs!$B$3*Inputs!$B$5*(1+G$4*(1-Inputs!$B$8))^Inputs!$B$10-Inputs!$B$3*Inputs!$B$5)*Inputs!$B$9) -> -172531.08
A7: 0.3 | B7: =Inputs!$B$3*(1+B$4)^Inputs!$B$10-(Inputs!$B$3*(1+B$4)^Inputs!$B$10*(1-$A7)+Inputs!$B$3*Inputs!$B$5*(1+B$4*(1-Inputs!$B$8))^Inputs!$B$10-(Inputs!$B$3*Inputs!$B$5*(1+B$4*(1-Inputs!$B$8))^Inputs!$B$10-Inputs!$B$3*Inputs!$B$5)*Inputs!$B$9) -> -65995.111 | C7: =Inputs!$B$3*(1+C$4)^Inputs!$B$10-(Inputs!$B$3*(1+C$4)^Inputs!$B$10*(1-$A7)+Inputs!$B$3*Inputs!$B$5*(1+C$4*(1-Inputs!$B$8))^Inputs!$B$10-(Inputs!$B$3*Inputs!$B$5*(1+C$4*(1-Inputs!$B$8))^Inputs!$B$10-Inputs!$B$3*Inputs!$B$5)*Inputs!$B$9) -> -58718.739 | D7: =Inputs!$B$3*(1+D$4)^Inputs!$B$10-(Inputs!$B$3*(1+D$4)^Inputs!$B$10*(1-$A7)+Inputs!$B$3*Inputs!$B$5*(1+D$4*(1-Inputs!$B$8))^Inputs!$B$10-(Inputs!$B$3*Inputs!$B$5*(1+D$4*(1-Inputs!$B$8))^Inputs!$B$10-Inputs!$B$3*Inputs!$B$5)*Inputs!$B$9) -> -50585.588 | E7: =Inputs!$B$3*(1+E$4)^Inputs!$B$10-(Inputs!$B$3*(1+E$4)^Inputs!$B$10*(1-$A7)+Inputs!$B$3*Inputs!$B$5*(1+E$4*(1-Inputs!$B$8))^Inputs!$B$10-(Inputs!$B$3*Inputs!$B$5*(1+E$4*(1-Inputs!$B$8))^Inputs!$B$10-Inputs!$B$3*Inputs!$B$5)*Inputs!$B$9) -> -41513.247 | F7: =Inputs!$B$3*(1+F$4)^Inputs!$B$10-(Inputs!$B$3*(1+F$4)^Inputs!$B$10*(1-$A7)+Inputs!$B$3*Inputs!$B$5*(1+F$4*(1-Inputs!$B$8))^Inputs!$B$10-(Inputs!$B$3*Inputs!$B$5*(1+F$4*(1-Inputs!$B$8))^Inputs!$B$10-Inputs!$B$3*Inputs!$B$5)*Inputs!$B$9) -> -20188.097 | G7: =Inputs!$B$3*(1+G$4)^Inputs!$B$10-(Inputs!$B$3*(1+G$4)^Inputs!$B$10*(1-$A7)+Inputs!$B$3*Inputs!$B$5*(1+G$4*(1-Inputs!$B$8))^Inputs!$B$10-(Inputs!$B$3*Inputs!$B$5*(1+G$4*(1-Inputs!$B$8))^Inputs!$B$10-Inputs!$B$3*Inputs!$B$5)*Inputs!$B$9) -> 6055.1914
A8: 0.35 | B8: =Inputs!$B$3*(1+B$4)^Inputs!$B$10-(Inputs!$B$3*(1+B$4)^Inputs!$B$10*(1-$A8)+Inputs!$B$3*Inputs!$B$5*(1+B$4*(1-Inputs!$B$8))^Inputs!$B$10-(Inputs!$B$3*Inputs!$B$5*(1+B$4*(1-Inputs!$B$8))^Inputs!$B$10-Inputs!$B$3*Inputs!$B$5)*Inputs!$B$9) -> 27666.33 | C8: =Inputs!$B$3*(1+C$4)^Inputs!$B$10-(Inputs!$B$3*(1+C$4)^Inputs!$B$10*(1-$A8)+Inputs!$B$3*Inputs!$B$5*(1+C$4*(1-Inputs!$B$8))^Inputs!$B$10-(Inputs!$B$3*Inputs!$B$5*(1+C$4*(1-Inputs!$B$8))^Inputs!$B$10-Inputs!$B$3*Inputs!$B$5)*Inputs!$B$9) -> 44255.004 | D8: =Inputs!$B$3*(1+D$4)^Inputs!$B$10-(Inputs!$B$3*(1+D$4)^Inputs!$B$10*(1-$A8)+Inputs!$B$3*Inputs!$B$5*(1+D$4*(1-Inputs!$B$8))^Inputs!$B$10-(Inputs!$B$3*Inputs!$B$5*(1+D$4*(1-Inputs!$B$8))^Inputs!$B$10-Inputs!$B$3*Inputs!$B$5)*Inputs!$B$9) -> 62525.615 | E8: =Inputs!$B$3*(1+E$4)^Inputs!$B$10-(Inputs!$B$3*(1+E$4)^Inputs!$B$10*(1-$A8)+Inputs!$B$3*Inputs!$B$5*(1+E$4*(1-Inputs!$B$8))^Inputs!$B$10-(Inputs!$B$3*Inputs!$B$5*(1+E$4*(1-Inputs!$B$8))^Inputs!$B$10-Inputs!$B$3*Inputs!$B$5)*Inputs!$B$9) -> 82624.941 | F8: =Inputs!$B$3*(1+F$4)^Inputs!$B$10-(Inputs!$B$3*(1+F$4)^Inputs!$B$10*(1-$A8)+Inputs!$B$3*Inputs!$B$5*(1+F$4*(1-Inputs!$B$8))^Inputs!$B$10-(Inputs!$B$3*Inputs!$B$5*(1+F$4*(1-Inputs!$B$8))^Inputs!$B$10-Inputs!$B$3*Inputs!$B$5)*Inputs!$B$9) -> 128952.09 | G8: =Inputs!$B$3*(1+G$4)^Inputs!$B$10-(Inputs!$B$3*(1+G$4)^Inputs!$B$10*(1-$A8)+Inputs!$B$3*Inputs!$B$5*(1+G$4*(1-Inputs!$B$8))^Inputs!$B$10-(Inputs!$B$3*Inputs!$B$5*(1+G$4*(1-Inputs!$B$8))^Inputs!$B$10-Inputs!$B$3*Inputs!$B$5)*Inputs!$B$9) -> 184641.46
A9: 0.4 | B9: =Inputs!$B$3*(1+B$4)^Inputs!$B$10-(Inputs!$B$3*(1+B$4)^Inputs!$B$10*(1-$A9)+Inputs!$B$3*Inputs!$B$5*(1+B$4*(1-Inputs!$B$8))^Inputs!$B$10-(Inputs!$B$3*Inputs!$B$5*(1+B$4*(1-Inputs!$B$8))^Inputs!$B$10-Inputs!$B$3*Inputs!$B$5)*Inputs!$B$9) -> 121327.77 | C9: =Inputs!$B$3*(1+C$4)^Inputs!$B$10-(Inputs!$B$3*(1+C$4)^Inputs!$B$10*(1-$A9)+Inputs!$B$3*Inputs!$B$5*(1+C$4*(1-Inputs!$B$8))^Inputs!$B$10-(Inputs!$B$3*Inputs!$B$5*(1+C$4*(1-Inputs!$B$8))^Inputs!$B$10-Inputs!$B$3*Inputs!$B$5)*Inputs!$B$9) -> 147228.75 | D9: =Inputs!$B$3*(1+D$4)^Inputs!$B$10-(Inputs!$B$3*(1+D$4)^Inputs!$B$10*(1-$A9)+Inputs!$B$3*Inputs!$B$5*(1+D$4*(1-Inputs!$B$8))^Inputs!$B$10-(Inputs!$B$3*Inputs!$B$5*(1+D$4*(1-Inputs!$B$8))^Inputs!$B$10-Inputs!$B$3*Inputs!$B$5)*Inputs!$B$9) -> 175636.82 | E9: =Inputs!$B$3*(1+E$4)^Inputs!$B$10-(Inputs!$B$3*(1+E$4)^Inputs!$B$10*(1-$A9)+Inputs!$B$3*Inputs!$B$5*(1+E$4*(1-Inputs!$B$8))^Inputs!$B$10-(Inputs!$B$3*Inputs!$B$5*(1+E$4*(1-Inputs!$B$8))^Inputs!$B$10-Inputs!$B$3*Inputs!$B$5)*Inputs!$B$9) -> 206763.13 | F9: =Inputs!$B$3*(1+F$4)^Inputs!$B$10-(Inputs!$B$3*(1+F$4)^Inputs!$B$10*(1-$A9)+Inputs!$B$3*Inputs!$B$5*(1+F$4*(1-Inputs!$B$8))^Inputs!$B$10-(Inputs!$B$3*Inputs!$B$5*(1+F$4*(1-Inputs!$B$8))^Inputs!$B$10-Inputs!$B$3*Inputs!$B$5)*Inputs!$B$9) -> 278092.29 | G9: =Inputs!$B$3*(1+G$4)^Inputs!$B$10-(Inputs!$B$3*(1+G$4)^Inputs!$B$10*(1-$A9)+Inputs!$B$3*Inputs!$B$5*(1+G$4*(1-Inputs!$B$8))^Inputs!$B$10-(Inputs!$B$3*Inputs!$B$5*(1+G$4*(1-Inputs!$B$8))^Inputs!$B$10-Inputs!$B$3*Inputs!$B$5)*Inputs!$B$9) -> 363227.74
A10: 0.45 | B10: =Inputs!$B$3*(1+B$4)^Inputs!$B$10-(Inputs!$B$3*(1+B$4)^Inputs!$B$10*(1-$A10)+Inputs!$B$3*Inputs!$B$5*(1+B$4*(1-Inputs!$B$8))^Inputs!$B$10-(Inputs!$B$3*Inputs!$B$5*(1+B$4*(1-Inputs!$B$8))^Inputs!$B$10-Inputs!$B$3*Inputs!$B$5)*Inputs!$B$9) -> 214989.21 | C10: =Inputs!$B$3*(1+C$4)^Inputs!$B$10-(Inputs!$B$3*(1+C$4)^Inputs!$B$10*(1-$A10)+Inputs!$B$3*Inputs!$B$5*(1+C$4*(1-Inputs!$B$8))^Inputs!$B$10-(Inputs!$B$3*Inputs!$B$5*(1+C$4*(1-Inputs!$B$8))^Inputs!$B$10-Inputs!$B$3*Inputs!$B$5)*Inputs!$B$9) -> 250202.49 | D10: =Inputs!$B$3*(1+D$4)^Inputs!$B$10-(Inputs!$B$3*(1+D$4)^Inputs!$B$10*(1-$A10)+Inputs!$B$3*Inputs!$B$5*(1+D$4*(1-Inputs!$B$8))^Inputs!$B$10-(Inputs!$B$3*Inputs!$B$5*(1+D$4*(1-Inputs!$B$8))^Inputs!$B$10-Inputs!$B$3*Inputs!$B$5)*Inputs!$B$9) -> 288748.02 | E10: =Inputs!$B$3*(1+E$4)^Inputs!$B$10-(Inputs!$B$3*(1+E$4)^Inputs!$B$10*(1-$A10)+Inputs!$B$3*Inputs!$B$5*(1+E$4*(1-Inputs!$B$8))^Inputs!$B$10-(Inputs!$B$3*Inputs!$B$5*(1+E$4*(1-Inputs!$B$8))^Inputs!$B$10-Inputs!$B$3*Inputs!$B$5)*Inputs!$B$9) -> 330901.32 | F10: =Inputs!$B$3*(1+F$4)^Inputs!$B$10-(Inputs!$B$3*(1+F$4)^Inputs!$B$10*(1-$A10)+Inputs!$B$3*Inputs!$B$5*(1+F$4*(1-Inputs!$B$8))^Inputs!$B$10-(Inputs!$B$3*Inputs!$B$5*(1+F$4*(1-Inputs!$B$8))^Inputs!$B$10-Inputs!$B$3*Inputs!$B$5)*Inputs!$B$9) -> 427232.48 | G10: =Inputs!$B$3*(1+G$4)^Inputs!$B$10-(Inputs!$B$3*(1+G$4)^Inputs!$B$10*(1-$A10)+Inputs!$B$3*Inputs!$B$5*(1+G$4*(1-Inputs!$B$8))^Inputs!$B$10-(Inputs!$B$3*Inputs!$B$5*(1+G$4*(1-Inputs!$B$8))^Inputs!$B$10-Inputs!$B$3*Inputs!$B$5)*Inputs!$B$9) -> 541814.01
A13: Break-even future tax rate by horizon and rate paid now
A14: Convert if your future rate is ABOVE the number. Return, drag and liquidation tax from Inputs.
A16: Rate now \ Horizon | B16: 5 | C16: 10 | D16: 15 | E16: 20 | F16: 25 | G16: 30
A17: 0.25 | B17: =($A17*(1+Inputs!$B$4*(1-Inputs!$B$8))^B$16*(1-Inputs!$B$9)+$A17*Inputs!$B$9)/(1+Inputs!$B$4)^B$16 -> 0.22119339 | C17: =($A17*(1+Inputs!$B$4*(1-Inputs!$B$8))^C$16*(1-Inputs!$B$9)+$A17*Inputs!$B$9)/(1+Inputs!$B$4)^C$16 -> 0.20182116 | D17: =($A17*(1+Inputs!$B$4*(1-Inputs!$B$8))^D$16*(1-Inputs!$B$9)+$A17*Inputs!$B$9)/(1+Inputs!$B$4)^D$16 -> 0.18834039 | E17: =($A17*(1+Inputs!$B$4*(1-Inputs!$B$8))^E$16*(1-Inputs!$B$9)+$A17*Inputs!$B$9)/(1+Inputs!$B$4)^E$16 -> 0.17855046 | F17: =($A17*(1+Inputs!$B$4*(1-Inputs!$B$8))^F$16*(1-Inputs!$B$9)+$A17*Inputs!$B$9)/(1+Inputs!$B$4)^F$16 -> 0.17108423 | G17: =($A17*(1+Inputs!$B$4*(1-Inputs!$B$8))^G$16*(1-Inputs!$B$9)+$A17*Inputs!$B$9)/(1+Inputs!$B$4)^G$16 -> 0.16509206
A18: 0.3 | B18: =($A18*(1+Inputs!$B$4*(1-Inputs!$B$8))^B$16*(1-Inputs!$B$9)+$A18*Inputs!$B$9)/(1+Inputs!$B$4)^B$16 -> 0.26543207 | C18: =($A18*(1+Inputs!$B$4*(1-Inputs!$B$8))^C$16*(1-Inputs!$B$9)+$A18*Inputs!$B$9)/(1+Inputs!$B$4)^C$16 -> 0.24218539 | D18: =($A18*(1+Inputs!$B$4*(1-Inputs!$B$8))^D$16*(1-Inputs!$B$9)+$A18*Inputs!$B$9)/(1+Inputs!$B$4)^D$16 -> 0.22600847 | E18: =($A18*(1+Inputs!$B$4*(1-Inputs!$B$8))^E$16*(1-Inputs!$B$9)+$A18*Inputs!$B$9)/(1+Inputs!$B$4)^E$16 -> 0.21426056 | F18: =($A18*(1+Inputs!$B$4*(1-Inputs!$B$8))^F$16*(1-Inputs!$B$9)+$A18*Inputs!$B$9)/(1+Inputs!$B$4)^F$16 -> 0.20530107 | G18: =($A18*(1+Inputs!$B$4*(1-Inputs!$B$8))^G$16*(1-Inputs!$B$9)+$A18*Inputs!$B$9)/(1+Inputs!$B$4)^G$16 -> 0.19811048
A19: 0.35 | B19: =($A19*(1+Inputs!$B$4*(1-Inputs!$B$8))^B$16*(1-Inputs!$B$9)+$A19*Inputs!$B$9)/(1+Inputs!$B$4)^B$16 -> 0.30967075 | C19: =($A19*(1+Inputs!$B$4*(1-Inputs!$B$8))^C$16*(1-Inputs!$B$9)+$A19*Inputs!$B$9)/(1+Inputs!$B$4)^C$16 -> 0.28254962 | D19: =($A19*(1+Inputs!$B$4*(1-Inputs!$B$8))^D$16*(1-Inputs!$B$9)+$A19*Inputs!$B$9)/(1+Inputs!$B$4)^D$16 -> 0.26367655 | E19: =($A19*(1+Inputs!$B$4*(1-Inputs!$B$8))^E$16*(1-Inputs!$B$9)+$A19*Inputs!$B$9)/(1+Inputs!$B$4)^E$16 -> 0.24997065 | F19: =($A19*(1+Inputs!$B$4*(1-Inputs!$B$8))^F$16*(1-Inputs!$B$9)+$A19*Inputs!$B$9)/(1+Inputs!$B$4)^F$16 -> 0.23951792 | G19: =($A19*(1+Inputs!$B$4*(1-Inputs!$B$8))^G$16*(1-Inputs!$B$9)+$A19*Inputs!$B$9)/(1+Inputs!$B$4)^G$16 -> 0.23112889
A20: 0.38 | B20: =($A20*(1+Inputs!$B$4*(1-Inputs!$B$8))^B$16*(1-Inputs!$B$9)+$A20*Inputs!$B$9)/(1+Inputs!$B$4)^B$16 -> 0.33621395 | C20: =($A20*(1+Inputs!$B$4*(1-Inputs!$B$8))^C$16*(1-Inputs!$B$9)+$A20*Inputs!$B$9)/(1+Inputs!$B$4)^C$16 -> 0.30676816 | D20: =($A20*(1+Inputs!$B$4*(1-Inputs!$B$8))^D$16*(1-Inputs!$B$9)+$A20*Inputs!$B$9)/(1+Inputs!$B$4)^D$16 -> 0.28627739 | E20: =($A20*(1+Inputs!$B$4*(1-Inputs!$B$8))^E$16*(1-Inputs!$B$9)+$A20*Inputs!$B$9)/(1+Inputs!$B$4)^E$16 -> 0.27139671 | F20: =($A20*(1+Inputs!$B$4*(1-Inputs!$B$8))^F$16*(1-Inputs!$B$9)+$A20*Inputs!$B$9)/(1+Inputs!$B$4)^F$16 -> 0.26004802 | G20: =($A20*(1+Inputs!$B$4*(1-Inputs!$B$8))^G$16*(1-Inputs!$B$9)+$A20*Inputs!$B$9)/(1+Inputs!$B$4)^G$16 -> 0.25093994
A21: 0.42 | B21: =($A21*(1+Inputs!$B$4*(1-Inputs!$B$8))^B$16*(1-Inputs!$B$9)+$A21*Inputs!$B$9)/(1+Inputs!$B$4)^B$16 -> 0.3716049 | C21: =($A21*(1+Inputs!$B$4*(1-Inputs!$B$8))^C$16*(1-Inputs!$B$9)+$A21*Inputs!$B$9)/(1+Inputs!$B$4)^C$16 -> 0.33905955 | D21: =($A21*(1+Inputs!$B$4*(1-Inputs!$B$8))^D$16*(1-Inputs!$B$9)+$A21*Inputs!$B$9)/(1+Inputs!$B$4)^D$16 -> 0.31641186 | E21: =($A21*(1+Inputs!$B$4*(1-Inputs!$B$8))^E$16*(1-Inputs!$B$9)+$A21*Inputs!$B$9)/(1+Inputs!$B$4)^E$16 -> 0.29996478 | F21: =($A21*(1+Inputs!$B$4*(1-Inputs!$B$8))^F$16*(1-Inputs!$B$9)+$A21*Inputs!$B$9)/(1+Inputs!$B$4)^F$16 -> 0.2874215 | G21: =($A21*(1+Inputs!$B$4*(1-Inputs!$B$8))^G$16*(1-Inputs!$B$9)+$A21*Inputs!$B$9)/(1+Inputs!$B$4)^G$16 -> 0.27735467
A22: 0.45 | B22: =($A22*(1+Inputs!$B$4*(1-Inputs!$B$8))^B$16*(1-Inputs!$B$9)+$A22*Inputs!$B$9)/(1+Inputs!$B$4)^B$16 -> 0.3981481 | C22: =($A22*(1+Inputs!$B$4*(1-Inputs!$B$8))^C$16*(1-Inputs!$B$9)+$A22*Inputs!$B$9)/(1+Inputs!$B$4)^C$16 -> 0.36327809 | D22: =($A22*(1+Inputs!$B$4*(1-Inputs!$B$8))^D$16*(1-Inputs!$B$9)+$A22*Inputs!$B$9)/(1+Inputs!$B$4)^D$16 -> 0.3390127 | E22: =($A22*(1+Inputs!$B$4*(1-Inputs!$B$8))^E$16*(1-Inputs!$B$9)+$A22*Inputs!$B$9)/(1+Inputs!$B$4)^E$16 -> 0.32139084 | F22: =($A22*(1+Inputs!$B$4*(1-Inputs!$B$8))^F$16*(1-Inputs!$B$9)+$A22*Inputs!$B$9)/(1+Inputs!$B$4)^F$16 -> 0.30795161 | G22: =($A22*(1+Inputs!$B$4*(1-Inputs!$B$8))^G$16*(1-Inputs!$B$9)+$A22*Inputs!$B$9)/(1+Inputs!$B$4)^G$16 -> 0.29716572
A25: Reading it: the longer the money stays invested and the heavier the tax drag on the outside pool, the lower the future rate has to be before keeping the IRA wins. With a 10% return and 25+ years, converting at 38% beats never converting even if the future rate is in the low 20s.

Sheet RMD & heirs
A1: What an unconverted IRA looks like at 75, and what the kids keep
A3: Years until age 75 | B3: =MAX(0,75-Inputs!$B$12) -> 18
A4: IRA balance at 75 if never converted | B4: =INDEX(Engine!I7:I47,MIN(40,B3)+1) -> 6393904.9
A5: First required minimum distribution (balance / divisor) | B5: =B4/Inputs!$B$14 -> 259914.83 | D5: Forced ordinary income every year from 75, whether you need it or not; it also pushes Social Security into taxation and raises Medicare premiums (IRMAA).
A6: Tax on that first RMD at the later rate | B6: =B5*Inputs!$B$6 -> 77974.45
A7: Roth balance at 75 if converted all at once (no RMDs) | B7: =INDEX(Engine!AA7:AA47,MIN(40,B3)+1) -> 6393904.9
A9: If the account passes to the kids at the Compare horizon
A10: Strategy | B10: Pre-tax IRA left | C10: Roth left | D10: What heirs keep after their tax (IRA x (1 - heirs' rate) + Roth + pool after liquidation tax)
A11: Never convert | B11: =INDEX(Engine!I7:I47,Inputs!$B$10+1) -> 2982803.8 | C11: =INDEX(Engine!J7:J47,Inputs!$B$10+1) -> 0 | D11: =B11*(1-Inputs!$B$13)+C11+INDEX(Engine!K7:K47,Inputs!$B$10+1)-(INDEX(Engine!K7:K47,Inputs!$B$10+1)-INDEX(Engine!L7:L47,Inputs!$B$10+1))*Inputs!$B$9 -> 3540123.7
A12: All at once | B12: =INDEX(Engine!Z7:Z47,Inputs!$B$10+1) -> 0 | C12: =INDEX(Engine!AA7:AA47,Inputs!$B$10+1) -> 2982803.8 | D12: =B12*(1-Inputs!$B$13)+C12+INDEX(Engine!AB7:AB47,Inputs!$B$10+1)-(INDEX(Engine!AB7:AB47,Inputs!$B$10+1)-INDEX(Engine!AC7:AC47,Inputs!$B$10+1))*Inputs!$B$9 -> 3669075.8
A13: Over 3 years | B13: =INDEX(Engine!AQ7:AQ47,Inputs!$B$10+1) -> 0 | C13: =INDEX(Engine!AR7:AR47,Inputs!$B$10+1) -> 2982803.8 | D13: =B13*(1-Inputs!$B$13)+C13+INDEX(Engine!AS7:AS47,Inputs!$B$10+1)-(INDEX(Engine!AS7:AS47,Inputs!$B$10+1)-INDEX(Engine!AT7:AT47,Inputs!$B$10+1))*Inputs!$B$9 -> 3664891.2
A14: Over 5 years | B14: =INDEX(Engine!BH7:BH47,Inputs!$B$10+1) -> 0 | C14: =INDEX(Engine!BI7:BI47,Inputs!$B$10+1) -> 2982803.8 | D14: =B14*(1-Inputs!$B$13)+C14+INDEX(Engine!BJ7:BJ47,Inputs!$B$10+1)-(INDEX(Engine!BJ7:BJ47,Inputs!$B$10+1)-INDEX(Engine!BK7:BK47,Inputs!$B$10+1))*Inputs!$B$9 -> 3660681.1
A15: Over 8 years | B15: =INDEX(Engine!BY7:BY47,Inputs!$B$10+1) -> 0 | C15: =INDEX(Engine!BZ7:BZ47,Inputs!$B$10+1) -> 2982803.8 | D15: =B15*(1-Inputs!$B$13)+C15+INDEX(Engine!CA7:CA47,Inputs!$B$10+1)-(INDEX(Engine!CA7:CA47,Inputs!$B$10+1)-INDEX(Engine!CB7:CB47,Inputs!$B$10+1))*Inputs!$B$9 -> 3654317.7
A16: Over 10 years | B16: =INDEX(Engine!CP7:CP47,Inputs!$B$10+1) -> 0 | C16: =INDEX(Engine!CQ7:CQ47,Inputs!$B$10+1) -> 2982803.8 | D16: =B16*(1-Inputs!$B$13)+C16+INDEX(Engine!CR7:CR47,Inputs!$B$10+1)-(INDEX(Engine!CR7:CR47,Inputs!$B$10+1)-INDEX(Engine!CS7:CS47,Inputs!$B$10+1))*Inputs!$B$9 -> 3650043
A18: Heirs must empty an inherited traditional IRA within 10 years of death (SECURE Act), taxed as ordinary income in their bracket. An inherited Roth also empties in 10 years but tax-free, and can sit growing until year 10. The heirs' rate on Inputs drives column D.
