Workbook

Sheet Holdings
A1: Rank | B1: Ticker | C1: Company | D1: GICS Sector | E1: Sub-Industry | F1: Weight | G1: Cumulative Weight | H1: Price ($) | I1: P/E (TTM) | J1: EPS (TTM) | K1: Mkt Cap ($B) | L1: Price/Sales | M1: Revenue TTM ($B) | N1: Notes
A2: 1 | B2: ISRG | C2: Intuitive Surgical, Inc. | D2: Health Care | E2: Medical Instruments & Supplies | F2: 0.084381 | G2: =SUM($F$2:F2) -> 0.084381 | H2: 398.3 | I2: 45.6243 | J2: 8.73 | K2: 142.7021 | L2: 12.9325 | M2: =IF(AND(N(K2)>0,N(L2)>0),K2/L2,"") -> 11.034379
A3: 2 | B3: ABBN | C3: ABB Ltd | D3: Industrials | E3: Electrical Equipment & Parts | F3: 0.082973 | G3: =SUM($F$2:F3) -> 0.167354 | I3: 36.7946 | J3: 2.24 | L3: 4.1744 | M3: =IF(AND(N(K3)>0,N(L3)>0),K3/L3,"") | N3: Local-currency listing (CHF); price and market cap blank
A4: 3 | B4: 6954 | C4: Fanuc Corporation | D4: Industrials | E4: Specialty Industrial Machinery | F4: 0.080559 | G4: =SUM($F$2:F4) -> 0.247913 | I4: 33.6938 | J4: 178.49 | L4: 6.2613 | M4: =IF(AND(N(K4)>0,N(L4)>0),K4/L4,"") | N4: Local-currency listing (JPY); price and market cap blank
A5: 4 | B5: NVDA | C5: NVIDIA Corporation | D5: Information Technology | E5: Semiconductors | F5: 0.079654 | G5: =SUM($F$2:F5) -> 0.327567 | H5: 225.51 | I5: 28.4735 | J5: 7.92 | K5: 5445.3899 | L5: 17.9734 | M5: =IF(AND(N(K5)>0,N(L5)>0),K5/L5,"") -> 302.96938
A6: 5 | B6: 6861 | C6: Keyence Corporation | D6: Information Technology | E6: Scientific & Technical Instruments | F6: 0.077643 | G6: =SUM($F$2:F6) -> 0.40521 | I6: 42.0421 | J6: 1837.92 | L6: 14.9342 | M6: =IF(AND(N(K6)>0,N(L6)>0),K6/L6,"") | N6: Local-currency listing (JPY); price and market cap blank
A7: 6 | B7: 6273 | C7: SMC Corporation | D7: Industrials | E7: Specialty Industrial Machinery | F7: 0.044453 | G7: =SUM($F$2:F7) -> 0.449663 | I7: 25.7545 | J7: 2639.93 | L7: 4.6509 | M7: =IF(AND(N(K7)>0,N(L7)>0),K7/L7,"") | N7: Local-currency listing (JPY); price and market cap blank
A8: 7 | B8: 6383 | C8: Daifuku Co., Ltd. | D8: Industrials | E8: Specialty Industrial Machinery | F8: 0.032887 | G8: =SUM($F$2:F8) -> 0.48255 | I8: 25.5268 | J8: 216.87 | L8: 2.9844 | M8: =IF(AND(N(K8)>0,N(L8)>0),K8/L8,"") | N8: Local-currency listing (JPY); price and market cap blank
A9: 8 | B9: AUR | C9: Aurora Innovation, Inc. | D9: Consumer Discretionary | E9: Auto Parts | F9: 0.027758 | G9: =SUM($F$2:F9) -> 0.510308 | H9: 6.32 | J9: -0.46 | K9: 12.6663 | L9: 2533.2522 | M9: =IF(AND(N(K9)>0,N(L9)>0),K9/L9,"") -> 0.0050000154 | N9: Negative trailing EPS; P/E blank
A10: 9 | B10: 300124 | C10: Shenzhen Inovance Technology Co.,Ltd | D10: Industrials | E10: Electrical Equipment & Parts | F10: 0.025948 | G10: =SUM($F$2:F10) -> 0.536256 | I10: 29.618 | J10: 1.78 | L10: 2.8995 | M10: =IF(AND(N(K10)>0,N(L10)>0),K10/L10,"") | N10: Local-currency listing (CNY); price and market cap blank
A11: 10 | B11: CGNX | C11: Cognex Corporation | D11: Information Technology | E11: Scientific & Technical Instruments | F11: 0.024942 | G11: =SUM($F$2:F11) -> 0.561198 | H11: 58.19 | I11: 55.9519 | J11: 1.04 | K11: 9.7889 | L11: 8.9895 | M11: =IF(AND(N(K11)>0,N(L11)>0),K11/L11,"") -> 1.088926
A12: 11 | B12: TSLA | C12: Tesla, Inc. | D12: Consumer Discretionary | E12: Auto Manufacturers | F12: 0.020718 | G12: =SUM($F$2:F12) -> 0.581916 | H12: 380.12 | I12: 345.5636 | J12: 1.1 | K12: 1501.302 | L12: 14.4887 | M12: =IF(AND(N(K12)>0,N(L12)>0),K12/L12,"") -> 103.61882
A13: 12 | B13: GOOGL | C13: Alphabet Inc. | D13: Communication Services | E13: Internet Content & Information | F13: 0.020316 | G13: =SUM($F$2:F13) -> 0.602232 | H13: 337.83 | I13: 16.9338 | J13: 19.95 | K13: 4131.6387 | L13: 9.2665 | M13: =IF(AND(N(K13)>0,N(L13)>0),K13/L13,"") -> 445.86831
A14: 13 | B14: 300757 | C14: RoboTechnik Intelligent Technology Co., Ltd. | D14: Industrials | E14: Specialty Industrial Machinery | F14: 0.020316 | G14: =SUM($F$2:F14) -> 0.622548 | J14: -0.18 | L14: 76.5233 | M14: =IF(AND(N(K14)>0,N(L14)>0),K14/L14,"") | N14: Local-currency listing (CNY); price and market cap blank; Negative trailing EPS; P/E blank
A15: 14 | B15: 6645 | C15: OMRON Corporation | D15: Information Technology | E15: Electronic Components | F15: 0.020215 | G15: =SUM($F$2:F15) -> 0.642763 | I15: 36.3401 | J15: 173.94 | L15: 1.533 | M15: =IF(AND(N(K15)>0,N(L15)>0),K15/L15,"") | N15: Local-currency listing (JPY); price and market cap blank
A16: 15 | B16: DE | C16: Deere & Company | D16: Industrials | E16: Farm & Heavy Construction Machinery | F16: 0.019612 | G16: =SUM($F$2:F16) -> 0.662375 | H16: 709.48 | I16: 39.4156 | J16: 18 | K16: 191.2938 | L16: 3.9914 | M16: =IF(AND(N(K16)>0,N(L16)>0),K16/L16,"") -> 47.926492
A17: 16 | B17: 6506 | C17: YASKAWA Electric Corporation | D17: Industrials | E17: Electrical Equipment & Parts | F17: 0.018606 | G17: =SUM($F$2:F17) -> 0.680981 | I17: 32.9653 | J17: 135.87 | L17: 2.0914 | M17: =IF(AND(N(K17)>0,N(L17)>0),K17/L17,"") | N17: Local-currency listing (JPY); price and market cap blank
A18: 17 | B18: 9660 | C18: Horizon Robotics | D18: Information Technology | E18: Software - Application | F18: 0.018103 | G18: =SUM($F$2:F18) -> 0.699084 | J18: -0.73 | L18: 14.8982 | M18: =IF(AND(N(K18)>0,N(L18)>0),K18/L18,"") | N18: Local-currency listing (HKD); price and market cap blank; Negative trailing EPS; P/E blank
A19: 18 | B19: 1810 | C19: Xiaomi Corporation | D19: Information Technology | E19: Consumer Electronics | F19: 0.016192 | G19: =SUM($F$2:F19) -> 0.715276 | I19: 18.2517 | J19: 1.43 | L19: 1.5324 | M19: =IF(AND(N(K19)>0,N(L19)>0),K19/L19,"") | N19: Local-currency listing (HKD); price and market cap blank
A20: 19 | B20: 277810 | C20: Rainbow Robotics | F20: 0.01579 | G20: =SUM($F$2:F20) -> 0.731066 | M20: =IF(AND(N(K20)>0,N(L20)>0),K20/L20,"") | N20: Local-currency listing (KRW); price and market cap blank
A21: 20 | B21: SYM | C21: Symbotic Inc. | D21: Industrials | E21: Specialty Industrial Machinery | F21: 0.014684 | G21: =SUM($F$2:F21) -> 0.74575 | H21: 43.69 | I21: 1092.25 | J21: 0.04 | K21: 26.4484 | L21: 9.9965 | M21: =IF(AND(N(K21)>0,N(L21)>0),K21/L21,"") -> 2.645766 | N21: P/E reflects near-zero earnings
A22: 21 | B22: AUTO | C22: AutoStore Holdings Ltd. | D22: Industrials | E22: Specialty Industrial Machinery | F22: 0.014583 | G22: =SUM($F$2:F22) -> 0.760333 | I22: 35.3778 | J22: 0.45 | L22: 78.9726 | M22: =IF(AND(N(K22)>0,N(L22)>0),K22/L22,"") | N22: Local-currency listing (NOK); price and market cap blank
A23: 22 | B23: 9880 | C23: Ubtech Robotics Corp Ltd | D23: Industrials | E23: Specialty Industrial Machinery | F23: 0.011264 | G23: =SUM($F$2:F23) -> 0.771597 | J23: -1.44 | L23: 15.0241 | M23: =IF(AND(N(K23)>0,N(L23)>0),K23/L23,"") | N23: Local-currency listing (HKD); price and market cap blank; Negative trailing EPS; P/E blank
A24: 23 | B24: 6134 | C24: Fuji Corporation | D24: Industrials | E24: Specialty Industrial Machinery | F24: 0.011264 | G24: =SUM($F$2:F24) -> 0.782861 | I24: 41.2788 | J24: 178.76 | L24: 3.2481 | M24: =IF(AND(N(K24)>0,N(L24)>0),K24/L24,"") | N24: Local-currency listing (JPY); price and market cap blank
A25: 24 | B25: 688017 | C25: Leader Harmonious Drive Systems Co., Ltd. | D25: Industrials | E25: Specialty Industrial Machinery | F25: 0.01056 | G25: =SUM($F$2:F25) -> 0.793421 | I25: 372.5974 | J25: 0.77 | L25: 78.7562 | M25: =IF(AND(N(K25)>0,N(L25)>0),K25/L25,"") | N25: Local-currency listing (CNY); price and market cap blank
A26: 25 | B26: ROK | C26: Rockwell Automation, Inc. | D26: Industrials | E26: Specialty Industrial Machinery | F26: 0.010359 | G26: =SUM($F$2:F26) -> 0.80378 | H26: 432.89 | I26: 40.5328 | J26: 10.68 | K26: 48.1694 | L26: 5.3683 | M26: =IF(AND(N(K26)>0,N(L26)>0),K26/L26,"") -> 8.9729337
A27: 26 | B27: 6324 | C27: Harmonic Drive Systems Inc. | D27: Industrials | E27: Specialty Industrial Machinery | F27: 0.009554 | G27: =SUM($F$2:F27) -> 0.813334 | I27: 375.7467 | J27: 16.74 | L27: 9.4905 | M27: =IF(AND(N(K27)>0,N(L27)>0),K27/L27,"") | N27: Local-currency listing (JPY); price and market cap blank
A28: 27 | B28: 2049 | C28: Hiwin Technologies Corporation | D28: Industrials | E28: Tools & Accessories | F28: 0.009253 | G28: =SUM($F$2:F28) -> 0.822587 | I28: 49.0152 | J28: 6.6 | L28: 4.3376 | M28: =IF(AND(N(K28)>0,N(L28)>0),K28/L28,"") | N28: Local-currency listing (TWD); price and market cap blank
A29: 28 | B29: 454910 | C29: Doosan Robotics Inc. | D29: Industrials | E29: Specialty Industrial Machinery | F29: 0.008549 | G29: =SUM($F$2:F29) -> 0.831136 | L29: 81.7533 | M29: =IF(AND(N(K29)>0,N(L29)>0),K29/L29,"") | N29: Local-currency listing (KRW); price and market cap blank
A30: 29 | B30: TECN | C30: Tecan Group AG | D30: Health Care | E30: Medical Instruments & Supplies | F30: 0.008549 | G30: =SUM($F$2:F30) -> 0.839685 | J30: -9.16 | L30: 3.0828 | M30: =IF(AND(N(K30)>0,N(L30)>0),K30/L30,"") | N30: Local-currency listing (CHF); price and market cap blank; Negative trailing EPS; P/E blank
A31: 30 | B31: 108490 | C31: Robotis Co Ltd | F31: 0.008146 | G31: =SUM($F$2:F31) -> 0.847831 | M31: =IF(AND(N(K31)>0,N(L31)>0),K31/L31,"") | N31: Local-currency listing (KRW); price and market cap blank
A32: 31 | B32: OUST | C32: Ouster, Inc. | D32: Information Technology | E32: Electronic Components | F32: 0.007342 | G32: =SUM($F$2:F32) -> 0.855173 | H32: 39.38 | J32: -0.83 | K32: 2.8398 | L32: 13.8589 | M32: =IF(AND(N(K32)>0,N(L32)>0),K32/L32,"") -> 0.20490804 | N32: Negative trailing EPS; P/E blank
A33: 32 | B33: PONY | C33: Pony AI Inc. | D33: Information Technology | E33: Information Technology Services | F33: 0.006437 | G33: =SUM($F$2:F33) -> 0.86161 | H33: 7.26 | J33: -0.33 | K33: 3.1538 | L33: 25.2233 | M33: =IF(AND(N(K33)>0,N(L33)>0),K33/L33,"") -> 0.12503519 | N33: Negative trailing EPS; P/E blank
A34: 33 | B34: 2252 | C34: Shanghai MicroPort MedBot (Group) Co., Ltd. | D34: Health Care | E34: Medical Devices | F34: 0.006336 | G34: =SUM($F$2:F34) -> 0.867946 | J34: -0.28 | L34: 39.6386 | M34: =IF(AND(N(K34)>0,N(L34)>0),K34/L34,"") | N34: Local-currency listing (HKD); price and market cap blank; Negative trailing EPS; P/E blank
A35: 34 | B35: EXA | C35: Exail Technologies | D35: Industrials | E35: Aerospace & Defense | F35: 0.006034 | G35: =SUM($F$2:F35) -> 0.87398 | I35: 735.2941 | J35: 0.17 | L35: 4.219 | M35: =IF(AND(N(K35)>0,N(L35)>0),K35/L35,"") | N35: Local-currency listing (EUR); price and market cap blank; P/E reflects near-zero earnings
A36: 35 | B36: 688169 | C36: Beijing Roborock Technology Co., Ltd. | D36: Industrials | E36: Specialty Industrial Machinery | F36: 0.006034 | G36: =SUM($F$2:F36) -> 0.880014 | I36: 17.9322 | J36: 6.49 | L36: 1.447 | M36: =IF(AND(N(K36)>0,N(L36)>0),K36/L36,"") | N36: Local-currency listing (CNY); price and market cap blank
A37: 36 | B37: 603486 | C37: Ecovacs Robotics Co., Ltd. | D37: Consumer Discretionary | E37: Furnishings, Fixtures & Appliances | F37: 0.005833 | G37: =SUM($F$2:F37) -> 0.885847 | I37: 14.5 | J37: 3.5 | L37: 1.4202 | M37: =IF(AND(N(K37)>0,N(L37)>0),K37/L37,"") | N37: Local-currency listing (CNY); price and market cap blank
A38: 37 | B38: 688297 | C38: AVIC (Chengdu)UAS Co., Ltd. | D38: Industrials | E38: Aerospace & Defense | F38: 0.005833 | G38: =SUM($F$2:F38) -> 0.89168 | I38: 268.9375 | J38: 0.16 | L38: 6.8972 | M38: =IF(AND(N(K38)>0,N(L38)>0),K38/L38,"") | N38: Local-currency listing (CNY); price and market cap blank
A39: 38 | B39: HSAI | C39: Hesai Group | D39: Consumer Discretionary | E39: Auto Parts | F39: 0.005632 | G39: =SUM($F$2:F39) -> 0.897312 | H39: 16.31 | K39: 20.5039 | M39: =IF(AND(N(K39)>0,N(L39)>0),K39/L39,"") | N39: ADR: Yahoo mixes USD price with CNY earnings; P/E, EPS, P/S blanked
A40: 39 | B40: BIDU | C40: Baidu, Inc. | D40: Communication Services | E40: Internet Content & Information | F40: 0.005532 | G40: =SUM($F$2:F40) -> 0.902844 | H40: 89.78 | K40: 30.5961 | M40: =IF(AND(N(K40)>0,N(L40)>0),K40/L40,"") | N40: ADR: Yahoo mixes USD price with CNY earnings; P/E, EPS, P/S blanked
A41: 40 | B41: WRD | C41: WeRide Inc. | D41: Information Technology | E41: Software - Application | F41: 0.004727 | G41: =SUM($F$2:F41) -> 0.907571 | H41: 5.85 | K41: 1.9244 | M41: =IF(AND(N(K41)>0,N(L41)>0),K41/L41,"") | N41: ADR: Yahoo mixes USD price with CNY earnings; P/E, EPS, P/S blanked
A42: 41 | B42: ATS | C42: ATS Corporation | D42: Industrials | E42: Specialty Industrial Machinery | F42: 0.004727 | G42: =SUM($F$2:F42) -> 0.912298 | H42: 19.21 | K42: 1.885 | M42: =IF(AND(N(K42)>0,N(L42)>0),K42/L42,"") | N42: ADR: Yahoo mixes USD price with CAD earnings; P/E, EPS, P/S blanked
A43: 42 | B43: 002747 | C43: Estun Automation Co., Ltd | D43: Industrials | E43: Specialty Industrial Machinery | F43: 0.004626 | G43: =SUM($F$2:F43) -> 0.916924 | I43: 133.9545 | J43: 0.22 | L43: 5.8058 | M43: =IF(AND(N(K43)>0,N(L43)>0),K43/L43,"") | N43: Local-currency listing (CNY); price and market cap blank
A44: 43 | B44: ALNT | C44: Allient Inc. | D44: Information Technology | E44: Electronic Components | F44: 0.004626 | G44: =SUM($F$2:F44) -> 0.92155 | H44: 113.6 | I44: 66.8235 | J44: 1.7 | K44: 1.9308 | L44: 3.3592 | M44: =IF(AND(N(K44)>0,N(L44)>0),K44/L44,"") -> 0.57477971
A45: 44 | B45: 300024 | C45: Siasun Robot&Automation Co.,Ltd. | D45: Industrials | E45: Specialty Industrial Machinery | F45: 0.004124 | G45: =SUM($F$2:F45) -> 0.925674 | J45: -0.31 | L45: 5.2893 | M45: =IF(AND(N(K45)>0,N(L45)>0),K45/L45,"") | N45: Local-currency listing (CNY); price and market cap blank; Negative trailing EPS; P/E blank
A46: 45 | B46: 058610 | C46: SPG CO LTD | F46: 0.004023 | G46: =SUM($F$2:F46) -> 0.929697 | M46: =IF(AND(N(K46)>0,N(L46)>0),K46/L46,"") | N46: Fundamentals not retrieved from Yahoo
A47: 46 | B47: 2675 | C47: Shenzhen Edge Medical Co., Ltd. | D47: Health Care | E47: Medical Devices | F47: 0.003922 | G47: =SUM($F$2:F47) -> 0.933619 | J47: -0.27 | L47: 23.4414 | M47: =IF(AND(N(K47)>0,N(L47)>0),K47/L47,"") | N47: Local-currency listing (HKD); price and market cap blank; Negative trailing EPS; P/E blank
A48: 47 | B48: OMCL | C48: Omnicell, Inc. | D48: Health Care | E48: Health Information Services | F48: 0.003822 | G48: =SUM($F$2:F48) -> 0.937441 | H48: 32.99 | I48: 39.2738 | J48: 0.84 | K48: 1.5003 | L48: 1.2035 | M48: =IF(AND(N(K48)>0,N(L48)>0),K48/L48,"") -> 1.246614
A49: 48 | B49: 2729 | C49: Zhejiang Galaxis Technology Group Co., Ltd. | D49: Information Technology | E49: Computer Hardware | F49: 0.003721 | G49: =SUM($F$2:F49) -> 0.941162 | J49: -0.47 | L49: 10.8334 | M49: =IF(AND(N(K49)>0,N(L49)>0),K49/L49,"") | N49: Local-currency listing (HKD); price and market cap blank; Negative trailing EPS; P/E blank
A50: 49 | B50: 688686 | C50: OPT Machine Vision Tech Co., Ltd. | D50: Information Technology | E50: Electronic Components | F50: 0.003419 | G50: =SUM($F$2:F50) -> 0.944581 | I50: 81.9595 | J50: 1.73 | L50: 11.6272 | M50: =IF(AND(N(K50)>0,N(L50)>0),K50/L50,"") | N50: Local-currency listing (CNY); price and market cap blank
A51: 50 | B51: 2464 | C51: Mirle Automation Corporation | D51: Industrials | E51: Specialty Industrial Machinery | F51: 0.003419 | G51: =SUM($F$2:F51) -> 0.948 | I51: 527.027 | J51: 0.37 | L51: 5.807 | M51: =IF(AND(N(K51)>0,N(L51)>0),K51/L51,"") | N51: Local-currency listing (TWD); price and market cap blank; P/E reflects near-zero earnings
A52: 51 | B52: 278A | C52: Terra Drone Corporation | D52: Industrials | E52: Aerospace & Defense | F52: 0.003419 | G52: =SUM($F$2:F52) -> 0.951419 | J52: -288.2 | L52: 42.8464 | M52: =IF(AND(N(K52)>0,N(L52)>0),K52/L52,"") | N52: Local-currency listing (JPY); price and market cap blank; Negative trailing EPS; P/E blank
A53: 52 | B53: UMAC | C53: Unusual Machines, Inc. | D53: Information Technology | E53: Computer Hardware | F53: 0.003017 | G53: =SUM($F$2:F53) -> 0.954436 | H53: 22.69 | J53: -0.14 | K53: 1.1335 | L53: 35.5877 | M53: =IF(AND(N(K53)>0,N(L53)>0),K53/L53,"") -> 0.031850892 | N53: Negative trailing EPS; P/E blank
A54: 53 | B54: 3881 | C54: CiDi Inc. | D54: Industrials | E54: Farm & Heavy Construction Machinery | F54: 0.002917 | G54: =SUM($F$2:F54) -> 0.957353 | J54: -1.81 | L54: 7.3114 | M54: =IF(AND(N(K54)>0,N(L54)>0),K54/L54,"") | N54: Local-currency listing (HKD); price and market cap blank; Negative trailing EPS; P/E blank
A55: 54 | B55: 2590 | C55: Beijing Geekplus Technology Co., Ltd. | D55: Information Technology | E55: Software - Application | F55: 0.002615 | G55: =SUM($F$2:F55) -> 0.959968 | J55: -0.09 | L55: 4.9777 | M55: =IF(AND(N(K55)>0,N(L55)>0),K55/L55,"") | N55: Local-currency listing (HKD); price and market cap blank; Negative trailing EPS; P/E blank
A56: 55 | B56: 2432 | C56: Shenzhen Dobot Corp Ltd | D56: Industrials | E56: Specialty Industrial Machinery | F56: 0.002615 | G56: =SUM($F$2:F56) -> 0.962583 | J56: -0.4 | L56: 14.0153 | M56: =IF(AND(N(K56)>0,N(L56)>0),K56/L56,"") | N56: Local-currency listing (HKD); price and market cap blank; Negative trailing EPS; P/E blank
A57: 56 | B57: PRCT | C57: PROCEPT BioRobotics Corporation | D57: Health Care | E57: Medical Devices | F57: 0.002615 | G57: =SUM($F$2:F57) -> 0.965198 | H57: 18.09 | J57: -1.95 | K57: 1.0297 | L57: 3.0523 | M57: =IF(AND(N(K57)>0,N(L57)>0),K57/L57,"") -> 0.33735216 | N57: Negative trailing EPS; P/E blank
A58: 57 | B58: 2498 | C58: Robosense Technology Co., Ltd | D58: Information Technology | E58: Computer Hardware | F58: 0.002615 | G58: =SUM($F$2:F58) -> 0.967813 | J58: -0.4 | L58: 3.4797 | M58: =IF(AND(N(K58)>0,N(L58)>0),K58/L58,"") | N58: Local-currency listing (HKD); price and market cap blank; Negative trailing EPS; P/E blank
A59: 58 | B59: 4585 | C59: Techman Robot Inc. | D59: Industrials | E59: Specialty Industrial Machinery | F59: 0.002414 | G59: =SUM($F$2:F59) -> 0.970227 | I59: 102.0979 | J59: 2.86 | L59: 15.8566 | M59: =IF(AND(N(K59)>0,N(L59)>0),K59/L59,"") | N59: Local-currency listing (TWD); price and market cap blank
A60: 59 | B60: 002896 | C60: Ningbo ZhongDa Leader Intelligent Transmission Co., Ltd. | D60: Industrials | E60: Specialty Industrial Machinery | F60: 0.002414 | G60: =SUM($F$2:F60) -> 0.972641 | I60: 276.0909 | J60: 0.22 | L60: 10.6443 | M60: =IF(AND(N(K60)>0,N(L60)>0),K60/L60,"") | N60: Local-currency listing (CNY); price and market cap blank
A61: 60 | B61: MOG/A | C61: Moog Inc. | D61: Industrials | E61: Aerospace & Defense | F61: 0.002313 | G61: =SUM($F$2:F61) -> 0.974954 | H61: 374.98 | I61: 31.859 | J61: 11.77 | K61: 11.8761 | L61: 2.7504 | M61: =IF(AND(N(K61)>0,N(L61)>0),K61/L61,"") -> 4.3179538
A62: 61 | B62: AVEX | C62: AEVEX Corp. | D62: Industrials | E62: Aerospace & Defense | F62: 0.002213 | G62: =SUM($F$2:F62) -> 0.977167 | H62: 16.44 | I62: 27.8644 | J62: 0.59 | K62: 1.1376 | L62: 1.6321 | M62: =IF(AND(N(K62)>0,N(L62)>0),K62/L62,"") -> 0.69701611
A63: 62 | B63: 6258 | C63: Hirata Corporation | D63: Industrials | E63: Specialty Industrial Machinery | F63: 0.001911 | G63: =SUM($F$2:F63) -> 0.979078 | I63: 19.3353 | J63: 198.6 | L63: 1.192 | M63: =IF(AND(N(K63)>0,N(L63)>0),K63/L63,"") | N63: Local-currency listing (JPY); price and market cap blank
A64: 63 | B64: 1021 | C64: Guangdong Huayan Robotics Co., Ltd. | D64: Industrials | E64: Specialty Industrial Machinery | F64: 0.00181 | G64: =SUM($F$2:F64) -> 0.980888 | J64: -0.14 | L64: 15.0795 | M64: =IF(AND(N(K64)>0,N(L64)>0),K64/L64,"") | N64: Local-currency listing (HKD); price and market cap blank; Negative trailing EPS; P/E blank
A65: 64 | B65: XPEV | C65: XPeng Inc. | D65: Consumer Discretionary | E65: Auto Manufacturers | F65: 0.00181 | G65: =SUM($F$2:F65) -> 0.982698 | H65: 10.29 | K65: 9.8576 | M65: =IF(AND(N(K65)>0,N(L65)>0),K65/L65,"") | N65: ADR: Yahoo mixes USD price with CNY earnings; P/E, EPS, P/S blanked
A66: 65 | B66: 688160 | C66: Kinco Automation (Shanghai) Co.,Ltd | D66: Industrials | E66: Specialty Industrial Machinery | F66: 0.00171 | G66: =SUM($F$2:F66) -> 0.984408 | I66: 105.9783 | J66: 0.92 | L66: 10.3359 | M66: =IF(AND(N(K66)>0,N(L66)>0),K66/L66,"") | N66: Local-currency listing (CNY); price and market cap blank
A67: 66 | B67: KDK | C67: Kodiak AI, Inc. | D67: Information Technology | E67: Software - Infrastructure | F67: 0.001609 | G67: =SUM($F$2:F67) -> 0.986017 | H67: 2.97 | J67: -1.85 | K67: 0.5958 | L67: 83.3104 | M67: =IF(AND(N(K67)>0,N(L67)>0),K67/L67,"") -> 0.0071515681 | N67: Negative trailing EPS; P/E blank
A68: 67 | B68: 688165 | C68: EFORT Intelligent Equipment Co., Ltd. | D68: Industrials | E68: Specialty Industrial Machinery | F68: 0.001609 | G68: =SUM($F$2:F68) -> 0.987626 | J68: -0.77 | L68: 7.2665 | M68: =IF(AND(N(K68)>0,N(L68)>0),K68/L68,"") | N68: Local-currency listing (CNY); price and market cap blank; Negative trailing EPS; P/E blank
A69: 68 | B69: 388720 | C69: Yuil Robotics Co Ltd | F69: 0.001509 | G69: =SUM($F$2:F69) -> 0.989135 | M69: =IF(AND(N(K69)>0,N(L69)>0),K69/L69,"") | N69: Local-currency listing (KRW); price and market cap blank
A70: 69 | B70: 688277 | C70: Tinavi Medical Technologies Co., Ltd. | D70: Health Care | E70: Medical Instruments & Supplies | F70: 0.001509 | G70: =SUM($F$2:F70) -> 0.990644 | J70: -0.42 | L70: 28.5341 | M70: =IF(AND(N(K70)>0,N(L70)>0),K70/L70,"") | N70: Local-currency listing (CNY); price and market cap blank; Negative trailing EPS; P/E blank
A71: 70 | B71: 090360 | C71: ROBOSTAR CO LTD | F71: 0.001408 | G71: =SUM($F$2:F71) -> 0.992052 | M71: =IF(AND(N(K71)>0,N(L71)>0),K71/L71,"") | N71: Fundamentals not retrieved from Yahoo
A72: 71 | B72: NOVT | C72: Novanta Inc. | D72: Information Technology | E72: Scientific & Technical Instruments | F72: 0.001207 | G72: =SUM($F$2:F72) -> 0.993259 | H72: 144.43 | I72: 91.9936 | J72: 1.57 | K72: 5.462 | L72: 5.3045 | M72: =IF(AND(N(K72)>0,N(L72)>0),K72/L72,"") -> 1.0296918
A73: 72 | B73: 603666 | C73: Yijiahe Technology Co., Ltd. | D73: Industrials | E73: Specialty Industrial Machinery | F73: 0.001106 | G73: =SUM($F$2:F73) -> 0.994365 | J73: -0.74 | L73: 14.4893 | M73: =IF(AND(N(K73)>0,N(L73)>0),K73/L73,"") | N73: Local-currency listing (CNY); price and market cap blank; Negative trailing EPS; P/E blank
A74: 73 | B74: 6481 | C74: THK Co., Ltd. | D74: Industrials | E74: Specialty Industrial Machinery | F74: 0.001006 | G74: =SUM($F$2:F74) -> 0.995371 | I74: 28.7999 | J74: 217.64 | L74: 3.2633 | M74: =IF(AND(N(K74)>0,N(L74)>0),K74/L74,"") | N74: Local-currency listing (JPY); price and market cap blank
A75: 74 | B75: SERV | C75: Serve Robotics Inc. | D75: Industrials | E75: Integrated Freight & Logistics | F75: 0.001006 | G75: =SUM($F$2:F75) -> 0.996377 | H75: 4.31 | J75: -2.48 | K75: 0.3737 | L75: 47.9668 | M75: =IF(AND(N(K75)>0,N(L75)>0),K75/L75,"") -> 0.0077908053 | N75: Negative trailing EPS; P/E blank
A76: 75 | B76: 348340 | C76: Neuromeka Co Ltd | F76: 0.000805 | G76: =SUM($F$2:F76) -> 0.997182 | M76: =IF(AND(N(K76)>0,N(L76)>0),K76/L76,"") | N76: Local-currency listing (KRW); price and market cap blank
A77: 76 | B77: RR | C77: Richtech Robotics Inc. | D77: Industrials | E77: Specialty Industrial Machinery | F77: 0.000805 | G77: =SUM($F$2:F77) -> 0.997987 | H77: 1.65 | I77: 23.5714 | J77: 0.07 | K77: 0.3714 | L77: 68.9215 | M77: =IF(AND(N(K77)>0,N(L77)>0),K77/L77,"") -> 0.0053887394
A78: 77 | B78: EH | C78: EHang Holdings Limited | D78: Industrials | E78: Aerospace & Defense | F78: 0.000704 | G78: =SUM($F$2:F78) -> 0.998691 | H78: 4.58 | K78: 0.3474 | M78: =IF(AND(N(K78)>0,N(L78)>0),K78/L78,"") | N78: ADR: Yahoo mixes USD price with CNY earnings; P/E, EPS, P/S blanked
A79: 78 | B79: 455900 | C79: Angel Robotics Co Ltd | F79: 0.000603 | G79: =SUM($F$2:F79) -> 0.999294 | M79: =IF(AND(N(K79)>0,N(L79)>0),K79/L79,"") | N79: Local-currency listing (KRW); price and market cap blank
A80: 79 | B80: 7779 | C80: CYBERDYNE Inc. | D80: Health Care | E80: Medical Devices | F80: 0.000503 | G80: =SUM($F$2:F80) -> 0.999797 | I80: 326.3889 | J80: 0.72 | L80: 12.8107 | M80: =IF(AND(N(K80)>0,N(L80)>0),K80/L80,"") | N80: Local-currency listing (JPY); price and market cap blank
A81: 80 | B81: 2431 | C81: Minieye Technology Co., Ltd | D81: Information Technology | E81: Software - Infrastructure | F81: 0.000201 | G81: =SUM($F$2:F81) -> 0.999998 | J81: -1.16 | L81: 1.0428 | M81: =IF(AND(N(K81)>0,N(L81)>0),K81/L81,"") | N81: Local-currency listing (HKD); price and market cap blank; Negative trailing EPS; P/E blank

Sheet Sectors
A1: GICS Sector | B1: Approx. Weight | C1: # of Tickers | D1: Avg P/E (simple, P/E<=100)
A2: Communication Services | B2: =SUMIF(Holdings!$D$2:$D$81,A2,Holdings!$F$2:$F$81) -> 0.025848 | C2: =COUNTIF(Holdings!$D$2:$D$81,A2) -> 2 | D2: =IFERROR(AVERAGEIFS(Holdings!$I$2:$I$81,Holdings!$D$2:$D$81,A2,Holdings!$I$2:$I$81,"<=100"),"") -> 16.9338
A3: Consumer Discretionary | B3: =SUMIF(Holdings!$D$2:$D$81,A3,Holdings!$F$2:$F$81) -> 0.061751 | C3: =COUNTIF(Holdings!$D$2:$D$81,A3) -> 5 | D3: =IFERROR(AVERAGEIFS(Holdings!$I$2:$I$81,Holdings!$D$2:$D$81,A3,Holdings!$I$2:$I$81,"<=100"),"") -> 14.5
A4: Consumer Staples | B4: =SUMIF(Holdings!$D$2:$D$81,A4,Holdings!$F$2:$F$81) -> 0 | C4: =COUNTIF(Holdings!$D$2:$D$81,A4) -> 0 | D4: =IFERROR(AVERAGEIFS(Holdings!$I$2:$I$81,Holdings!$D$2:$D$81,A4,Holdings!$I$2:$I$81,"<=100"),"")
A5: Energy | B5: =SUMIF(Holdings!$D$2:$D$81,A5,Holdings!$F$2:$F$81) -> 0 | C5: =COUNTIF(Holdings!$D$2:$D$81,A5) -> 0 | D5: =IFERROR(AVERAGEIFS(Holdings!$I$2:$I$81,Holdings!$D$2:$D$81,A5,Holdings!$I$2:$I$81,"<=100"),"")
A6: Financials | B6: =SUMIF(Holdings!$D$2:$D$81,A6,Holdings!$F$2:$F$81) -> 0 | C6: =COUNTIF(Holdings!$D$2:$D$81,A6) -> 0 | D6: =IFERROR(AVERAGEIFS(Holdings!$I$2:$I$81,Holdings!$D$2:$D$81,A6,Holdings!$I$2:$I$81,"<=100"),"")
A7: Health Care | B7: =SUMIF(Holdings!$D$2:$D$81,A7,Holdings!$F$2:$F$81) -> 0.111637 | C7: =COUNTIF(Holdings!$D$2:$D$81,A7) -> 8 | D7: =IFERROR(AVERAGEIFS(Holdings!$I$2:$I$81,Holdings!$D$2:$D$81,A7,Holdings!$I$2:$I$81,"<=100"),"") -> 42.44905
A8: Industrials | B8: =SUMIF(Holdings!$D$2:$D$81,A8,Holdings!$F$2:$F$81) -> 0.490193 | C8: =COUNTIF(Holdings!$D$2:$D$81,A8) -> 40 | D8: =IFERROR(AVERAGEIFS(Holdings!$I$2:$I$81,Holdings!$D$2:$D$81,A8,Holdings!$I$2:$I$81,"<=100"),"") -> 31.725612
A9: Information Technology | B9: =SUMIF(Holdings!$D$2:$D$81,A9,Holdings!$F$2:$F$81) -> 0.278285 | C9: =COUNTIF(Holdings!$D$2:$D$81,A9) -> 18 | D9: =IFERROR(AVERAGEIFS(Holdings!$I$2:$I$81,Holdings!$D$2:$D$81,A9,Holdings!$I$2:$I$81,"<=100"),"") -> 52.729487
A10: Materials | B10: =SUMIF(Holdings!$D$2:$D$81,A10,Holdings!$F$2:$F$81) -> 0 | C10: =COUNTIF(Holdings!$D$2:$D$81,A10) -> 0 | D10: =IFERROR(AVERAGEIFS(Holdings!$I$2:$I$81,Holdings!$D$2:$D$81,A10,Holdings!$I$2:$I$81,"<=100"),"")
A11: Real Estate | B11: =SUMIF(Holdings!$D$2:$D$81,A11,Holdings!$F$2:$F$81) -> 0 | C11: =COUNTIF(Holdings!$D$2:$D$81,A11) -> 0 | D11: =IFERROR(AVERAGEIFS(Holdings!$I$2:$I$81,Holdings!$D$2:$D$81,A11,Holdings!$I$2:$I$81,"<=100"),"")
A12: Utilities | B12: =SUMIF(Holdings!$D$2:$D$81,A12,Holdings!$F$2:$F$81) -> 0 | C12: =COUNTIF(Holdings!$D$2:$D$81,A12) -> 0 | D12: =IFERROR(AVERAGEIFS(Holdings!$I$2:$I$81,Holdings!$D$2:$D$81,A12,Holdings!$I$2:$I$81,"<=100"),"")
A13: Unclassified (no sector retrieved) | B13: =1-SUM(B2:B12) -> 0.032286 | C13: =COUNTBLANK(Holdings!$D$2:$D$81) -> 7
A14: Total | B14: =SUM(B2:B13) -> 1 | C14: =SUM(C2:C13) -> 80

Sheet Overlap vs S&P 500
A1: Holdings shared with the S&P 500 (S&P weights from the companion S&P 500 workbook, Sept 2026)
A2: 6 of 80 holdings are S&P 500 members
A3: Share of this fund's weight that is inside the S&P 500 | B3: 0.235
A4: Share of the S&P 500 that those names represent | B4: 0.135
A6: Ticker | B6: Weight in this fund | C6: Weight in S&P 500 | D6: Ratio (fund ÷ S&P)
A7: ISRG | B7: 0.0844 | C7: 0.002 | D7: =IF(C7>0,B7/C7,"") -> 42.2
A8: NVDA | B8: 0.0797 | C8: 0.0773 | D8: =IF(C8>0,B8/C8,"") -> 1.0310479
A9: TSLA | B9: 0.0207 | C9: 0.0208 | D9: =IF(C9>0,B9/C9,"") -> 0.99519231
A10: GOOGL | B10: 0.0203 | C10: 0.0316 | D10: =IF(C10>0,B10/C10,"") -> 0.64240506
A11: DE | B11: 0.0196 | C11: 0.0026 | D11: =IF(C11>0,B11/C11,"") -> 7.5384615
A12: ROK | B12: 0.0104 | C12: 0.0007 | D12: =IF(C12>0,B12/C12,"") -> 14.857143
A13: Total (shared names) | B13: =SUM(B7:B12) -> 0.2351 | C13: =SUM(C7:C12) -> 0.135

Sheet Notes
A1: BOTZ: Global X Robotics & Artificial Intelligence ETF, constituents, weights, trailing P/E and fund history
A2: Holdings and weights: Global X's daily full-holdings file (assets.globalxetfs.com). Cash and currency lines are removed and weights rescaled to 100%. BOTZ tracks the Indxx Global Robotics & Artificial Intelligence Thematic Index: about 80 companies worldwide, roughly 40% Japanese, cap-weighted with caps. Local tickers (e.g. 6954 = Fanuc, 6861 = Keyence) are Global X's; the Yahoo symbol is in the Notes column where fundamentals were found. As of Sep 22, 2026.
A3: P/E (TTM), EPS (TTM), Market Cap, Price/Sales, Price, Company name, GICS sector and Sub-Industry: Yahoo Finance via the yfinance library, retrieved Sept 23, 2026. Yahoo's sectors are mapped to GICS sector names; Yahoo's industry label stands in for the GICS sub-industry.
A4: Revenue TTM ($B) is derived as Market Cap / Price-to-Sales, so it is approximate. Blank where either input is missing.
A5: About half the fund is non-US industrial automation (Keyence, Fanuc, SMC, Daifuku, ABB) and the rest US names led by Intuitive Surgical and Nvidia. Local-currency prices and market caps are left blank rather than converted. The Sectors tab average excludes blanks and P/Es above 100.
A6: Cumulative Weight assumes the default sort by rank; after re-sorting it shows the running weight in the new order.
A7: Overlap tab: every holding whose ticker also appears in the companion S&P 500 workbook, with its weight in each. 'Ratio' shows how many times more concentrated the name is here than in the index.
A8: For information only; not investment advice.
A10: Historical tabs 'Annual Returns' (2017-2025) and 'By Decade': the fund launched September 13, 2016, so returns are the fund's own, from Yahoo Finance daily prices. Price Return uses closing prices on the last trading day of each year; Total Return uses dividend-adjusted closes (distributions reinvested). S&P 500 total return (SPY, dividend-adjusted) is shown alongside for the same years. The launch year is a stub and is excluded; 2026 is incomplete and excluded.
A11: Real returns use December-over-December US CPI-U (NSA) from the BLS (series CUUR0000SA0).
A12: Fees: the fund's expense ratio is 0.68%; returns above are net of it. The index funds in the companion workbooks charge 0.03% to 0.05%.

Sheet Annual Returns
A1: Year | B1: Decade | C1: Price Return | D1: Total Return (w/ dividends) | E1: Real Price Return (inflation-adj.) | F1: Real Total Return (inflation-adj.) | G1: Up / Down (Total Return) | H1: Growth of $1 (Total Return) | I1: Growth of $1 (Price only) | J1: S&P 500 Total Return (SPY, comparison)
A2: 2017 | B2: =INT(A2/10)*10&"s" -> 2010s | C2: 0.58 | D2: 0.5801 | E2: 0.5474 | F2: 0.5475 | G2: =IF(D2>=0,"Up","Down") -> Up | H2: =1+D2 -> 1.5801 | I2: =1+C2 -> 1.58 | J2: 0.2171
A3: 2018 | B3: =INT(A3/10)*10&"s" -> 2010s | C3: -0.2937 | D3: -0.2834 | E3: -0.3069 | F3: -0.2969 | G3: =IF(D3>=0,"Up","Down") -> Down | H3: =H2*(1+D3) -> 1.1322997 | I3: =I2*(1+C3) -> 1.115954 | J3: -0.0457
A4: 2019 | B4: =INT(A4/10)*10&"s" -> 2010s | C4: 0.3065 | D4: 0.318 | E4: 0.2773 | F4: 0.2886 | G4: =IF(D4>=0,"Up","Down") -> Up | H4: =H3*(1+D4) -> 1.492371 | I4: =I3*(1+C4) -> 1.4579939 | J4: 0.3122
A5: 2020 | B5: =INT(A5/10)*10&"s" -> 2020s | C5: 0.5151 | D5: 0.5192 | E5: 0.4947 | F5: 0.4988 | G5: =IF(D5>=0,"Up","Down") -> Up | H5: =H4*(1+D5) -> 2.26721 | I5: =I4*(1+C5) -> 2.2090066 | J5: 0.1833
A6: 2021 | B6: =INT(A6/10)*10&"s" -> 2020s | C6: 0.0847 | D6: 0.0865 | E6: 0.0134 | F6: 0.015 | G6: =IF(D6>=0,"Up","Down") -> Up | H6: =H5*(1+D6) -> 2.4633236 | I6: =I5*(1+C6) -> 2.3961094 | J6: 0.2873
A7: 2022 | B7: =INT(A7/10)*10&"s" -> 2020s | C7: -0.4282 | D7: -0.4269 | E7: -0.4629 | F7: -0.4617 | G7: =IF(D7>=0,"Up","Down") -> Down | H7: =H6*(1+D7) -> 1.4117308 | I7: =I6*(1+C7) -> 1.3700954 | J7: -0.1818
A8: 2023 | B8: =INT(A8/10)*10&"s" -> 2020s | C8: 0.3869 | D8: 0.3896 | E8: 0.3419 | F8: 0.3446 | G8: =IF(D8>=0,"Up","Down") -> Up | H8: =H7*(1+D8) -> 1.9617411 | I8: =I7*(1+C8) -> 1.9001853 | J8: 0.2618
A9: 2024 | B9: =INT(A9/10)*10&"s" -> 2020s | C9: 0.1211 | D9: 0.1226 | E9: 0.0896 | F9: 0.0911 | G9: =IF(D9>=0,"Up","Down") -> Up | H9: =H8*(1+D9) -> 2.2022505 | I9: =I8*(1+C9) -> 2.1302977 | J9: 0.2489
A10: 2025 | B10: =INT(A10/10)*10&"s" -> 2020s | C10: 0.134 | D10: 0.1416 | E10: 0.1044 | F10: 0.1119 | G10: =IF(D10>=0,"Up","Down") -> Up | H10: =H9*(1+D10) -> 2.5140892 | I10: =I9*(1+C10) -> 2.4157576 | J10: 0.1772
A12: Summary
A13: Years | C13: =COUNT(A2:A10) -> 9
A14: Up years | C14: =COUNTIF(D2:D10,">=0") -> 7
A15: Down years | C15: =COUNTIF(D2:D10,"<0") -> 2
A16: Average annual total return | C16: =AVERAGE(D2:D10) -> 0.16081111
A17: Annualized (CAGR) total return | C17: =(H10)^(1/COUNT(A2:A10))-1 -> 0.10786475
A18: Average annual real total return | C18: =AVERAGE(F2:F10) -> 0.12654444
A19: Best year (total) | C19: =MAX(D2:D10) -> 0.5801
A20: Worst year (total) | C20: =MIN(D2:D10) -> -0.4269
A21: Standard deviation of annual returns | C21: =STDEV(D2:D10) -> 0.34120698
A22: $1 grew to (total, 2017-2025) | C22: =H10 -> 2.5140892
A23: S&P 500 (SPY) average annual total return | C23: =AVERAGE(J2:J10) -> 0.16225556
A24: S&P 500 (SPY) CAGR, same years | C24: =EXP(SUMPRODUCT(LN(1+J2:J10)))^(1/COUNT(J2:J10))-1 -> 0.15021574
A25: S&P 500 (SPY) $1 grew to | C25: =EXP(SUMPRODUCT(LN(1+J2:J10))) -> 3.5238204
A26: S&P 500 (SPY) standard deviation | C26: =STDEV(J2:J10) -> 0.16614364
A28: Fund returns from Yahoo Finance daily data (last trading day of each year). Total return reinvests distributions. Real returns are CPI-adjusted. 'Average' is the simple mean; 'Annualized / CAGR' is the compound rate actually earned.
A29: 2016 (launch year, partial) and 2026 (incomplete) are excluded. See the Notes tab.

Sheet By Decade
A1: Decade | B1: Years Covered | C1: # of Years | D1: Up Years | E1: Down Years | F1: Avg Annual Total Return | G1: Annualized (CAGR) Total Return | H1: Cumulative Total Return | I1: Avg Annual Price Return | J1: Annualized (CAGR) Price Return | K1: Avg Annual Real Total Return | L1: Best Year (Total) | M1: Worst Year (Total) | N1: $1 Grew To (Total) | O1: S&P 500 (SPY) CAGR, same years
A2: 2010s | B2: 2017–2019 (partial) | C2: =COUNTIF('Annual Returns'!$B$2:$B$10,"2010s") -> 3 | D2: =COUNTIFS('Annual Returns'!$B$2:$B$10,"2010s",'Annual Returns'!$D$2:$D$10,">=0") -> 2 | E2: =COUNTIFS('Annual Returns'!$B$2:$B$10,"2010s",'Annual Returns'!$D$2:$D$10,"<0") -> 1 | F2: =AVERAGEIF('Annual Returns'!$B$2:$B$10,"2010s",'Annual Returns'!$D$2:$D$10) -> 0.2049 | G2: =(1+H2)^(1/C2)-1 -> 0.14277026 | H2: =EXP(SUMPRODUCT(('Annual Returns'!$B$2:$B$10="2010s")*LN(1+'Annual Returns'!$D$2:$D$10)))-1 -> 0.49237095 | I2: =AVERAGEIF('Annual Returns'!$B$2:$B$10,"2010s",'Annual Returns'!$C$2:$C$10) -> 0.1976 | J2: =(EXP(SUMPRODUCT(('Annual Returns'!$B$2:$B$10="2010s")*LN(1+'Annual Returns'!$C$2:$C$10))))^(1/C2)-1 -> 0.13392736 | K2: =AVERAGEIF('Annual Returns'!$B$2:$B$10,"2010s",'Annual Returns'!$F$2:$F$10) -> 0.17973333 | L2: =_xlfn.MAXIFS('Annual Returns'!$D$2:$D$10,'Annual Returns'!$B$2:$B$10,"2010s") -> 0.5801 | M2: =_xlfn.MINIFS('Annual Returns'!$D$2:$D$10,'Annual Returns'!$B$2:$B$10,"2010s") -> -0.2834 | N2: =1+H2 -> 1.492371 | O2: =(EXP(SUMPRODUCT(('Annual Returns'!$B$2:$B$10="2010s")*LN(1+'Annual Returns'!$J$2:$J$10))))^(1/C2)-1 -> 0.1508103
A3: 2020s | B3: 2020–2025 (partial) | C3: =COUNTIF('Annual Returns'!$B$2:$B$10,"2020s") -> 6 | D3: =COUNTIFS('Annual Returns'!$B$2:$B$10,"2020s",'Annual Returns'!$D$2:$D$10,">=0") -> 5 | E3: =COUNTIFS('Annual Returns'!$B$2:$B$10,"2020s",'Annual Returns'!$D$2:$D$10,"<0") -> 1 | F3: =AVERAGEIF('Annual Returns'!$B$2:$B$10,"2020s",'Annual Returns'!$D$2:$D$10) -> 0.13876667 | G3: =(1+H3)^(1/C3)-1 -> 0.090813864 | H3: =EXP(SUMPRODUCT(('Annual Returns'!$B$2:$B$10="2020s")*LN(1+'Annual Returns'!$D$2:$D$10)))-1 -> 0.68462753 | I3: =AVERAGEIF('Annual Returns'!$B$2:$B$10,"2020s",'Annual Returns'!$C$2:$C$10) -> 0.1356 | J3: =(EXP(SUMPRODUCT(('Annual Returns'!$B$2:$B$10="2020s")*LN(1+'Annual Returns'!$C$2:$C$10))))^(1/C3)-1 -> 0.087801385 | K3: =AVERAGEIF('Annual Returns'!$B$2:$B$10,"2020s",'Annual Returns'!$F$2:$F$10) -> 0.09995 | L3: =_xlfn.MAXIFS('Annual Returns'!$D$2:$D$10,'Annual Returns'!$B$2:$B$10,"2020s") -> 0.5192 | M3: =_xlfn.MINIFS('Annual Returns'!$D$2:$D$10,'Annual Returns'!$B$2:$B$10,"2020s") -> -0.4269 | N3: =1+H3 -> 1.6846275 | O3: =(EXP(SUMPRODUCT(('Annual Returns'!$B$2:$B$10="2020s")*LN(1+'Annual Returns'!$J$2:$J$10))))^(1/C3)-1 -> 0.14991858
A4: All years | B4: 2017–2025 | C4: =COUNT('Annual Returns'!$A$2:$A$10) -> 9 | D4: =COUNTIF('Annual Returns'!$D$2:$D$10,">=0") -> 7 | E4: =COUNTIF('Annual Returns'!$D$2:$D$10,"<0") -> 2 | F4: =AVERAGE('Annual Returns'!$D$2:$D$10) -> 0.16081111 | G4: =(1+H4)^(1/C4)-1 -> 0.10786475 | H4: =EXP(SUMPRODUCT(LN(1+'Annual Returns'!$D$2:$D$10)))-1 -> 1.5140892 | I4: =AVERAGE('Annual Returns'!$C$2:$C$10) -> 0.15626667 | J4: =(EXP(SUMPRODUCT(LN(1+'Annual Returns'!$C$2:$C$10))))^(1/C4)-1 -> 0.10296437 | K4: =AVERAGE('Annual Returns'!$F$2:$F$10) -> 0.12654444 | L4: =MAX('Annual Returns'!$D$2:$D$10) -> 0.5801 | M4: =MIN('Annual Returns'!$D$2:$D$10) -> -0.4269 | N4: =1+H4 -> 2.5140892 | O4: =(EXP(SUMPRODUCT(LN(1+'Annual Returns'!$J$2:$J$10))))^(1/C4)-1 -> 0.15021574
A7: Decades are calendar decades; partial decades are marked.
A8: Avg Annual = simple average of the yearly returns. Annualized (CAGR) = the compound rate that turns the starting dollar into the ending dollar.
A9: All figures pull live from the 'Annual Returns' tab. Source and methodology: see the Notes tab.
