Workbook

Sheet Basket
A1: Rank | B1: Ticker (Yahoo) | C1: Company | D1: Category | E1: Role | F1: Suggested weight of sleeve | G1: Cumulative | H1: Exchange | I1: US ADR / OTC alternative | J1: P/E (TTM) | K1: EPS (TTM) | L1: Mkt Cap ($B, USD listings) | M1: Price/Sales | N1: In S&P 500? (index wt) | O1: Weight in ARKQ | P1: Weight in BOTZ | Q1: Notes
A2: 1 | B2: NVDA | C2: NVIDIA Corporation | D2: Vision & AI enablers | E2: GPUs and the software stack every robot and AV runs on | F2: 0.06 | G2: =SUM($F$2:F2) -> 0.06 | H2: NASDAQ | J2: 28.47 | K2: 7.92 | L2: 5445.4 | M2: 17.97 | N2: yes (7.73%) | O2: 0.049764694 | P2: 0.079654028
A3: 2 | B3: TSLA | C3: Tesla, Inc. | D3: Autonomous vehicles & physical AI | E3: FSD, robotaxi, Optimus humanoid | F3: 0.06 | G3: =SUM($F$2:F3) -> 0.12 | H3: NASDAQ | J3: 345.56 | K3: 1.1 | L3: 1501.3 | M3: 14.49 | N3: yes (2.08%) | O3: 0.10794032 | P3: 0.020718093 | Q3: P/E reflects near-zero earnings
A4: 3 | B4: GOOGL | C4: Alphabet Inc. | D4: Autonomous vehicles & physical AI | E4: Waymo, the only scaled robotaxi; Gemini robotics models | F4: 0.06 | G4: =SUM($F$2:F4) -> 0.18 | H4: NASDAQ | J4: 16.93 | K4: 19.95 | L4: 4131.6 | M4: 9.27 | N4: yes (3.16%) | O4: 0.0028036447 | P4: 0.0203158
A5: 4 | B5: ISRG | C5: Intuitive Surgical, Inc. | D5: Surgical robotics | E5: da Vinci; ~10,000 systems installed | F5: 0.06 | G5: =SUM($F$2:F5) -> 0.24 | H5: NASDAQ | J5: 45.62 | K5: 8.73 | L5: 142.7 | M5: 12.93 | N5: yes (0.20%) | O5: 0.013517573 | P5: 0.084380972
A6: 5 | B6: 6861.T | C6: Keyence Corporation | D6: Industrial robotics & machine vision | E6: Machine-vision sensors and controllers; ~50% operating margin | F6: 0.06 | G6: =SUM($F$2:F6) -> 0.3 | H6: Tokyo | I6: KYCCF (OTC) | J6: 42.04 | K6: 1837.92 | M6: 14.93 | N6: no | P6: 0.077642563 | Q6: Local listing in JPY; market cap not converted
A7: 6 | B7: 6954.T | C7: Fanuc Corporation | D7: Industrial robotics & machine vision | E7: Largest industrial-robot and CNC maker | F7: 0.06 | G7: =SUM($F$2:F7) -> 0.36 | H7: Tokyo | I7: FANUY (OTC) | J7: 33.69 | K7: 178.49 | M7: 6.26 | N7: no | P7: 0.080559187 | Q7: Local listing in JPY; market cap not converted
A8: 7 | B8: ABBN.SW | C8: ABB Ltd | D8: Industrial robotics & machine vision | E8: Robotics & discrete automation, electrification | F8: 0.04 | G8: =SUM($F$2:F8) -> 0.4 | H8: Zurich | I8: ABBNY (OTC) | J8: 36.79 | K8: 2.24 | M8: 4.17 | N8: no | P8: 0.082972946 | Q8: Local listing in CHF; market cap not converted
A9: 8 | B9: 6273.T | C9: SMC Corporation | D9: Industrial robotics & machine vision | E9: Pneumatic components in nearly every factory robot cell | F9: 0.04 | G9: =SUM($F$2:F9) -> 0.44 | H9: Tokyo | I9: SMCAY (OTC) | J9: 25.75 | K9: 2639.93 | M9: 4.65 | N9: no | P9: 0.044453384 | Q9: Local listing in JPY; market cap not converted
A10: 9 | B10: TSM | C10: Taiwan Semiconductor Manufacturing Company Limited | D10: Vision & AI enablers | E10: Makes the chips for Nvidia, AMD, Tesla, Horizon | F10: 0.04 | G10: =SUM($F$2:F10) -> 0.48 | H10: NYSE (ADR) | J10: 33.23 | K10: 13.44 | L10: 2316.2 | M10: 0.52 | N10: no | O10: 0.036547512
A11: 10 | B11: AMZN | C11: Amazon.com, Inc. | D11: Autonomous vehicles & physical AI | E11: Kiva/Proteus warehouse robots (750k+), Zoox robotaxi | F11: 0.04 | G11: =SUM($F$2:F11) -> 0.52 | H11: NASDAQ | J11: 20.68 | K11: 12.43 | L11: 2772.8 | M11: 3.57 | N11: yes (3.94%) | O11: 0.034845299
A12: 11 | B12: DE | C12: Deere & Company | D12: Autonomous vehicles & physical AI | E12: Autonomous tractors, See & Spray vision | F12: 0.04 | G12: =SUM($F$2:F12) -> 0.56 | H12: NYSE | J12: 39.42 | K12: 18 | L12: 191.3 | M12: 3.99 | N12: yes (0.26%) | O12: 0.028837489 | P12: 0.019611787
A13: 12 | B13: TER | C13: Teradyne, Inc. | D13: Industrial robotics & machine vision | E13: Universal Robots cobots, MiR mobile robots, chip test | F13: 0.04 | G13: =SUM($F$2:F13) -> 0.6 | H13: NASDAQ | J13: 52.98 | K13: 7.28 | L13: 60.3 | M13: 13.51 | N13: yes (0.08%) | O13: 0.063182137
A14: 13 | B14: SPCX | C14: Space Exploration Technologies Corp. | D14: Space, defense & aerial autonomy | E14: SpaceX: reusable launch, Starlink, Starship (confirm ticker; MOSE notes say it may be SPCK) | F14: 0.04 | G14: =SUM($F$2:F14) -> 0.64 | H14: verify listing | K14: -1.1 | L14: 2017.2 | M14: 87.54 | N14: no | O14: 0.081505958 | Q14: Negative trailing EPS; Confirm the listing and ticker before buying
A15: 14 | B15: AMD | C15: Advanced Micro Devices, Inc. | D15: Vision & AI enablers | E15: Second-source AI compute; Xilinx adaptive chips in vision systems | F15: 0.04 | G15: =SUM($F$2:F15) -> 0.68 | H15: NASDAQ | J15: 157.32 | K15: 3.94 | L15: 1011.9 | M15: 24.5 | N15: yes (1.34%) | O15: 0.048863523
A16: 15 | B16: ROK | C16: Rockwell Automation, Inc. | D16: Industrial robotics & machine vision | E16: Factory automation software and controls (US) | F16: 0.03 | G16: =SUM($F$2:F16) -> 0.71 | H16: NYSE | J16: 40.53 | K16: 10.68 | L16: 48.2 | M16: 5.37 | N16: yes (0.07%) | P16: 0.010359047
A17: 16 | B17: CGNX | C17: Cognex Corporation | D17: Industrial robotics & machine vision | E17: Machine vision cameras and software for robot guidance | F17: 0.03 | G17: =SUM($F$2:F17) -> 0.74 | H17: NASDAQ | J17: 55.95 | K17: 1.04 | L17: 9.8 | M17: 8.99 | N17: no | P17: 0.02494217
A18: 17 | B18: 6506.T | C18: YASKAWA Electric Corporation | D18: Industrial robotics & machine vision | E18: Motoman robots, servo motors | F18: 0.03 | G18: =SUM($F$2:F18) -> 0.77 | H18: Tokyo | I18: YASKY (OTC) | J18: 32.97 | K18: 135.87 | M18: 2.09 | N18: no | P18: 0.018606055 | Q18: Local listing in JPY; market cap not converted
A19: 18 | B19: 6383.T | C19: Daifuku Co., Ltd. | D19: Industrial robotics & machine vision | E19: Warehouse and airport automation systems | F19: 0.03 | G19: =SUM($F$2:F19) -> 0.8 | H19: Tokyo | I19: DFKCY (OTC) | J19: 25.53 | K19: 216.87 | M19: 2.98 | N19: no | P19: 0.032887459 | Q19: Local listing in JPY; market cap not converted
A20: 19 | B20: KTOS | C20: Kratos Defense & Security Solutions, Inc. | D20: Space, defense & aerial autonomy | E20: Unmanned combat jets (Valkyrie), target drones | F20: 0.03 | G20: =SUM($F$2:F20) -> 0.83 | H20: NASDAQ | J20: 274.72 | K20: 0.17 | L20: 8.8 | M20: 5.76 | N20: no | O20: 0.055572244
A21: 20 | B21: RKLB | C21: Rocket Lab Corporation | D21: Space, defense & aerial autonomy | E21: Electron/Neutron launch, satellite components | F21: 0.03 | G21: =SUM($F$2:F21) -> 0.86 | H21: NASDAQ | K21: -0.27 | L21: 45.6 | M21: 59.33 | N21: no | Q21: Negative trailing EPS
A22: 21 | B22: PLTR | C22: Palantir Technologies Inc. | D22: Vision & AI enablers | E22: AI integration layer for defense and industry | F22: 0.03 | G22: =SUM($F$2:F22) -> 0.89 | H22: NASDAQ | J22: 156.97 | K22: 1.17 | L22: 441.3 | M22: 71.69 | N22: yes (0.61%) | O22: 0.046360268
A23: 22 | B23: AVAV | C23: AeroVironment, Inc. | D23: Space, defense & aerial autonomy | E23: Small military drones and loitering munitions | F23: 0.0275 | G23: =SUM($F$2:F23) -> 0.9175 | H23: NASDAQ | K23: -4.05 | L23: 7.9 | M23: 3.96 | N23: no | O23: 0.028036447 | Q23: Negative trailing EPS
A24: 23 | B24: ACHR | C24: Archer Aviation Inc. | D24: Space, defense & aerial autonomy | E24: eVTOL air taxi; pre-revenue | F24: 0.0275 | G24: =SUM($F$2:F24) -> 0.945 | H24: NYSE | K24: -1.08 | L24: 4.3 | M24: 621.68 | N24: no | O24: 0.024732152 | Q24: Negative trailing EPS
A25: 24 | B25: AUR | C25: Aurora Innovation, Inc. | D25: Autonomous vehicles & physical AI | E25: Driverless trucking; pre-profit | F25: 0.0275 | G25: =SUM($F$2:F25) -> 0.9725 | H25: NASDAQ | K25: -0.46 | L25: 12.7 | M25: 2533.25 | N25: no | O25: 0.016821868 | P25: 0.027758222 | Q25: Negative trailing EPS
A26: 25 | B26: SYM | C26: Symbotic Inc. | D26: Industrial robotics & machine vision | E26: Warehouse robotics for Walmart; pre-profit | F26: 0.0275 | G26: =SUM($F$2:F26) -> 1 | H26: NASDAQ | J26: 1107.25 | K26: 0.04 | L26: 26.8 | M26: 10.13 | N26: no | P26: 0.014683697 | Q26: P/E reflects near-zero earnings
E27: Total | F27: =SUM(F2:F26) -> 1

Sheet Categories
A1: Category | B1: Weight of sleeve | C1: # of names | D1: Names
A2: Autonomous vehicles & physical AI | B2: =SUMIF(Basket!$D$2:$D$26,A2,Basket!$F$2:$F$26) -> 0.2275 | C2: =COUNTIF(Basket!$D$2:$D$26,A2) -> 5 | D2: TSLA, GOOGL, AMZN, DE, AUR
A3: Industrial robotics & machine vision | B3: =SUMIF(Basket!$D$2:$D$26,A3,Basket!$F$2:$F$26) -> 0.3875 | C3: =COUNTIF(Basket!$D$2:$D$26,A3) -> 10 | D3: 6861.T, 6954.T, ABBN.SW, 6273.T, TER, ROK, CGNX, 6506.T, 6383.T, SYM
A4: Space, defense & aerial autonomy | B4: =SUMIF(Basket!$D$2:$D$26,A4,Basket!$F$2:$F$26) -> 0.155 | C4: =COUNTIF(Basket!$D$2:$D$26,A4) -> 5 | D4: SPCX, KTOS, RKLB, AVAV, ACHR
A5: Surgical robotics | B5: =SUMIF(Basket!$D$2:$D$26,A5,Basket!$F$2:$F$26) -> 0.06 | C5: =COUNTIF(Basket!$D$2:$D$26,A5) -> 1 | D5: ISRG
A6: Vision & AI enablers | B6: =SUMIF(Basket!$D$2:$D$26,A6,Basket!$F$2:$F$26) -> 0.17 | C6: =COUNTIF(Basket!$D$2:$D$26,A6) -> 4 | D6: NVDA, TSM, AMD, PLTR
A7: Total | B7: =SUM(B2:B6) -> 1 | C7: =SUM(C2:C6) -> 25

Sheet Overlap vs S&P 500
A1: Basket names that are S&P 500 members
A2: 10 of 25 names
A3: Share of the basket (by suggested weight) inside the S&P 500 | B3: 0.46
A4: Share of the S&P 500 those names represent | B4: 0.1947
A6: Ticker | B6: Basket weight | C6: S&P 500 weight | D6: Ratio
A7: NVDA | B7: 0.06 | C7: 0.0773 | D7: =IF(C7>0,B7/C7,"") -> 0.77619664
A8: TSLA | B8: 0.06 | C8: 0.0208 | D8: =IF(C8>0,B8/C8,"") -> 2.8846154
A9: GOOGL | B9: 0.06 | C9: 0.0316 | D9: =IF(C9>0,B9/C9,"") -> 1.8987342
A10: ISRG | B10: 0.06 | C10: 0.002 | D10: =IF(C10>0,B10/C10,"") -> 30
A11: AMZN | B11: 0.04 | C11: 0.0394 | D11: =IF(C11>0,B11/C11,"") -> 1.0152284
A12: DE | B12: 0.04 | C12: 0.0026 | D12: =IF(C12>0,B12/C12,"") -> 15.384615
A13: TER | B13: 0.04 | C13: 0.0008 | D13: =IF(C13>0,B13/C13,"") -> 50
A14: AMD | B14: 0.04 | C14: 0.0134 | D14: =IF(C14>0,B14/C14,"") -> 2.9850746
A15: ROK | B15: 0.03 | C15: 0.0007 | D15: =IF(C15>0,B15/C15,"") -> 42.857143
A16: PLTR | B16: 0.03 | C16: 0.0061 | D16: =IF(C16>0,B16/C16,"") -> 4.9180328

Sheet Notes
A1: Robotics, autonomy and physical-AI basket: 25 stocks drawn from the ARKQ and BOTZ holdings, to be bought directly instead of through the funds
A2: How the 25 were chosen (Sept 24, 2026): start from the union of ARKQ's 37 and BOTZ's 80 holdings (105 companies); keep the names that (a) are the largest and most established in their category, (b) have a robotics, autonomy or machine-vision business that is central rather than incidental, and (c) cover five roles: industrial robotics and machine vision, autonomous vehicles and physical AI, space/defense/aerial autonomy, surgical robotics, and the vision/AI enablers that supply all of them. Weights are tiered by conviction and size: 6% / 4% / 3% / 2.75% of the sleeve.
A3: What this replaces: the 20% robotics slot in the 60/20/10/10 plan (or the 10% ARKQ + 10% BOTZ alternative). Buying the names directly saves the funds' 0.68% to 0.75% a year, gives control over which names and how much, and lets Joe harvest losses lot by lot. It gives up ARK's active trading and the funds' automatic rebalancing, and it requires buying six Tokyo and Zurich listings.
A4: Foreign listings: Keyence, Fanuc, SMC, Yaskawa and Daifuku trade in Tokyo; ABB trades in Zurich. IBKR can buy all six directly in local currency (recommended: full liquidity, and the foreign tax credit applies in a taxable account). The OTC ADR alternatives in column I are thinly traded and priced off the home market; use them only if direct access is not available.
A5: Compared with the funds: this basket is more concentrated in profitable large companies (Keyence, Fanuc, ABB, SMC, Nvidia, Alphabet, Intuitive) and lighter in early-stage names than ARKQ. It deliberately omits the Chinese and Korean robotics names in BOTZ (Inovance, Horizon, Ubtech, Rainbow, Doosan), the nuclear names in ARKQ (Oklo, X-Energy, BWXT, Cameco), and DoorDash, L3Harris, Caterpillar and Komatsu, which are not robotics businesses at the core. Add or drop to taste; the weights renormalize on the Basket tab.
A6: Fundamentals: Yahoo Finance via yfinance, Sept 24, 2026. Local-currency market caps are blanked. P/E is blank where trailing EPS is negative (Aurora, Archer, Symbotic, Rocket Lab, AeroVironment, SpaceX).
A7: SpaceX: ARK carries it as SPCX. Confirm the public listing and ticker before buying; MOSE's notes say the ticker may have become SPCK.
A8: Overlap tab: names that also sit in the S&P 500, with weights in each. Roughly half the basket by weight is S&P members, the same as ARKQ; that is the nature of the theme, since the largest robotics and AI companies are index constituents.
A9: For information only; not investment advice.
