Workbook

Sheet Holdings
A1: Rank | B1: Ticker | C1: Company | D1: GICS Sector | E1: Sub-Industry | F1: Weight | G1: Cumulative Weight | H1: Price ($) | I1: P/E (TTM) | J1: EPS (TTM) | K1: Mkt Cap ($B) | L1: Price/Sales | M1: Revenue TTM ($B) | N1: Notes
A2: 1 | B2: TWLO | C2: Twilio Inc. | D2: Information Technology | E2: Software - Infrastructure | F2: 0.008014 | G2: =SUM($F$2:F2) -> 0.008014 | H2: 266.06 | I2: 36.7486 | J2: 7.24 | K2: 40.8602 | L2: 7.3327 | M2: =IF(AND(N(K2)>0,N(L2)>0),K2/L2,"") -> 5.5723267
A3: 2 | B3: OKTA | C3: Okta, Inc. | D3: Information Technology | E3: Software - Infrastructure | F3: 0.006173 | G3: =SUM($F$2:F3) -> 0.014187 | H3: 191.33 | I3: 115.259 | J3: 1.66 | K3: 33.4485 | L3: 10.8846 | M3: =IF(AND(N(K3)>0,N(L3)>0),K3/L3,"") -> 3.0730114
A4: 3 | B4: NVT | C4: nVent Electric plc | D4: Industrials | E4: Electrical Equipment & Parts | F4: 0.005159 | G4: =SUM($F$2:F4) -> 0.019346 | H4: 159.44 | I4: 44.2889 | J4: 3.6 | K4: 25.8066 | L4: 5.3386 | M4: =IF(AND(N(K4)>0,N(L4)>0),K4/L4,"") -> 4.833964
A5: 4 | B5: FTI | C5: TechnipFMC plc | D5: Energy | E5: Oil & Gas Equipment & Services | F5: 0.005113 | G5: =SUM($F$2:F5) -> 0.024459 | H5: 71.31 | I5: 24.9336 | J5: 2.86 | K5: 27.9652 | L5: 2.6838 | M5: =IF(AND(N(K5)>0,N(L5)>0),K5/L5,"") -> 10.420001
A6: 5 | B6: ATI | C6: ATI Inc. | D6: Industrials | E6: Metal Fabrication | F6: 0.004943 | G6: =SUM($F$2:F6) -> 0.029402 | H6: 189.16 | I6: 55.6353 | J6: 3.4 | K6: 25.758 | L6: 5.4628 | M6: =IF(AND(N(K6)>0,N(L6)>0),K6/L6,"") -> 4.7151644
A7: 6 | B7: UTHR | C7: United Therapeutics Corporation | D7: Health Care | E7: Drug Manufacturers - Specialty & Generic | F7: 0.004403 | G7: =SUM($F$2:F7) -> 0.033805 | H7: 493.1 | I7: 17.6738 | J7: 27.9 | K7: 21.1494 | L7: 6.7045 | M7: =IF(AND(N(K7)>0,N(L7)>0),K7/L7,"") -> 3.1545082
A8: 7 | B8: SNX | C8: TD SYNNEX Corporation | D8: Information Technology | E8: Electronics & Computer Distribution | F8: 0.004301 | G8: =SUM($F$2:F8) -> 0.038106 | H8: 279.59 | I8: 20.0423 | J8: 13.95 | M8: =IF(AND(N(K8)>0,N(L8)>0),K8/L8,"")
A9: 8 | B9: CW | C9: Curtiss-Wright Corporation | D9: Industrials | E9: Aerospace & Defense | F9: 0.004295 | G9: =SUM($F$2:F9) -> 0.042401 | H9: 568.02 | I9: 39.066 | J9: 14.54 | K9: 20.9795 | L9: 5.7418 | M9: =IF(AND(N(K9)>0,N(L9)>0),K9/L9,"") -> 3.6538194
A10: 9 | B10: ENTG | C10: Entegris, Inc. | D10: Information Technology | E10: Semiconductor Equipment & Materials | F10: 0.004267 | G10: =SUM($F$2:F10) -> 0.046668 | H10: 143.14 | I10: 71.57 | J10: 2 | K10: 21.8718 | L10: 6.5758 | M10: =IF(AND(N(K10)>0,N(L10)>0),K10/L10,"") -> 3.3261048
A11: 10 | B11: THC | C11: Tenet Healthcare Corporation | D11: Health Care | E11: Medical Care Facilities | F11: 0.004146 | G11: =SUM($F$2:F11) -> 0.050814 | H11: 260.97 | I11: 10.0916 | J11: 25.86 | K11: 21.013 | L11: 0.9634 | M11: =IF(AND(N(K11)>0,N(L11)>0),K11/L11,"") -> 21.811293
A12: 11 | B12: ROIV | C12: Roivant Sciences Ltd. | D12: Health Care | E12: Biotechnology | F12: 0.004071 | G12: =SUM($F$2:F12) -> 0.054885 | H12: 38.99 | J12: -0.47 | K12: 28.1634 | L12: 3739.1628 | M12: =IF(AND(N(K12)>0,N(L12)>0),K12/L12,"") -> 0.0075320069 | N12: Negative trailing EPS; P/E blank
A13: 12 | B13: XPO | C13: XPO, Inc. | D13: Industrials | E13: Trucking | F13: 0.004068 | G13: =SUM($F$2:F13) -> 0.058953 | H13: 174.34 | I13: 51.5799 | J13: 3.38 | K13: 20.4129 | L13: 2.3808 | M13: =IF(AND(N(K13)>0,N(L13)>0),K13/L13,"") -> 8.5739667
A14: 13 | B14: CRS | C14: Carpenter Technology Corporation | D14: Industrials | E14: Metal Fabrication | F14: 0.003967 | G14: =SUM($F$2:F14) -> 0.06292 | H14: 402.9 | I14: 38.2985 | J14: 10.52 | K14: 19.9671 | L14: 6.3911 | M14: =IF(AND(N(K14)>0,N(L14)>0),K14/L14,"") -> 3.124204
A15: 14 | B15: USFD | C15: US Foods Holding Corp. | D15: Consumer Staples | E15: Food Distribution | F15: 0.003956 | G15: =SUM($F$2:F15) -> 0.066876 | H15: 94.22 | I15: 28.9908 | J15: 3.25 | K15: 20.3827 | L15: 0.5079 | M15: =IF(AND(N(K15)>0,N(L15)>0),K15/L15,"") -> 40.131325
A16: 15 | B16: RGLD | C16: Royal Gold, Inc. | D16: Materials | E16: Gold | F16: 0.003937 | G16: =SUM($F$2:F16) -> 0.070813 | H16: 250.11 | I16: 27.6977 | J16: 9.03 | K16: 21.1913 | L16: 13.7993 | M16: =IF(AND(N(K16)>0,N(L16)>0),K16/L16,"") -> 1.5356793
A17: 16 | B17: ROKU | C17: Roku, Inc. | D17: Communication Services | E17: Entertainment | F17: 0.003914 | G17: =SUM($F$2:F17) -> 0.074727 | H17: 154.33 | I17: 65.1181 | J17: 2.37 | K17: 22.9196 | L17: 4.3999 | M17: =IF(AND(N(K17)>0,N(L17)>0),K17/L17,"") -> 5.2091184
A18: 17 | B18: CDE | C18: Coeur Mining, Inc. | D18: Materials | E18: Gold | F18: 0.003896 | G18: =SUM($F$2:F18) -> 0.078623 | H18: 19.52 | I18: 16.4034 | J18: 1.19 | K18: 20.0653 | L18: 6.3274 | M18: =IF(AND(N(K18)>0,N(L18)>0),K18/L18,"") -> 3.1711762
A19: 18 | B19: WWD | C19: Woodward, Inc. | D19: Industrials | E19: Aerospace & Defense | F19: 0.003788 | G19: =SUM($F$2:F19) -> 0.082411 | H19: 325.16 | I19: 36.2094 | J19: 8.98 | K19: 19.1993 | L19: 4.58 | M19: =IF(AND(N(K19)>0,N(L19)>0),K19/L19,"") -> 4.1919869
A20: 19 | B20: RS | C20: Reliance, Inc. | D20: Materials | E20: Steel | F20: 0.00371 | G20: =SUM($F$2:F20) -> 0.086121 | H20: 384.65 | I20: 22.3504 | J20: 17.21 | K20: 19.6381 | L20: 1.2425 | M20: =IF(AND(N(K20)>0,N(L20)>0),K20/L20,"") -> 15.805312
A21: 20 | B21: NTNX | C21: Nutanix, Inc. | D21: Information Technology | E21: Software - Infrastructure | F21: 0.003681 | G21: =SUM($F$2:F21) -> 0.089802 | H21: 70.04 | I21: 13.5474 | J21: 5.17 | K21: 18.9507 | L21: 6.6411 | M21: =IF(AND(N(K21)>0,N(L21)>0),K21/L21,"") -> 2.8535484
A22: 21 | B22: EWBC | C22: East West Bancorp, Inc. | D22: Financials | E22: Banks - Regional | F22: 0.003611 | G22: =SUM($F$2:F22) -> 0.093413 | H22: 127.77 | I22: 12.2738 | J22: 10.41 | K22: 17.506 | L22: 6.0604 | M22: =IF(AND(N(K22)>0,N(L22)>0),K22/L22,"") -> 2.8885882
A23: 22 | B23: ITT | C23: ITT Inc. | D23: Industrials | E23: Specialty Industrial Machinery | F23: 0.003559 | G23: =SUM($F$2:F23) -> 0.096972 | H23: 205.68 | I23: 40.3294 | J23: 5.1 | M23: =IF(AND(N(K23)>0,N(L23)>0),K23/L23,"")
A24: 23 | B24: JLL | C24: Jones Lang LaSalle Incorporated | D24: Real Estate | E24: Real Estate Services | F24: 0.003361 | G24: =SUM($F$2:F24) -> 0.100333 | H24: 340.07 | I24: 16.3103 | J24: 20.85 | K24: 15.6458 | L24: 0.5703 | M24: =IF(AND(N(K24)>0,N(L24)>0),K24/L24,"") -> 27.434333
A25: 24 | B25: DINO | C25: HF Sinclair Corporation | D25: Energy | E25: Oil & Gas Refining & Marketing | F25: 0.003309 | G25: =SUM($F$2:F25) -> 0.103642 | H25: 109.29 | I25: 10.4185 | J25: 10.49 | K25: 19.43 | L25: 0.6222 | M25: =IF(AND(N(K25)>0,N(L25)>0),K25/L25,"") -> 31.227901
A26: 25 | B26: BURL | C26: Burlington Stores, Inc. | D26: Consumer Discretionary | E26: Apparel Retail | F26: 0.003224 | G26: =SUM($F$2:F26) -> 0.106866 | H26: 251.8 | I26: 22.6235 | J26: 11.13 | K26: 15.8169 | L26: 1.2956 | M26: =IF(AND(N(K26)>0,N(L26)>0),K26/L26,"") -> 12.208166
A27: 26 | B27: WCC | C27: WESCO International, Inc. | D27: Industrials | E27: Industrial Distribution | F27: 0.00321 | G27: =SUM($F$2:F27) -> 0.110076 | H27: 355.31 | I27: 24.5889 | J27: 14.45 | K27: 17.3153 | L27: 0.6923 | M27: =IF(AND(N(K27)>0,N(L27)>0),K27/L27,"") -> 25.011267
A28: 27 | B28: RGA | C28: Reinsurance Group of America, Incorporated | D28: Financials | E28: Insurance - Reinsurance | F28: 0.003191 | G28: =SUM($F$2:F28) -> 0.113267 | H28: 245.13 | I28: 10.7987 | J28: 22.7 | K28: 16.0074 | L28: 0.6164 | M28: =IF(AND(N(K28)>0,N(L28)>0),K28/L28,"") -> 25.969176
A29: 28 | B29: PR | C29: Permian Resources Corporation | D29: Energy | E29: Oil & Gas E&P | F29: 0.003176 | G29: =SUM($F$2:F29) -> 0.116443 | H29: 21.97 | I29: 14.1742 | J29: 1.55 | K29: 18.4011 | L29: 3.2073 | M29: =IF(AND(N(K29)>0,N(L29)>0),K29/L29,"") -> 5.7372556
A30: 29 | B30: LSCC | C30: Lattice Semiconductor Corporation | D30: Information Technology | E30: Semiconductors | F30: 0.003164 | G30: =SUM($F$2:F30) -> 0.119607 | H30: 117.24 | I30: 468.96 | J30: 0.25 | K30: 16.6516 | L30: 25.5739 | M30: =IF(AND(N(K30)>0,N(L30)>0),K30/L30,"") -> 0.65111696
A31: 30 | B31: STRL | C31: Sterling Infrastructure, Inc. | D31: Industrials | E31: Engineering & Construction | F31: 0.003116 | G31: =SUM($F$2:F31) -> 0.122723 | H31: 512.64 | I31: 36.8806 | J31: 13.9 | K31: 15.6809 | L31: 4.5604 | M31: =IF(AND(N(K31)>0,N(L31)>0),K31/L31,"") -> 3.4384922
A32: 31 | B32: LECO | C32: Lincoln Electric Holdings, Inc. | D32: Industrials | E32: Tools & Accessories | F32: 0.003088 | G32: =SUM($F$2:F32) -> 0.125811 | H32: 258.32 | I32: 25.8062 | J32: 10.01 | K32: 14.0799 | L32: 3.1421 | M32: =IF(AND(N(K32)>0,N(L32)>0),K32/L32,"") -> 4.4810477
A33: 32 | B33: OVV | C33: Ovintiv Inc. | D33: Energy | E33: Oil & Gas E&P | F33: 0.003062 | G33: =SUM($F$2:F33) -> 0.128873 | H33: 60.18 | I33: 16.8101 | J33: 3.58 | K33: 16.6458 | L33: 1.748 | M33: =IF(AND(N(K33)>0,N(L33)>0),K33/L33,"") -> 9.5227689
A34: 33 | B34: RBA | C34: RB Global, Inc. | D34: Industrials | E34: Specialty Business Services | F34: 0.003054 | G34: =SUM($F$2:F34) -> 0.131927 | H34: 83.7 | I34: 36.0776 | J34: 2.32 | K34: 15.5012 | L34: 3.1976 | M34: =IF(AND(N(K34)>0,N(L34)>0),K34/L34,"") -> 4.8477608
A35: 34 | B35: CLH | C35: Clean Harbors, Inc. | D35: Industrials | E35: Waste Management | F35: 0.003028 | G35: =SUM($F$2:F35) -> 0.134955 | H35: 311.43 | I35: 37.7949 | J35: 8.24 | K35: 16.4395 | L35: 2.633 | M35: =IF(AND(N(K35)>0,N(L35)>0),K35/L35,"") -> 6.2436384
... A53: 52 | B53: MLI | C53: Mueller Industries, Inc. | D53: Industrials | E53: Metal Fabrication | F53: 0.002713 | G53: =SUM($F$2:F53) -> 0.185728 | H53: 59.93 | I53: 15.6068 | J53: 3.84 | K53: 13.2554 | L53: 2.8438 | M53: =IF(AND(N(K53)>0,N(L53)>0),K53/L53,"") -> 4.6611576
A54: 53 | B54: APG | C54: APi Group Corporation | D54: Industrials | E54: Engineering & Construction | F54: 0.002702 | G54: =SUM($F$2:F54) -> 0.18843 | H54: 37.46 | J54: -0.61 | K54: 16.1887 | L54: 1.9185 | M54: =IF(AND(N(K54)>0,N(L54)>0),K54/L54,"") -> 8.4382069 | N54: Negative trailing EPS; P/E blank
A55: 54 | B55: TOST | C55: Toast, Inc. | D55: Information Technology | E55: Software - Infrastructure | F55: 0.0027 | G55: =SUM($F$2:F55) -> 0.19113 | H55: 29.8 | I55: 37.7215 | J55: 0.79 | K55: 17.2244 | L55: 2.5315 | M55: =IF(AND(N(K55)>0,N(L55)>0),K55/L55,"") -> 6.8040292
A56: 55 | B56: BWXT | C56: BWX Technologies, Inc. | D56: Industrials | E56: Aerospace & Defense | F56: 0.002693 | G56: =SUM($F$2:F56) -> 0.193823 | H56: 147.47 | I56: 38.2047 | J56: 3.86 | K56: 13.5115 | L56: 3.8451 | M56: =IF(AND(N(K56)>0,N(L56)>0),K56/L56,"") -> 3.5139528
A57: 56 | B57: TLN | C57: Talen Energy Corporation | D57: Utilities | E57: Utilities - Independent Power Producers | F57: 0.002685 | G57: =SUM($F$2:F57) -> 0.196508 | H57: 299.97 | J57: -4.03 | K57: 14.3728 | L57: 3.842 | M57: =IF(AND(N(K57)>0,N(L57)>0),K57/L57,"") -> 3.7409682 | N57: Negative trailing EPS; P/E blank
A58: 57 | B58: FIVE | C58: Five Below, Inc. | D58: Consumer Discretionary | E58: Specialty Retail | F58: 0.002642 | G58: =SUM($F$2:F58) -> 0.19915 | H58: 236.14 | I58: 21.1785 | J58: 11.15 | K58: 13.0005 | L58: 2.4465 | M58: =IF(AND(N(K58)>0,N(L58)>0),K58/L58,"") -> 5.3139178
A59: 58 | B59: CACI | C59: CACI International Inc | D59: Information Technology | E59: Information Technology Services | F59: 0.002627 | G59: =SUM($F$2:F59) -> 0.201777 | H59: 632.87 | I59: 26.1733 | J59: 24.18 | K59: 13.9862 | L59: 1.4618 | M59: =IF(AND(N(K59)>0,N(L59)>0),K59/L59,"") -> 9.5677931
A60: 59 | B60: SGI | C60: Somnigroup International Inc. | D60: Consumer Discretionary | E60: Furnishings, Fixtures & Appliances | F60: 0.002627 | G60: =SUM($F$2:F60) -> 0.204404 | H60: 63.36 | I60: 25.0435 | J60: 2.53 | K60: 13.3288 | L60: 1.7501 | M60: =IF(AND(N(K60)>0,N(L60)>0),K60/L60,"") -> 7.6160219
A61: 60 | B61: MANH | C61: Manhattan Associates, Inc. | D61: Information Technology | E61: Software - Application | F61: 0.002603 | G61: =SUM($F$2:F61) -> 0.207007 | H61: 209.35 | I61: 59.9857 | J61: 3.49 | K61: 12.2061 | L61: 10.8384 | M61: =IF(AND(N(K61)>0,N(L61)>0),K61/L61,"") -> 1.1261902
A62: 61 | B62: CCK | C62: Crown Holdings, Inc. | D62: Consumer Discretionary | E62: Packaging & Containers | F62: 0.002603 | G62: =SUM($F$2:F62) -> 0.20961 | H62: 108.73 | I62: 15.6446 | J62: 6.95 | K62: 11.8255 | L62: 0.8921 | M62: =IF(AND(N(K62)>0,N(L62)>0),K62/L62,"") -> 13.255801
A63: 62 | B63: RPM | C63: RPM International Inc. | D63: Materials | E63: Specialty Chemicals | F63: 0.002592 | G63: =SUM($F$2:F63) -> 0.212202 | H63: 99.01 | I63: 19.1509 | J63: 5.17 | K63: 12.6379 | L63: 1.6072 | M63: =IF(AND(N(K63)>0,N(L63)>0),K63/L63,"") -> 7.8633026
A64: 63 | B64: MTZ | C64: MasTec, Inc. | D64: Industrials | E64: Engineering & Construction | F64: 0.002588 | G64: =SUM($F$2:F64) -> 0.21479 | H64: 222.9 | I64: 35.4936 | J64: 6.28 | K64: 17.9 | L64: 1.1112 | M64: =IF(AND(N(K64)>0,N(L64)>0),K64/L64,"") -> 16.108711
A65: 64 | B65: LAMR | C65: Lamar Advertising Company | D65: Real Estate | E65: REIT - Specialty | F65: 0.002585 | G65: =SUM($F$2:F65) -> 0.217375 | H65: 146.08 | I65: 26.6569 | J65: 5.48 | K65: 14.8344 | L65: 6.377 | M65: =IF(AND(N(K65)>0,N(L65)>0),K65/L65,"") -> 2.3262349
A66: 65 | B66: AIT | C66: Applied Industrial Technologies, Inc. | D66: Industrials | E66: Industrial Distribution | F66: 0.002577 | G66: =SUM($F$2:F66) -> 0.219952 | H66: 320.39 | I66: 29.2861 | J66: 10.94 | K66: 11.7692 | L66: 2.3696 | M66: =IF(AND(N(K66)>0,N(L66)>0),K66/L66,"") -> 4.9667454
A67: 66 | B67: GGG | C67: Graco Inc. | D67: Industrials | E67: Specialty Industrial Machinery | F67: 0.00256 | G67: =SUM($F$2:F67) -> 0.222512 | H67: 76.59 | I67: 24.0849 | J67: 3.18 | K67: 12.404 | L67: 5.4711 | M67: =IF(AND(N(K67)>0,N(L67)>0),K67/L67,"") -> 2.2671858
A68: 67 | B68: TTMI | C68: TTM Technologies, Inc. | D68: Information Technology | E68: Electronic Components | F68: 0.002554 | G68: =SUM($F$2:F68) -> 0.225066 | H68: 124.02 | I68: 55.8649 | J68: 2.22 | K68: 13.0654 | L68: 3.8688 | M68: =IF(AND(N(K68)>0,N(L68)>0),K68/L68,"") -> 3.3771195
A69: 68 | B69: SUI | C69: Sun Communities, Inc. | D69: Real Estate | E69: REIT - Residential | F69: 0.00254 | G69: =SUM($F$2:F69) -> 0.227606 | H69: 113.74 | I69: 145.8205 | J69: 0.78 | K69: 14.3714 | L69: 6.1635 | M69: =IF(AND(N(K69)>0,N(L69)>0),K69/L69,"") -> 2.3316947
... A78: 77 | B78: HL | C78: Hecla Mining Company | D78: Materials | E78: Other Precious Metals & Mining | F78: 0.002378 | G78: =SUM($F$2:F78) -> 0.24946 | H78: 18.35 | I78: 22.1084 | J78: 0.83 | K78: 12.327 | L78: 7.0683 | M78: =IF(AND(N(K78)>0,N(L78)>0),K78/L78,"") -> 1.7439837
A79: 78 | B79: EQH | C79: Equitable Holdings, Inc. | D79: Financials | E79: Asset Management | F79: 0.002361 | G79: =SUM($F$2:F79) -> 0.251821 | H79: 53.87 | J79: -3.29 | K79: 14.6939 | L79: 1.3836 | M79: =IF(AND(N(K79)>0,N(L79)>0),K79/L79,"") -> 10.620049 | N79: Negative trailing EPS; P/E blank
A80: 79 | B80: SF | C80: Stifel Financial Corp. | D80: Financials | E80: Capital Markets | F80: 0.002361 | G80: =SUM($F$2:F80) -> 0.254182 | H80: 75.72 | I80: 13.5456 | J80: 5.59 | K80: 11.4339 | L80: 1.9597 | M80: =IF(AND(N(K80)>0,N(L80)>0),K80/L80,"") -> 5.8345155
A81: 80 | B81: FHN | C81: First Horizon Corporation | D81: Financials | E81: Banks - Regional | F81: 0.00235 | G81: =SUM($F$2:F81) -> 0.256532 | H81: 23.93 | I81: 11.5048 | J81: 2.08 | K81: 11.3375 | L81: 3.2384 | M81: =IF(AND(N(K81)>0,N(L81)>0),K81/L81,"") -> 3.5009573
A82: 81 | B82: MTCH | C82: Match Group, Inc. | D82: Communication Services | E82: Internet Content & Information | F82: 0.002334 | G82: =SUM($F$2:F82) -> 0.258866 | H82: 43.16 | I82: 15.305 | J82: 2.82 | K82: 10.0678 | L82: 2.8689 | M82: =IF(AND(N(K82)>0,N(L82)>0),K82/L82,"") -> 3.5092893
A83: 82 | B83: TOL | C83: Toll Brothers, Inc. | D83: Consumer Discretionary | E83: Residential Construction | F83: 0.002326 | G83: =SUM($F$2:F83) -> 0.261192 | H83: 135.5 | I83: 10.9186 | J83: 12.41 | K83: 12.4859 | L83: 1.1605 | M83: =IF(AND(N(K83)>0,N(L83)>0),K83/L83,"") -> 10.759069
A84: 83 | B84: UNM | C84: Unum Group | D84: Financials | E84: Insurance - Life | F84: 0.002323 | G84: =SUM($F$2:F84) -> 0.263515 | H84: 93.56 | I84: 21.7077 | J84: 4.31 | K84: 14.8112 | L84: 1.1096 | M84: =IF(AND(N(K84)>0,N(L84)>0),K84/L84,"") -> 13.348234
A85: 84 | B85: PEN | C85: Penumbra, Inc. | D85: Health Care | E85: Medical Devices | F85: 0.002318 | G85: =SUM($F$2:F85) -> 0.265833 | H85: 318.78 | I85: 78.1324 | J85: 4.08 | K85: 12.5566 | L85: 8.3439 | M85: =IF(AND(N(K85)>0,N(L85)>0),K85/L85,"") -> 1.5048838
A86: 85 | B86: SN | C86: SharkNinja, Inc. | D86: Consumer Discretionary | E86: Furnishings, Fixtures & Appliances | F86: 0.002308 | G86: =SUM($F$2:F86) -> 0.268141 | H86: 167.5 | I86: 34.1141 | J86: 4.91 | K86: 23.7047 | L86: 3.4305 | M86: =IF(AND(N(K86)>0,N(L86)>0),K86/L86,"") -> 6.909984
A87: 86 | B87: KNX | C87: Knight-Swift Transportation Holdings Inc. | D87: Industrials | E87: Trucking | F87: 0.002287 | G87: =SUM($F$2:F87) -> 0.270428 | H87: 66.62 | I87: 246.7407 | J87: 0.27 | K87: 10.8428 | L87: 1.4028 | M87: =IF(AND(N(K87)>0,N(L87)>0),K87/L87,"") -> 7.7293983
A88: 87 | B88: CORT | C88: Corcept Therapeutics Incorporated | D88: Health Care | E88: Biotechnology | F88: 0.002285 | G88: =SUM($F$2:F88) -> 0.272713 | H88: 113.76 | I88: 247.3043 | J88: 0.46 | K88: 12.2973 | L88: 14.8015 | M88: =IF(AND(N(K88)>0,N(L88)>0),K88/L88,"") -> 0.83081444
A89: 88 | B89: AGNC | C89: AGNC Investment Corp. | D89: Real Estate | E89: REIT - Mortgage | F89: 0.002277 | G89: =SUM($F$2:F89) -> 0.27499 | H89: 9.97 | I89: 4.9602 | J89: 2.01 | K89: 11.8193 | L89: 4.9226 | M89: =IF(AND(N(K89)>0,N(L89)>0),K89/L89,"") -> 2.4010279
A90: 89 | B90: SCI | C90: Service Corporation International | D90: Consumer Discretionary | E90: Personal Services | F90: 0.002273 | G90: =SUM($F$2:F90) -> 0.277263 | H90: 77.56 | I90: 20.2507 | J90: 3.83 | K90: 10.5708 | L90: 2.4193 | M90: =IF(AND(N(K90)>0,N(L90)>0),K90/L90,"") -> 4.369363
A91: 90 | B91: CSL | C91: Carlisle Companies Incorporated | D91: Industrials | E91: Building Products & Equipment | F91: 0.002263 | G91: =SUM($F$2:F91) -> 0.279526 | H91: 317.85 | I91: 18.0494 | J91: 17.61 | K91: 12.6231 | L91: 2.4766 | M91: =IF(AND(N(K91)>0,N(L91)>0),K91/L91,"") -> 5.0969474
... A96: 95 | B96: SANM | C96: Sanmina Corporation | D96: Information Technology | E96: Electronic Components | F96: 0.002199 | G96: =SUM($F$2:F96) -> 0.290645 | H96: 209.47 | I96: 37.4054 | J96: 5.6 | K96: 11.227 | L96: 0.8796 | M96: =IF(AND(N(K96)>0,N(L96)>0),K96/L96,"") -> 12.763756
A97: 96 | B97: ELAN | C97: Elanco Animal Health Incorporated | D97: Health Care | E97: Drug Manufacturers - Specialty & Generic | F97: 0.002195 | G97: =SUM($F$2:F97) -> 0.29284 | H97: 22.43 | J97: -0.41 | K97: 11.2027 | L97: 2.2316 | M97: =IF(AND(N(K97)>0,N(L97)>0),K97/L97,"") -> 5.0200305 | N97: Negative trailing EPS; P/E blank
A98: 97 | B98: FNF | C98: Fidelity National Financial, Inc. | D98: Financials | E98: Insurance - Specialty | F98: 0.002184 | G98: =SUM($F$2:F98) -> 0.295024 | H98: 42.46 | I98: 14.7944 | J98: 2.87 | K98: 11.3875 | L98: 0.7419 | M98: =IF(AND(N(K98)>0,N(L98)>0),K98/L98,"") -> 15.349104
A99: 98 | B99: MOG.A | C99: Moog Inc. | D99: Industrials | E99: Aerospace & Defense | F99: 0.002182 | G99: =SUM($F$2:F99) -> 0.297206 | H99: 369.42 | I99: 31.3599 | J99: 11.78 | K99: 11.7 | L99: 2.7096 | M99: =IF(AND(N(K99)>0,N(L99)>0),K99/L99,"") -> 4.3179805
A100: 99 | B100: CGNX | C100: Cognex Corporation | D100: Information Technology | E100: Scientific & Technical Instruments | F100: 0.002173 | G100: =SUM($F$2:F100) -> 0.299379 | H100: 61.99 | I100: 59.6058 | J100: 1.04 | K100: 10.4282 | L100: 9.5766 | M100: =IF(AND(N(K100)>0,N(L100)>0),K100/L100,"") -> 1.0889251
A101: 100 | B101: LFUS | C101: Littelfuse, Inc. | D101: Information Technology | E101: Electronic Components | F101: 0.002171 | G101: =SUM($F$2:F101) -> 0.30155 | H101: 409.54 | J101: -0.49 | K101: 10.4018 | L101: 3.9788 | M101: =IF(AND(N(K101)>0,N(L101)>0),K101/L101,"") -> 2.6143058 | N101: Negative trailing EPS; P/E blank
A102: 101 | B102: TXRH | C102: Texas Roadhouse, Inc. | D102: Consumer Discretionary | E102: Restaurants | F102: 0.00216 | G102: =SUM($F$2:F102) -> 0.30371 | H102: 165.54 | I102: 26.4441 | J102: 6.26 | K102: 10.8662 | L102: 1.7437 | M102: =IF(AND(N(K102)>0,N(L102)>0),K102/L102,"") -> 6.2316912
A103: 102 | B103: ALLY | C103: Ally Financial Inc. | D103: Financials | E103: Credit Services | F103: 0.002159 | G103: =SUM($F$2:F103) -> 0.305869 | H103: 39.89 | I103: 9.3859 | J103: 4.25 | K103: 12.1345 | L103: 1.5364 | M103: =IF(AND(N(K103)>0,N(L103)>0),K103/L103,"") -> 7.8980083
A104: 103 | B104: ELS | C104: Equity LifeStyle Properties, Inc. | D104: Real Estate | E104: REIT - Residential | F104: 0.002157 | G104: =SUM($F$2:F104) -> 0.308026 | H104: 60.44 | I104: 29.1981 | J104: 2.07 | K104: 12.1189 | L104: 7.7285 | M104: =IF(AND(N(K104)>0,N(L104)>0),K104/L104,"") -> 1.5680792
A105: 104 | B105: OC | C105: Owens Corning | D105: Industrials | E105: Building Products & Equipment | F105: 0.002152 | G105: =SUM($F$2:F105) -> 0.310178 | H105: 121.59 | J105: -4.82 | K105: 9.6115 | L105: 0.9761 | M105: =IF(AND(N(K105)>0,N(L105)>0),K105/L105,"") -> 9.8468395 | N105: Negative trailing EPS; P/E blank
A106: 105 | B106: DCI | C106: Donaldson Company, Inc. | D106: Industrials | E106: Specialty Industrial Machinery | F106: 0.002145 | G106: =SUM($F$2:F106) -> 0.312323 | H106: 86.07 | I106: 22.3558 | J106: 3.85 | M106: =IF(AND(N(K106)>0,N(L106)>0),K106/L106,"")
A107: 106 | B107: VOYA | C107: Voya Financial, Inc. | D107: Financials | E107: Financial Conglomerates | F107: 0.002142 | G107: =SUM($F$2:F107) -> 0.314465 | H107: 100.53 | I107: 16.9528 | J107: 5.93 | K107: 9.1077 | L107: 1.1153 | M107: =IF(AND(N(K107)>0,N(L107)>0),K107/L107,"") -> 8.1661436
A108: 107 | B108: PAYC | C108: Paycom Software, Inc. | D108: Information Technology | E108: Software - Application | F108: 0.00213 | G108: =SUM($F$2:F108) -> 0.316595 | H108: 226.24 | I108: 23.9154 | J108: 9.46 | K108: 10.197 | L108: 4.7634 | M108: =IF(AND(N(K108)>0,N(L108)>0),K108/L108,"") -> 2.1406978
A109: 108 | B109: CNH | C109: CNH Industrial N.V. | D109: Industrials | E109: Farm & Heavy Construction Machinery | F109: 0.00212 | G109: =SUM($F$2:F109) -> 0.318715 | H109: 13.48 | I109: 53.92 | J109: 0.25 | K109: 21.678 | L109: 1.1921 | M109: =IF(AND(N(K109)>0,N(L109)>0),K109/L109,"") -> 18.184716
A110: 109 | B110: R | C110: Ryder System, Inc. | D110: Industrials | E110: Rental & Leasing Services | F110: 0.002106 | G110: =SUM($F$2:F110) -> 0.320821 | H110: 237.14 | I110: 19.264 | J110: 12.31 | K110: 9.0936 | L110: 0.7094 | M110: =IF(AND(N(K110)>0,N(L110)>0),K110/L110,"") -> 12.81872
A111: 110 | B111: NLY | C111: Annaly Capital Management, Inc. | D111: Real Estate | E111: REIT - Mortgage | F111: 0.002098 | G111: =SUM($F$2:F111) -> 0.322919 | H111: 21.31 | I111: 5.1473 | J111: 4.14 | K111: 16.0617 | L111: 4.9351 | M111: =IF(AND(N(K111)>0,N(L111)>0),K111/L111,"") -> 3.2545845
A112: 111 | B112: GLPI | C112: Gaming and Leisure Properties, Inc. | D112: Real Estate | E112: REIT - Specialty | F112: 0.002097 | G112: =SUM($F$2:F112) -> 0.325016 | H112: 39.67 | I112: 11.5994 | J112: 3.42 | K112: 11.8812 | L112: 7.1784 | M112: =IF(AND(N(K112)>0,N(L112)>0),K112/L112,"") -> 1.6551321
A113: 112 | B113: NYT | C113: The New York Times Company | D113: Communication Services | E113: Publishing | F113: 0.002091 | G113: =SUM($F$2:F113) -> 0.327107 | H113: 70.53 | I113: 29.3875 | J113: 2.4 | K113: 11.3753 | L113: 3.8551 | M113: =IF(AND(N(K113)>0,N(L113)>0),K113/L113,"") -> 2.9507146
A114: 113 | B114: NXT | C114: Nextpower Inc. | D114: Information Technology | E114: Solar | F114: 0.002084 | G114: =SUM($F$2:F114) -> 0.329191 | H114: 83.15 | I114: 21.4858 | J114: 3.87 | K114: 12.775 | L114: 3.519 | M114: =IF(AND(N(K114)>0,N(L114)>0),K114/L114,"") -> 3.6302927
A115: 114 | B115: SEIC | C115: SEI Investments Company | D115: Financials | E115: Asset Management | F115: 0.00208 | G115: =SUM($F$2:F115) -> 0.331271 | H115: 105.38 | I115: 18.5855 | J115: 5.67 | K115: 12.6476 | L115: 5.1618 | M115: =IF(AND(N(K115)>0,N(L115)>0),K115/L115,"") -> 2.4502305
A116: 115 | B116: HUBS | C116: HubSpot, Inc. | D116: Information Technology | E116: Software - Application | F116: 0.002057 | G116: =SUM($F$2:F116) -> 0.333328 | H116: 213.86 | I116: 76.3786 | J116: 2.8 | K116: 10.9476 | L116: 3.1742 | M116: =IF(AND(N(K116)>0,N(L116)>0),K116/L116,"") -> 3.448932
A117: 116 | B117: RRX | C117: Regal Rexnord Corporation | D117: Industrials | E117: Specialty Industrial Machinery | F117: 0.002057 | G117: =SUM($F$2:F117) -> 0.335385 | H117: 150.73 | I117: 31.0144 | J117: 4.86 | K117: 10.034 | L117: 1.6564 | M117: =IF(AND(N(K117)>0,N(L117)>0),K117/L117,"") -> 6.0577155
A118: 117 | B118: ZION | C118: Zions Bancorporation, National Association | D118: Financials | E118: Banks - Regional | F118: 0.002056 | G118: =SUM($F$2:F118) -> 0.337441 | H118: 64.98 | I118: 8.2777 | J118: 7.85 | K118: 9.484 | L118: 2.5723 | M118: =IF(AND(N(K118)>0,N(L118)>0),K118/L118,"") -> 3.6869727
A119: 118 | B119: DAR | C119: Darling Ingredients Inc. | D119: Consumer Staples | E119: Packaged Foods | F119: 0.002055 | G119: =SUM($F$2:F119) -> 0.339496 | H119: 63.26 | I119: 17.0054 | J119: 3.72 | K119: 9.9826 | L119: 1.5244 | M119: =IF(AND(N(K119)>0,N(L119)>0),K119/L119,"") -> 6.5485437
A120: 119 | B120: AVTR | C120: Avantor, Inc. | D120: Health Care | E120: Medical Instruments & Supplies | F120: 0.002042 | G120: =SUM($F$2:F120) -> 0.341538 | H120: 15.1 | J120: -0.85 | K120: 10.213 | L120: 1.5566 | M120: =IF(AND(N(K120)>0,N(L120)>0),K120/L120,"") -> 6.5610947 | N120: Negative trailing EPS; P/E blank
A121: 120 | B121: WSO | C121: Watsco, Inc. | D121: Industrials | E121: Industrial Distribution | F121: 0.00203 | G121: =SUM($F$2:F121) -> 0.343568 | H121: 317.69 | I121: 27.2461 | J121: 11.66 | K121: 13.1054 | L121: 1.7993 | M121: =IF(AND(N(K121)>0,N(L121)>0),K121/L121,"") -> 7.2836103
A122: 121 | B122: PINS | C122: Pinterest, Inc. | D122: Communication Services | E122: Internet Content & Information | F122: 0.00203 | G122: =SUM($F$2:F122) -> 0.345598 | H122: 19.36 | I122: 56.9412 | J122: 0.34 | K122: 10.9638 | L122: 2.4066 | M122: =IF(AND(N(K122)>0,N(L122)>0),K122/L122,"") -> 4.5557218
A123: 122 | B123: GME | C123: GameStop Corp. | D123: Consumer Discretionary | E123: Specialty Retail | F123: 0.002023 | G123: =SUM($F$2:F123) -> 0.347621 | H123: 22.76 | I123: 14.9737 | J123: 1.52 | K123: 11.4824 | L123: 3.2338 | M123: =IF(AND(N(K123)>0,N(L123)>0),K123/L123,"") -> 3.5507453
A124: 123 | B124: WTS | C124: Watts Water Technologies, Inc. | D124: Industrials | E124: Specialty Industrial Machinery | F124: 0.00202 | G124: =SUM($F$2:F124) -> 0.349641 | H124: 350.62 | I124: 30.5684 | J124: 11.47 | K124: 11.7048 | L124: 4.372 | M124: =IF(AND(N(K124)>0,N(L124)>0),K124/L124,"") -> 2.6772187
A125: 124 | B125: FLS | C125: Flowserve Corporation | D125: Industrials | E125: Specialty Industrial Machinery | F125: 0.002005 | G125: =SUM($F$2:F125) -> 0.351646 | H125: 74.67 | I125: 26.0174 | J125: 2.87 | K125: 9.4915 | L125: 2.0482 | M125: =IF(AND(N(K125)>0,N(L125)>0),K125/L125,"") -> 4.6340689
A126: 125 | B126: MOH | C126: Molina Healthcare, Inc. | D126: Health Care | E126: Healthcare Plans | F126: 0.001994 | G126: =SUM($F$2:F126) -> 0.35364 | H126: 197.8 | I126: 1236.25 | J126: 0.16 | K126: 10.3252 | L126: 0.2431 | M126: =IF(AND(N(K126)>0,N(L126)>0),K126/L126,"") -> 42.473056 | N126: P/E reflects near-zero earnings
A127: 126 | B127: SSB | C127: SouthState Bank Corporation | D127: Financials | E127: Banks - Regional | F127: 0.00199 | G127: =SUM($F$2:F127) -> 0.35563 | H127: 103.11 | I127: 10.8309 | J127: 9.52 | K127: 9.999 | L127: 3.7365 | M127: =IF(AND(N(K127)>0,N(L127)>0),K127/L127,"") -> 2.6760337
A128: 127 | B128: EVR | C128: Evercore Inc. | D128: Financials | E128: Capital Markets | F128: 0.001987 | G128: =SUM($F$2:F128) -> 0.357617 | H128: 269.01 | I128: 15.1555 | J128: 17.75 | K128: 10.3455 | L128: 2.1965 | M128: =IF(AND(N(K128)>0,N(L128)>0),K128/L128,"") -> 4.7099932
A129: 128 | B129: TTEK | C129: Tetra Tech, Inc. | D129: Industrials | E129: Engineering & Construction | F129: 0.001986 | G129: =SUM($F$2:F129) -> 0.359603 | H129: 35.96 | I129: 21.6627 | J129: 1.66 | K129: 9.2074 | L129: 2.1124 | M129: =IF(AND(N(K129)>0,N(L129)>0),K129/L129,"") -> 4.3587389
...

Sheet Sectors
A1: GICS Sector | B1: Approx. Weight | C1: # of Tickers | D1: Avg P/E (simple, P/E<=100)
A2: Communication Services | B2: =SUMIF(Holdings!$D$2:$D$1010,A2,Holdings!$F$2:$F$1010) -> 0.022914 | C2: =COUNTIF(Holdings!$D$2:$D$1010,A2) -> 19 | D2: =AVERAGEIFS(Holdings!$I$2:$I$1010,Holdings!$D$2:$D$1010,A2,Holdings!$I$2:$I$1010,"<=100") -> 25.8534
A3: Consumer Discretionary | B3: =SUMIF(Holdings!$D$2:$D$1010,A3,Holdings!$F$2:$F$1010) -> 0.109184 | C3: =COUNTIF(Holdings!$D$2:$D$1010,A3) -> 110 | D3: =AVERAGEIFS(Holdings!$I$2:$I$1010,Holdings!$D$2:$D$1010,A3,Holdings!$I$2:$I$1010,"<=100") -> 19.466876
A4: Consumer Staples | B4: =SUMIF(Holdings!$D$2:$D$1010,A4,Holdings!$F$2:$F$1010) -> 0.034458 | C4: =COUNTIF(Holdings!$D$2:$D$1010,A4) -> 33 | D4: =AVERAGEIFS(Holdings!$I$2:$I$1010,Holdings!$D$2:$D$1010,A4,Holdings!$I$2:$I$1010,"<=100") -> 25.436139
A5: Energy | B5: =SUMIF(Holdings!$D$2:$D$1010,A5,Holdings!$F$2:$F$1010) -> 0.052034 | C5: =COUNTIF(Holdings!$D$2:$D$1010,A5) -> 42 | D5: =AVERAGEIFS(Holdings!$I$2:$I$1010,Holdings!$D$2:$D$1010,A5,Holdings!$I$2:$I$1010,"<=100") -> 23.869118
A6: Financials | B6: =SUMIF(Holdings!$D$2:$D$1010,A6,Holdings!$F$2:$F$1010) -> 0.147639 | C6: =COUNTIF(Holdings!$D$2:$D$1010,A6) -> 138 | D6: =AVERAGEIFS(Holdings!$I$2:$I$1010,Holdings!$D$2:$D$1010,A6,Holdings!$I$2:$I$1010,"<=100") -> 14.459862
A7: Health Care | B7: =SUMIF(Holdings!$D$2:$D$1010,A7,Holdings!$F$2:$F$1010) -> 0.096018 | C7: =COUNTIF(Holdings!$D$2:$D$1010,A7) -> 77 | D7: =AVERAGEIFS(Holdings!$I$2:$I$1010,Holdings!$D$2:$D$1010,A7,Holdings!$I$2:$I$1010,"<=100") -> 31.926148
A8: Industrials | B8: =SUMIF(Holdings!$D$2:$D$1010,A8,Holdings!$F$2:$F$1010) -> 0.201057 | C8: =COUNTIF(Holdings!$D$2:$D$1010,A8) -> 142 | D8: =AVERAGEIFS(Holdings!$I$2:$I$1010,Holdings!$D$2:$D$1010,A8,Holdings!$I$2:$I$1010,"<=100") -> 27.423206
A9: Information Technology | B9: =SUMIF(Holdings!$D$2:$D$1010,A9,Holdings!$F$2:$F$1010) -> 0.160422 | C9: =COUNTIF(Holdings!$D$2:$D$1010,A9) -> 122 | D9: =AVERAGEIFS(Holdings!$I$2:$I$1010,Holdings!$D$2:$D$1010,A9,Holdings!$I$2:$I$1010,"<=100") -> 35.964602
A10: Materials | B10: =SUMIF(Holdings!$D$2:$D$1010,A10,Holdings!$F$2:$F$1010) -> 0.046625 | C10: =COUNTIF(Holdings!$D$2:$D$1010,A10) -> 41 | D10: =AVERAGEIFS(Holdings!$I$2:$I$1010,Holdings!$D$2:$D$1010,A10,Holdings!$I$2:$I$1010,"<=100") -> 26.662688
A11: Real Estate | B11: =SUMIF(Holdings!$D$2:$D$1010,A11,Holdings!$F$2:$F$1010) -> 0.069053 | C11: =COUNTIF(Holdings!$D$2:$D$1010,A11) -> 62 | D11: =AVERAGEIFS(Holdings!$I$2:$I$1010,Holdings!$D$2:$D$1010,A11,Holdings!$I$2:$I$1010,"<=100") -> 29.167674
A12: Utilities | B12: =SUMIF(Holdings!$D$2:$D$1010,A12,Holdings!$F$2:$F$1010) -> 0.022411 | C12: =COUNTIF(Holdings!$D$2:$D$1010,A12) -> 24 | D12: =AVERAGEIFS(Holdings!$I$2:$I$1010,Holdings!$D$2:$D$1010,A12,Holdings!$I$2:$I$1010,"<=100") -> 21.109257
A13: Unclassified (no sector retrieved) | B13: =1-SUM(B2:B12) -> 0.038185 | C13: =COUNTBLANK(Holdings!$D$2:$D$1010) -> 199
A14: Total | B14: =SUM(B2:B13) -> 1 | C14: =SUM(C2:C13) -> 1009

Sheet Notes
A1: VXF proxy: US mid & small caps outside the S&P 500 (S&P 1500 minus S&P 500 = S&P MidCap 400 + SmallCap 600)
A2: Holdings and weights: State Street SPDR Portfolio S&P 1500 ETF (SPTM) daily holdings file, as of 21-Sep-2026, with the 503 S&P 500 tickers from the companion S&P 500 workbook removed and the remaining weights rescaled to 100%. That leaves the S&P MidCap 400 and SmallCap 600 members.
A3: Why this is a proxy: VXF tracks the S&P Completion Index (about 3,500 stocks: everything in the S&P Total Market Index that is not in the S&P 500). Vanguard's full holdings file is not downloadable from here. The 1,000 mid and small caps above are the largest and most liquid part of that index and carry most of its weight; micro-caps are not included. IJH + IJR track exactly this list.
A4: P/E (TTM), EPS (TTM), Market Cap, Price/Sales, Price, Company name, GICS sector and Sub-Industry: Yahoo Finance via the yfinance library, retrieved Sept 22, 2026. Yahoo's 11 sectors are mapped to the GICS sector names used on the S&P 500 sheet; Yahoo's industry label stands in for the GICS sub-industry.
A5: Revenue TTM ($B) is derived as Market Cap / Price-to-Sales, so it is approximate. Blank where either input is missing.
A6: Where Yahoo shows negative trailing EPS, P/E is left blank. Extreme P/Es (several hundred or more) reflect near-zero earnings, not meaningful valuation. Small caps have many more loss-makers than the S&P 500; the Sectors tab average excludes blanks and P/Es above 100.
A7: Cumulative Weight assumes the default sort by rank; after re-sorting it shows the running weight in the new order.
A8: For information only; not investment advice.
A10: Historical tabs 'Annual Returns' (1927-2025) and 'By Decade': there is no 100-year history of the S&P Completion Index itself (it began in 2001). The closest long-run series is Kenneth French's CRSP size-decile portfolios: all NYSE/AMEX/NASDAQ stocks are sorted into ten groups by market cap each year. Deciles 1 through 9 (everything except the largest 10% of companies) are combined here, cap-weighted, which is the same idea as 'the market outside the S&P 500'. Total returns include dividends. The largest-10% decile is shown alongside as an S&P 500-like comparison. Source: mba.tuck.dartmouth.edu/pages/faculty/ken.french/data_library.html, 'Portfolios Formed on Size', file created from the 202607 CRSP database.
A11: Real returns use December-over-December CPI-U (NSA): Robert Shiller's dataset through 2023, then BLS series CUUR0000SA0 (Dec 2024 = 315.605, Dec 2025 = 324.054). There is no separate price-only series for the decile portfolios, so the price-return columns on the S&P 500 sheet are omitted here.

Sheet Annual Returns
A1: Year | B1: Decade | C1: Total Return (w/ dividends) | D1: Real Total Return (inflation-adj.) | E1: Up / Down (Total Return) | F1: Growth of $1 (Total Return) | G1: Growth of $1 (Real) | H1: Largest-10% decile (S&P 500-like), for comparison
A2: 1927 | B2: =INT(A2/10)*10&"s" -> 1920s | C2: 0.3215 | D2: 0.352 | E2: =IF(C2>=0,"Up","Down") -> Up | F2: =1+C2 -> 1.3215 | G2: =1+D2 -> 1.352 | H2: 0.3422
A3: 1928 | B3: =INT(A3/10)*10&"s" -> 1920s | C3: 0.3947 | D3: 0.411 | E3: =IF(C3>=0,"Up","Down") -> Up | F3: =F2*(1+C3) -> 1.843096 | G3: =G2*(1+D3) -> 1.907672 | H3: 0.3782
A4: 1929 | B4: =INT(A4/10)*10&"s" -> 1920s | C4: -0.1968 | D4: -0.2015 | E4: =IF(C4>=0,"Up","Down") -> Down | F4: =F3*(1+C4) -> 1.4803747 | G4: =G3*(1+D4) -> 1.5232761 | H4: -0.0936
A5: 1930 | B5: =INT(A5/10)*10&"s" -> 1930s | C5: -0.3714 | D5: -0.3284 | E5: =IF(C5>=0,"Up","Down") -> Down | F5: =F4*(1+C5) -> 0.93056357 | G5: =G4*(1+D5) -> 1.0230322 | H5: -0.2385
A6: 1931 | B6: =INT(A6/10)*10&"s" -> 1930s | C6: -0.4869 | D6: -0.4341 | E6: =IF(C6>=0,"Up","Down") -> Down | F6: =F5*(1+C6) -> 0.47747217 | G6: =G5*(1+D6) -> 0.57893394 | H6: -0.4164
A7: 1932 | B7: =INT(A7/10)*10&"s" -> 1930s | C7: -0.0237 | D7: 0.0881 | E7: =IF(C7>=0,"Up","Down") -> Down | F7: =F6*(1+C7) -> 0.46615608 | G7: =G6*(1+D7) -> 0.62993801 | H7: -0.1084
A8: 1933 | B8: =INT(A8/10)*10&"s" -> 1930s | C8: 0.8714 | D8: 0.8572 | E8: =IF(C8>=0,"Up","Down") -> Up | F8: =F7*(1+C8) -> 0.87236448 | G8: =G7*(1+D8) -> 1.1699209 | H8: 0.4591
A9: 1934 | B9: =INT(A9/10)*10&"s" -> 1930s | C9: 0.0769 | D9: 0.0608 | E9: =IF(C9>=0,"Up","Down") -> Up | F9: =F8*(1+C9) -> 0.93944931 | G9: =G8*(1+D9) -> 1.2410521 | H9: 0.0138
A10: 1935 | B10: =INT(A10/10)*10&"s" -> 1930s | C10: 0.4826 | D10: 0.4397 | E10: =IF(C10>=0,"Up","Down") -> Up | F10: =F9*(1+C10) -> 1.3928275 | G10: =G9*(1+D10) -> 1.7867427 | H10: 0.433
A11: 1936 | B11: =INT(A11/10)*10&"s" -> 1930s | C11: 0.3738 | D11: 0.3542 | E11: =IF(C11>=0,"Up","Down") -> Up | F11: =F10*(1+C11) -> 1.9134665 | G11: =G10*(1+D11) -> 2.4196069 | H11: 0.305
A12: 1937 | B12: =INT(A12/10)*10&"s" -> 1930s | C12: -0.4112 | D12: -0.4275 | E12: =IF(C12>=0,"Up","Down") -> Down | F12: =F11*(1+C12) -> 1.1266491 | G12: =G11*(1+D12) -> 1.385225 | H12: -0.3167
A13: 1938 | B13: =INT(A13/10)*10&"s" -> 1930s | C13: 0.3599 | D13: 0.3988 | E13: =IF(C13>=0,"Up","Down") -> Up | F13: =F12*(1+C13) -> 1.5321301 | G13: =G12*(1+D13) -> 1.9376527 | H13: 0.252
A14: 1939 | B14: =INT(A14/10)*10&"s" -> 1930s | C14: -0.0379 | D14: -0.0379 | E14: =IF(C14>=0,"Up","Down") -> Down | F14: =F13*(1+C14) -> 1.4740623 | G14: =G13*(1+D14) -> 1.8642156 | H14: 0.0535
... A100: 2025 | B100: =INT(A100/10)*10&"s" -> 2020s | C100: 0.1099 | D100: 0.081 | E100: =IF(C100>=0,"Up","Down") -> Up | F100: =F99*(1+C100) -> 33274.33 | G100: =G99*(1+D100) -> 1817.7895 | H100: 0.1952
A102: Summary
A103: Years | C103: =COUNT(A2:A100) -> 99
A104: Up years | C104: =COUNTIF(C2:C100,">=0") -> 71
A105: Down years | C105: =COUNTIF(C2:C100,"<0") -> 28
A106: Average annual total return | C106: =AVERAGE(C2:C100) -> 0.13563131
A107: Annualized (CAGR) total return | C107: =(F100)^(1/COUNT(A2:A100))-1 -> 0.11090743
A108: Average annual real return | C108: =AVERAGE(D2:D100) -> 0.10323737
A109: Annualized (CAGR) real return | C109: =(G100)^(1/COUNT(D2:D100))-1 -> 0.078759623
A110: Best year (total) | C110: =MAX(C2:C100) -> 0.8714
A111: Worst year (total) | C111: =MIN(C2:C100) -> -0.4869
A112: Standard deviation of annual returns | C112: =STDEV(C2:C100) -> 0.22792587
A113: $1 grew to (total, 1927-2025) | C113: =F100 -> 33274.33
A114: $1 grew to (real) | C114: =G100 -> 1817.7895
A115: Comparison series: average | C115: =AVERAGE(H2:H100) -> 0.11692727
A116: Comparison series: CAGR | C116: =EXP(SUMPRODUCT(LN(1+H2:H100)))^(1/COUNT(H2:H100))-1 -> 0.099500179
A118: US stocks outside the largest 10% (Fama-French size deciles 1-9, cap-weighted)
A119: Returns are calendar-year, compounded from monthly data, with dividends reinvested. Real returns are CPI-adjusted. 'Average' is the simple mean of yearly returns; 'Annualized / CAGR' is the compound rate actually earned, always lower because of volatility drag.
A120: 2026 is excluded because the year is not complete. See the Notes tab for sources and why this series stands in for the index.

Sheet By Decade
A1: Decade | B1: Years Covered | C1: # of Years | D1: Up Years | E1: Down Years | F1: Avg Annual Total Return | G1: Annualized (CAGR) Total Return | H1: Cumulative Total Return | I1: Avg Annual Real Total Return | J1: Annualized (CAGR) Real Return | K1: Best Year (Total) | L1: Worst Year (Total) | M1: $1 Grew To (Total) | N1: Comparison series CAGR
A2: 1920s | B2: 1927–1929 (partial) | C2: =COUNTIF('Annual Returns'!$B$2:$B$100,"1920s") -> 3 | D2: =COUNTIFS('Annual Returns'!$B$2:$B$100,"1920s",'Annual Returns'!$C$2:$C$100,">=0") -> 2 | E2: =COUNTIFS('Annual Returns'!$B$2:$B$100,"1920s",'Annual Returns'!$C$2:$C$100,"<0") -> 1 | F2: =AVERAGEIF('Annual Returns'!$B$2:$B$100,"1920s",'Annual Returns'!$C$2:$C$100) -> 0.17313333 | G2: =(1+H2)^(1/C2)-1 -> 0.13970002 | H2: =EXP(SUMPRODUCT(('Annual Returns'!$B$2:$B$100="1920s")*LN(1+'Annual Returns'!$C$2:$C$100)))-1 -> 0.48037475 | I2: =AVERAGEIF('Annual Returns'!$B$2:$B$100,"1920s",'Annual Returns'!$D$2:$D$100) -> 0.18716667 | J2: =(EXP(SUMPRODUCT(('Annual Returns'!$B$2:$B$100="1920s")*LN(1+'Annual Returns'!$D$2:$D$100))))^(1/C2)-1 -> 0.15060487 | K2: =_xlfn.MAXIFS('Annual Returns'!$C$2:$C$100,'Annual Returns'!$B$2:$B$100,"1920s") -> 0.3947 | L2: =_xlfn.MINIFS('Annual Returns'!$C$2:$C$100,'Annual Returns'!$B$2:$B$100,"1920s") -> -0.1968 | M2: =1+H2 -> 1.4803747 | N2: =(EXP(SUMPRODUCT(('Annual Returns'!$B$2:$B$100="1920s")*LN(1+'Annual Returns'!$H$2:$H$100))))^(1/C2)-1 -> 0.18800005
A3: 1930s | B3: 1930–1939 | C3: =COUNTIF('Annual Returns'!$B$2:$B$100,"1930s") -> 10 | D3: =COUNTIFS('Annual Returns'!$B$2:$B$100,"1930s",'Annual Returns'!$C$2:$C$100,">=0") -> 5 | E3: =COUNTIFS('Annual Returns'!$B$2:$B$100,"1930s",'Annual Returns'!$C$2:$C$100,"<0") -> 5 | F3: =AVERAGEIF('Annual Returns'!$B$2:$B$100,"1930s",'Annual Returns'!$C$2:$C$100) -> 0.08335 | G3: =(1+H3)^(1/C3)-1 -> -0.00042722698 | H3: =EXP(SUMPRODUCT(('Annual Returns'!$B$2:$B$100="1930s")*LN(1+'Annual Returns'!$C$2:$C$100)))-1 -> -0.0042640656 | I3: =AVERAGEIF('Annual Returns'!$B$2:$B$100,"1930s",'Annual Returns'!$D$2:$D$100) -> 0.09709 | J3: =(EXP(SUMPRODUCT(('Annual Returns'!$B$2:$B$100="1930s")*LN(1+'Annual Returns'!$D$2:$D$100))))^(1/C3)-1 -> 0.02040306 | K3: =_xlfn.MAXIFS('Annual Returns'!$C$2:$C$100,'Annual Returns'!$B$2:$B$100,"1930s") -> 0.8714 | L3: =_xlfn.MINIFS('Annual Returns'!$C$2:$C$100,'Annual Returns'!$B$2:$B$100,"1930s") -> -0.4869 | M3: =1+H3 -> 0.99573593 | N3: =(EXP(SUMPRODUCT(('Annual Returns'!$B$2:$B$100="1930s")*LN(1+'Annual Returns'!$H$2:$H$100))))^(1/C3)-1 -> -0.0012197208
A4: 1940s | B4: 1940–1949 | C4: =COUNTIF('Annual Returns'!$B$2:$B$100,"1940s") -> 10 | D4: =COUNTIFS('Annual Returns'!$B$2:$B$100,"1940s",'Annual Returns'!$C$2:$C$100,">=0") -> 6 | E4: =COUNTIFS('Annual Returns'!$B$2:$B$100,"1940s",'Annual Returns'!$C$2:$C$100,"<0") -> 4 | F4: =AVERAGEIF('Annual Returns'!$B$2:$B$100,"1940s",'Annual Returns'!$C$2:$C$100) -> 0.14884 | G4: =(1+H4)^(1/C4)-1 -> 0.12917643 | H4: =EXP(SUMPRODUCT(('Annual Returns'!$B$2:$B$100="1940s")*LN(1+'Annual Returns'!$C$2:$C$100)))-1 -> 2.3699081 | I4: =AVERAGEIF('Annual Returns'!$B$2:$B$100,"1940s",'Annual Returns'!$D$2:$D$100) -> 0.09682 | J4: =(EXP(SUMPRODUCT(('Annual Returns'!$B$2:$B$100="1940s")*LN(1+'Annual Returns'!$D$2:$D$100))))^(1/C4)-1 -> 0.071742572 | K4: =_xlfn.MAXIFS('Annual Returns'!$C$2:$C$100,'Annual Returns'!$B$2:$B$100,"1940s") -> 0.5472 | L4: =_xlfn.MINIFS('Annual Returns'!$C$2:$C$100,'Annual Returns'!$B$2:$B$100,"1940s") -> -0.0863 | M4: =1+H4 -> 3.3699081 | N4: =(EXP(SUMPRODUCT(('Annual Returns'!$B$2:$B$100="1940s")*LN(1+'Annual Returns'!$H$2:$H$100))))^(1/C4)-1 -> 0.079595666
A5: 1950s | B5: 1950–1959 | C5: =COUNTIF('Annual Returns'!$B$2:$B$100,"1950s") -> 10 | D5: =COUNTIFS('Annual Returns'!$B$2:$B$100,"1950s",'Annual Returns'!$C$2:$C$100,">=0") -> 8 | E5: =COUNTIFS('Annual Returns'!$B$2:$B$100,"1950s",'Annual Returns'!$C$2:$C$100,"<0") -> 2 | F5: =AVERAGEIF('Annual Returns'!$B$2:$B$100,"1950s",'Annual Returns'!$C$2:$C$100) -> 0.20058 | G5: =(1+H5)^(1/C5)-1 -> 0.18400798 | H5: =EXP(SUMPRODUCT(('Annual Returns'!$B$2:$B$100="1950s")*LN(1+'Annual Returns'!$C$2:$C$100)))-1 -> 4.4143497 | I5: =AVERAGEIF('Annual Returns'!$B$2:$B$100,"1950s",'Annual Returns'!$D$2:$D$100) -> 0.17533 | J5: =(EXP(SUMPRODUCT(('Annual Returns'!$B$2:$B$100="1950s")*LN(1+'Annual Returns'!$D$2:$D$100))))^(1/C5)-1 -> 0.15825101 | K5: =_xlfn.MAXIFS('Annual Returns'!$C$2:$C$100,'Annual Returns'!$B$2:$B$100,"1950s") -> 0.539 | L5: =_xlfn.MINIFS('Annual Returns'!$C$2:$C$100,'Annual Returns'!$B$2:$B$100,"1950s") -> -0.1182 | M5: =1+H5 -> 5.4143497 | N5: =(EXP(SUMPRODUCT(('Annual Returns'!$B$2:$B$100="1950s")*LN(1+'Annual Returns'!$H$2:$H$100))))^(1/C5)-1 -> 0.18406032
A6: 1960s | B6: 1960–1969 | C6: =COUNTIF('Annual Returns'!$B$2:$B$100,"1960s") -> 10 | D6: =COUNTIFS('Annual Returns'!$B$2:$B$100,"1960s",'Annual Returns'!$C$2:$C$100,">=0") -> 7 | E6: =COUNTIFS('Annual Returns'!$B$2:$B$100,"1960s",'Annual Returns'!$C$2:$C$100,"<0") -> 3 | F6: =AVERAGEIF('Annual Returns'!$B$2:$B$100,"1960s",'Annual Returns'!$C$2:$C$100) -> 0.12174 | G6: =(1+H6)^(1/C6)-1 -> 0.10721938 | H6: =EXP(SUMPRODUCT(('Annual Returns'!$B$2:$B$100="1960s")*LN(1+'Annual Returns'!$C$2:$C$100)))-1 -> 1.7690881 | I6: =AVERAGEIF('Annual Returns'!$B$2:$B$100,"1960s",'Annual Returns'!$D$2:$D$100) -> 0.09521 | J6: =(EXP(SUMPRODUCT(('Annual Returns'!$B$2:$B$100="1960s")*LN(1+'Annual Returns'!$D$2:$D$100))))^(1/C6)-1 -> 0.080020316 | K6: =_xlfn.MAXIFS('Annual Returns'!$C$2:$C$100,'Annual Returns'!$B$2:$B$100,"1960s") -> 0.3899 | L6: =_xlfn.MINIFS('Annual Returns'!$C$2:$C$100,'Annual Returns'!$B$2:$B$100,"1960s") -> -0.1697 | M6: =1+H6 -> 2.7690881 | N6: =(EXP(SUMPRODUCT(('Annual Returns'!$B$2:$B$100="1960s")*LN(1+'Annual Returns'!$H$2:$H$100))))^(1/C6)-1 -> 0.06925492
A7: 1970s | B7: 1970–1979 | C7: =COUNTIF('Annual Returns'!$B$2:$B$100,"1970s") -> 10 | D7: =COUNTIFS('Annual Returns'!$B$2:$B$100,"1970s",'Annual Returns'!$C$2:$C$100,">=0") -> 7 | E7: =COUNTIFS('Annual Returns'!$B$2:$B$100,"1970s",'Annual Returns'!$C$2:$C$100,"<0") -> 3 | F7: =AVERAGEIF('Annual Returns'!$B$2:$B$100,"1970s",'Annual Returns'!$C$2:$C$100) -> 0.10637 | G7: =(1+H7)^(1/C7)-1 -> 0.079127872 | H7: =EXP(SUMPRODUCT(('Annual Returns'!$B$2:$B$100="1970s")*LN(1+'Annual Returns'!$C$2:$C$100)))-1 -> 1.1415543 | I7: =AVERAGEIF('Annual Returns'!$B$2:$B$100,"1970s",'Annual Returns'!$D$2:$D$100) -> 0.03254 | J7: =(EXP(SUMPRODUCT(('Annual Returns'!$B$2:$B$100="1970s")*LN(1+'Annual Returns'!$D$2:$D$100))))^(1/C7)-1 -> 0.0051331599 | K7: =_xlfn.MAXIFS('Annual Returns'!$C$2:$C$100,'Annual Returns'!$B$2:$B$100,"1970s") -> 0.4707 | L7: =_xlfn.MINIFS('Annual Returns'!$C$2:$C$100,'Annual Returns'!$B$2:$B$100,"1970s") -> -0.2733 | M7: =1+H7 -> 2.1415543 | N7: =(EXP(SUMPRODUCT(('Annual Returns'!$B$2:$B$100="1970s")*LN(1+'Annual Returns'!$H$2:$H$100))))^(1/C7)-1 -> 0.046974065
A8: 1980s | B8: 1980–1989 | C8: =COUNTIF('Annual Returns'!$B$2:$B$100,"1980s") -> 10 | D8: =COUNTIFS('Annual Returns'!$B$2:$B$100,"1980s",'Annual Returns'!$C$2:$C$100,">=0") -> 9 | E8: =COUNTIFS('Annual Returns'!$B$2:$B$100,"1980s",'Annual Returns'!$C$2:$C$100,"<0") -> 1 | F8: =AVERAGEIF('Annual Returns'!$B$2:$B$100,"1980s",'Annual Returns'!$C$2:$C$100) -> 0.17418 | G8: =(1+H8)^(1/C8)-1 -> 0.16727534 | H8: =EXP(SUMPRODUCT(('Annual Returns'!$B$2:$B$100="1980s")*LN(1+'Annual Returns'!$C$2:$C$100)))-1 -> 3.6960542 | I8: =AVERAGEIF('Annual Returns'!$B$2:$B$100,"1980s",'Annual Returns'!$D$2:$D$100) -> 0.11718 | J8: =(EXP(SUMPRODUCT(('Annual Returns'!$B$2:$B$100="1980s")*LN(1+'Annual Returns'!$D$2:$D$100))))^(1/C8)-1 -> 0.11065783 | K8: =_xlfn.MAXIFS('Annual Returns'!$C$2:$C$100,'Annual Returns'!$B$2:$B$100,"1980s") -> 0.3363 | L8: =_xlfn.MINIFS('Annual Returns'!$C$2:$C$100,'Annual Returns'!$B$2:$B$100,"1980s") -> -0.0145 | M8: =1+H8 -> 4.6960542 | N8: =(EXP(SUMPRODUCT(('Annual Returns'!$B$2:$B$100="1980s")*LN(1+'Annual Returns'!$H$2:$H$100))))^(1/C8)-1 -> 0.17174099
A9: 1990s | B9: 1990–1999 | C9: =COUNTIF('Annual Returns'!$B$2:$B$100,"1990s") -> 10 | D9: =COUNTIFS('Annual Returns'!$B$2:$B$100,"1990s",'Annual Returns'!$C$2:$C$100,">=0") -> 8 | E9: =COUNTIFS('Annual Returns'!$B$2:$B$100,"1990s",'Annual Returns'!$C$2:$C$100,"<0") -> 2 | F9: =AVERAGEIF('Annual Returns'!$B$2:$B$100,"1990s",'Annual Returns'!$C$2:$C$100) -> 0.1682 | G9: =(1+H9)^(1/C9)-1 -> 0.15749031 | H9: =EXP(SUMPRODUCT(('Annual Returns'!$B$2:$B$100="1990s")*LN(1+'Annual Returns'!$C$2:$C$100)))-1 -> 3.3169165 | I9: =AVERAGEIF('Annual Returns'!$B$2:$B$100,"1990s",'Annual Returns'!$D$2:$D$100) -> 0.13589 | J9: =(EXP(SUMPRODUCT(('Annual Returns'!$B$2:$B$100="1990s")*LN(1+'Annual Returns'!$D$2:$D$100))))^(1/C9)-1 -> 0.12456799 | K9: =_xlfn.MAXIFS('Annual Returns'!$C$2:$C$100,'Annual Returns'!$B$2:$B$100,"1990s") -> 0.4168 | L9: =_xlfn.MINIFS('Annual Returns'!$C$2:$C$100,'Annual Returns'!$B$2:$B$100,"1990s") -> -0.1259 | M9: =1+H9 -> 4.3169165 | N9: =(EXP(SUMPRODUCT(('Annual Returns'!$B$2:$B$100="1990s")*LN(1+'Annual Returns'!$H$2:$H$100))))^(1/C9)-1 -> 0.19184698
A10: 2000s | B10: 2000–2009 | C10: =COUNTIF('Annual Returns'!$B$2:$B$100,"2000s") -> 10 | D10: =COUNTIFS('Annual Returns'!$B$2:$B$100,"2000s",'Annual Returns'!$C$2:$C$100,">=0") -> 7 | E10: =COUNTIFS('Annual Returns'!$B$2:$B$100,"2000s",'Annual Returns'!$C$2:$C$100,"<0") -> 3 | F10: =AVERAGEIF('Annual Returns'!$B$2:$B$100,"2000s",'Annual Returns'!$C$2:$C$100) -> 0.07436 | G10: =(1+H10)^(1/C10)-1 -> 0.047369844 | H10: =EXP(SUMPRODUCT(('Annual Returns'!$B$2:$B$100="2000s")*LN(1+'Annual Returns'!$C$2:$C$100)))-1 -> 0.58854914 | I10: =AVERAGEIF('Annual Returns'!$B$2:$B$100,"2000s",'Annual Returns'!$D$2:$D$100) -> 0.0469 | J10: =(EXP(SUMPRODUCT(('Annual Returns'!$B$2:$B$100="2000s")*LN(1+'Annual Returns'!$D$2:$D$100))))^(1/C10)-1 -> 0.021581892 | K10: =_xlfn.MAXIFS('Annual Returns'!$C$2:$C$100,'Annual Returns'!$B$2:$B$100,"2000s") -> 0.4272 | L10: =_xlfn.MINIFS('Annual Returns'!$C$2:$C$100,'Annual Returns'!$B$2:$B$100,"2000s") -> -0.3871 | M10: =1+H10 -> 1.5885491 | N10: =(EXP(SUMPRODUCT(('Annual Returns'!$B$2:$B$100="2000s")*LN(1+'Annual Returns'!$H$2:$H$100))))^(1/C10)-1 -> -0.023245097
A11: 2010s | B11: 2010–2019 | C11: =COUNTIF('Annual Returns'!$B$2:$B$100,"2010s") -> 10 | D11: =COUNTIFS('Annual Returns'!$B$2:$B$100,"2010s",'Annual Returns'!$C$2:$C$100,">=0") -> 7 | E11: =COUNTIFS('Annual Returns'!$B$2:$B$100,"2010s",'Annual Returns'!$C$2:$C$100,"<0") -> 3 | F11: =AVERAGEIF('Annual Returns'!$B$2:$B$100,"2010s",'Annual Returns'!$C$2:$C$100) -> 0.14433 | G11: =(1+H11)^(1/C11)-1 -> 0.13464105 | H11: =EXP(SUMPRODUCT(('Annual Returns'!$B$2:$B$100="2010s")*LN(1+'Annual Returns'!$C$2:$C$100)))-1 -> 2.5365916 | I11: =AVERAGEIF('Annual Returns'!$B$2:$B$100,"2010s",'Annual Returns'!$D$2:$D$100) -> 0.12462 | J11: =(EXP(SUMPRODUCT(('Annual Returns'!$B$2:$B$100="2010s")*LN(1+'Annual Returns'!$D$2:$D$100))))^(1/C11)-1 -> 0.11507455 | K11: =_xlfn.MAXIFS('Annual Returns'!$C$2:$C$100,'Annual Returns'!$B$2:$B$100,"2010s") -> 0.3926 | L11: =_xlfn.MINIFS('Annual Returns'!$C$2:$C$100,'Annual Returns'!$B$2:$B$100,"2010s") -> -0.0964 | M11: =1+H11 -> 3.5365916 | N11: =(EXP(SUMPRODUCT(('Annual Returns'!$B$2:$B$100="2010s")*LN(1+'Annual Returns'!$H$2:$H$100))))^(1/C11)-1 -> 0.13641933
A12: 2020s | B12: 2020–2025 (partial) | C12: =COUNTIF('Annual Returns'!$B$2:$B$100,"2020s") -> 6 | D12: =COUNTIFS('Annual Returns'!$B$2:$B$100,"2020s",'Annual Returns'!$C$2:$C$100,">=0") -> 5 | E12: =COUNTIFS('Annual Returns'!$B$2:$B$100,"2020s",'Annual Returns'!$C$2:$C$100,"<0") -> 1 | F12: =AVERAGEIF('Annual Returns'!$B$2:$B$100,"2020s",'Annual Returns'!$C$2:$C$100) -> 0.11476667 | G12: =(1+H12)^(1/C12)-1 -> 0.10614439 | H12: =EXP(SUMPRODUCT(('Annual Returns'!$B$2:$B$100="2020s")*LN(1+'Annual Returns'!$C$2:$C$100)))-1 -> 0.8317699 | I12: =AVERAGEIF('Annual Returns'!$B$2:$B$100,"2020s",'Annual Returns'!$D$2:$D$100) -> 0.073866667 | J12: =(EXP(SUMPRODUCT(('Annual Returns'!$B$2:$B$100="2020s")*LN(1+'Annual Returns'!$D$2:$D$100))))^(1/C12)-1 -> 0.064195948 | K12: =_xlfn.MAXIFS('Annual Returns'!$C$2:$C$100,'Annual Returns'!$B$2:$B$100,"2020s") -> 0.2314 | L12: =_xlfn.MINIFS('Annual Returns'!$C$2:$C$100,'Annual Returns'!$B$2:$B$100,"2020s") -> -0.1615 | M12: =1+H12 -> 1.8317699 | N12: =(EXP(SUMPRODUCT(('Annual Returns'!$B$2:$B$100="2020s")*LN(1+'Annual Returns'!$H$2:$H$100))))^(1/C12)-1 -> 0.16542295
A13: All years | B13: 1927–2025 | C13: =COUNT('Annual Returns'!$A$2:$A$100) -> 99 | D13: =COUNTIF('Annual Returns'!$C$2:$C$100,">=0") -> 71 | E13: =COUNTIF('Annual Returns'!$C$2:$C$100,"<0") -> 28 | F13: =AVERAGE('Annual Returns'!$C$2:$C$100) -> 0.13563131 | G13: =(1+H13)^(1/C13)-1 -> 0.11090743 | H13: =EXP(SUMPRODUCT(LN(1+'Annual Returns'!$C$2:$C$100)))-1 -> 33273.33 | I13: =AVERAGE('Annual Returns'!$D$2:$D$100) -> 0.10323737 | J13: =(EXP(SUMPRODUCT(LN(1+'Annual Returns'!$D$2:$D$100))))^(1/C13)-1 -> 0.078759623 | K13: =MAX('Annual Returns'!$C$2:$C$100) -> 0.8714 | L13: =MIN('Annual Returns'!$C$2:$C$100) -> -0.4869 | M13: =1+H13 -> 33274.33 | N13: =(EXP(SUMPRODUCT(LN(1+'Annual Returns'!$H$2:$H$100))))^(1/C13)-1 -> 0.099500179
A16: Decades are calendar decades. Partial decades are marked.
A17: Avg Annual = simple average of the yearly returns in that decade. Annualized (CAGR) = the compound rate that turns the starting dollar into the ending dollar; this is the number that reflects what you actually earned.
A18: Cumulative Total Return = total growth over the decade with dividends reinvested. All figures pull live from the 'Annual Returns' tab.
A19: Comparison series = Largest-10% decile (S&P 500-like), for comparison. Source and methodology: see the Notes tab.
